Workbook

Sheet COVER
B3: BridgeToRetired
B4: PRO RETIREMENT BRIDGE PLANNER
B5: Version 3.1 · 2026 Tax Year · bridgetoretired.com
B10: WHAT'S INSIDE
B11: INPUTS | C11: Ages, balances, spending, state, filing status — single entry point for all sheets
B12: BRIDGE | C12: Year-by-year funding plan retirement → 59½ with Taxable → Roth → 401k cascade
B13: TAX ESTIMATE | C13: Federal tax per bridge year — MFJ or Single brackets switchable in INPUTS
B14: ROTH LADDER | C14: Optimal Roth conversions with 12% bracket space and ACA cliff cross-check per year
B15: POST-59.5 | C15: Portfolio projection 59½ → life expectancy with Social Security income modeled
B16: MONTE CARLO | C16: 200-scenario simulator — plan success rate across randomized return sequences
B17: RISK FLAGS | C17: 9 automated checks: withdrawal rate, ACA cliff, IRMAA, SS delay, Monte Carlo
B18: REBALANCE | C18: Annual target vs actual allocation by asset class with drift alerts and signals
B20: COLOR CODING GUIDE
B22: Blue text = Input cells — change these to your numbers
B23: Green text = Linked from another sheet
B24: Black text = Formula / calculated — do not edit
B25: Gold highlight = Key result or flag
B27: ⚠ Not financial advice. For modeling purposes only. Consult a qualified fee-only advisor.
B29: v3.1 (Aug 2026): 2026 brackets & std deduction · ACA cliff by household size · balances grown to retirement date · retire-at-60+ fix · capacity: 25-yr bridge, 45-yr projection, 60-yr Monte Carlo

Sheet INPUTS
A1: RETIREMENT INPUTS
A2: Blue cells are inputs. Change any value — every sheet updates automatically.
A3: PERSONAL
A4: PERSONAL
A5: Current Age | B5: 52
A6: Planned Retirement Age | B6: 55
A7: Social Security Claiming Age | B7: 67 | D7: 62 / 67 / 70
A8: Life Expectancy (planning age) | B8: 90 | D8: Conservative = 90–95
A9: Filing Status | B9: MFJ | D9: MFJ or Single — drives TAX ESTIMATE brackets
A10: State of Residence | B10: TX | D10: No-tax states: AK FL NV NH SD TN TX WA WY
A11: State Tax Rate (if any) | B11: 0 | D11: 0% for the 9 no-tax states; else your flat est.
A12: First Projection Year | B12: 2026
A13: PORTFOLIO BALANCES
A14: PORTFOLIO BALANCES (TODAY)
A15: Taxable Brokerage | B15: 350000
A16: Traditional 401k / IRA | B16: 650000
A17: Roth IRA / Roth 401k | B17: 150000
A18: Cash / Money Market | B18: 75000 | D18: Bridge buffer — counted in taxable cascade
A19: Total Portfolio (today) | B19: =B15+B16+B17+B18 -> 1225000
A21: SPENDING & INCOME
A22: Annual Spending (today $) | B22: 55000
A23: Inflation Rate | B23: 0.025
A24: Other Income ($/yr, today $) | B24: 0 | D24: Pension, rental, part-time — applied every year
A25: Estimated Social Security ($/yr today $) | B25: 24000 | D25: At claiming age
A26: ACA Household Size | B26: 2 | D26: People on your marketplace plan — sets the 400% FPL cliff
A27: RETURN ASSUMPTIONS
A28: Expected Return (nominal) | B28: 0.065 | D28: Long-run nominal. 60/40 ≈ 6–7%. Also the Monte Carlo mean.
A29: Portfolio Volatility (std dev) | B29: 0.12 | D29: Used by MONTE CARLO. 60/40 ≈ 10–12%
A31: AUTO-CALCULATED
A32: Bridge Length (years) | B32: =MAX(0, 59.5 - B6) -> 4.5
A33: Withdrawal Rate (at retirement) | B33: =B22*(1+B23)^MAX(0,B6-B5)/B35 -> 0.040026662
A34: Std Deduction (2026) | B34: =IF(B9="MFJ",32200,16100) -> 32200
A35: Portfolio at Retirement (est.) | B35: =B19*(1+B28)^MAX(0,B6-B5) -> 1479738.3 | D35: Today's balances grown at Expected Return to retirement — excludes new contributions

Sheet BRIDGE
A1: BRIDGE FUNDING PLAN · Retirement to Age 59½
A2: =IF(INPUTS!$B$32=0,"No bridge needed — retiring at or after age 59½. See POST-59.5 for your projection.","Withdrawal cascade: Taxable+Cash first → Roth → 401k. Starting balances = today's balances grown to retirement age.") -> Withdrawal cascade: Taxable+Cash first → Roth → 401k. Starting balances = today's balances grown to retirement age.
A3: Year | B3: Age | C3: Spending (Inflated) | D3: Other Income | E3: Net Needed | F3: Taxable+Cash Start | G3: Roth Start | H3: 401k Start | I3: From Taxable | J3: From Roth | K3: From 401k | L3: Taxable End | M3: Roth End | N3: 401k End | O3: Total End
A4: =IF(INPUTS!$B$32=0,"",IF(0>=INPUTS!$B$32,"",INPUTS!$B$12+(INPUTS!$B$6-INPUTS!$B$5)+0)) -> 2029 | B4: =IF(INPUTS!$B$32=0,"",IF(0>=INPUTS!$B$32,"",INPUTS!$B$6+0)) -> 55 | C4: =IF(INPUTS!$B$32=0,"",IF(0>=INPUTS!$B$32,"",INPUTS!$B$22*(1+INPUTS!$B$23)^(INPUTS!$B$6-INPUTS!$B$5+0))) -> 59228.984 | D4: =IF(INPUTS!$B$32=0,"",IF(0>=INPUTS!$B$32,"",INPUTS!$B$24)) -> 0 | E4: =IF(INPUTS!$B$32=0,"",IF(0>=INPUTS!$B$32,"",MAX(0,C4-D4))) -> 59228.984 | F4: =IF(INPUTS!$B$32=0,"",IF(0>=INPUTS!$B$32,"",(INPUTS!$B$15+INPUTS!$B$18)*(1+INPUTS!$B$28)^MAX(0,INPUTS!$B$6-INPUTS!$B$5))) -> 513378.59 | G4: =IF(INPUTS!$B$32=0,"",IF(0>=INPUTS!$B$32,"",INPUTS!$B$17*(1+INPUTS!$B$28)^MAX(0,INPUTS!$B$6-INPUTS!$B$5))) -> 181192.44 | H4: =IF(INPUTS!$B$32=0,"",IF(0>=INPUTS!$B$32,"",INPUTS!$B$16*(1+INPUTS!$B$28)^MAX(0,INPUTS!$B$6-INPUTS!$B$5))) -> 785167.26 | I4: =IF(INPUTS!$B$32=0,"",IF(0>=INPUTS!$B$32,"",MIN(E4,F4))) -> 59228.984 | J4: =IF(INPUTS!$B$32=0,"",IF(0>=INPUTS!$B$32,"",MIN(E4-I4,G4))) -> 0 | K4: =IF(INPUTS!$B$32=0,"",IF(0>=INPUTS!$B$32,"",MIN(E4-I4-J4,H4))) -> 0 | L4: =IF(INPUTS!$B$32=0,"",IF(0>=INPUTS!$B$32,"",(F4-I4)*(1+INPUTS!$B$28))) -> 483669.33 | M4: =IF(INPUTS!$B$32=0,"",IF(0>=INPUTS!$B$32,"",(G4-J4)*(1+INPUTS!$B$28))) -> 192969.95 | N4: =IF(INPUTS!$B$32=0,"",IF(0>=INPUTS!$B$32,"",(H4-K4)*(1+INPUTS!$B$28))) -> 836203.13 | O4: =IF(INPUTS!$B$32=0,"",IF(0>=INPUTS!$B$32,"",L4+M4+N4)) -> 1512842.4
A5: =IF(INPUTS!$B$32=0,"",IF(1>=INPUTS!$B$32,"",INPUTS!$B$12+(INPUTS!$B$6-INPUTS!$B$5)+1)) -> 2030 | B5: =IF(INPUTS!$B$32=0,"",IF(1>=INPUTS!$B$32,"",INPUTS!$B$6+1)) -> 56 | C5: =IF(INPUTS!$B$32=0,"",IF(1>=INPUTS!$B$32,"",INPUTS!$B$22*(1+INPUTS!$B$23)^(INPUTS!$B$6-INPUTS!$B$5+1))) -> 60709.709 | D5: =IF(INPUTS!$B$32=0,"",IF(1>=INPUTS!$B$32,"",INPUTS!$B$24)) -> 0 | E5: =IF(INPUTS!$B$32=0,"",IF(1>=INPUTS!$B$32,"",MAX(0,C5-D5))) -> 60709.709 | F5: =IF(INPUTS!$B$32=0,"",IF(1>=INPUTS!$B$32,"",L4)) -> 483669.33 | G5: =IF(INPUTS!$B$32=0,"",IF(1>=INPUTS!$B$32,"",M4)) -> 192969.95 | H5: =IF(INPUTS!$B$32=0,"",IF(1>=INPUTS!$B$32,"",N4)) -> 836203.13 | I5: =IF(INPUTS!$B$32=0,"",IF(1>=INPUTS!$B$32,"",MIN(E5,F5))) -> 60709.709 | J5: =IF(INPUTS!$B$32=0,"",IF(1>=INPUTS!$B$32,"",MIN(E5-I5,G5))) -> 0 | K5: =IF(INPUTS!$B$32=0,"",IF(1>=INPUTS!$B$32,"",MIN(E5-I5-J5,H5))) -> 0 | L5: =IF(INPUTS!$B$32=0,"",IF(1>=INPUTS!$B$32,"",(F5-I5)*(1+INPUTS!$B$28))) -> 450452 | M5: =IF(INPUTS!$B$32=0,"",IF(1>=INPUTS!$B$32,"",(G5-J5)*(1+INPUTS!$B$28))) -> 205513 | N5: =IF(INPUTS!$B$32=0,"",IF(1>=INPUTS!$B$32,"",(H5-K5)*(1+INPUTS!$B$28))) -> 890556.33 | O5: =IF(INPUTS!$B$32=0,"",IF(1>=INPUTS!$B$32,"",L5+M5+N5)) -> 1546521.3
A6: =IF(INPUTS!$B$32=0,"",IF(2>=INPUTS!$B$32,"",INPUTS!$B$12+(INPUTS!$B$6-INPUTS!$B$5)+2)) -> 2031 | B6: =IF(INPUTS!$B$32=0,"",IF(2>=INPUTS!$B$32,"",INPUTS!$B$6+2)) -> 57 | C6: =IF(INPUTS!$B$32=0,"",IF(2>=INPUTS!$B$32,"",INPUTS!$B$22*(1+INPUTS!$B$23)^(INPUTS!$B$6-INPUTS!$B$5+2))) -> 62227.452 | D6: =IF(INPUTS!$B$32=0,"",IF(2>=INPUTS!$B$32,"",INPUTS!$B$24)) -> 0 | E6: =IF(INPUTS!$B$32=0,"",IF(2>=INPUTS!$B$32,"",MAX(0,C6-D6))) -> 62227.452 | F6: =IF(INPUTS!$B$32=0,"",IF(2>=INPUTS!$B$32,"",L5)) -> 450452 | G6: =IF(INPUTS!$B$32=0,"",IF(2>=INPUTS!$B$32,"",M5)) -> 205513 | H6: =IF(INPUTS!$B$32=0,"",IF(2>=INPUTS!$B$32,"",N5)) -> 890556.33 | I6: =IF(INPUTS!$B$32=0,"",IF(2>=INPUTS!$B$32,"",MIN(E6,F6))) -> 62227.452 | J6: =IF(INPUTS!$B$32=0,"",IF(2>=INPUTS!$B$32,"",MIN(E6-I6,G6))) -> 0 | K6: =IF(INPUTS!$B$32=0,"",IF(2>=INPUTS!$B$32,"",MIN(E6-I6-J6,H6))) -> 0 | L6: =IF(INPUTS!$B$32=0,"",IF(2>=INPUTS!$B$32,"",(F6-I6)*(1+INPUTS!$B$28))) -> 413459.14 | M6: =IF(INPUTS!$B$32=0,"",IF(2>=INPUTS!$B$32,"",(G6-J6)*(1+INPUTS!$B$28))) -> 218871.34 | N6: =IF(INPUTS!$B$32=0,"",IF(2>=INPUTS!$B$32,"",(H6-K6)*(1+INPUTS!$B$28))) -> 948442.49 | O6: =IF(INPUTS!$B$32=0,"",IF(2>=INPUTS!$B$32,"",L6+M6+N6)) -> 1580773
A7: =IF(INPUTS!$B$32=0,"",IF(3>=INPUTS!$B$32,"",INPUTS!$B$12+(INPUTS!$B$6-INPUTS!$B$5)+3)) -> 2032 | B7: =IF(INPUTS!$B$32=0,"",IF(3>=INPUTS!$B$32,"",INPUTS!$B$6+3)) -> 58 | C7: =IF(INPUTS!$B$32=0,"",IF(3>=INPUTS!$B$32,"",INPUTS!$B$22*(1+INPUTS!$B$23)^(INPUTS!$B$6-INPUTS!$B$5+3))) -> 63783.138 | D7: =IF(INPUTS!$B$32=0,"",IF(3>=INPUTS!$B$32,"",INPUTS!$B$24)) -> 0 | E7: =IF(INPUTS!$B$32=0,"",IF(3>=INPUTS!$B$32,"",MAX(0,C7-D7))) -> 63783.138 | F7: =IF(INPUTS!$B$32=0,"",IF(3>=INPUTS!$B$32,"",L6)) -> 413459.14 | G7: =IF(INPUTS!$B$32=0,"",IF(3>=INPUTS!$B$32,"",M6)) -> 218871.34 | H7: =IF(INPUTS!$B$32=0,"",IF(3>=INPUTS!$B$32,"",N6)) -> 948442.49 | I7: =IF(INPUTS!$B$32=0,"",IF(3>=INPUTS!$B$32,"",MIN(E7,F7))) -> 63783.138 | J7: =IF(INPUTS!$B$32=0,"",IF(3>=INPUTS!$B$32,"",MIN(E7-I7,G7))) -> 0 | K7: =IF(INPUTS!$B$32=0,"",IF(3>=INPUTS!$B$32,"",MIN(E7-I7-J7,H7))) -> 0 | L7: =IF(INPUTS!$B$32=0,"",IF(3>=INPUTS!$B$32,"",(F7-I7)*(1+INPUTS!$B$28))) -> 372404.94 | M7: =IF(INPUTS!$B$32=0,"",IF(3>=INPUTS!$B$32,"",(G7-J7)*(1+INPUTS!$B$28))) -> 233097.98 | N7: =IF(INPUTS!$B$32=0,"",IF(3>=INPUTS!$B$32,"",(H7-K7)*(1+INPUTS!$B$28))) -> 1010091.3 | O7: =IF(INPUTS!$B$32=0,"",IF(3>=INPUTS!$B$32,"",L7+M7+N7)) -> 1615594.2
A8: =IF(INPUTS!$B$32=0,"",IF(4>=INPUTS!$B$32,"",INPUTS!$B$12+(INPUTS!$B$6-INPUTS!$B$5)+4)) -> 2033 | B8: =IF(INPUTS!$B$32=0,"",IF(4>=INPUTS!$B$32,"",INPUTS!$B$6+4)) -> 59 | C8: =IF(INPUTS!$B$32=0,"",IF(4>=INPUTS!$B$32,"",INPUTS!$B$22*(1+INPUTS!$B$23)^(INPUTS!$B$6-INPUTS!$B$5+4))) -> 65377.716 | D8: =IF(INPUTS!$B$32=0,"",IF(4>=INPUTS!$B$32,"",INPUTS!$B$24)) -> 0 | E8: =IF(INPUTS!$B$32=0,"",IF(4>=INPUTS!$B$32,"",MAX(0,C8-D8))) -> 65377.716 | F8: =IF(INPUTS!$B$32=0,"",IF(4>=INPUTS!$B$32,"",L7)) -> 372404.94 | G8: =IF(INPUTS!$B$32=0,"",IF(4>=INPUTS!$B$32,"",M7)) -> 233097.98 | H8: =IF(INPUTS!$B$32=0,"",IF(4>=INPUTS!$B$32,"",N7)) -> 1010091.3 | I8: =IF(INPUTS!$B$32=0,"",IF(4>=INPUTS!$B$32,"",MIN(E8,F8))) -> 65377.716 | J8: =IF(INPUTS!$B$32=0,"",IF(4>=INPUTS!$B$32,"",MIN(E8-I8,G8))) -> 0 | K8: =IF(INPUTS!$B$32=0,"",IF(4>=INPUTS!$B$32,"",MIN(E8-I8-J8,H8))) -> 0 | L8: =IF(INPUTS!$B$32=0,"",IF(4>=INPUTS!$B$32,"",(F8-I8)*(1+INPUTS!$B$28))) -> 326984 | M8: =IF(INPUTS!$B$32=0,"",IF(4>=INPUTS!$B$32,"",(G8-J8)*(1+INPUTS!$B$28))) -> 248249.35 | N8: =IF(INPUTS!$B$32=0,"",IF(4>=INPUTS!$B$32,"",(H8-K8)*(1+INPUTS!$B$28))) -> 1075747.2 | O8: =IF(INPUTS!$B$32=0,"",IF(4>=INPUTS!$B$32,"",L8+M8+N8)) -> 1650980.5
A9: =IF(INPUTS!$B$32=0,"",IF(5>=INPUTS!$B$32,"",INPUTS!$B$12+(INPUTS!$B$6-INPUTS!$B$5)+5)) | B9: =IF(INPUTS!$B$32=0,"",IF(5>=INPUTS!$B$32,"",INPUTS!$B$6+5)) | C9: =IF(INPUTS!$B$32=0,"",IF(5>=INPUTS!$B$32,"",INPUTS!$B$22*(1+INPUTS!$B$23)^(INPUTS!$B$6-INPUTS!$B$5+5))) | D9: =IF(INPUTS!$B$32=0,"",IF(5>=INPUTS!$B$32,"",INPUTS!$B$24)) | E9: =IF(INPUTS!$B$32=0,"",IF(5>=INPUTS!$B$32,"",MAX(0,C9-D9))) | F9: =IF(INPUTS!$B$32=0,"",IF(5>=INPUTS!$B$32,"",L8)) | G9: =IF(INPUTS!$B$32=0,"",IF(5>=INPUTS!$B$32,"",M8)) | H9: =IF(INPUTS!$B$32=0,"",IF(5>=INPUTS!$B$32,"",N8)) | I9: =IF(INPUTS!$B$32=0,"",IF(5>=INPUTS!$B$32,"",MIN(E9,F9))) | J9: =IF(INPUTS!$B$32=0,"",IF(5>=INPUTS!$B$32,"",MIN(E9-I9,G9))) | K9: =IF(INPUTS!$B$32=0,"",IF(5>=INPUTS!$B$32,"",MIN(E9-I9-J9,H9))) | L9: =IF(INPUTS!$B$32=0,"",IF(5>=INPUTS!$B$32,"",(F9-I9)*(1+INPUTS!$B$28))) | M9: =IF(INPUTS!$B$32=0,"",IF(5>=INPUTS!$B$32,"",(G9-J9)*(1+INPUTS!$B$28))) | N9: =IF(INPUTS!$B$32=0,"",IF(5>=INPUTS!$B$32,"",(H9-K9)*(1+INPUTS!$B$28))) | O9: =IF(INPUTS!$B$32=0,"",IF(5>=INPUTS!$B$32,"",L9+M9+N9))
A10: =IF(INPUTS!$B$32=0,"",IF(6>=INPUTS!$B$32,"",INPUTS!$B$12+(INPUTS!$B$6-INPUTS!$B$5)+6)) | B10: =IF(INPUTS!$B$32=0,"",IF(6>=INPUTS!$B$32,"",INPUTS!$B$6+6)) | C10: =IF(INPUTS!$B$32=0,"",IF(6>=INPUTS!$B$32,"",INPUTS!$B$22*(1+INPUTS!$B$23)^(INPUTS!$B$6-INPUTS!$B$5+6))) | D10: =IF(INPUTS!$B$32=0,"",IF(6>=INPUTS!$B$32,"",INPUTS!$B$24)) | E10: =IF(INPUTS!$B$32=0,"",IF(6>=INPUTS!$B$32,"",MAX(0,C10-D10))) | F10: =IF(INPUTS!$B$32=0,"",IF(6>=INPUTS!$B$32,"",L9)) | G10: =IF(INPUTS!$B$32=0,"",IF(6>=INPUTS!$B$32,"",M9)) | H10: =IF(INPUTS!$B$32=0,"",IF(6>=INPUTS!$B$32,"",N9)) | I10: =IF(INPUTS!$B$32=0,"",IF(6>=INPUTS!$B$32,"",MIN(E10,F10))) | J10: =IF(INPUTS!$B$32=0,"",IF(6>=INPUTS!$B$32,"",MIN(E10-I10,G10))) | K10: =IF(INPUTS!$B$32=0,"",IF(6>=INPUTS!$B$32,"",MIN(E10-I10-J10,H10))) | L10: =IF(INPUTS!$B$32=0,"",IF(6>=INPUTS!$B$32,"",(F10-I10)*(1+INPUTS!$B$28))) | M10: =IF(INPUTS!$B$32=0,"",IF(6>=INPUTS!$B$32,"",(G10-J10)*(1+INPUTS!$B$28))) | N10: =IF(INPUTS!$B$32=0,"",IF(6>=INPUTS!$B$32,"",(H10-K10)*(1+INPUTS!$B$28))) | O10: =IF(INPUTS!$B$32=0,"",IF(6>=INPUTS!$B$32,"",L10+M10+N10))
A11: =IF(INPUTS!$B$32=0,"",IF(7>=INPUTS!$B$32,"",INPUTS!$B$12+(INPUTS!$B$6-INPUTS!$B$5)+7)) | B11: =IF(INPUTS!$B$32=0,"",IF(7>=INPUTS!$B$32,"",INPUTS!$B$6+7)) | C11: =IF(INPUTS!$B$32=0,"",IF(7>=INPUTS!$B$32,"",INPUTS!$B$22*(1+INPUTS!$B$23)^(INPUTS!$B$6-INPUTS!$B$5+7))) | D11: =IF(INPUTS!$B$32=0,"",IF(7>=INPUTS!$B$32,"",INPUTS!$B$24)) | E11: =IF(INPUTS!$B$32=0,"",IF(7>=INPUTS!$B$32,"",MAX(0,C11-D11))) | F11: =IF(INPUTS!$B$32=0,"",IF(7>=INPUTS!$B$32,"",L10)) | G11: =IF(INPUTS!$B$32=0,"",IF(7>=INPUTS!$B$32,"",M10)) | H11: =IF(INPUTS!$B$32=0,"",IF(7>=INPUTS!$B$32,"",N10)) | I11: =IF(INPUTS!$B$32=0,"",IF(7>=INPUTS!$B$32,"",MIN(E11,F11))) | J11: =IF(INPUTS!$B$32=0,"",IF(7>=INPUTS!$B$32,"",MIN(E11-I11,G11))) | K11: =IF(INPUTS!$B$32=0,"",IF(7>=INPUTS!$B$32,"",MIN(E11-I11-J11,H11))) | L11: =IF(INPUTS!$B$32=0,"",IF(7>=INPUTS!$B$32,"",(F11-I11)*(1+INPUTS!$B$28))) | M11: =IF(INPUTS!$B$32=0,"",IF(7>=INPUTS!$B$32,"",(G11-J11)*(1+INPUTS!$B$28))) | N11: =IF(INPUTS!$B$32=0,"",IF(7>=INPUTS!$B$32,"",(H11-K11)*(1+INPUTS!$B$28))) | O11: =IF(INPUTS!$B$32=0,"",IF(7>=INPUTS!$B$32,"",L11+M11+N11))
A12: =IF(INPUTS!$B$32=0,"",IF(8>=INPUTS!$B$32,"",INPUTS!$B$12+(INPUTS!$B$6-INPUTS!$B$5)+8)) | B12: =IF(INPUTS!$B$32=0,"",IF(8>=INPUTS!$B$32,"",INPUTS!$B$6+8)) | C12: =IF(INPUTS!$B$32=0,"",IF(8>=INPUTS!$B$32,"",INPUTS!$B$22*(1+INPUTS!$B$23)^(INPUTS!$B$6-INPUTS!$B$5+8))) | D12: =IF(INPUTS!$B$32=0,"",IF(8>=INPUTS!$B$32,"",INPUTS!$B$24)) | E12: =IF(INPUTS!$B$32=0,"",IF(8>=INPUTS!$B$32,"",MAX(0,C12-D12))) | F12: =IF(INPUTS!$B$32=0,"",IF(8>=INPUTS!$B$32,"",L11)) | G12: =IF(INPUTS!$B$32=0,"",IF(8>=INPUTS!$B$32,"",M11)) | H12: =IF(INPUTS!$B$32=0,"",IF(8>=INPUTS!$B$32,"",N11)) | I12: =IF(INPUTS!$B$32=0,"",IF(8>=INPUTS!$B$32,"",MIN(E12,F12))) | J12: =IF(INPUTS!$B$32=0,"",IF(8>=INPUTS!$B$32,"",MIN(E12-I12,G12))) | K12: =IF(INPUTS!$B$32=0,"",IF(8>=INPUTS!$B$32,"",MIN(E12-I12-J12,H12))) | L12: =IF(INPUTS!$B$32=0,"",IF(8>=INPUTS!$B$32,"",(F12-I12)*(1+INPUTS!$B$28))) | M12: =IF(INPUTS!$B$32=0,"",IF(8>=INPUTS!$B$32,"",(G12-J12)*(1+INPUTS!$B$28))) | N12: =IF(INPUTS!$B$32=0,"",IF(8>=INPUTS!$B$32,"",(H12-K12)*(1+INPUTS!$B$28))) | O12: =IF(INPUTS!$B$32=0,"",IF(8>=INPUTS!$B$32,"",L12+M12+N12))
A13: =IF(INPUTS!$B$32=0,"",IF(9>=INPUTS!$B$32,"",INPUTS!$B$12+(INPUTS!$B$6-INPUTS!$B$5)+9)) | B13: =IF(INPUTS!$B$32=0,"",IF(9>=INPUTS!$B$32,"",INPUTS!$B$6+9)) | C13: =IF(INPUTS!$B$32=0,"",IF(9>=INPUTS!$B$32,"",INPUTS!$B$22*(1+INPUTS!$B$23)^(INPUTS!$B$6-INPUTS!$B$5+9))) | D13: =IF(INPUTS!$B$32=0,"",IF(9>=INPUTS!$B$32,"",INPUTS!$B$24)) | E13: =IF(INPUTS!$B$32=0,"",IF(9>=INPUTS!$B$32,"",MAX(0,C13-D13))) | F13: =IF(INPUTS!$B$32=0,"",IF(9>=INPUTS!$B$32,"",L12)) | G13: =IF(INPUTS!$B$32=0,"",IF(9>=INPUTS!$B$32,"",M12)) | H13: =IF(INPUTS!$B$32=0,"",IF(9>=INPUTS!$B$32,"",N12)) | I13: =IF(INPUTS!$B$32=0,"",IF(9>=INPUTS!$B$32,"",MIN(E13,F13))) | J13: =IF(INPUTS!$B$32=0,"",IF(9>=INPUTS!$B$32,"",MIN(E13-I13,G13))) | K13: =IF(INPUTS!$B$32=0,"",IF(9>=INPUTS!$B$32,"",MIN(E13-I13-J13,H13))) | L13: =IF(INPUTS!$B$32=0,"",IF(9>=INPUTS!$B$32,"",(F13-I13)*(1+INPUTS!$B$28))) | M13: =IF(INPUTS!$B$32=0,"",IF(9>=INPUTS!$B$32,"",(G13-J13)*(1+INPUTS!$B$28))) | N13: =IF(INPUTS!$B$32=0,"",IF(9>=INPUTS!$B$32,"",(H13-K13)*(1+INPUTS!$B$28))) | O13: =IF(INPUTS!$B$32=0,"",IF(9>=INPUTS!$B$32,"",L13+M13+N13))
A14: =IF(INPUTS!$B$32=0,"",IF(10>=INPUTS!$B$32,"",INPUTS!$B$12+(INPUTS!$B$6-INPUTS!$B$5)+10)) | B14: =IF(INPUTS!$B$32=0,"",IF(10>=INPUTS!$B$32,"",INPUTS!$B$6+10)) | C14: =IF(INPUTS!$B$32=0,"",IF(10>=INPUTS!$B$32,"",INPUTS!$B$22*(1+INPUTS!$B$23)^(INPUTS!$B$6-INPUTS!$B$5+10))) | D14: =IF(INPUTS!$B$32=0,"",IF(10>=INPUTS!$B$32,"",INPUTS!$B$24)) | E14: =IF(INPUTS!$B$32=0,"",IF(10>=INPUTS!$B$32,"",MAX(0,C14-D14))) | F14: =IF(INPUTS!$B$32=0,"",IF(10>=INPUTS!$B$32,"",L13)) | G14: =IF(INPUTS!$B$32=0,"",IF(10>=INPUTS!$B$32,"",M13)) | H14: =IF(INPUTS!$B$32=0,"",IF(10>=INPUTS!$B$32,"",N13)) | I14: =IF(INPUTS!$B$32=0,"",IF(10>=INPUTS!$B$32,"",MIN(E14,F14))) | J14: =IF(INPUTS!$B$32=0,"",IF(10>=INPUTS!$B$32,"",MIN(E14-I14,G14))) | K14: =IF(INPUTS!$B$32=0,"",IF(10>=INPUTS!$B$32,"",MIN(E14-I14-J14,H14))) | L14: =IF(INPUTS!$B$32=0,"",IF(10>=INPUTS!$B$32,"",(F14-I14)*(1+INPUTS!$B$28))) | M14: =IF(INPUTS!$B$32=0,"",IF(10>=INPUTS!$B$32,"",(G14-J14)*(1+INPUTS!$B$28))) | N14: =IF(INPUTS!$B$32=0,"",IF(10>=INPUTS!$B$32,"",(H14-K14)*(1+INPUTS!$B$28))) | O14: =IF(INPUTS!$B$32=0,"",IF(10>=INPUTS!$B$32,"",L14+M14+N14))
A15: =IF(INPUTS!$B$32=0,"",IF(11>=INPUTS!$B$32,"",INPUTS!$B$12+(INPUTS!$B$6-INPUTS!$B$5)+11)) | B15: =IF(INPUTS!$B$32=0,"",IF(11>=INPUTS!$B$32,"",INPUTS!$B$6+11)) | C15: =IF(INPUTS!$B$32=0,"",IF(11>=INPUTS!$B$32,"",INPUTS!$B$22*(1+INPUTS!$B$23)^(INPUTS!$B$6-INPUTS!$B$5+11))) | D15: =IF(INPUTS!$B$32=0,"",IF(11>=INPUTS!$B$32,"",INPUTS!$B$24)) | E15: =IF(INPUTS!$B$32=0,"",IF(11>=INPUTS!$B$32,"",MAX(0,C15-D15))) | F15: =IF(INPUTS!$B$32=0,"",IF(11>=INPUTS!$B$32,"",L14)) | G15: =IF(INPUTS!$B$32=0,"",IF(11>=INPUTS!$B$32,"",M14)) | H15: =IF(INPUTS!$B$32=0,"",IF(11>=INPUTS!$B$32,"",N14)) | I15: =IF(INPUTS!$B$32=0,"",IF(11>=INPUTS!$B$32,"",MIN(E15,F15))) | J15: =IF(INPUTS!$B$32=0,"",IF(11>=INPUTS!$B$32,"",MIN(E15-I15,G15))) | K15: =IF(INPUTS!$B$32=0,"",IF(11>=INPUTS!$B$32,"",MIN(E15-I15-J15,H15))) | L15: =IF(INPUTS!$B$32=0,"",IF(11>=INPUTS!$B$32,"",(F15-I15)*(1+INPUTS!$B$28))) | M15: =IF(INPUTS!$B$32=0,"",IF(11>=INPUTS!$B$32,"",(G15-J15)*(1+INPUTS!$B$28))) | N15: =IF(INPUTS!$B$32=0,"",IF(11>=INPUTS!$B$32,"",(H15-K15)*(1+INPUTS!$B$28))) | O15: =IF(INPUTS!$B$32=0,"",IF(11>=INPUTS!$B$32,"",L15+M15+N15))
A16: =IF(INPUTS!$B$32=0,"",IF(12>=INPUTS!$B$32,"",INPUTS!$B$12+(INPUTS!$B$6-INPUTS!$B$5)+12)) | B16: =IF(INPUTS!$B$32=0,"",IF(12>=INPUTS!$B$32,"",INPUTS!$B$6+12)) | C16: =IF(INPUTS!$B$32=0,"",IF(12>=INPUTS!$B$32,"",INPUTS!$B$22*(1+INPUTS!$B$23)^(INPUTS!$B$6-INPUTS!$B$5+12))) | D16: =IF(INPUTS!$B$32=0,"",IF(12>=INPUTS!$B$32,"",INPUTS!$B$24)) | E16: =IF(INPUTS!$B$32=0,"",IF(12>=INPUTS!$B$32,"",MAX(0,C16-D16))) | F16: =IF(INPUTS!$B$32=0,"",IF(12>=INPUTS!$B$32,"",L15)) | G16: =IF(INPUTS!$B$32=0,"",IF(12>=INPUTS!$B$32,"",M15)) | H16: =IF(INPUTS!$B$32=0,"",IF(12>=INPUTS!$B$32,"",N15)) | I16: =IF(INPUTS!$B$32=0,"",IF(12>=INPUTS!$B$32,"",MIN(E16,F16))) | J16: =IF(INPUTS!$B$32=0,"",IF(12>=INPUTS!$B$32,"",MIN(E16-I16,G16))) | K16: =IF(INPUTS!$B$32=0,"",IF(12>=INPUTS!$B$32,"",MIN(E16-I16-J16,H16))) | L16: =IF(INPUTS!$B$32=0,"",IF(12>=INPUTS!$B$32,"",(F16-I16)*(1+INPUTS!$B$28))) | M16: =IF(INPUTS!$B$32=0,"",IF(12>=INPUTS!$B$32,"",(G16-J16)*(1+INPUTS!$B$28))) | N16: =IF(INPUTS!$B$32=0,"",IF(12>=INPUTS!$B$32,"",(H16-K16)*(1+INPUTS!$B$28))) | O16: =IF(INPUTS!$B$32=0,"",IF(12>=INPUTS!$B$32,"",L16+M16+N16))
A17: =IF(INPUTS!$B$32=0,"",IF(13>=INPUTS!$B$32,"",INPUTS!$B$12+(INPUTS!$B$6-INPUTS!$B$5)+13)) | B17: =IF(INPUTS!$B$32=0,"",IF(13>=INPUTS!$B$32,"",INPUTS!$B$6+13)) | C17: =IF(INPUTS!$B$32=0,"",IF(13>=INPUTS!$B$32,"",INPUTS!$B$22*(1+INPUTS!$B$23)^(INPUTS!$B$6-INPUTS!$B$5+13))) | D17: =IF(INPUTS!$B$32=0,"",IF(13>=INPUTS!$B$32,"",INPUTS!$B$24)) | E17: =IF(INPUTS!$B$32=0,"",IF(13>=INPUTS!$B$32,"",MAX(0,C17-D17))) | F17: =IF(INPUTS!$B$32=0,"",IF(13>=INPUTS!$B$32,"",L16)) | G17: =IF(INPUTS!$B$32=0,"",IF(13>=INPUTS!$B$32,"",M16)) | H17: =IF(INPUTS!$B$32=0,"",IF(13>=INPUTS!$B$32,"",N16)) | I17: =IF(INPUTS!$B$32=0,"",IF(13>=INPUTS!$B$32,"",MIN(E17,F17))) | J17: =IF(INPUTS!$B$32=0,"",IF(13>=INPUTS!$B$32,"",MIN(E17-I17,G17))) | K17: =IF(INPUTS!$B$32=0,"",IF(13>=INPUTS!$B$32,"",MIN(E17-I17-J17,H17))) | L17: =IF(INPUTS!$B$32=0,"",IF(13>=INPUTS!$B$32,"",(F17-I17)*(1+INPUTS!$B$28))) | M17: =IF(INPUTS!$B$32=0,"",IF(13>=INPUTS!$B$32,"",(G17-J17)*(1+INPUTS!$B$28))) | N17: =IF(INPUTS!$B$32=0,"",IF(13>=INPUTS!$B$32,"",(H17-K17)*(1+INPUTS!$B$28))) | O17: =IF(INPUTS!$B$32=0,"",IF(13>=INPUTS!$B$32,"",L17+M17+N17))
A18: =IF(INPUTS!$B$32=0,"",IF(14>=INPUTS!$B$32,"",INPUTS!$B$12+(INPUTS!$B$6-INPUTS!$B$5)+14)) | B18: =IF(INPUTS!$B$32=0,"",IF(14>=INPUTS!$B$32,"",INPUTS!$B$6+14)) | C18: =IF(INPUTS!$B$32=0,"",IF(14>=INPUTS!$B$32,"",INPUTS!$B$22*(1+INPUTS!$B$23)^(INPUTS!$B$6-INPUTS!$B$5+14))) | D18: =IF(INPUTS!$B$32=0,"",IF(14>=INPUTS!$B$32,"",INPUTS!$B$24)) | E18: =IF(INPUTS!$B$32=0,"",IF(14>=INPUTS!$B$32,"",MAX(0,C18-D18))) | F18: =IF(INPUTS!$B$32=0,"",IF(14>=INPUTS!$B$32,"",L17)) | G18: =IF(INPUTS!$B$32=0,"",IF(14>=INPUTS!$B$32,"",M17)) | H18: =IF(INPUTS!$B$32=0,"",IF(14>=INPUTS!$B$32,"",N17)) | I18: =IF(INPUTS!$B$32=0,"",IF(14>=INPUTS!$B$32,"",MIN(E18,F18))) | J18: =IF(INPUTS!$B$32=0,"",IF(14>=INPUTS!$B$32,"",MIN(E18-I18,G18))) | K18: =IF(INPUTS!$B$32=0,"",IF(14>=INPUTS!$B$32,"",MIN(E18-I18-J18,H18))) | L18: =IF(INPUTS!$B$32=0,"",IF(14>=INPUTS!$B$32,"",(F18-I18)*(1+INPUTS!$B$28))) | M18: =IF(INPUTS!$B$32=0,"",IF(14>=INPUTS!$B$32,"",(G18-J18)*(1+INPUTS!$B$28))) | N18: =IF(INPUTS!$B$32=0,"",IF(14>=INPUTS!$B$32,"",(H18-K18)*(1+INPUTS!$B$28))) | O18: =IF(INPUTS!$B$32=0,"",IF(14>=INPUTS!$B$32,"",L18+M18+N18))
A19: =IF(INPUTS!$B$32=0,"",IF(15>=INPUTS!$B$32,"",INPUTS!$B$12+(INPUTS!$B$6-INPUTS!$B$5)+15)) | B19: =IF(INPUTS!$B$32=0,"",IF(15>=INPUTS!$B$32,"",INPUTS!$B$6+15)) | C19: =IF(INPUTS!$B$32=0,"",IF(15>=INPUTS!$B$32,"",INPUTS!$B$22*(1+INPUTS!$B$23)^(INPUTS!$B$6-INPUTS!$B$5+15))) | D19: =IF(INPUTS!$B$32=0,"",IF(15>=INPUTS!$B$32,"",INPUTS!$B$24)) | E19: =IF(INPUTS!$B$32=0,"",IF(15>=INPUTS!$B$32,"",MAX(0,C19-D19))) | F19: =IF(INPUTS!$B$32=0,"",IF(15>=INPUTS!$B$32,"",L18)) | G19: =IF(INPUTS!$B$32=0,"",IF(15>=INPUTS!$B$32,"",M18)) | H19: =IF(INPUTS!$B$32=0,"",IF(15>=INPUTS!$B$32,"",N18)) | I19: =IF(INPUTS!$B$32=0,"",IF(15>=INPUTS!$B$32,"",MIN(E19,F19))) | J19: =IF(INPUTS!$B$32=0,"",IF(15>=INPUTS!$B$32,"",MIN(E19-I19,G19))) | K19: =IF(INPUTS!$B$32=0,"",IF(15>=INPUTS!$B$32,"",MIN(E19-I19-J19,H19))) | L19: =IF(INPUTS!$B$32=0,"",IF(15>=INPUTS!$B$32,"",(F19-I19)*(1+INPUTS!$B$28))) | M19: =IF(INPUTS!$B$32=0,"",IF(15>=INPUTS!$B$32,"",(G19-J19)*(1+INPUTS!$B$28))) | N19: =IF(INPUTS!$B$32=0,"",IF(15>=INPUTS!$B$32,"",(H19-K19)*(1+INPUTS!$B$28))) | O19: =IF(INPUTS!$B$32=0,"",IF(15>=INPUTS!$B$32,"",L19+M19+N19))
A20: =IF(INPUTS!$B$32=0,"",IF(16>=INPUTS!$B$32,"",INPUTS!$B$12+(INPUTS!$B$6-INPUTS!$B$5)+16)) | B20: =IF(INPUTS!$B$32=0,"",IF(16>=INPUTS!$B$32,"",INPUTS!$B$6+16)) | C20: =IF(INPUTS!$B$32=0,"",IF(16>=INPUTS!$B$32,"",INPUTS!$B$22*(1+INPUTS!$B$23)^(INPUTS!$B$6-INPUTS!$B$5+16))) | D20: =IF(INPUTS!$B$32=0,"",IF(16>=INPUTS!$B$32,"",INPUTS!$B$24)) | E20: =IF(INPUTS!$B$32=0,"",IF(16>=INPUTS!$B$32,"",MAX(0,C20-D20))) | F20: =IF(INPUTS!$B$32=0,"",IF(16>=INPUTS!$B$32,"",L19)) | G20: =IF(INPUTS!$B$32=0,"",IF(16>=INPUTS!$B$32,"",M19)) | H20: =IF(INPUTS!$B$32=0,"",IF(16>=INPUTS!$B$32,"",N19)) | I20: =IF(INPUTS!$B$32=0,"",IF(16>=INPUTS!$B$32,"",MIN(E20,F20))) | J20: =IF(INPUTS!$B$32=0,"",IF(16>=INPUTS!$B$32,"",MIN(E20-I20,G20))) | K20: =IF(INPUTS!$B$32=0,"",IF(16>=INPUTS!$B$32,"",MIN(E20-I20-J20,H20))) | L20: =IF(INPUTS!$B$32=0,"",IF(16>=INPUTS!$B$32,"",(F20-I20)*(1+INPUTS!$B$28))) | M20: =IF(INPUTS!$B$32=0,"",IF(16>=INPUTS!$B$32,"",(G20-J20)*(1+INPUTS!$B$28))) | N20: =IF(INPUTS!$B$32=0,"",IF(16>=INPUTS!$B$32,"",(H20-K20)*(1+INPUTS!$B$28))) | O20: =IF(INPUTS!$B$32=0,"",IF(16>=INPUTS!$B$32,"",L20+M20+N20))
A21: =IF(INPUTS!$B$32=0,"",IF(17>=INPUTS!$B$32,"",INPUTS!$B$12+(INPUTS!$B$6-INPUTS!$B$5)+17)) | B21: =IF(INPUTS!$B$32=0,"",IF(17>=INPUTS!$B$32,"",INPUTS!$B$6+17)) | C21: =IF(INPUTS!$B$32=0,"",IF(17>=INPUTS!$B$32,"",INPUTS!$B$22*(1+INPUTS!$B$23)^(INPUTS!$B$6-INPUTS!$B$5+17))) | D21: =IF(INPUTS!$B$32=0,"",IF(17>=INPUTS!$B$32,"",INPUTS!$B$24)) | E21: =IF(INPUTS!$B$32=0,"",IF(17>=INPUTS!$B$32,"",MAX(0,C21-D21))) | F21: =IF(INPUTS!$B$32=0,"",IF(17>=INPUTS!$B$32,"",L20)) | G21: =IF(INPUTS!$B$32=0,"",IF(17>=INPUTS!$B$32,"",M20)) | H21: =IF(INPUTS!$B$32=0,"",IF(17>=INPUTS!$B$32,"",N20)) | I21: =IF(INPUTS!$B$32=0,"",IF(17>=INPUTS!$B$32,"",MIN(E21,F21))) | J21: =IF(INPUTS!$B$32=0,"",IF(17>=INPUTS!$B$32,"",MIN(E21-I21,G21))) | K21: =IF(INPUTS!$B$32=0,"",IF(17>=INPUTS!$B$32,"",MIN(E21-I21-J21,H21))) | L21: =IF(INPUTS!$B$32=0,"",IF(17>=INPUTS!$B$32,"",(F21-I21)*(1+INPUTS!$B$28))) | M21: =IF(INPUTS!$B$32=0,"",IF(17>=INPUTS!$B$32,"",(G21-J21)*(1+INPUTS!$B$28))) | N21: =IF(INPUTS!$B$32=0,"",IF(17>=INPUTS!$B$32,"",(H21-K21)*(1+INPUTS!$B$28))) | O21: =IF(INPUTS!$B$32=0,"",IF(17>=INPUTS!$B$32,"",L21+M21+N21))
A22: =IF(INPUTS!$B$32=0,"",IF(18>=INPUTS!$B$32,"",INPUTS!$B$12+(INPUTS!$B$6-INPUTS!$B$5)+18)) | B22: =IF(INPUTS!$B$32=0,"",IF(18>=INPUTS!$B$32,"",INPUTS!$B$6+18)) | C22: =IF(INPUTS!$B$32=0,"",IF(18>=INPUTS!$B$32,"",INPUTS!$B$22*(1+INPUTS!$B$23)^(INPUTS!$B$6-INPUTS!$B$5+18))) | D22: =IF(INPUTS!$B$32=0,"",IF(18>=INPUTS!$B$32,"",INPUTS!$B$24)) | E22: =IF(INPUTS!$B$32=0,"",IF(18>=INPUTS!$B$32,"",MAX(0,C22-D22))) | F22: =IF(INPUTS!$B$32=0,"",IF(18>=INPUTS!$B$32,"",L21)) | G22: =IF(INPUTS!$B$32=0,"",IF(18>=INPUTS!$B$32,"",M21)) | H22: =IF(INPUTS!$B$32=0,"",IF(18>=INPUTS!$B$32,"",N21)) | I22: =IF(INPUTS!$B$32=0,"",IF(18>=INPUTS!$B$32,"",MIN(E22,F22))) | J22: =IF(INPUTS!$B$32=0,"",IF(18>=INPUTS!$B$32,"",MIN(E22-I22,G22))) | K22: =IF(INPUTS!$B$32=0,"",IF(18>=INPUTS!$B$32,"",MIN(E22-I22-J22,H22))) | L22: =IF(INPUTS!$B$32=0,"",IF(18>=INPUTS!$B$32,"",(F22-I22)*(1+INPUTS!$B$28))) | M22: =IF(INPUTS!$B$32=0,"",IF(18>=INPUTS!$B$32,"",(G22-J22)*(1+INPUTS!$B$28))) | N22: =IF(INPUTS!$B$32=0,"",IF(18>=INPUTS!$B$32,"",(H22-K22)*(1+INPUTS!$B$28))) | O22: =IF(INPUTS!$B$32=0,"",IF(18>=INPUTS!$B$32,"",L22+M22+N22))
A23: =IF(INPUTS!$B$32=0,"",IF(19>=INPUTS!$B$32,"",INPUTS!$B$12+(INPUTS!$B$6-INPUTS!$B$5)+19)) | B23: =IF(INPUTS!$B$32=0,"",IF(19>=INPUTS!$B$32,"",INPUTS!$B$6+19)) | C23: =IF(INPUTS!$B$32=0,"",IF(19>=INPUTS!$B$32,"",INPUTS!$B$22*(1+INPUTS!$B$23)^(INPUTS!$B$6-INPUTS!$B$5+19))) | D23: =IF(INPUTS!$B$32=0,"",IF(19>=INPUTS!$B$32,"",INPUTS!$B$24)) | E23: =IF(INPUTS!$B$32=0,"",IF(19>=INPUTS!$B$32,"",MAX(0,C23-D23))) | F23: =IF(INPUTS!$B$32=0,"",IF(19>=INPUTS!$B$32,"",L22)) | G23: =IF(INPUTS!$B$32=0,"",IF(19>=INPUTS!$B$32,"",M22)) | H23: =IF(INPUTS!$B$32=0,"",IF(19>=INPUTS!$B$32,"",N22)) | I23: =IF(INPUTS!$B$32=0,"",IF(19>=INPUTS!$B$32,"",MIN(E23,F23))) | J23: =IF(INPUTS!$B$32=0,"",IF(19>=INPUTS!$B$32,"",MIN(E23-I23,G23))) | K23: =IF(INPUTS!$B$32=0,"",IF(19>=INPUTS!$B$32,"",MIN(E23-I23-J23,H23))) | L23: =IF(INPUTS!$B$32=0,"",IF(19>=INPUTS!$B$32,"",(F23-I23)*(1+INPUTS!$B$28))) | M23: =IF(INPUTS!$B$32=0,"",IF(19>=INPUTS!$B$32,"",(G23-J23)*(1+INPUTS!$B$28))) | N23: =IF(INPUTS!$B$32=0,"",IF(19>=INPUTS!$B$32,"",(H23-K23)*(1+INPUTS!$B$28))) | O23: =IF(INPUTS!$B$32=0,"",IF(19>=INPUTS!$B$32,"",L23+M23+N23))
A24: =IF(INPUTS!$B$32=0,"",IF(20>=INPUTS!$B$32,"",INPUTS!$B$12+(INPUTS!$B$6-INPUTS!$B$5)+20)) | B24: =IF(INPUTS!$B$32=0,"",IF(20>=INPUTS!$B$32,"",INPUTS!$B$6+20)) | C24: =IF(INPUTS!$B$32=0,"",IF(20>=INPUTS!$B$32,"",INPUTS!$B$22*(1+INPUTS!$B$23)^(INPUTS!$B$6-INPUTS!$B$5+20))) | D24: =IF(INPUTS!$B$32=0,"",IF(20>=INPUTS!$B$32,"",INPUTS!$B$24)) | E24: =IF(INPUTS!$B$32=0,"",IF(20>=INPUTS!$B$32,"",MAX(0,C24-D24))) | F24: =IF(INPUTS!$B$32=0,"",IF(20>=INPUTS!$B$32,"",L23)) | G24: =IF(INPUTS!$B$32=0,"",IF(20>=INPUTS!$B$32,"",M23)) | H24: =IF(INPUTS!$B$32=0,"",IF(20>=INPUTS!$B$32,"",N23)) | I24: =IF(INPUTS!$B$32=0,"",IF(20>=INPUTS!$B$32,"",MIN(E24,F24))) | J24: =IF(INPUTS!$B$32=0,"",IF(20>=INPUTS!$B$32,"",MIN(E24-I24,G24))) | K24: =IF(INPUTS!$B$32=0,"",IF(20>=INPUTS!$B$32,"",MIN(E24-I24-J24,H24))) | L24: =IF(INPUTS!$B$32=0,"",IF(20>=INPUTS!$B$32,"",(F24-I24)*(1+INPUTS!$B$28))) | M24: =IF(INPUTS!$B$32=0,"",IF(20>=INPUTS!$B$32,"",(G24-J24)*(1+INPUTS!$B$28))) | N24: =IF(INPUTS!$B$32=0,"",IF(20>=INPUTS!$B$32,"",(H24-K24)*(1+INPUTS!$B$28))) | O24: =IF(INPUTS!$B$32=0,"",IF(20>=INPUTS!$B$32,"",L24+M24+N24))
A25: =IF(INPUTS!$B$32=0,"",IF(21>=INPUTS!$B$32,"",INPUTS!$B$12+(INPUTS!$B$6-INPUTS!$B$5)+21)) | B25: =IF(INPUTS!$B$32=0,"",IF(21>=INPUTS!$B$32,"",INPUTS!$B$6+21)) | C25: =IF(INPUTS!$B$32=0,"",IF(21>=INPUTS!$B$32,"",INPUTS!$B$22*(1+INPUTS!$B$23)^(INPUTS!$B$6-INPUTS!$B$5+21))) | D25: =IF(INPUTS!$B$32=0,"",IF(21>=INPUTS!$B$32,"",INPUTS!$B$24)) | E25: =IF(INPUTS!$B$32=0,"",IF(21>=INPUTS!$B$32,"",MAX(0,C25-D25))) | F25: =IF(INPUTS!$B$32=0,"",IF(21>=INPUTS!$B$32,"",L24)) | G25: =IF(INPUTS!$B$32=0,"",IF(21>=INPUTS!$B$32,"",M24)) | H25: =IF(INPUTS!$B$32=0,"",IF(21>=INPUTS!$B$32,"",N24)) | I25: =IF(INPUTS!$B$32=0,"",IF(21>=INPUTS!$B$32,"",MIN(E25,F25))) | J25: =IF(INPUTS!$B$32=0,"",IF(21>=INPUTS!$B$32,"",MIN(E25-I25,G25))) | K25: =IF(INPUTS!$B$32=0,"",IF(21>=INPUTS!$B$32,"",MIN(E25-I25-J25,H25))) | L25: =IF(INPUTS!$B$32=0,"",IF(21>=INPUTS!$B$32,"",(F25-I25)*(1+INPUTS!$B$28))) | M25: =IF(INPUTS!$B$32=0,"",IF(21>=INPUTS!$B$32,"",(G25-J25)*(1+INPUTS!$B$28))) | N25: =IF(INPUTS!$B$32=0,"",IF(21>=INPUTS!$B$32,"",(H25-K25)*(1+INPUTS!$B$28))) | O25: =IF(INPUTS!$B$32=0,"",IF(21>=INPUTS!$B$32,"",L25+M25+N25))
A26: =IF(INPUTS!$B$32=0,"",IF(22>=INPUTS!$B$32,"",INPUTS!$B$12+(INPUTS!$B$6-INPUTS!$B$5)+22)) | B26: =IF(INPUTS!$B$32=0,"",IF(22>=INPUTS!$B$32,"",INPUTS!$B$6+22)) | C26: =IF(INPUTS!$B$32=0,"",IF(22>=INPUTS!$B$32,"",INPUTS!$B$22*(1+INPUTS!$B$23)^(INPUTS!$B$6-INPUTS!$B$5+22))) | D26: =IF(INPUTS!$B$32=0,"",IF(22>=INPUTS!$B$32,"",INPUTS!$B$24)) | E26: =IF(INPUTS!$B$32=0,"",IF(22>=INPUTS!$B$32,"",MAX(0,C26-D26))) | F26: =IF(INPUTS!$B$32=0,"",IF(22>=INPUTS!$B$32,"",L25)) | G26: =IF(INPUTS!$B$32=0,"",IF(22>=INPUTS!$B$32,"",M25)) | H26: =IF(INPUTS!$B$32=0,"",IF(22>=INPUTS!$B$32,"",N25)) | I26: =IF(INPUTS!$B$32=0,"",IF(22>=INPUTS!$B$32,"",MIN(E26,F26))) | J26: =IF(INPUTS!$B$32=0,"",IF(22>=INPUTS!$B$32,"",MIN(E26-I26,G26))) | K26: =IF(INPUTS!$B$32=0,"",IF(22>=INPUTS!$B$32,"",MIN(E26-I26-J26,H26))) | L26: =IF(INPUTS!$B$32=0,"",IF(22>=INPUTS!$B$32,"",(F26-I26)*(1+INPUTS!$B$28))) | M26: =IF(INPUTS!$B$32=0,"",IF(22>=INPUTS!$B$32,"",(G26-J26)*(1+INPUTS!$B$28))) | N26: =IF(INPUTS!$B$32=0,"",IF(22>=INPUTS!$B$32,"",(H26-K26)*(1+INPUTS!$B$28))) | O26: =IF(INPUTS!$B$32=0,"",IF(22>=INPUTS!$B$32,"",L26+M26+N26))
A27: =IF(INPUTS!$B$32=0,"",IF(23>=INPUTS!$B$32,"",INPUTS!$B$12+(INPUTS!$B$6-INPUTS!$B$5)+23)) | B27: =IF(INPUTS!$B$32=0,"",IF(23>=INPUTS!$B$32,"",INPUTS!$B$6+23)) | C27: =IF(INPUTS!$B$32=0,"",IF(23>=INPUTS!$B$32,"",INPUTS!$B$22*(1+INPUTS!$B$23)^(INPUTS!$B$6-INPUTS!$B$5+23))) | D27: =IF(INPUTS!$B$32=0,"",IF(23>=INPUTS!$B$32,"",INPUTS!$B$24)) | E27: =IF(INPUTS!$B$32=0,"",IF(23>=INPUTS!$B$32,"",MAX(0,C27-D27))) | F27: =IF(INPUTS!$B$32=0,"",IF(23>=INPUTS!$B$32,"",L26)) | G27: =IF(INPUTS!$B$32=0,"",IF(23>=INPUTS!$B$32,"",M26)) | H27: =IF(INPUTS!$B$32=0,"",IF(23>=INPUTS!$B$32,"",N26)) | I27: =IF(INPUTS!$B$32=0,"",IF(23>=INPUTS!$B$32,"",MIN(E27,F27))) | J27: =IF(INPUTS!$B$32=0,"",IF(23>=INPUTS!$B$32,"",MIN(E27-I27,G27))) | K27: =IF(INPUTS!$B$32=0,"",IF(23>=INPUTS!$B$32,"",MIN(E27-I27-J27,H27))) | L27: =IF(INPUTS!$B$32=0,"",IF(23>=INPUTS!$B$32,"",(F27-I27)*(1+INPUTS!$B$28))) | M27: =IF(INPUTS!$B$32=0,"",IF(23>=INPUTS!$B$32,"",(G27-J27)*(1+INPUTS!$B$28))) | N27: =IF(INPUTS!$B$32=0,"",IF(23>=INPUTS!$B$32,"",(H27-K27)*(1+INPUTS!$B$28))) | O27: =IF(INPUTS!$B$32=0,"",IF(23>=INPUTS!$B$32,"",L27+M27+N27))
A28: =IF(INPUTS!$B$32=0,"",IF(24>=INPUTS!$B$32,"",INPUTS!$B$12+(INPUTS!$B$6-INPUTS!$B$5)+24)) | B28: =IF(INPUTS!$B$32=0,"",IF(24>=INPUTS!$B$32,"",INPUTS!$B$6+24)) | C28: =IF(INPUTS!$B$32=0,"",IF(24>=INPUTS!$B$32,"",INPUTS!$B$22*(1+INPUTS!$B$23)^(INPUTS!$B$6-INPUTS!$B$5+24))) | D28: =IF(INPUTS!$B$32=0,"",IF(24>=INPUTS!$B$32,"",INPUTS!$B$24)) | E28: =IF(INPUTS!$B$32=0,"",IF(24>=INPUTS!$B$32,"",MAX(0,C28-D28))) | F28: =IF(INPUTS!$B$32=0,"",IF(24>=INPUTS!$B$32,"",L27)) | G28: =IF(INPUTS!$B$32=0,"",IF(24>=INPUTS!$B$32,"",M27)) | H28: =IF(INPUTS!$B$32=0,"",IF(24>=INPUTS!$B$32,"",N27)) | I28: =IF(INPUTS!$B$32=0,"",IF(24>=INPUTS!$B$32,"",MIN(E28,F28))) | J28: =IF(INPUTS!$B$32=0,"",IF(24>=INPUTS!$B$32,"",MIN(E28-I28,G28))) | K28: =IF(INPUTS!$B$32=0,"",IF(24>=INPUTS!$B$32,"",MIN(E28-I28-J28,H28))) | L28: =IF(INPUTS!$B$32=0,"",IF(24>=INPUTS!$B$32,"",(F28-I28)*(1+INPUTS!$B$28))) | M28: =IF(INPUTS!$B$32=0,"",IF(24>=INPUTS!$B$32,"",(G28-J28)*(1+INPUTS!$B$28))) | N28: =IF(INPUTS!$B$32=0,"",IF(24>=INPUTS!$B$32,"",(H28-K28)*(1+INPUTS!$B$28))) | O28: =IF(INPUTS!$B$32=0,"",IF(24>=INPUTS!$B$32,"",L28+M28+N28))
A30: END OF BRIDGE → | C30: =IF(INPUTS!$B$32=0,INPUTS!$B$22,IFERROR(LOOKUP(9.99E+307,C4:C28),INPUTS!$B$22)) -> 65377.716 | L30: =IF(INPUTS!$B$32=0,(INPUTS!$B$15+INPUTS!$B$18)*(1+INPUTS!$B$28)^MAX(0,INPUTS!$B$6-INPUTS!$B$5),IFERROR(LOOKUP(9.99E+307,L4:L28),(INPUTS!$B$15+INPUTS!$B$18)*(1+INPUTS!$B$28)^MAX(0,INPUTS!$B$6-INPUTS!$B$5))) -> 326984 | M30: =IF(INPUTS!$B$32=0,INPUTS!$B$17*(1+INPUTS!$B$28)^MAX(0,INPUTS!$B$6-INPUTS!$B$5),IFERROR(LOOKUP(9.99E+307,M4:M28),INPUTS!$B$17*(1+INPUTS!$B$28)^MAX(0,INPUTS!$B$6-INPUTS!$B$5))) -> 248249.35 | N30: =IF(INPUTS!$B$32=0,INPUTS!$B$16*(1+INPUTS!$B$28)^MAX(0,INPUTS!$B$6-INPUTS!$B$5),IFERROR(LOOKUP(9.99E+307,N4:N28),INPUTS!$B$16*(1+INPUTS!$B$28)^MAX(0,INPUTS!$B$6-INPUTS!$B$5))) -> 1075747.2

Sheet TAX ESTIMATE
A1: FEDERAL TAX ESTIMATE · Bridge Years
A2: =IF(INPUTS!B9="MFJ","Using 2026 MFJ brackets + $32,200 standard deduction.","Using 2026 Single brackets + $16,100 standard deduction.") -> Using 2026 MFJ brackets + $32,200 standard deduction.
A4: 2026 BRACKETS (auto-switch via INPUTS Filing Status)
A5: Rate | B5: From | C5: To | D5: RateΔ
A6: 0.1 | B6: =IF(INPUTS!$B$9="MFJ",0,0) -> 0 | C6: =IF(INPUTS!$B$9="MFJ",24800,12400) -> 24800 | D6: 0.1
A7: 0.12 | B7: =IF(INPUTS!$B$9="MFJ",24800,12400) -> 24800 | C7: =IF(INPUTS!$B$9="MFJ",100800,50400) -> 100800 | D7: 0.02
A8: 0.22 | B8: =IF(INPUTS!$B$9="MFJ",100800,50400) -> 100800 | C8: =IF(INPUTS!$B$9="MFJ",211400,105700) -> 211400 | D8: 0.1
A9: 0.24 | B9: =IF(INPUTS!$B$9="MFJ",211400,105700) -> 211400 | C9: =IF(INPUTS!$B$9="MFJ",403550,201775) -> 403550 | D9: 0.02
A10: 0.32 | B10: =IF(INPUTS!$B$9="MFJ",403550,201775) -> 403550 | C10: =IF(INPUTS!$B$9="MFJ",512450,256225) -> 512450 | D10: 0.08
A11: 0.35 | B11: =IF(INPUTS!$B$9="MFJ",512450,256225) -> 512450 | C11: =IF(INPUTS!$B$9="MFJ",768700,640600) -> 768700 | D11: 0.03
A12: 0.37 | B12: =IF(INPUTS!$B$9="MFJ",768700,640600) -> 768700 | C12: =IF(INPUTS!$B$9="MFJ",99999999,99999999) -> 99999999 | D12: 0.02
A13: Source: IRS Rev. Proc. 2025-32 (2026 inflation adjustments). Update annually.
A14: ESTIMATED TAX BY BRIDGE YEAR
A16: Year | B16: Income (401k + conv. + other) | C16: Std Deduction | D16: Taxable Income | E16: Fed Tax | F16: State Tax | G16: Note
A17: =IF(BRIDGE!A4="","",BRIDGE!A4) -> 2029 | B17: =IF(A17="","",BRIDGE!K4+'ROTH LADDER'!D6+INPUTS!$B$24) -> 84600 | C17: =IF(A17="","",INPUTS!$B$34) -> 32200 | D17: =IF(A17="","",MAX(0,B17-C17)) -> 52400 | E17: =IF(A17="","",SUMPRODUCT(((D17-$B$6:$B$12)>0)*(D17-$B$6:$B$12)*$D$6:$D$12)) -> 5792 | F17: =IF(A17="","",D17*INPUTS!$B$11) -> 0 | G17: =IF(A17="","",IF(D17=0,"No federal tax",IF(D17<=$C$7,"Inside 12% bracket","⚠ Above 12% bracket"))) -> Inside 12% bracket
A18: =IF(BRIDGE!A5="","",BRIDGE!A5) -> 2030 | B18: =IF(A18="","",BRIDGE!K5+'ROTH LADDER'!D7+INPUTS!$B$24) -> 84600 | C18: =IF(A18="","",INPUTS!$B$34) -> 32200 | D18: =IF(A18="","",MAX(0,B18-C18)) -> 52400 | E18: =IF(A18="","",SUMPRODUCT(((D18-$B$6:$B$12)>0)*(D18-$B$6:$B$12)*$D$6:$D$12)) -> 5792 | F18: =IF(A18="","",D18*INPUTS!$B$11) -> 0 | G18: =IF(A18="","",IF(D18=0,"No federal tax",IF(D18<=$C$7,"Inside 12% bracket","⚠ Above 12% bracket"))) -> Inside 12% bracket
A19: =IF(BRIDGE!A6="","",BRIDGE!A6) -> 2031 | B19: =IF(A19="","",BRIDGE!K6+'ROTH LADDER'!D8+INPUTS!$B$24) -> 84600 | C19: =IF(A19="","",INPUTS!$B$34) -> 32200 | D19: =IF(A19="","",MAX(0,B19-C19)) -> 52400 | E19: =IF(A19="","",SUMPRODUCT(((D19-$B$6:$B$12)>0)*(D19-$B$6:$B$12)*$D$6:$D$12)) -> 5792 | F19: =IF(A19="","",D19*INPUTS!$B$11) -> 0 | G19: =IF(A19="","",IF(D19=0,"No federal tax",IF(D19<=$C$7,"Inside 12% bracket","⚠ Above 12% bracket"))) -> Inside 12% bracket
A20: =IF(BRIDGE!A7="","",BRIDGE!A7) -> 2032 | B20: =IF(A20="","",BRIDGE!K7+'ROTH LADDER'!D9+INPUTS!$B$24) -> 84600 | C20: =IF(A20="","",INPUTS!$B$34) -> 32200 | D20: =IF(A20="","",MAX(0,B20-C20)) -> 52400 | E20: =IF(A20="","",SUMPRODUCT(((D20-$B$6:$B$12)>0)*(D20-$B$6:$B$12)*$D$6:$D$12)) -> 5792 | F20: =IF(A20="","",D20*INPUTS!$B$11) -> 0 | G20: =IF(A20="","",IF(D20=0,"No federal tax",IF(D20<=$C$7,"Inside 12% bracket","⚠ Above 12% bracket"))) -> Inside 12% bracket
A21: =IF(BRIDGE!A8="","",BRIDGE!A8) -> 2033 | B21: =IF(A21="","",BRIDGE!K8+'ROTH LADDER'!D10+INPUTS!$B$24) -> 84600 | C21: =IF(A21="","",INPUTS!$B$34) -> 32200 | D21: =IF(A21="","",MAX(0,B21-C21)) -> 52400 | E21: =IF(A21="","",SUMPRODUCT(((D21-$B$6:$B$12)>0)*(D21-$B$6:$B$12)*$D$6:$D$12)) -> 5792 | F21: =IF(A21="","",D21*INPUTS!$B$11) -> 0 | G21: =IF(A21="","",IF(D21=0,"No federal tax",IF(D21<=$C$7,"Inside 12% bracket","⚠ Above 12% bracket"))) -> Inside 12% bracket
A22: =IF(BRIDGE!A9="","",BRIDGE!A9) | B22: =IF(A22="","",BRIDGE!K9+'ROTH LADDER'!D11+INPUTS!$B$24) | C22: =IF(A22="","",INPUTS!$B$34) | D22: =IF(A22="","",MAX(0,B22-C22)) | E22: =IF(A22="","",SUMPRODUCT(((D22-$B$6:$B$12)>0)*(D22-$B$6:$B$12)*$D$6:$D$12)) | F22: =IF(A22="","",D22*INPUTS!$B$11) | G22: =IF(A22="","",IF(D22=0,"No federal tax",IF(D22<=$C$7,"Inside 12% bracket","⚠ Above 12% bracket")))
A23: =IF(BRIDGE!A10="","",BRIDGE!A10) | B23: =IF(A23="","",BRIDGE!K10+'ROTH LADDER'!D12+INPUTS!$B$24) | C23: =IF(A23="","",INPUTS!$B$34) | D23: =IF(A23="","",MAX(0,B23-C23)) | E23: =IF(A23="","",SUMPRODUCT(((D23-$B$6:$B$12)>0)*(D23-$B$6:$B$12)*$D$6:$D$12)) | F23: =IF(A23="","",D23*INPUTS!$B$11) | G23: =IF(A23="","",IF(D23=0,"No federal tax",IF(D23<=$C$7,"Inside 12% bracket","⚠ Above 12% bracket")))
A24: =IF(BRIDGE!A11="","",BRIDGE!A11) | B24: =IF(A24="","",BRIDGE!K11+'ROTH LADDER'!D13+INPUTS!$B$24) | C24: =IF(A24="","",INPUTS!$B$34) | D24: =IF(A24="","",MAX(0,B24-C24)) | E24: =IF(A24="","",SUMPRODUCT(((D24-$B$6:$B$12)>0)*(D24-$B$6:$B$12)*$D$6:$D$12)) | F24: =IF(A24="","",D24*INPUTS!$B$11) | G24: =IF(A24="","",IF(D24=0,"No federal tax",IF(D24<=$C$7,"Inside 12% bracket","⚠ Above 12% bracket")))
A25: =IF(BRIDGE!A12="","",BRIDGE!A12) | B25: =IF(A25="","",BRIDGE!K12+'ROTH LADDER'!D14+INPUTS!$B$24) | C25: =IF(A25="","",INPUTS!$B$34) | D25: =IF(A25="","",MAX(0,B25-C25)) | E25: =IF(A25="","",SUMPRODUCT(((D25-$B$6:$B$12)>0)*(D25-$B$6:$B$12)*$D$6:$D$12)) | F25: =IF(A25="","",D25*INPUTS!$B$11) | G25: =IF(A25="","",IF(D25=0,"No federal tax",IF(D25<=$C$7,"Inside 12% bracket","⚠ Above 12% bracket")))
A26: =IF(BRIDGE!A13="","",BRIDGE!A13) | B26: =IF(A26="","",BRIDGE!K13+'ROTH LADDER'!D15+INPUTS!$B$24) | C26: =IF(A26="","",INPUTS!$B$34) | D26: =IF(A26="","",MAX(0,B26-C26)) | E26: =IF(A26="","",SUMPRODUCT(((D26-$B$6:$B$12)>0)*(D26-$B$6:$B$12)*$D$6:$D$12)) | F26: =IF(A26="","",D26*INPUTS!$B$11) | G26: =IF(A26="","",IF(D26=0,"No federal tax",IF(D26<=$C$7,"Inside 12% bracket","⚠ Above 12% bracket")))
A27: =IF(BRIDGE!A14="","",BRIDGE!A14) | B27: =IF(A27="","",BRIDGE!K14+'ROTH LADDER'!D16+INPUTS!$B$24) | C27: =IF(A27="","",INPUTS!$B$34) | D27: =IF(A27="","",MAX(0,B27-C27)) | E27: =IF(A27="","",SUMPRODUCT(((D27-$B$6:$B$12)>0)*(D27-$B$6:$B$12)*$D$6:$D$12)) | F27: =IF(A27="","",D27*INPUTS!$B$11) | G27: =IF(A27="","",IF(D27=0,"No federal tax",IF(D27<=$C$7,"Inside 12% bracket","⚠ Above 12% bracket")))
A28: =IF(BRIDGE!A15="","",BRIDGE!A15) | B28: =IF(A28="","",BRIDGE!K15+'ROTH LADDER'!D17+INPUTS!$B$24) | C28: =IF(A28="","",INPUTS!$B$34) | D28: =IF(A28="","",MAX(0,B28-C28)) | E28: =IF(A28="","",SUMPRODUCT(((D28-$B$6:$B$12)>0)*(D28-$B$6:$B$12)*$D$6:$D$12)) | F28: =IF(A28="","",D28*INPUTS!$B$11) | G28: =IF(A28="","",IF(D28=0,"No federal tax",IF(D28<=$C$7,"Inside 12% bracket","⚠ Above 12% bracket")))
... A41: =IF(BRIDGE!A28="","",BRIDGE!A28) | B41: =IF(A41="","",BRIDGE!K28+'ROTH LADDER'!D30+INPUTS!$B$24) | C41: =IF(A41="","",INPUTS!$B$34) | D41: =IF(A41="","",MAX(0,B41-C41)) | E41: =IF(A41="","",SUMPRODUCT(((D41-$B$6:$B$12)>0)*(D41-$B$6:$B$12)*$D$6:$D$12)) | F41: =IF(A41="","",D41*INPUTS!$B$11) | G41: =IF(A41="","",IF(D41=0,"No federal tax",IF(D41<=$C$7,"Inside 12% bracket","⚠ Above 12% bracket")))

Sheet ROTH LADDER
A1: ROTH CONVERSION LADDER · 5-Year Pipeline
A2: Suggested conversion = remaining 12% bracket space after bridge income. Each rung unlocks penalty-free after 5 years.
A3: ACA WARNING: conversions count toward MAGI. The cross-check below flags any year total MAGI exceeds the est. 400% FPL cliff (~$81,760 for 2-person household, 2026).
A4: ACA 400% FPL cliff (est.) → | C4: =4*(15650+5500*(MAX(1,INPUTS!$B$26)-1)) -> 84600 | D4: =("Household of "&INPUTS!$B$26&" — 2025 HHS guideline, verify annually") -> Household of 2 — 2025 HHS guideline, verify annually
A5: Year | B5: Age | C5: 12% Bracket Room (gross) | D5: Suggested Conversion | E5: Tax on Conv. (12%) | F5: MAGI (income+conv.) | G5: ACA Cliff Check | H5: Unlocks Penalty-Free
A6: =IF(BRIDGE!A4="","",BRIDGE!A4) -> 2029 | B6: =IF(A6="","",BRIDGE!B4) -> 55 | C6: =IF(A6="","",MAX(0,'TAX ESTIMATE'!$C$7+INPUTS!$B$34-BRIDGE!K4-INPUTS!$B$24)) -> 133000 | D6: =IF(A6="","",MAX(0,MIN(C6,$C$4-BRIDGE!K4-INPUTS!$B$24))) -> 84600 | E6: =IF(A6="","",D6*0.12) -> 10152 | F6: =IF(A6="","",BRIDGE!K4+D6+INPUTS!$B$24) -> 84600 | G6: =IF(A6="","",IF(F6>$C$4,"⚠ OVER CLIFF — trims subsidy to $0","✓ Under cliff")) -> ✓ Under cliff | H6: =IF(A6="","",A6+5&" (5-yr rule)") -> 2034 (5-yr rule)
A7: =IF(BRIDGE!A5="","",BRIDGE!A5) -> 2030 | B7: =IF(A7="","",BRIDGE!B5) -> 56 | C7: =IF(A7="","",MAX(0,'TAX ESTIMATE'!$C$7+INPUTS!$B$34-BRIDGE!K5-INPUTS!$B$24)) -> 133000 | D7: =IF(A7="","",MAX(0,MIN(C7,$C$4-BRIDGE!K5-INPUTS!$B$24))) -> 84600 | E7: =IF(A7="","",D7*0.12) -> 10152 | F7: =IF(A7="","",BRIDGE!K5+D7+INPUTS!$B$24) -> 84600 | G7: =IF(A7="","",IF(F7>$C$4,"⚠ OVER CLIFF — trims subsidy to $0","✓ Under cliff")) -> ✓ Under cliff | H7: =IF(A7="","",A7+5&" (5-yr rule)") -> 2035 (5-yr rule)
A8: =IF(BRIDGE!A6="","",BRIDGE!A6) -> 2031 | B8: =IF(A8="","",BRIDGE!B6) -> 57 | C8: =IF(A8="","",MAX(0,'TAX ESTIMATE'!$C$7+INPUTS!$B$34-BRIDGE!K6-INPUTS!$B$24)) -> 133000 | D8: =IF(A8="","",MAX(0,MIN(C8,$C$4-BRIDGE!K6-INPUTS!$B$24))) -> 84600 | E8: =IF(A8="","",D8*0.12) -> 10152 | F8: =IF(A8="","",BRIDGE!K6+D8+INPUTS!$B$24) -> 84600 | G8: =IF(A8="","",IF(F8>$C$4,"⚠ OVER CLIFF — trims subsidy to $0","✓ Under cliff")) -> ✓ Under cliff | H8: =IF(A8="","",A8+5&" (5-yr rule)") -> 2036 (5-yr rule)
A9: =IF(BRIDGE!A7="","",BRIDGE!A7) -> 2032 | B9: =IF(A9="","",BRIDGE!B7) -> 58 | C9: =IF(A9="","",MAX(0,'TAX ESTIMATE'!$C$7+INPUTS!$B$34-BRIDGE!K7-INPUTS!$B$24)) -> 133000 | D9: =IF(A9="","",MAX(0,MIN(C9,$C$4-BRIDGE!K7-INPUTS!$B$24))) -> 84600 | E9: =IF(A9="","",D9*0.12) -> 10152 | F9: =IF(A9="","",BRIDGE!K7+D9+INPUTS!$B$24) -> 84600 | G9: =IF(A9="","",IF(F9>$C$4,"⚠ OVER CLIFF — trims subsidy to $0","✓ Under cliff")) -> ✓ Under cliff | H9: =IF(A9="","",A9+5&" (5-yr rule)") -> 2037 (5-yr rule)
A10: =IF(BRIDGE!A8="","",BRIDGE!A8) -> 2033 | B10: =IF(A10="","",BRIDGE!B8) -> 59 | C10: =IF(A10="","",MAX(0,'TAX ESTIMATE'!$C$7+INPUTS!$B$34-BRIDGE!K8-INPUTS!$B$24)) -> 133000 | D10: =IF(A10="","",MAX(0,MIN(C10,$C$4-BRIDGE!K8-INPUTS!$B$24))) -> 84600 | E10: =IF(A10="","",D10*0.12) -> 10152 | F10: =IF(A10="","",BRIDGE!K8+D10+INPUTS!$B$24) -> 84600 | G10: =IF(A10="","",IF(F10>$C$4,"⚠ OVER CLIFF — trims subsidy to $0","✓ Under cliff")) -> ✓ Under cliff | H10: =IF(A10="","",A10+5&" (5-yr rule)") -> 2038 (5-yr rule)
A11: =IF(BRIDGE!A9="","",BRIDGE!A9) | B11: =IF(A11="","",BRIDGE!B9) | C11: =IF(A11="","",MAX(0,'TAX ESTIMATE'!$C$7+INPUTS!$B$34-BRIDGE!K9-INPUTS!$B$24)) | D11: =IF(A11="","",MAX(0,MIN(C11,$C$4-BRIDGE!K9-INPUTS!$B$24))) | E11: =IF(A11="","",D11*0.12) | F11: =IF(A11="","",BRIDGE!K9+D11+INPUTS!$B$24) | G11: =IF(A11="","",IF(F11>$C$4,"⚠ OVER CLIFF — trims subsidy to $0","✓ Under cliff")) | H11: =IF(A11="","",A11+5&" (5-yr rule)")
A12: =IF(BRIDGE!A10="","",BRIDGE!A10) | B12: =IF(A12="","",BRIDGE!B10) | C12: =IF(A12="","",MAX(0,'TAX ESTIMATE'!$C$7+INPUTS!$B$34-BRIDGE!K10-INPUTS!$B$24)) | D12: =IF(A12="","",MAX(0,MIN(C12,$C$4-BRIDGE!K10-INPUTS!$B$24))) | E12: =IF(A12="","",D12*0.12) | F12: =IF(A12="","",BRIDGE!K10+D12+INPUTS!$B$24) | G12: =IF(A12="","",IF(F12>$C$4,"⚠ OVER CLIFF — trims subsidy to $0","✓ Under cliff")) | H12: =IF(A12="","",A12+5&" (5-yr rule)")
A13: =IF(BRIDGE!A11="","",BRIDGE!A11) | B13: =IF(A13="","",BRIDGE!B11) | C13: =IF(A13="","",MAX(0,'TAX ESTIMATE'!$C$7+INPUTS!$B$34-BRIDGE!K11-INPUTS!$B$24)) | D13: =IF(A13="","",MAX(0,MIN(C13,$C$4-BRIDGE!K11-INPUTS!$B$24))) | E13: =IF(A13="","",D13*0.12) | F13: =IF(A13="","",BRIDGE!K11+D13+INPUTS!$B$24) | G13: =IF(A13="","",IF(F13>$C$4,"⚠ OVER CLIFF — trims subsidy to $0","✓ Under cliff")) | H13: =IF(A13="","",A13+5&" (5-yr rule)")
A14: =IF(BRIDGE!A12="","",BRIDGE!A12) | B14: =IF(A14="","",BRIDGE!B12) | C14: =IF(A14="","",MAX(0,'TAX ESTIMATE'!$C$7+INPUTS!$B$34-BRIDGE!K12-INPUTS!$B$24)) | D14: =IF(A14="","",MAX(0,MIN(C14,$C$4-BRIDGE!K12-INPUTS!$B$24))) | E14: =IF(A14="","",D14*0.12) | F14: =IF(A14="","",BRIDGE!K12+D14+INPUTS!$B$24) | G14: =IF(A14="","",IF(F14>$C$4,"⚠ OVER CLIFF — trims subsidy to $0","✓ Under cliff")) | H14: =IF(A14="","",A14+5&" (5-yr rule)")
A15: =IF(BRIDGE!A13="","",BRIDGE!A13) | B15: =IF(A15="","",BRIDGE!B13) | C15: =IF(A15="","",MAX(0,'TAX ESTIMATE'!$C$7+INPUTS!$B$34-BRIDGE!K13-INPUTS!$B$24)) | D15: =IF(A15="","",MAX(0,MIN(C15,$C$4-BRIDGE!K13-INPUTS!$B$24))) | E15: =IF(A15="","",D15*0.12) | F15: =IF(A15="","",BRIDGE!K13+D15+INPUTS!$B$24) | G15: =IF(A15="","",IF(F15>$C$4,"⚠ OVER CLIFF — trims subsidy to $0","✓ Under cliff")) | H15: =IF(A15="","",A15+5&" (5-yr rule)")
A16: =IF(BRIDGE!A14="","",BRIDGE!A14) | B16: =IF(A16="","",BRIDGE!B14) | C16: =IF(A16="","",MAX(0,'TAX ESTIMATE'!$C$7+INPUTS!$B$34-BRIDGE!K14-INPUTS!$B$24)) | D16: =IF(A16="","",MAX(0,MIN(C16,$C$4-BRIDGE!K14-INPUTS!$B$24))) | E16: =IF(A16="","",D16*0.12) | F16: =IF(A16="","",BRIDGE!K14+D16+INPUTS!$B$24) | G16: =IF(A16="","",IF(F16>$C$4,"⚠ OVER CLIFF — trims subsidy to $0","✓ Under cliff")) | H16: =IF(A16="","",A16+5&" (5-yr rule)")
A17: =IF(BRIDGE!A15="","",BRIDGE!A15) | B17: =IF(A17="","",BRIDGE!B15) | C17: =IF(A17="","",MAX(0,'TAX ESTIMATE'!$C$7+INPUTS!$B$34-BRIDGE!K15-INPUTS!$B$24)) | D17: =IF(A17="","",MAX(0,MIN(C17,$C$4-BRIDGE!K15-INPUTS!$B$24))) | E17: =IF(A17="","",D17*0.12) | F17: =IF(A17="","",BRIDGE!K15+D17+INPUTS!$B$24) | G17: =IF(A17="","",IF(F17>$C$4,"⚠ OVER CLIFF — trims subsidy to $0","✓ Under cliff")) | H17: =IF(A17="","",A17+5&" (5-yr rule)")
... A30: =IF(BRIDGE!A28="","",BRIDGE!A28) | B30: =IF(A30="","",BRIDGE!B28) | C30: =IF(A30="","",MAX(0,'TAX ESTIMATE'!$C$7+INPUTS!$B$34-BRIDGE!K28-INPUTS!$B$24)) | D30: =IF(A30="","",MAX(0,MIN(C30,$C$4-BRIDGE!K28-INPUTS!$B$24))) | E30: =IF(A30="","",D30*0.12) | F30: =IF(A30="","",BRIDGE!K28+D30+INPUTS!$B$24) | G30: =IF(A30="","",IF(F30>$C$4,"⚠ OVER CLIFF — trims subsidy to $0","✓ Under cliff")) | H30: =IF(A30="","",A30+5&" (5-yr rule)")
A32: Suggested Conversion = smaller of 12% bracket space and ACA cliff headroom (cliff − 401k draws − other income). MAGI shown includes conversion + 401k + other income; taxable-account dividends/gains not modeled.

Sheet POST-59.5
A1: POST-59½ PROJECTION · To Life Expectancy
A2: 401k+Taxable draws first, Roth preserved. Starts at the later of 59½ or your retirement age. Social Security begins at your claiming age. Balances are pre-tax — 401k withdrawals are taxable, budget a 15–20% gross-up.
A4: Year | B4: Age | C4: Spending (Infl.) | D4: SS Income | E4: Other Income | F4: Net Withdrawal | G4: 401k+Taxable Bal. | H4: Roth Bal.
A5: =IF(MAX(59.5,INPUTS!$B$6)+0>INPUTS!$B$8,"",INPUTS!$B$12+(MAX(59.5,INPUTS!$B$6)-INPUTS!$B$5)+0) -> 2033.5 | B5: =IF(A5="","",MAX(59.5,INPUTS!$B$6)+0) -> 59.5 | C5: =IF(A5="","",INPUTS!$B$22*(1+INPUTS!$B$23)^(A5-INPUTS!$B$12)) -> 66189.893 | D5: =IF(A5="","",IF(B5>=INPUTS!$B$7,INPUTS!$B$25*(1+INPUTS!$B$23)^(A5-INPUTS!$B$12),0)) -> 0 | E5: =IF(A5="","",INPUTS!$B$24) -> 0 | F5: =IF(A5="","",MAX(0,C5-D5-E5)) -> 66189.893 | G5: =IF(A5="","",MAX(0,BRIDGE!L30+BRIDGE!N30-F5)*(1+INPUTS!$B$28)) -> 1423416.5 | H5: =IF(A5="","",MAX(0,BRIDGE!M30-MAX(0,F5-BRIDGE!L30-BRIDGE!N30))*(1+INPUTS!$B$28)) -> 264385.56
A6: =IF(MAX(59.5,INPUTS!$B$6)+1>INPUTS!$B$8,"",INPUTS!$B$12+(MAX(59.5,INPUTS!$B$6)-INPUTS!$B$5)+1) -> 2034.5 | B6: =IF(A6="","",MAX(59.5,INPUTS!$B$6)+1) -> 60.5 | C6: =IF(A6="","",INPUTS!$B$22*(1+INPUTS!$B$23)^(A6-INPUTS!$B$12)) -> 67844.64 | D6: =IF(A6="","",IF(B6>=INPUTS!$B$7,INPUTS!$B$25*(1+INPUTS!$B$23)^(A6-INPUTS!$B$12),0)) -> 0 | E6: =IF(A6="","",INPUTS!$B$24) -> 0 | F6: =IF(A6="","",IF(G5+H5=0,0,MAX(0,C6-D6-E6))) -> 67844.64 | G6: =IF(A6="","",MAX(0,G5-F6)*(1+INPUTS!$B$28)) -> 1443684 | H6: =IF(A6="","",MAX(0,H5-MAX(0,F6-G5))*(1+INPUTS!$B$28)) -> 281570.62
A7: =IF(MAX(59.5,INPUTS!$B$6)+2>INPUTS!$B$8,"",INPUTS!$B$12+(MAX(59.5,INPUTS!$B$6)-INPUTS!$B$5)+2) -> 2035.5 | B7: =IF(A7="","",MAX(59.5,INPUTS!$B$6)+2) -> 61.5 | C7: =IF(A7="","",INPUTS!$B$22*(1+INPUTS!$B$23)^(A7-INPUTS!$B$12)) -> 69540.756 | D7: =IF(A7="","",IF(B7>=INPUTS!$B$7,INPUTS!$B$25*(1+INPUTS!$B$23)^(A7-INPUTS!$B$12),0)) -> 0 | E7: =IF(A7="","",INPUTS!$B$24) -> 0 | F7: =IF(A7="","",IF(G6+H6=0,0,MAX(0,C7-D7-E7))) -> 69540.756 | G7: =IF(A7="","",MAX(0,G6-F7)*(1+INPUTS!$B$28)) -> 1463462.6 | H7: =IF(A7="","",MAX(0,H6-MAX(0,F7-G6))*(1+INPUTS!$B$28)) -> 299872.71
A8: =IF(MAX(59.5,INPUTS!$B$6)+3>INPUTS!$B$8,"",INPUTS!$B$12+(MAX(59.5,INPUTS!$B$6)-INPUTS!$B$5)+3) -> 2036.5 | B8: =IF(A8="","",MAX(59.5,INPUTS!$B$6)+3) -> 62.5 | C8: =IF(A8="","",INPUTS!$B$22*(1+INPUTS!$B$23)^(A8-INPUTS!$B$12)) -> 71279.275 | D8: =IF(A8="","",IF(B8>=INPUTS!$B$7,INPUTS!$B$25*(1+INPUTS!$B$23)^(A8-INPUTS!$B$12),0)) -> 0 | E8: =IF(A8="","",INPUTS!$B$24) -> 0 | F8: =IF(A8="","",IF(G7+H7=0,0,MAX(0,C8-D8-E8))) -> 71279.275 | G8: =IF(A8="","",MAX(0,G7-F8)*(1+INPUTS!$B$28)) -> 1482675.2 | H8: =IF(A8="","",MAX(0,H7-MAX(0,F8-G7))*(1+INPUTS!$B$28)) -> 319364.44
A9: =IF(MAX(59.5,INPUTS!$B$6)+4>INPUTS!$B$8,"",INPUTS!$B$12+(MAX(59.5,INPUTS!$B$6)-INPUTS!$B$5)+4) -> 2037.5 | B9: =IF(A9="","",MAX(59.5,INPUTS!$B$6)+4) -> 63.5 | C9: =IF(A9="","",INPUTS!$B$22*(1+INPUTS!$B$23)^(A9-INPUTS!$B$12)) -> 73061.257 | D9: =IF(A9="","",IF(B9>=INPUTS!$B$7,INPUTS!$B$25*(1+INPUTS!$B$23)^(A9-INPUTS!$B$12),0)) -> 0 | E9: =IF(A9="","",INPUTS!$B$24) -> 0 | F9: =IF(A9="","",IF(G8+H8=0,0,MAX(0,C9-D9-E9))) -> 73061.257 | G9: =IF(A9="","",MAX(0,G8-F9)*(1+INPUTS!$B$28)) -> 1501238.8 | H9: =IF(A9="","",MAX(0,H8-MAX(0,F9-G8))*(1+INPUTS!$B$28)) -> 340123.12
A10: =IF(MAX(59.5,INPUTS!$B$6)+5>INPUTS!$B$8,"",INPUTS!$B$12+(MAX(59.5,INPUTS!$B$6)-INPUTS!$B$5)+5) -> 2038.5 | B10: =IF(A10="","",MAX(59.5,INPUTS!$B$6)+5) -> 64.5 | C10: =IF(A10="","",INPUTS!$B$22*(1+INPUTS!$B$23)^(A10-INPUTS!$B$12)) -> 74887.789 | D10: =IF(A10="","",IF(B10>=INPUTS!$B$7,INPUTS!$B$25*(1+INPUTS!$B$23)^(A10-INPUTS!$B$12),0)) -> 0 | E10: =IF(A10="","",INPUTS!$B$24) -> 0 | F10: =IF(A10="","",IF(G9+H9=0,0,MAX(0,C10-D10-E10))) -> 74887.789 | G10: =IF(A10="","",MAX(0,G9-F10)*(1+INPUTS!$B$28)) -> 1519063.9 | H10: =IF(A10="","",MAX(0,H9-MAX(0,F10-G9))*(1+INPUTS!$B$28)) -> 362231.13
A11: =IF(MAX(59.5,INPUTS!$B$6)+6>INPUTS!$B$8,"",INPUTS!$B$12+(MAX(59.5,INPUTS!$B$6)-INPUTS!$B$5)+6) -> 2039.5 | B11: =IF(A11="","",MAX(59.5,INPUTS!$B$6)+6) -> 65.5 | C11: =IF(A11="","",INPUTS!$B$22*(1+INPUTS!$B$23)^(A11-INPUTS!$B$12)) -> 76759.983 | D11: =IF(A11="","",IF(B11>=INPUTS!$B$7,INPUTS!$B$25*(1+INPUTS!$B$23)^(A11-INPUTS!$B$12),0)) -> 0 | E11: =IF(A11="","",INPUTS!$B$24) -> 0 | F11: =IF(A11="","",IF(G10+H10=0,0,MAX(0,C11-D11-E11))) -> 76759.983 | G11: =IF(A11="","",MAX(0,G10-F11)*(1+INPUTS!$B$28)) -> 1536053.6 | H11: =IF(A11="","",MAX(0,H10-MAX(0,F11-G10))*(1+INPUTS!$B$28)) -> 385776.15
A12: =IF(MAX(59.5,INPUTS!$B$6)+7>INPUTS!$B$8,"",INPUTS!$B$12+(MAX(59.5,INPUTS!$B$6)-INPUTS!$B$5)+7) -> 2040.5 | B12: =IF(A12="","",MAX(59.5,INPUTS!$B$6)+7) -> 66.5 | C12: =IF(A12="","",INPUTS!$B$22*(1+INPUTS!$B$23)^(A12-INPUTS!$B$12)) -> 78678.983 | D12: =IF(A12="","",IF(B12>=INPUTS!$B$7,INPUTS!$B$25*(1+INPUTS!$B$23)^(A12-INPUTS!$B$12),0)) -> 0 | E12: =IF(A12="","",INPUTS!$B$24) -> 0 | F12: =IF(A12="","",IF(G11+H11=0,0,MAX(0,C12-D12-E12))) -> 78678.983 | G12: =IF(A12="","",MAX(0,G11-F12)*(1+INPUTS!$B$28)) -> 1552104 | H12: =IF(A12="","",MAX(0,H11-MAX(0,F12-G11))*(1+INPUTS!$B$28)) -> 410851.6
A13: =IF(MAX(59.5,INPUTS!$B$6)+8>INPUTS!$B$8,"",INPUTS!$B$12+(MAX(59.5,INPUTS!$B$6)-INPUTS!$B$5)+8) -> 2041.5 | B13: =IF(A13="","",MAX(59.5,INPUTS!$B$6)+8) -> 67.5 | C13: =IF(A13="","",INPUTS!$B$22*(1+INPUTS!$B$23)^(A13-INPUTS!$B$12)) -> 80645.958 | D13: =IF(A13="","",IF(B13>=INPUTS!$B$7,INPUTS!$B$25*(1+INPUTS!$B$23)^(A13-INPUTS!$B$12),0)) -> 35190.963 | E13: =IF(A13="","",INPUTS!$B$24) -> 0 | F13: =IF(A13="","",IF(G12+H12=0,0,MAX(0,C13-D13-E13))) -> 45454.994 | G13: =IF(A13="","",MAX(0,G12-F13)*(1+INPUTS!$B$28)) -> 1604581.2 | H13: =IF(A13="","",MAX(0,H12-MAX(0,F13-G12))*(1+INPUTS!$B$28)) -> 437556.95
A14: =IF(MAX(59.5,INPUTS!$B$6)+9>INPUTS!$B$8,"",INPUTS!$B$12+(MAX(59.5,INPUTS!$B$6)-INPUTS!$B$5)+9) -> 2042.5 | B14: =IF(A14="","",MAX(59.5,INPUTS!$B$6)+9) -> 68.5 | C14: =IF(A14="","",INPUTS!$B$22*(1+INPUTS!$B$23)^(A14-INPUTS!$B$12)) -> 82662.107 | D14: =IF(A14="","",IF(B14>=INPUTS!$B$7,INPUTS!$B$25*(1+INPUTS!$B$23)^(A14-INPUTS!$B$12),0)) -> 36070.737 | E14: =IF(A14="","",INPUTS!$B$24) -> 0 | F14: =IF(A14="","",IF(G13+H13=0,0,MAX(0,C14-D14-E14))) -> 46591.369 | G14: =IF(A14="","",MAX(0,G13-F14)*(1+INPUTS!$B$28)) -> 1659259.2 | H14: =IF(A14="","",MAX(0,H13-MAX(0,F14-G13))*(1+INPUTS!$B$28)) -> 465998.16
A15: =IF(MAX(59.5,INPUTS!$B$6)+10>INPUTS!$B$8,"",INPUTS!$B$12+(MAX(59.5,INPUTS!$B$6)-INPUTS!$B$5)+10) -> 2043.5 | B15: =IF(A15="","",MAX(59.5,INPUTS!$B$6)+10) -> 69.5 | C15: =IF(A15="","",INPUTS!$B$22*(1+INPUTS!$B$23)^(A15-INPUTS!$B$12)) -> 84728.659 | D15: =IF(A15="","",IF(B15>=INPUTS!$B$7,INPUTS!$B$25*(1+INPUTS!$B$23)^(A15-INPUTS!$B$12),0)) -> 36972.506 | E15: =IF(A15="","",INPUTS!$B$24) -> 0 | F15: =IF(A15="","",IF(G14+H14=0,0,MAX(0,C15-D15-E15))) -> 47756.153 | G15: =IF(A15="","",MAX(0,G14-F15)*(1+INPUTS!$B$28)) -> 1716250.7 | H15: =IF(A15="","",MAX(0,H14-MAX(0,F15-G14))*(1+INPUTS!$B$28)) -> 496288.04
A16: =IF(MAX(59.5,INPUTS!$B$6)+11>INPUTS!$B$8,"",INPUTS!$B$12+(MAX(59.5,INPUTS!$B$6)-INPUTS!$B$5)+11) -> 2044.5 | B16: =IF(A16="","",MAX(59.5,INPUTS!$B$6)+11) -> 70.5 | C16: =IF(A16="","",INPUTS!$B$22*(1+INPUTS!$B$23)^(A16-INPUTS!$B$12)) -> 86846.876 | D16: =IF(A16="","",IF(B16>=INPUTS!$B$7,INPUTS!$B$25*(1+INPUTS!$B$23)^(A16-INPUTS!$B$12),0)) -> 37896.818 | E16: =IF(A16="","",INPUTS!$B$24) -> 0 | F16: =IF(A16="","",IF(G15+H15=0,0,MAX(0,C16-D16-E16))) -> 48950.057 | G16: =IF(A16="","",MAX(0,G15-F16)*(1+INPUTS!$B$28)) -> 1775675.2 | H16: =IF(A16="","",MAX(0,H15-MAX(0,F16-G15))*(1+INPUTS!$B$28)) -> 528546.76
A17: =IF(MAX(59.5,INPUTS!$B$6)+12>INPUTS!$B$8,"",INPUTS!$B$12+(MAX(59.5,INPUTS!$B$6)-INPUTS!$B$5)+12) -> 2045.5 | B17: =IF(A17="","",MAX(59.5,INPUTS!$B$6)+12) -> 71.5 | C17: =IF(A17="","",INPUTS!$B$22*(1+INPUTS!$B$23)^(A17-INPUTS!$B$12)) -> 89018.048 | D17: =IF(A17="","",IF(B17>=INPUTS!$B$7,INPUTS!$B$25*(1+INPUTS!$B$23)^(A17-INPUTS!$B$12),0)) -> 38844.239 | E17: =IF(A17="","",INPUTS!$B$24) -> 0 | F17: =IF(A17="","",IF(G16+H16=0,0,MAX(0,C17-D17-E17))) -> 50173.809 | G17: =IF(A17="","",MAX(0,G16-F17)*(1+INPUTS!$B$28)) -> 1837659 | H17: =IF(A17="","",MAX(0,H16-MAX(0,F17-G16))*(1+INPUTS!$B$28)) -> 562902.3
A18: =IF(MAX(59.5,INPUTS!$B$6)+13>INPUTS!$B$8,"",INPUTS!$B$12+(MAX(59.5,INPUTS!$B$6)-INPUTS!$B$5)+13) -> 2046.5 | B18: =IF(A18="","",MAX(59.5,INPUTS!$B$6)+13) -> 72.5 | C18: =IF(A18="","",INPUTS!$B$22*(1+INPUTS!$B$23)^(A18-INPUTS!$B$12)) -> 91243.499 | D18: =IF(A18="","",IF(B18>=INPUTS!$B$7,INPUTS!$B$25*(1+INPUTS!$B$23)^(A18-INPUTS!$B$12),0)) -> 39815.345 | E18: =IF(A18="","",INPUTS!$B$24) -> 0 | F18: =IF(A18="","",IF(G17+H17=0,0,MAX(0,C18-D18-E18))) -> 51428.154 | G18: =IF(A18="","",MAX(0,G17-F18)*(1+INPUTS!$B$28)) -> 1902335.8 | H18: =IF(A18="","",MAX(0,H17-MAX(0,F18-G17))*(1+INPUTS!$B$28)) -> 599490.95
A19: =IF(MAX(59.5,INPUTS!$B$6)+14>INPUTS!$B$8,"",INPUTS!$B$12+(MAX(59.5,INPUTS!$B$6)-INPUTS!$B$5)+14) -> 2047.5 | B19: =IF(A19="","",MAX(59.5,INPUTS!$B$6)+14) -> 73.5 | C19: =IF(A19="","",INPUTS!$B$22*(1+INPUTS!$B$23)^(A19-INPUTS!$B$12)) -> 93524.586 | D19: =IF(A19="","",IF(B19>=INPUTS!$B$7,INPUTS!$B$25*(1+INPUTS!$B$23)^(A19-INPUTS!$B$12),0)) -> 40810.729 | E19: =IF(A19="","",INPUTS!$B$24) -> 0 | F19: =IF(A19="","",IF(G18+H18=0,0,MAX(0,C19-D19-E19))) -> 52713.858 | G19: =IF(A19="","",MAX(0,G18-F19)*(1+INPUTS!$B$28)) -> 1969847.4 | H19: =IF(A19="","",MAX(0,H18-MAX(0,F19-G18))*(1+INPUTS!$B$28)) -> 638457.86
A20: =IF(MAX(59.5,INPUTS!$B$6)+15>INPUTS!$B$8,"",INPUTS!$B$12+(MAX(59.5,INPUTS!$B$6)-INPUTS!$B$5)+15) -> 2048.5 | B20: =IF(A20="","",MAX(59.5,INPUTS!$B$6)+15) -> 74.5 | C20: =IF(A20="","",INPUTS!$B$22*(1+INPUTS!$B$23)^(A20-INPUTS!$B$12)) -> 95862.701 | D20: =IF(A20="","",IF(B20>=INPUTS!$B$7,INPUTS!$B$25*(1+INPUTS!$B$23)^(A20-INPUTS!$B$12),0)) -> 41830.997 | E20: =IF(A20="","",INPUTS!$B$24) -> 0 | F20: =IF(A20="","",IF(G19+H19=0,0,MAX(0,C20-D20-E20))) -> 54031.704 | G20: =IF(A20="","",MAX(0,G19-F20)*(1+INPUTS!$B$28)) -> 2040343.7 | H20: =IF(A20="","",MAX(0,H19-MAX(0,F20-G19))*(1+INPUTS!$B$28)) -> 679957.62
A21: =IF(MAX(59.5,INPUTS!$B$6)+16>INPUTS!$B$8,"",INPUTS!$B$12+(MAX(59.5,INPUTS!$B$6)-INPUTS!$B$5)+16) -> 2049.5 | B21: =IF(A21="","",MAX(59.5,INPUTS!$B$6)+16) -> 75.5 | C21: =IF(A21="","",INPUTS!$B$22*(1+INPUTS!$B$23)^(A21-INPUTS!$B$12)) -> 98259.268 | D21: =IF(A21="","",IF(B21>=INPUTS!$B$7,INPUTS!$B$25*(1+INPUTS!$B$23)^(A21-INPUTS!$B$12),0)) -> 42876.772 | E21: =IF(A21="","",INPUTS!$B$24) -> 0 | F21: =IF(A21="","",IF(G20+H20=0,0,MAX(0,C21-D21-E21))) -> 55382.497 | G21: =IF(A21="","",MAX(0,G20-F21)*(1+INPUTS!$B$28)) -> 2113983.7 | H21: =IF(A21="","",MAX(0,H20-MAX(0,F21-G20))*(1+INPUTS!$B$28)) -> 724154.87
A22: =IF(MAX(59.5,INPUTS!$B$6)+17>INPUTS!$B$8,"",INPUTS!$B$12+(MAX(59.5,INPUTS!$B$6)-INPUTS!$B$5)+17) -> 2050.5 | B22: =IF(A22="","",MAX(59.5,INPUTS!$B$6)+17) -> 76.5 | C22: =IF(A22="","",INPUTS!$B$22*(1+INPUTS!$B$23)^(A22-INPUTS!$B$12)) -> 100715.75 | D22: =IF(A22="","",IF(B22>=INPUTS!$B$7,INPUTS!$B$25*(1+INPUTS!$B$23)^(A22-INPUTS!$B$12),0)) -> 43948.691 | E22: =IF(A22="","",INPUTS!$B$24) -> 0 | F22: =IF(A22="","",IF(G21+H21=0,0,MAX(0,C22-D22-E22))) -> 56767.059 | G22: =IF(A22="","",MAX(0,G21-F22)*(1+INPUTS!$B$28)) -> 2190935.7 | H22: =IF(A22="","",MAX(0,H21-MAX(0,F22-G21))*(1+INPUTS!$B$28)) -> 771224.93
A23: =IF(MAX(59.5,INPUTS!$B$6)+18>INPUTS!$B$8,"",INPUTS!$B$12+(MAX(59.5,INPUTS!$B$6)-INPUTS!$B$5)+18) -> 2051.5 | B23: =IF(A23="","",MAX(59.5,INPUTS!$B$6)+18) -> 77.5 | C23: =IF(A23="","",INPUTS!$B$22*(1+INPUTS!$B$23)^(A23-INPUTS!$B$12)) -> 103233.64 | D23: =IF(A23="","",IF(B23>=INPUTS!$B$7,INPUTS!$B$25*(1+INPUTS!$B$23)^(A23-INPUTS!$B$12),0)) -> 45047.408 | E23: =IF(A23="","",INPUTS!$B$24) -> 0 | F23: =IF(A23="","",IF(G22+H22=0,0,MAX(0,C23-D23-E23))) -> 58186.236 | G23: =IF(A23="","",MAX(0,G22-F23)*(1+INPUTS!$B$28)) -> 2271378.2 | H23: =IF(A23="","",MAX(0,H22-MAX(0,F23-G22))*(1+INPUTS!$B$28)) -> 821354.55
A24: =IF(MAX(59.5,INPUTS!$B$6)+19>INPUTS!$B$8,"",INPUTS!$B$12+(MAX(59.5,INPUTS!$B$6)-INPUTS!$B$5)+19) -> 2052.5 | B24: =IF(A24="","",MAX(59.5,INPUTS!$B$6)+19) -> 78.5 | C24: =IF(A24="","",INPUTS!$B$22*(1+INPUTS!$B$23)^(A24-INPUTS!$B$12)) -> 105814.48 | D24: =IF(A24="","",IF(B24>=INPUTS!$B$7,INPUTS!$B$25*(1+INPUTS!$B$23)^(A24-INPUTS!$B$12),0)) -> 46173.593 | E24: =IF(A24="","",INPUTS!$B$24) -> 0 | F24: =IF(A24="","",IF(G23+H23=0,0,MAX(0,C24-D24-E24))) -> 59640.892 | G24: =IF(A24="","",MAX(0,G23-F24)*(1+INPUTS!$B$28)) -> 2355500.2 | H24: =IF(A24="","",MAX(0,H23-MAX(0,F24-G23))*(1+INPUTS!$B$28)) -> 874742.6
A25: =IF(MAX(59.5,INPUTS!$B$6)+20>INPUTS!$B$8,"",INPUTS!$B$12+(MAX(59.5,INPUTS!$B$6)-INPUTS!$B$5)+20) -> 2053.5 | B25: =IF(A25="","",MAX(59.5,INPUTS!$B$6)+20) -> 79.5 | C25: =IF(A25="","",INPUTS!$B$22*(1+INPUTS!$B$23)^(A25-INPUTS!$B$12)) -> 108459.85 | D25: =IF(A25="","",IF(B25>=INPUTS!$B$7,INPUTS!$B$25*(1+INPUTS!$B$23)^(A25-INPUTS!$B$12),0)) -> 47327.933 | E25: =IF(A25="","",INPUTS!$B$24) -> 0 | F25: =IF(A25="","",IF(G24+H24=0,0,MAX(0,C25-D25-E25))) -> 61131.914 | G25: =IF(A25="","",MAX(0,G24-F25)*(1+INPUTS!$B$28)) -> 2443502.3 | H25: =IF(A25="","",MAX(0,H24-MAX(0,F25-G24))*(1+INPUTS!$B$28)) -> 931600.87
A26: =IF(MAX(59.5,INPUTS!$B$6)+21>INPUTS!$B$8,"",INPUTS!$B$12+(MAX(59.5,INPUTS!$B$6)-INPUTS!$B$5)+21) -> 2054.5 | B26: =IF(A26="","",MAX(59.5,INPUTS!$B$6)+21) -> 80.5 | C26: =IF(A26="","",INPUTS!$B$22*(1+INPUTS!$B$23)^(A26-INPUTS!$B$12)) -> 111171.34 | D26: =IF(A26="","",IF(B26>=INPUTS!$B$7,INPUTS!$B$25*(1+INPUTS!$B$23)^(A26-INPUTS!$B$12),0)) -> 48511.132 | E26: =IF(A26="","",INPUTS!$B$24) -> 0 | F26: =IF(A26="","",IF(G25+H25=0,0,MAX(0,C26-D26-E26))) -> 62660.212 | G26: =IF(A26="","",MAX(0,G25-F26)*(1+INPUTS!$B$28)) -> 2535596.8 | H26: =IF(A26="","",MAX(0,H25-MAX(0,F26-G25))*(1+INPUTS!$B$28)) -> 992154.92
A27: =IF(MAX(59.5,INPUTS!$B$6)+22>INPUTS!$B$8,"",INPUTS!$B$12+(MAX(59.5,INPUTS!$B$6)-INPUTS!$B$5)+22) -> 2055.5 | B27: =IF(A27="","",MAX(59.5,INPUTS!$B$6)+22) -> 81.5 | C27: =IF(A27="","",INPUTS!$B$22*(1+INPUTS!$B$23)^(A27-INPUTS!$B$12)) -> 113950.63 | D27: =IF(A27="","",IF(B27>=INPUTS!$B$7,INPUTS!$B$25*(1+INPUTS!$B$23)^(A27-INPUTS!$B$12),0)) -> 49723.91 | E27: =IF(A27="","",INPUTS!$B$24) -> 0 | F27: =IF(A27="","",IF(G26+H26=0,0,MAX(0,C27-D27-E27))) -> 64226.717 | G27: =IF(A27="","",MAX(0,G26-F27)*(1+INPUTS!$B$28)) -> 2632009.1 | H27: =IF(A27="","",MAX(0,H26-MAX(0,F27-G26))*(1+INPUTS!$B$28)) -> 1056645
A28: =IF(MAX(59.5,INPUTS!$B$6)+23>INPUTS!$B$8,"",INPUTS!$B$12+(MAX(59.5,INPUTS!$B$6)-INPUTS!$B$5)+23) -> 2056.5 | B28: =IF(A28="","",MAX(59.5,INPUTS!$B$6)+23) -> 82.5 | C28: =IF(A28="","",INPUTS!$B$22*(1+INPUTS!$B$23)^(A28-INPUTS!$B$12)) -> 116799.39 | D28: =IF(A28="","",IF(B28>=INPUTS!$B$7,INPUTS!$B$25*(1+INPUTS!$B$23)^(A28-INPUTS!$B$12),0)) -> 50967.008 | E28: =IF(A28="","",INPUTS!$B$24) -> 0 | F28: =IF(A28="","",IF(G27+H27=0,0,MAX(0,C28-D28-E28))) -> 65832.385 | G28: =IF(A28="","",MAX(0,G27-F28)*(1+INPUTS!$B$28)) -> 2732978.2 | H28: =IF(A28="","",MAX(0,H27-MAX(0,F28-G27))*(1+INPUTS!$B$28)) -> 1125326.9
A29: =IF(MAX(59.5,INPUTS!$B$6)+24>INPUTS!$B$8,"",INPUTS!$B$12+(MAX(59.5,INPUTS!$B$6)-INPUTS!$B$5)+24) -> 2057.5 | B29: =IF(A29="","",MAX(59.5,INPUTS!$B$6)+24) -> 83.5 | C29: =IF(A29="","",INPUTS!$B$22*(1+INPUTS!$B$23)^(A29-INPUTS!$B$12)) -> 119719.38 | D29: =IF(A29="","",IF(B29>=INPUTS!$B$7,INPUTS!$B$25*(1+INPUTS!$B$23)^(A29-INPUTS!$B$12),0)) -> 52241.183 | E29: =IF(A29="","",INPUTS!$B$24) -> 0 | F29: =IF(A29="","",IF(G28+H28=0,0,MAX(0,C29-D29-E29))) -> 67478.194 | G29: =IF(A29="","",MAX(0,G28-F29)*(1+INPUTS!$B$28)) -> 2838757.5 | H29: =IF(A29="","",MAX(0,H28-MAX(0,F29-G28))*(1+INPUTS!$B$28)) -> 1198473.2
A30: =IF(MAX(59.5,INPUTS!$B$6)+25>INPUTS!$B$8,"",INPUTS!$B$12+(MAX(59.5,INPUTS!$B$6)-INPUTS!$B$5)+25) -> 2058.5 | B30: =IF(A30="","",MAX(59.5,INPUTS!$B$6)+25) -> 84.5 | C30: =IF(A30="","",INPUTS!$B$22*(1+INPUTS!$B$23)^(A30-INPUTS!$B$12)) -> 122712.36 | D30: =IF(A30="","",IF(B30>=INPUTS!$B$7,INPUTS!$B$25*(1+INPUTS!$B$23)^(A30-INPUTS!$B$12),0)) -> 53547.212 | E30: =IF(A30="","",INPUTS!$B$24) -> 0 | F30: =IF(A30="","",IF(G29+H29=0,0,MAX(0,C30-D30-E30))) -> 69165.149 | G30: =IF(A30="","",MAX(0,G29-F30)*(1+INPUTS!$B$28)) -> 2949615.9 | H30: =IF(A30="","",MAX(0,H29-MAX(0,F30-G29))*(1+INPUTS!$B$28)) -> 1276373.9
A31: =IF(MAX(59.5,INPUTS!$B$6)+26>INPUTS!$B$8,"",INPUTS!$B$12+(MAX(59.5,INPUTS!$B$6)-INPUTS!$B$5)+26) -> 2059.5 | B31: =IF(A31="","",MAX(59.5,INPUTS!$B$6)+26) -> 85.5 | C31: =IF(A31="","",INPUTS!$B$22*(1+INPUTS!$B$23)^(A31-INPUTS!$B$12)) -> 125780.17 | D31: =IF(A31="","",IF(B31>=INPUTS!$B$7,INPUTS!$B$25*(1+INPUTS!$B$23)^(A31-INPUTS!$B$12),0)) -> 54885.893 | E31: =IF(A31="","",INPUTS!$B$24) -> 0 | F31: =IF(A31="","",IF(G30+H30=0,0,MAX(0,C31-D31-E31))) -> 70894.278 | G31: =IF(A31="","",MAX(0,G30-F31)*(1+INPUTS!$B$28)) -> 3065838.5 | H31: =IF(A31="","",MAX(0,H30-MAX(0,F31-G30))*(1+INPUTS!$B$28)) -> 1359338.2
A32: =IF(MAX(59.5,INPUTS!$B$6)+27>INPUTS!$B$8,"",INPUTS!$B$12+(MAX(59.5,INPUTS!$B$6)-INPUTS!$B$5)+27) -> 2060.5 | B32: =IF(A32="","",MAX(59.5,INPUTS!$B$6)+27) -> 86.5 | C32: =IF(A32="","",INPUTS!$B$22*(1+INPUTS!$B$23)^(A32-INPUTS!$B$12)) -> 128924.68 | D32: =IF(A32="","",IF(B32>=INPUTS!$B$7,INPUTS!$B$25*(1+INPUTS!$B$23)^(A32-INPUTS!$B$12),0)) -> 56258.04 | E32: =IF(A32="","",INPUTS!$B$24) -> 0 | F32: =IF(A32="","",IF(G31+H31=0,0,MAX(0,C32-D32-E32))) -> 72666.635 | G32: =IF(A32="","",MAX(0,G31-F32)*(1+INPUTS!$B$28)) -> 3187728.1 | H32: =IF(A32="","",MAX(0,H31-MAX(0,F32-G31))*(1+INPUTS!$B$28)) -> 1447695.2
A33: =IF(MAX(59.5,INPUTS!$B$6)+28>INPUTS!$B$8,"",INPUTS!$B$12+(MAX(59.5,INPUTS!$B$6)-INPUTS!$B$5)+28) -> 2061.5 | B33: =IF(A33="","",MAX(59.5,INPUTS!$B$6)+28) -> 87.5 | C33: =IF(A33="","",INPUTS!$B$22*(1+INPUTS!$B$23)^(A33-INPUTS!$B$12)) -> 132147.79 | D33: =IF(A33="","",IF(B33>=INPUTS!$B$7,INPUTS!$B$25*(1+INPUTS!$B$23)^(A33-INPUTS!$B$12),0)) -> 57664.491 | E33: =IF(A33="","",INPUTS!$B$24) -> 0 | F33: =IF(A33="","",IF(G32+H32=0,0,MAX(0,C33-D33-E33))) -> 74483.301 | G33: =IF(A33="","",MAX(0,G32-F33)*(1+INPUTS!$B$28)) -> 3315605.7 | H33: =IF(A33="","",MAX(0,H32-MAX(0,F33-G32))*(1+INPUTS!$B$28)) -> 1541795.4
A34: =IF(MAX(59.5,INPUTS!$B$6)+29>INPUTS!$B$8,"",INPUTS!$B$12+(MAX(59.5,INPUTS!$B$6)-INPUTS!$B$5)+29) -> 2062.5 | B34: =IF(A34="","",MAX(59.5,INPUTS!$B$6)+29) -> 88.5 | C34: =IF(A34="","",INPUTS!$B$22*(1+INPUTS!$B$23)^(A34-INPUTS!$B$12)) -> 135451.49 | D34: =IF(A34="","",IF(B34>=INPUTS!$B$7,INPUTS!$B$25*(1+INPUTS!$B$23)^(A34-INPUTS!$B$12),0)) -> 59106.103 | E34: =IF(A34="","",INPUTS!$B$24) -> 0 | F34: =IF(A34="","",IF(G33+H33=0,0,MAX(0,C34-D34-E34))) -> 76345.383 | G34: =IF(A34="","",MAX(0,G33-F34)*(1+INPUTS!$B$28)) -> 3449812.2 | H34: =IF(A34="","",MAX(0,H33-MAX(0,F34-G33))*(1+INPUTS!$B$28)) -> 1642012.1
A35: =IF(MAX(59.5,INPUTS!$B$6)+30>INPUTS!$B$8,"",INPUTS!$B$12+(MAX(59.5,INPUTS!$B$6)-INPUTS!$B$5)+30) -> 2063.5 | B35: =IF(A35="","",MAX(59.5,INPUTS!$B$6)+30) -> 89.5 | C35: =IF(A35="","",INPUTS!$B$22*(1+INPUTS!$B$23)^(A35-INPUTS!$B$12)) -> 138837.77 | D35: =IF(A35="","",IF(B35>=INPUTS!$B$7,INPUTS!$B$25*(1+INPUTS!$B$23)^(A35-INPUTS!$B$12),0)) -> 60583.756 | E35: =IF(A35="","",INPUTS!$B$24) -> 0 | F35: =IF(A35="","",IF(G34+H34=0,0,MAX(0,C35-D35-E35))) -> 78254.018 | G35: =IF(A35="","",MAX(0,G34-F35)*(1+INPUTS!$B$28)) -> 3590709.5 | H35: =IF(A35="","",MAX(0,H34-MAX(0,F35-G34))*(1+INPUTS!$B$28)) -> 1748742.9
A36: =IF(MAX(59.5,INPUTS!$B$6)+31>INPUTS!$B$8,"",INPUTS!$B$12+(MAX(59.5,INPUTS!$B$6)-INPUTS!$B$5)+31) | B36: =IF(A36="","",MAX(59.5,INPUTS!$B$6)+31) | C36: =IF(A36="","",INPUTS!$B$22*(1+INPUTS!$B$23)^(A36-INPUTS!$B$12)) | D36: =IF(A36="","",IF(B36>=INPUTS!$B$7,INPUTS!$B$25*(1+INPUTS!$B$23)^(A36-INPUTS!$B$12),0)) | E36: =IF(A36="","",INPUTS!$B$24) | F36: =IF(A36="","",IF(G35+H35=0,0,MAX(0,C36-D36-E36))) | G36: =IF(A36="","",MAX(0,G35-F36)*(1+INPUTS!$B$28)) | H36: =IF(A36="","",MAX(0,H35-MAX(0,F36-G35))*(1+INPUTS!$B$28))
A37: =IF(MAX(59.5,INPUTS!$B$6)+32>INPUTS!$B$8,"",INPUTS!$B$12+(MAX(59.5,INPUTS!$B$6)-INPUTS!$B$5)+32) | B37: =IF(A37="","",MAX(59.5,INPUTS!$B$6)+32) | C37: =IF(A37="","",INPUTS!$B$22*(1+INPUTS!$B$23)^(A37-INPUTS!$B$12)) | D37: =IF(A37="","",IF(B37>=INPUTS!$B$7,INPUTS!$B$25*(1+INPUTS!$B$23)^(A37-INPUTS!$B$12),0)) | E37: =IF(A37="","",INPUTS!$B$24) | F37: =IF(A37="","",IF(G36+H36=0,0,MAX(0,C37-D37-E37))) | G37: =IF(A37="","",MAX(0,G36-F37)*(1+INPUTS!$B$28)) | H37: =IF(A37="","",MAX(0,H36-MAX(0,F37-G36))*(1+INPUTS!$B$28))
A38: =IF(MAX(59.5,INPUTS!$B$6)+33>INPUTS!$B$8,"",INPUTS!$B$12+(MAX(59.5,INPUTS!$B$6)-INPUTS!$B$5)+33) | B38: =IF(A38="","",MAX(59.5,INPUTS!$B$6)+33) | C38: =IF(A38="","",INPUTS!$B$22*(1+INPUTS!$B$23)^(A38-INPUTS!$B$12)) | D38: =IF(A38="","",IF(B38>=INPUTS!$B$7,INPUTS!$B$25*(1+INPUTS!$B$23)^(A38-INPUTS!$B$12),0)) | E38: =IF(A38="","",INPUTS!$B$24) | F38: =IF(A38="","",IF(G37+H37=0,0,MAX(0,C38-D38-E38))) | G38: =IF(A38="","",MAX(0,G37-F38)*(1+INPUTS!$B$28)) | H38: =IF(A38="","",MAX(0,H37-MAX(0,F38-G37))*(1+INPUTS!$B$28))
A39: =IF(MAX(59.5,INPUTS!$B$6)+34>INPUTS!$B$8,"",INPUTS!$B$12+(MAX(59.5,INPUTS!$B$6)-INPUTS!$B$5)+34) | B39: =IF(A39="","",MAX(59.5,INPUTS!$B$6)+34) | C39: =IF(A39="","",INPUTS!$B$22*(1+INPUTS!$B$23)^(A39-INPUTS!$B$12)) | D39: =IF(A39="","",IF(B39>=INPUTS!$B$7,INPUTS!$B$25*(1+INPUTS!$B$23)^(A39-INPUTS!$B$12),0)) | E39: =IF(A39="","",INPUTS!$B$24) | F39: =IF(A39="","",IF(G38+H38=0,0,MAX(0,C39-D39-E39))) | G39: =IF(A39="","",MAX(0,G38-F39)*(1+INPUTS!$B$28)) | H39: =IF(A39="","",MAX(0,H38-MAX(0,F39-G38))*(1+INPUTS!$B$28))
A40: =IF(MAX(59.5,INPUTS!$B$6)+35>INPUTS!$B$8,"",INPUTS!$B$12+(MAX(59.5,INPUTS!$B$6)-INPUTS!$B$5)+35) | B40: =IF(A40="","",MAX(59.5,INPUTS!$B$6)+35) | C40: =IF(A40="","",INPUTS!$B$22*(1+INPUTS!$B$23)^(A40-INPUTS!$B$12)) | D40: =IF(A40="","",IF(B40>=INPUTS!$B$7,INPUTS!$B$25*(1+INPUTS!$B$23)^(A40-INPUTS!$B$12),0)) | E40: =IF(A40="","",INPUTS!$B$24) | F40: =IF(A40="","",IF(G39+H39=0,0,MAX(0,C40-D40-E40))) | G40: =IF(A40="","",MAX(0,G39-F40)*(1+INPUTS!$B$28)) | H40: =IF(A40="","",MAX(0,H39-MAX(0,F40-G39))*(1+INPUTS!$B$28))
A41: =IF(MAX(59.5,INPUTS!$B$6)+36>INPUTS!$B$8,"",INPUTS!$B$12+(MAX(59.5,INPUTS!$B$6)-INPUTS!$B$5)+36) | B41: =IF(A41="","",MAX(59.5,INPUTS!$B$6)+36) | C41: =IF(A41="","",INPUTS!$B$22*(1+INPUTS!$B$23)^(A41-INPUTS!$B$12)) | D41: =IF(A41="","",IF(B41>=INPUTS!$B$7,INPUTS!$B$25*(1+INPUTS!$B$23)^(A41-INPUTS!$B$12),0)) | E41: =IF(A41="","",INPUTS!$B$24) | F41: =IF(A41="","",IF(G40+H40=0,0,MAX(0,C41-D41-E41))) | G41: =IF(A41="","",MAX(0,G40-F41)*(1+INPUTS!$B$28)) | H41: =IF(A41="","",MAX(0,H40-MAX(0,F41-G40))*(1+INPUTS!$B$28))
A42: =IF(MAX(59.5,INPUTS!$B$6)+37>INPUTS!$B$8,"",INPUTS!$B$12+(MAX(59.5,INPUTS!$B$6)-INPUTS!$B$5)+37) | B42: =IF(A42="","",MAX(59.5,INPUTS!$B$6)+37) | C42: =IF(A42="","",INPUTS!$B$22*(1+INPUTS!$B$23)^(A42-INPUTS!$B$12)) | D42: =IF(A42="","",IF(B42>=INPUTS!$B$7,INPUTS!$B$25*(1+INPUTS!$B$23)^(A42-INPUTS!$B$12),0)) | E42: =IF(A42="","",INPUTS!$B$24) | F42: =IF(A42="","",IF(G41+H41=0,0,MAX(0,C42-D42-E42))) | G42: =IF(A42="","",MAX(0,G41-F42)*(1+INPUTS!$B$28)) | H42: =IF(A42="","",MAX(0,H41-MAX(0,F42-G41))*(1+INPUTS!$B$28))
A43: =IF(MAX(59.5,INPUTS!$B$6)+38>INPUTS!$B$8,"",INPUTS!$B$12+(MAX(59.5,INPUTS!$B$6)-INPUTS!$B$5)+38) | B43: =IF(A43="","",MAX(59.5,INPUTS!$B$6)+38) | C43: =IF(A43="","",INPUTS!$B$22*(1+INPUTS!$B$23)^(A43-INPUTS!$B$12)) | D43: =IF(A43="","",IF(B43>=INPUTS!$B$7,INPUTS!$B$25*(1+INPUTS!$B$23)^(A43-INPUTS!$B$12),0)) | E43: =IF(A43="","",INPUTS!$B$24) | F43: =IF(A43="","",IF(G42+H42=0,0,MAX(0,C43-D43-E43))) | G43: =IF(A43="","",MAX(0,G42-F43)*(1+INPUTS!$B$28)) | H43: =IF(A43="","",MAX(0,H42-MAX(0,F43-G42))*(1+INPUTS!$B$28))
A44: =IF(MAX(59.5,INPUTS!$B$6)+39>INPUTS!$B$8,"",INPUTS!$B$12+(MAX(59.5,INPUTS!$B$6)-INPUTS!$B$5)+39) | B44: =IF(A44="","",MAX(59.5,INPUTS!$B$6)+39) | C44: =IF(A44="","",INPUTS!$B$22*(1+INPUTS!$B$23)^(A44-INPUTS!$B$12)) | D44: =IF(A44="","",IF(B44>=INPUTS!$B$7,INPUTS!$B$25*(1+INPUTS!$B$23)^(A44-INPUTS!$B$12),0)) | E44: =IF(A44="","",INPUTS!$B$24) | F44: =IF(A44="","",IF(G43+H43=0,0,MAX(0,C44-D44-E44))) | G44: =IF(A44="","",MAX(0,G43-F44)*(1+INPUTS!$B$28)) | H44: =IF(A44="","",MAX(0,H43-MAX(0,F44-G43))*(1+INPUTS!$B$28))
A45: =IF(MAX(59.5,INPUTS!$B$6)+40>INPUTS!$B$8,"",INPUTS!$B$12+(MAX(59.5,INPUTS!$B$6)-INPUTS!$B$5)+40) | B45: =IF(A45="","",MAX(59.5,INPUTS!$B$6)+40) | C45: =IF(A45="","",INPUTS!$B$22*(1+INPUTS!$B$23)^(A45-INPUTS!$B$12)) | D45: =IF(A45="","",IF(B45>=INPUTS!$B$7,INPUTS!$B$25*(1+INPUTS!$B$23)^(A45-INPUTS!$B$12),0)) | E45: =IF(A45="","",INPUTS!$B$24) | F45: =IF(A45="","",IF(G44+H44=0,0,MAX(0,C45-D45-E45))) | G45: =IF(A45="","",MAX(0,G44-F45)*(1+INPUTS!$B$28)) | H45: =IF(A45="","",MAX(0,H44-MAX(0,F45-G44))*(1+INPUTS!$B$28))
A46: =IF(MAX(59.5,INPUTS!$B$6)+41>INPUTS!$B$8,"",INPUTS!$B$12+(MAX(59.5,INPUTS!$B$6)-INPUTS!$B$5)+41) | B46: =IF(A46="","",MAX(59.5,INPUTS!$B$6)+41) | C46: =IF(A46="","",INPUTS!$B$22*(1+INPUTS!$B$23)^(A46-INPUTS!$B$12)) | D46: =IF(A46="","",IF(B46>=INPUTS!$B$7,INPUTS!$B$25*(1+INPUTS!$B$23)^(A46-INPUTS!$B$12),0)) | E46: =IF(A46="","",INPUTS!$B$24) | F46: =IF(A46="","",IF(G45+H45=0,0,MAX(0,C46-D46-E46))) | G46: =IF(A46="","",MAX(0,G45-F46)*(1+INPUTS!$B$28)) | H46: =IF(A46="","",MAX(0,H45-MAX(0,F46-G45))*(1+INPUTS!$B$28))
A47: =IF(MAX(59.5,INPUTS!$B$6)+42>INPUTS!$B$8,"",INPUTS!$B$12+(MAX(59.5,INPUTS!$B$6)-INPUTS!$B$5)+42) | B47: =IF(A47="","",MAX(59.5,INPUTS!$B$6)+42) | C47: =IF(A47="","",INPUTS!$B$22*(1+INPUTS!$B$23)^(A47-INPUTS!$B$12)) | D47: =IF(A47="","",IF(B47>=INPUTS!$B$7,INPUTS!$B$25*(1+INPUTS!$B$23)^(A47-INPUTS!$B$12),0)) | E47: =IF(A47="","",INPUTS!$B$24) | F47: =IF(A47="","",IF(G46+H46=0,0,MAX(0,C47-D47-E47))) | G47: =IF(A47="","",MAX(0,G46-F47)*(1+INPUTS!$B$28)) | H47: =IF(A47="","",MAX(0,H46-MAX(0,F47-G46))*(1+INPUTS!$B$28))
A48: =IF(MAX(59.5,INPUTS!$B$6)+43>INPUTS!$B$8,"",INPUTS!$B$12+(MAX(59.5,INPUTS!$B$6)-INPUTS!$B$5)+43) | B48: =IF(A48="","",MAX(59.5,INPUTS!$B$6)+43) | C48: =IF(A48="","",INPUTS!$B$22*(1+INPUTS!$B$23)^(A48-INPUTS!$B$12)) | D48: =IF(A48="","",IF(B48>=INPUTS!$B$7,INPUTS!$B$25*(1+INPUTS!$B$23)^(A48-INPUTS!$B$12),0)) | E48: =IF(A48="","",INPUTS!$B$24) | F48: =IF(A48="","",IF(G47+H47=0,0,MAX(0,C48-D48-E48))) | G48: =IF(A48="","",MAX(0,G47-F48)*(1+INPUTS!$B$28)) | H48: =IF(A48="","",MAX(0,H47-MAX(0,F48-G47))*(1+INPUTS!$B$28))
A49: =IF(MAX(59.5,INPUTS!$B$6)+44>INPUTS!$B$8,"",INPUTS!$B$12+(MAX(59.5,INPUTS!$B$6)-INPUTS!$B$5)+44) | B49: =IF(A49="","",MAX(59.5,INPUTS!$B$6)+44) | C49: =IF(A49="","",INPUTS!$B$22*(1+INPUTS!$B$23)^(A49-INPUTS!$B$12)) | D49: =IF(A49="","",IF(B49>=INPUTS!$B$7,INPUTS!$B$25*(1+INPUTS!$B$23)^(A49-INPUTS!$B$12),0)) | E49: =IF(A49="","",INPUTS!$B$24) | F49: =IF(A49="","",IF(G48+H48=0,0,MAX(0,C49-D49-E49))) | G49: =IF(A49="","",MAX(0,G48-F49)*(1+INPUTS!$B$28)) | H49: =IF(A49="","",MAX(0,H48-MAX(0,F49-G48))*(1+INPUTS!$B$28))
A51: BALANCE AT LIFE EXPECTANCY → | F51: =IFERROR(G51+H51,0) -> 5339452.4 | G51: =IFERROR(LOOKUP(9.99E+307,G5:G49),0) -> 3590709.5 | H51: =IFERROR(LOOKUP(9.99E+307,H5:H49),0) -> 1748742.9

Sheet MONTE CARLO
A1: MONTE CARLO SIMULATOR · 200 Randomized Return Sequences · up to 60 years
A2: Each row = one possible retirement. Returns drawn from Normal(mean=INPUTS return, sd=INPUTS volatility). Press F9 / Ctrl+Shift+F9 to re-run.
A4: Net Withdrawal → | C4: =IFERROR(MAX(0,INPUTS!$B$22*(1+INPUTS!$B$23)^(INPUTS!$B$6-INPUTS!$B$5+0)-IF(INPUTS!$B$6+0>=INPUTS!$B$7,INPUTS!$B$25*(1+INPUTS!$B$23)^(INPUTS!$B$6-INPUTS!$B$5+0),0)-INPUTS!$B$24),0) -> 59228.984 | D4: =IFERROR(MAX(0,INPUTS!$B$22*(1+INPUTS!$B$23)^(INPUTS!$B$6-INPUTS!$B$5+1)-IF(INPUTS!$B$6+1>=INPUTS!$B$7,INPUTS!$B$25*(1+INPUTS!$B$23)^(INPUTS!$B$6-INPUTS!$B$5+1),0)-INPUTS!$B$24),0) -> 60709.709 | E4: =IFERROR(MAX(0,INPUTS!$B$22*(1+INPUTS!$B$23)^(INPUTS!$B$6-INPUTS!$B$5+2)-IF(INPUTS!$B$6+2>=INPUTS!$B$7,INPUTS!$B$25*(1+INPUTS!$B$23)^(INPUTS!$B$6-INPUTS!$B$5+2),0)-INPUTS!$B$24),0) -> 62227.452 | F4: =IFERROR(MAX(0,INPUTS!$B$22*(1+INPUTS!$B$23)^(INPUTS!$B$6-INPUTS!$B$5+3)-IF(INPUTS!$B$6+3>=INPUTS!$B$7,INPUTS!$B$25*(1+INPUTS!$B$23)^(INPUTS!$B$6-INPUTS!$B$5+3),0)-INPUTS!$B$24),0) -> 63783.138 | G4: =IFERROR(MAX(0,INPUTS!$B$22*(1+INPUTS!$B$23)^(INPUTS!$B$6-INPUTS!$B$5+4)-IF(INPUTS!$B$6+4>=INPUTS!$B$7,INPUTS!$B$25*(1+INPUTS!$B$23)^(INPUTS!$B$6-INPUTS!$B$5+4),0)-INPUTS!$B$24),0) -> 65377.716 | H4: =IFERROR(MAX(0,INPUTS!$B$22*(1+INPUTS!$B$23)^(INPUTS!$B$6-INPUTS!$B$5+5)-IF(INPUTS!$B$6+5>=INPUTS!$B$7,INPUTS!$B$25*(1+INPUTS!$B$23)^(INPUTS!$B$6-INPUTS!$B$5+5),0)-INPUTS!$B$24),0) -> 67012.159 | I4: =IFERROR(MAX(0,INPUTS!$B$22*(1+INPUTS!$B$23)^(INPUTS!$B$6-INPUTS!$B$5+6)-IF(INPUTS!$B$6+6>=INPUTS!$B$7,INPUTS!$B$25*(1+INPUTS!$B$23)^(INPUTS!$B$6-INPUTS!$B$5+6),0)-INPUTS!$B$24),0) -> 68687.463 | J4: =IFERROR(MAX(0,INPUTS!$B$22*(1+INPUTS!$B$23)^(INPUTS!$B$6-INPUTS!$B$5+7)-IF(INPUTS!$B$6+7>=INPUTS!$B$7,INPUTS!$B$25*(1+INPUTS!$B$23)^(INPUTS!$B$6-INPUTS!$B$5+7),0)-INPUTS!$B$24),0) -> 70404.65 | K4: =IFERROR(MAX(0,INPUTS!$B$22*(1+INPUTS!$B$23)^(INPUTS!$B$6-INPUTS!$B$5+8)-IF(INPUTS!$B$6+8>=INPUTS!$B$7,INPUTS!$B$25*(1+INPUTS!$B$23)^(INPUTS!$B$6-INPUTS!$B$5+8),0)-INPUTS!$B$24),0) -> 72164.766 | L4: =IFERROR(MAX(0,INPUTS!$B$22*(1+INPUTS!$B$23)^(INPUTS!$B$6-INPUTS!$B$5+9)-IF(INPUTS!$B$6+9>=INPUTS!$B$7,INPUTS!$B$25*(1+INPUTS!$B$23)^(INPUTS!$B$6-INPUTS!$B$5+9),0)-INPUTS!$B$24),0) -> 73968.885 | M4: =IFERROR(MAX(0,INPUTS!$B$22*(1+INPUTS!$B$23)^(INPUTS!$B$6-INPUTS!$B$5+10)-IF(INPUTS!$B$6+10>=INPUTS!$B$7,INPUTS!$B$25*(1+INPUTS!$B$23)^(INPUTS!$B$6-INPUTS!$B$5+10),0)-INPUTS!$B$24),0) -> 75818.107 | N4: =IFERROR(MAX(0,INPUTS!$B$22*(1+INPUTS!$B$23)^(INPUTS!$B$6-INPUTS!$B$5+11)-IF(INPUTS!$B$6+11>=INPUTS!$B$7,INPUTS!$B$25*(1+INPUTS!$B$23)^(INPUTS!$B$6-INPUTS!$B$5+11),0)-INPUTS!$B$24),0) -> 77713.56 | O4: =IFERROR(MAX(0,INPUTS!$B$22*(1+INPUTS!$B$23)^(INPUTS!$B$6-INPUTS!$B$5+12)-IF(INPUTS!$B$6+12>=INPUTS!$B$7,INPUTS!$B$25*(1+INPUTS!$B$23)^(INPUTS!$B$6-INPUTS!$B$5+12),0)-INPUTS!$B$24),0) -> 44897.243 | P4: =IFERROR(MAX(0,INPUTS!$B$22*(1+INPUTS!$B$23)^(INPUTS!$B$6-INPUTS!$B$5+13)-IF(INPUTS!$B$6+13>=INPUTS!$B$7,INPUTS!$B$25*(1+INPUTS!$B$23)^(INPUTS!$B$6-INPUTS!$B$5+13),0)-INPUTS!$B$24),0) -> 46019.674 | Q4: =IFERROR(MAX(0,INPUTS!$B$22*(1+INPUTS!$B$23)^(INPUTS!$B$6-INPUTS!$B$5+14)-IF(INPUTS!$B$6+14>=INPUTS!$B$7,INPUTS!$B$25*(1+INPUTS!$B$23)^(INPUTS!$B$6-INPUTS!$B$5+14),0)-INPUTS!$B$24),0) -> 47170.166 | R4: =IFERROR(MAX(0,INPUTS!$B$22*(1+INPUTS!$B$23)^(INPUTS!$B$6-INPUTS!$B$5+15)-IF(INPUTS!$B$6+15>=INPUTS!$B$7,INPUTS!$B$25*(1+INPUTS!$B$23)^(INPUTS!$B$6-INPUTS!$B$5+15),0)-INPUTS!$B$24),0) -> 48349.42 | S4: =IFERROR(MAX(0,INPUTS!$B$22*(1+INPUTS!$B$23)^(INPUTS!$B$6-INPUTS!$B$5+16)-IF(INPUTS!$B$6+16>=INPUTS!$B$7,INPUTS!$B$25*(1+INPUTS!$B$23)^(INPUTS!$B$6-INPUTS!$B$5+16),0)-INPUTS!$B$24),0) -> 49558.156 | T4: =IFERROR(MAX(0,INPUTS!$B$22*(1+INPUTS!$B$23)^(INPUTS!$B$6-INPUTS!$B$5+17)-IF(INPUTS!$B$6+17>=INPUTS!$B$7,INPUTS!$B$25*(1+INPUTS!$B$23)^(INPUTS!$B$6-INPUTS!$B$5+17),0)-INPUTS!$B$24),0) -> 50797.11 | U4: =IFERROR(MAX(0,INPUTS!$B$22*(1+INPUTS!$B$23)^(INPUTS!$B$6-INPUTS!$B$5+18)-IF(INPUTS!$B$6+18>=INPUTS!$B$7,INPUTS!$B$25*(1+INPUTS!$B$23)^(INPUTS!$B$6-INPUTS!$B$5+18),0)-INPUTS!$B$24),0) -> 52067.037 | V4: =IFERROR(MAX(0,INPUTS!$B$22*(1+INPUTS!$B$23)^(INPUTS!$B$6-INPUTS!$B$5+19)-IF(INPUTS!$B$6+19>=INPUTS!$B$7,INPUTS!$B$25*(1+INPUTS!$B$23)^(INPUTS!$B$6-INPUTS!$B$5+19),0)-INPUTS!$B$24),0) -> 53368.713 | W4: =IFERROR(MAX(0,INPUTS!$B$22*(1+INPUTS!$B$23)^(INPUTS!$B$6-INPUTS!$B$5+20)-IF(INPUTS!$B$6+20>=INPUTS!$B$7,INPUTS!$B$25*(1+INPUTS!$B$23)^(INPUTS!$B$6-INPUTS!$B$5+20),0)-INPUTS!$B$24),0) -> 54702.931 | X4: =IFERROR(MAX(0,INPUTS!$B$22*(1+INPUTS!$B$23)^(INPUTS!$B$6-INPUTS!$B$5+21)-IF(INPUTS!$B$6+21>=INPUTS!$B$7,INPUTS!$B$25*(1+INPUTS!$B$23)^(INPUTS!$B$6-INPUTS!$B$5+21),0)-INPUTS!$B$24),0) -> 56070.504 | Y4: =IFERROR(MAX(0,INPUTS!$B$22*(1+INPUTS!$B$23)^(INPUTS!$B$6-INPUTS!$B$5+22)-IF(INPUTS!$B$6+22>=INPUTS!$B$7,INPUTS!$B$25*(1+INPUTS!$B$23)^(INPUTS!$B$6-INPUTS!$B$5+22),0)-INPUTS!$B$24),0) -> 57472.267 | Z4: =IFERROR(MAX(0,INPUTS!$B$22*(1+INPUTS!$B$23)^(INPUTS!$B$6-INPUTS!$B$5+23)-IF(INPUTS!$B$6+23>=INPUTS!$B$7,INPUTS!$B$25*(1+INPUTS!$B$23)^(INPUTS!$B$6-INPUTS!$B$5+23),0)-INPUTS!$B$24),0) -> 58909.074 | AA4: =IFERROR(MAX(0,INPUTS!$B$22*(1+INPUTS!$B$23)^(INPUTS!$B$6-INPUTS!$B$5+24)-IF(INPUTS!$B$6+24>=INPUTS!$B$7,INPUTS!$B$25*(1+INPUTS!$B$23)^(INPUTS!$B$6-INPUTS!$B$5+24),0)-INPUTS!$B$24),0) -> 60381.801 | AB4: =IFERROR(MAX(0,INPUTS!$B$22*(1+INPUTS!$B$23)^(INPUTS!$B$6-INPUTS!$B$5+25)-IF(INPUTS!$B$6+25>=INPUTS!$B$7,INPUTS!$B$25*(1+INPUTS!$B$23)^(INPUTS!$B$6-INPUTS!$B$5+25),0)-INPUTS!$B$24),0) -> 61891.346 | AC4: =IFERROR(MAX(0,INPUTS!$B$22*(1+INPUTS!$B$23)^(INPUTS!$B$6-INPUTS!$B$5+26)-IF(INPUTS!$B$6+26>=INPUTS!$B$7,INPUTS!$B$25*(1+INPUTS!$B$23)^(INPUTS!$B$6-INPUTS!$B$5+26),0)-INPUTS!$B$24),0) -> 63438.629 | AD4: =IFERROR(MAX(0,INPUTS!$B$22*(1+INPUTS!$B$23)^(INPUTS!$B$6-INPUTS!$B$5+27)-IF(INPUTS!$B$6+27>=INPUTS!$B$7,INPUTS!$B$25*(1+INPUTS!$B$23)^(INPUTS!$B$6-INPUTS!$B$5+27),0)-INPUTS!$B$24),0) -> 65024.595 | AE4: =IFERROR(MAX(0,INPUTS!$B$22*(1+INPUTS!$B$23)^(INPUTS!$B$6-INPUTS!$B$5+28)-IF(INPUTS!$B$6+28>=INPUTS!$B$7,INPUTS!$B$25*(1+INPUTS!$B$23)^(INPUTS!$B$6-INPUTS!$B$5+28),0)-INPUTS!$B$24),0) -> 66650.21 | AF4: =IFERROR(MAX(0,INPUTS!$B$22*(1+INPUTS!$B$23)^(INPUTS!$B$6-INPUTS!$B$5+29)-IF(INPUTS!$B$6+29>=INPUTS!$B$7,INPUTS!$B$25*(1+INPUTS!$B$23)^(INPUTS!$B$6-INPUTS!$B$5+29),0)-INPUTS!$B$24),0) -> 68316.465 | AG4: =IFERROR(MAX(0,INPUTS!$B$22*(1+INPUTS!$B$23)^(INPUTS!$B$6-INPUTS!$B$5+30)-IF(INPUTS!$B$6+30>=INPUTS!$B$7,INPUTS!$B$25*(1+INPUTS!$B$23)^(INPUTS!$B$6-INPUTS!$B$5+30),0)-INPUTS!$B$24),0) -> 70024.377 | AH4: =IFERROR(MAX(0,INPUTS!$B$22*(1+INPUTS!$B$23)^(INPUTS!$B$6-INPUTS!$B$5+31)-IF(INPUTS!$B$6+31>=INPUTS!$B$7,INPUTS!$B$25*(1+INPUTS!$B$23)^(INPUTS!$B$6-INPUTS!$B$5+31),0)-INPUTS!$B$24),0) -> 71774.986 | AI4: =IFERROR(MAX(0,INPUTS!$B$22*(1+INPUTS!$B$23)^(INPUTS!$B$6-INPUTS!$B$5+32)-IF(INPUTS!$B$6+32>=INPUTS!$B$7,INPUTS!$B$25*(1+INPUTS!$B$23)^(INPUTS!$B$6-INPUTS!$B$5+32),0)-INPUTS!$B$24),0) -> 73569.361 | AJ4: =IFERROR(MAX(0,INPUTS!$B$22*(1+INPUTS!$B$23)^(INPUTS!$B$6-INPUTS!$B$5+33)-IF(INPUTS!$B$6+33>=INPUTS!$B$7,INPUTS!$B$25*(1+INPUTS!$B$23)^(INPUTS!$B$6-INPUTS!$B$5+33),0)-INPUTS!$B$24),0) -> 75408.595 | AK4: =IFERROR(MAX(0,INPUTS!$B$22*(1+INPUTS!$B$23)^(INPUTS!$B$6-INPUTS!$B$5+34)-IF(INPUTS!$B$6+34>=INPUTS!$B$7,INPUTS!$B$25*(1+INPUTS!$B$23)^(INPUTS!$B$6-INPUTS!$B$5+34),0)-INPUTS!$B$24),0) -> 77293.81 | AL4: =IFERROR(MAX(0,INPUTS!$B$22*(1+INPUTS!$B$23)^(INPUTS!$B$6-INPUTS!$B$5+35)-IF(INPUTS!$B$6+35>=INPUTS!$B$7,INPUTS!$B$25*(1+INPUTS!$B$23)^(INPUTS!$B$6-INPUTS!$B$5+35),0)-INPUTS!$B$24),0) -> 79226.155 | AM4: =IFERROR(MAX(0,INPUTS!$B$22*(1+INPUTS!$B$23)^(INPUTS!$B$6-INPUTS!$B$5+36)-IF(INPUTS!$B$6+36>=INPUTS!$B$7,INPUTS!$B$25*(1+INPUTS!$B$23)^(INPUTS!$B$6-INPUTS!$B$5+36),0)-INPUTS!$B$24),0) -> 81206.809 | AN4: =IFERROR(MAX(0,INPUTS!$B$22*(1+INPUTS!$B$23)^(INPUTS!$B$6-INPUTS!$B$5+37)-IF(INPUTS!$B$6+37>=INPUTS!$B$7,INPUTS!$B$25*(1+INPUTS!$B$23)^(INPUTS!$B$6-INPUTS!$B$5+37),0)-INPUTS!$B$24),0) -> 83236.979 | AO4: =IFERROR(MAX(0,INPUTS!$B$22*(1+INPUTS!$B$23)^(INPUTS!$B$6-INPUTS!$B$5+38)-IF(INPUTS!$B$6+38>=INPUTS!$B$7,INPUTS!$B$25*(1+INPUTS!$B$23)^(INPUTS!$B$6-INPUTS!$B$5+38),0)-INPUTS!$B$24),0) -> 85317.903 | AP4: =IFERROR(MAX(0,INPUTS!$B$22*(1+INPUTS!$B$23)^(INPUTS!$B$6-INPUTS!$B$5+39)-IF(INPUTS!$B$6+39>=INPUTS!$B$7,INPUTS!$B$25*(1+INPUTS!$B$23)^(INPUTS!$B$6-INPUTS!$B$5+39),0)-INPUTS!$B$24),0) -> 87450.851 | AQ4: =IFERROR(MAX(0,INPUTS!$B$22*(1+INPUTS!$B$23)^(INPUTS!$B$6-INPUTS!$B$5+40)-IF(INPUTS!$B$6+40>=INPUTS!$B$7,INPUTS!$B$25*(1+INPUTS!$B$23)^(INPUTS!$B$6-INPUTS!$B$5+40),0)-INPUTS!$B$24),0) -> 89637.122 | AR4: =IFERROR(MAX(0,INPUTS!$B$22*(1+INPUTS!$B$23)^(INPUTS!$B$6-INPUTS!$B$5+41)-IF(INPUTS!$B$6+41>=INPUTS!$B$7,INPUTS!$B$25*(1+INPUTS!$B$23)^(INPUTS!$B$6-INPUTS!$B$5+41),0)-INPUTS!$B$24),0) -> 91878.05 | AS4: =IFERROR(MAX(0,INPUTS!$B$22*(1+INPUTS!$B$23)^(INPUTS!$B$6-INPUTS!$B$5+42)-IF(INPUTS!$B$6+42>=INPUTS!$B$7,INPUTS!$B$25*(1+INPUTS!$B$23)^(INPUTS!$B$6-INPUTS!$B$5+42),0)-INPUTS!$B$24),0) -> 94175.002 | AT4: =IFERROR(MAX(0,INPUTS!$B$22*(1+INPUTS!$B$23)^(INPUTS!$B$6-INPUTS!$B$5+43)-IF(INPUTS!$B$6+43>=INPUTS!$B$7,INPUTS!$B$25*(1+INPUTS!$B$23)^(INPUTS!$B$6-INPUTS!$B$5+43),0)-INPUTS!$B$24),0) -> 96529.377 | AU4: =IFERROR(MAX(0,INPUTS!$B$22*(1+INPUTS!$B$23)^(INPUTS!$B$6-INPUTS!$B$5+44)-IF(INPUTS!$B$6+44>=INPUTS!$B$7,INPUTS!$B$25*(1+INPUTS!$B$23)^(INPUTS!$B$6-INPUTS!$B$5+44),0)-INPUTS!$B$24),0) -> 98942.611 | AV4: =IFERROR(MAX(0,INPUTS!$B$22*(1+INPUTS!$B$23)^(INPUTS!$B$6-INPUTS!$B$5+45)-IF(INPUTS!$B$6+45>=INPUTS!$B$7,INPUTS!$B$25*(1+INPUTS!$B$23)^(INPUTS!$B$6-INPUTS!$B$5+45),0)-INPUTS!$B$24),0) -> 101416.18 | AW4: =IFERROR(MAX(0,INPUTS!$B$22*(1+INPUTS!$B$23)^(INPUTS!$B$6-INPUTS!$B$5+46)-IF(INPUTS!$B$6+46>=INPUTS!$B$7,INPUTS!$B$25*(1+INPUTS!$B$23)^(INPUTS!$B$6-INPUTS!$B$5+46),0)-INPUTS!$B$24),0) -> 103951.58 | AX4: =IFERROR(MAX(0,INPUTS!$B$22*(1+INPUTS!$B$23)^(INPUTS!$B$6-INPUTS!$B$5+47)-IF(INPUTS!$B$6+47>=INPUTS!$B$7,INPUTS!$B$25*(1+INPUTS!$B$23)^(INPUTS!$B$6-INPUTS!$B$5+47),0)-INPUTS!$B$24),0) -> 106550.37 | AY4: =IFERROR(MAX(0,INPUTS!$B$22*(1+INPUTS!$B$23)^(INPUTS!$B$6-INPUTS!$B$5+48)-IF(INPUTS!$B$6+48>=INPUTS!$B$7,INPUTS!$B$25*(1+INPUTS!$B$23)^(INPUTS!$B$6-INPUTS!$B$5+48),0)-INPUTS!$B$24),0) -> 109214.13 | AZ4: =IFERROR(MAX(0,INPUTS!$B$22*(1+INPUTS!$B$23)^(INPUTS!$B$6-INPUTS!$B$5+49)-IF(INPUTS!$B$6+49>=INPUTS!$B$7,INPUTS!$B$25*(1+INPUTS!$B$23)^(INPUTS!$B$6-INPUTS!$B$5+49),0)-INPUTS!$B$24),0) -> 111944.48 | BA4: =IFERROR(MAX(0,INPUTS!$B$22*(1+INPUTS!$B$23)^(INPUTS!$B$6-INPUTS!$B$5+50)-IF(INPUTS!$B$6+50>=INPUTS!$B$7,INPUTS!$B$25*(1+INPUTS!$B$23)^(INPUTS!$B$6-INPUTS!$B$5+50),0)-INPUTS!$B$24),0) -> 114743.09 | BB4: =IFERROR(MAX(0,INPUTS!$B$22*(1+INPUTS!$B$23)^(INPUTS!$B$6-INPUTS!$B$5+51)-IF(INPUTS!$B$6+51>=INPUTS!$B$7,INPUTS!$B$25*(1+INPUTS!$B$23)^(INPUTS!$B$6-INPUTS!$B$5+51),0)-INPUTS!$B$24),0) -> 117611.67 | BC4: =IFERROR(MAX(0,INPUTS!$B$22*(1+INPUTS!$B$23)^(INPUTS!$B$6-INPUTS!$B$5+52)-IF(INPUTS!$B$6+52>=INPUTS!$B$7,INPUTS!$B$25*(1+INPUTS!$B$23)^(INPUTS!$B$6-INPUTS!$B$5+52),0)-INPUTS!$B$24),0) -> 120551.96 | BD4: =IFERROR(MAX(0,INPUTS!$B$22*(1+INPUTS!$B$23)^(INPUTS!$B$6-INPUTS!$B$5+53)-IF(INPUTS!$B$6+53>=INPUTS!$B$7,INPUTS!$B$25*(1+INPUTS!$B$23)^(INPUTS!$B$6-INPUTS!$B$5+53),0)-INPUTS!$B$24),0) -> 123565.76 | BE4: =IFERROR(MAX(0,INPUTS!$B$22*(1+INPUTS!$B$23)^(INPUTS!$B$6-INPUTS!$B$5+54)-IF(INPUTS!$B$6+54>=INPUTS!$B$7,INPUTS!$B$25*(1+INPUTS!$B$23)^(INPUTS!$B$6-INPUTS!$B$5+54),0)-INPUTS!$B$24),0) -> 126654.91 | BF4: =IFERROR(MAX(0,INPUTS!$B$22*(1+INPUTS!$B$23)^(INPUTS!$B$6-INPUTS!$B$5+55)-IF(INPUTS!$B$6+55>=INPUTS!$B$7,INPUTS!$B$25*(1+INPUTS!$B$23)^(INPUTS!$B$6-INPUTS!$B$5+55),0)-INPUTS!$B$24),0) -> 129821.28 | BG4: =IFERROR(MAX(0,INPUTS!$B$22*(1+INPUTS!$B$23)^(INPUTS!$B$6-INPUTS!$B$5+56)-IF(INPUTS!$B$6+56>=INPUTS!$B$7,INPUTS!$B$25*(1+INPUTS!$B$23)^(INPUTS!$B$6-INPUTS!$B$5+56),0)-INPUTS!$B$24),0) -> 133066.81 | BH4: =IFERROR(MAX(0,INPUTS!$B$22*(1+INPUTS!$B$23)^(INPUTS!$B$6-INPUTS!$B$5+57)-IF(INPUTS!$B$6+57>=INPUTS!$B$7,INPUTS!$B$25*(1+INPUTS!$B$23)^(INPUTS!$B$6-INPUTS!$B$5+57),0)-INPUTS!$B$24),0) -> 136393.48 | BI4: =IFERROR(MAX(0,INPUTS!$B$22*(1+INPUTS!$B$23)^(INPUTS!$B$6-INPUTS!$B$5+58)-IF(INPUTS!$B$6+58>=INPUTS!$B$7,INPUTS!$B$25*(1+INPUTS!$B$23)^(INPUTS!$B$6-INPUTS!$B$5+58),0)-INPUTS!$B$24),0) -> 139803.32 | BJ4: =IFERROR(MAX(0,INPUTS!$B$22*(1+INPUTS!$B$23)^(INPUTS!$B$6-INPUTS!$B$5+59)-IF(INPUTS!$B$6+59>=INPUTS!$B$7,INPUTS!$B$25*(1+INPUTS!$B$23)^(INPUTS!$B$6-INPUTS!$B$5+59),0)-INPUTS!$B$24),0) -> 143298.4
A5: Years active → | C5: =IF(INPUTS!$B$6+0>INPUTS!$B$8,0,1) -> 1 | D5: =IF(INPUTS!$B$6+1>INPUTS!$B$8,0,1) -> 1 | E5: =IF(INPUTS!$B$6+2>INPUTS!$B$8,0,1) -> 1 | F5: =IF(INPUTS!$B$6+3>INPUTS!$B$8,0,1) -> 1 | G5: =IF(INPUTS!$B$6+4>INPUTS!$B$8,0,1) -> 1 | H5: =IF(INPUTS!$B$6+5>INPUTS!$B$8,0,1) -> 1 | I5: =IF(INPUTS!$B$6+6>INPUTS!$B$8,0,1) -> 1 | J5: =IF(INPUTS!$B$6+7>INPUTS!$B$8,0,1) -> 1 | K5: =IF(INPUTS!$B$6+8>INPUTS!$B$8,0,1) -> 1 | L5: =IF(INPUTS!$B$6+9>INPUTS!$B$8,0,1) -> 1 | M5: =IF(INPUTS!$B$6+10>INPUTS!$B$8,0,1) -> 1 | N5: =IF(INPUTS!$B$6+11>INPUTS!$B$8,0,1) -> 1 | O5: =IF(INPUTS!$B$6+12>INPUTS!$B$8,0,1) -> 1 | P5: =IF(INPUTS!$B$6+13>INPUTS!$B$8,0,1) -> 1 | Q5: =IF(INPUTS!$B$6+14>INPUTS!$B$8,0,1) -> 1 | R5: =IF(INPUTS!$B$6+15>INPUTS!$B$8,0,1) -> 1 | S5: =IF(INPUTS!$B$6+16>INPUTS!$B$8,0,1) -> 1 | T5: =IF(INPUTS!$B$6+17>INPUTS!$B$8,0,1) -> 1 | U5: =IF(INPUTS!$B$6+18>INPUTS!$B$8,0,1) -> 1 | V5: =IF(INPUTS!$B$6+19>INPUTS!$B$8,0,1) -> 1 | W5: =IF(INPUTS!$B$6+20>INPUTS!$B$8,0,1) -> 1 | X5: =IF(INPUTS!$B$6+21>INPUTS!$B$8,0,1) -> 1 | Y5: =IF(INPUTS!$B$6+22>INPUTS!$B$8,0,1) -> 1 | Z5: =IF(INPUTS!$B$6+23>INPUTS!$B$8,0,1) -> 1 | AA5: =IF(INPUTS!$B$6+24>INPUTS!$B$8,0,1) -> 1 | AB5: =IF(INPUTS!$B$6+25>INPUTS!$B$8,0,1) -> 1 | AC5: =IF(INPUTS!$B$6+26>INPUTS!$B$8,0,1) -> 1 | AD5: =IF(INPUTS!$B$6+27>INPUTS!$B$8,0,1) -> 1 | AE5: =IF(INPUTS!$B$6+28>INPUTS!$B$8,0,1) -> 1 | AF5: =IF(INPUTS!$B$6+29>INPUTS!$B$8,0,1) -> 1 | AG5: =IF(INPUTS!$B$6+30>INPUTS!$B$8,0,1) -> 1 | AH5: =IF(INPUTS!$B$6+31>INPUTS!$B$8,0,1) -> 1 | AI5: =IF(INPUTS!$B$6+32>INPUTS!$B$8,0,1) -> 1 | AJ5: =IF(INPUTS!$B$6+33>INPUTS!$B$8,0,1) -> 1 | AK5: =IF(INPUTS!$B$6+34>INPUTS!$B$8,0,1) -> 1 | AL5: =IF(INPUTS!$B$6+35>INPUTS!$B$8,0,1) -> 1 | AM5: =IF(INPUTS!$B$6+36>INPUTS!$B$8,0,1) -> 0 | AN5: =IF(INPUTS!$B$6+37>INPUTS!$B$8,0,1) -> 0 | AO5: =IF(INPUTS!$B$6+38>INPUTS!$B$8,0,1) -> 0 | AP5: =IF(INPUTS!$B$6+39>INPUTS!$B$8,0,1) -> 0 | AQ5: =IF(INPUTS!$B$6+40>INPUTS!$B$8,0,1) -> 0 | AR5: =IF(INPUTS!$B$6+41>INPUTS!$B$8,0,1) -> 0 | AS5: =IF(INPUTS!$B$6+42>INPUTS!$B$8,0,1) -> 0 | AT5: =IF(INPUTS!$B$6+43>INPUTS!$B$8,0,1) -> 0 | AU5: =IF(INPUTS!$B$6+44>INPUTS!$B$8,0,1) -> 0 | AV5: =IF(INPUTS!$B$6+45>INPUTS!$B$8,0,1) -> 0 | AW5: =IF(INPUTS!$B$6+46>INPUTS!$B$8,0,1) -> 0 | AX5: =IF(INPUTS!$B$6+47>INPUTS!$B$8,0,1) -> 0 | AY5: =IF(INPUTS!$B$6+48>INPUTS!$B$8,0,1) -> 0 | AZ5: =IF(INPUTS!$B$6+49>INPUTS!$B$8,0,1) -> 0 | BA5: =IF(INPUTS!$B$6+50>INPUTS!$B$8,0,1) -> 0 | BB5: =IF(INPUTS!$B$6+51>INPUTS!$B$8,0,1) -> 0 | BC5: =IF(INPUTS!$B$6+52>INPUTS!$B$8,0,1) -> 0 | BD5: =IF(INPUTS!$B$6+53>INPUTS!$B$8,0,1) -> 0 | BE5: =IF(INPUTS!$B$6+54>INPUTS!$B$8,0,1) -> 0 | BF5: =IF(INPUTS!$B$6+55>INPUTS!$B$8,0,1) -> 0 | BG5: =IF(INPUTS!$B$6+56>INPUTS!$B$8,0,1) -> 0 | BH5: =IF(INPUTS!$B$6+57>INPUTS!$B$8,0,1) -> 0 | BI5: =IF(INPUTS!$B$6+58>INPUTS!$B$8,0,1) -> 0 | BJ5: =IF(INPUTS!$B$6+59>INPUTS!$B$8,0,1) -> 0
A7: Sim # | B7: Final Balance | C7: Y1 | D7: Y2 | E7: Y3 | F7: Y4 | G7: Y5 | H7: Y6 | I7: Y7 | J7: Y8 | K7: Y9 | L7: Y10 | M7: Y11 | N7: Y12 | O7: Y13 | P7: Y14 | Q7: Y15 | R7: Y16 | S7: Y17 | T7: Y18 | U7: Y19 | V7: Y20 | W7: Y21 | X7: Y22 | Y7: Y23 | Z7: Y24 | AA7: Y25 | AB7: Y26 | AC7: Y27 | AD7: Y28 | AE7: Y29 | AF7: Y30 | AG7: Y31 | AH7: Y32 | AI7: Y33 | AJ7: Y34 | AK7: Y35 | AL7: Y36 | AM7: Y37 | AN7: Y38 | AO7: Y39 | AP7: Y40 | AQ7: Y41 | AR7: Y42 | AS7: Y43 | AT7: Y44 | AU7: Y45 | AV7: Y46 | AW7: Y47 | AX7: Y48 | AY7: Y49 | AZ7: Y50 | BA7: Y51 | BB7: Y52 | BC7: Y53 | BD7: Y54 | BE7: Y55 | BF7: Y56 | BG7: Y57 | BH7: Y58 | BI7: Y59 | BJ7: Y60
A8: 1 | B8: =LOOKUP(9.99E+307,C8:BJ8) -> 18306393 | C8: =IF(C$5=0,INPUTS!$B$35,MAX(0,(INPUTS!$B$35-C$4)*(1+NORMINV(RAND(),INPUTS!$B$28,INPUTS!$B$29)))) -> 1604124.1 | D8: =IF(D$5=0,C8,MAX(0,(C8-D$4)*(1+NORMINV(RAND(),INPUTS!$B$28,INPUTS!$B$29)))) -> 1998753.9 | E8: =IF(E$5=0,D8,MAX(0,(D8-E$4)*(1+NORMINV(RAND(),INPUTS!$B$28,INPUTS!$B$29)))) -> 2302363.4 | F8: =IF(F$5=0,E8,MAX(0,(E8-F$4)*(1+NORMINV(RAND(),INPUTS!$B$28,INPUTS!$B$29)))) -> 2794207.7 | G8: =IF(G$5=0,F8,MAX(0,(F8-G$4)*(1+NORMINV(RAND(),INPUTS!$B$28,INPUTS!$B$29)))) -> 3037556.1 | H8: =IF(H$5=0,G8,MAX(0,(G8-H$4)*(1+NORMINV(RAND(),INPUTS!$B$28,INPUTS!$B$29)))) -> 2923700.5 | I8: =IF(I$5=0,H8,MAX(0,(H8-I$4)*(1+NORMINV(RAND(),INPUTS!$B$28,INPUTS!$B$29)))) -> 3010727.7 | J8: =IF(J$5=0,I8,MAX(0,(I8-J$4)*(1+NORMINV(RAND(),INPUTS!$B$28,INPUTS!$B$29)))) -> 3097179.4 | K8: =IF(K$5=0,J8,MAX(0,(J8-K$4)*(1+NORMINV(RAND(),INPUTS!$B$28,INPUTS!$B$29)))) -> 2870730 | ... BJ8: =IF(BJ$5=0,BI8,MAX(0,(BI8-BJ$4)*(1+NORMINV(RAND(),INPUTS!$B$28,INPUTS!$B$29)))) -> 18306393
A9: 2 | B9: =LOOKUP(9.99E+307,C9:BJ9) -> 3205204.5 | C9: =IF(C$5=0,INPUTS!$B$35,MAX(0,(INPUTS!$B$35-C$4)*(1+NORMINV(RAND(),INPUTS!$B$28,INPUTS!$B$29)))) -> 1518941 | D9: =IF(D$5=0,C9,MAX(0,(C9-D$4)*(1+NORMINV(RAND(),INPUTS!$B$28,INPUTS!$B$29)))) -> 1421444.9 | E9: =IF(E$5=0,D9,MAX(0,(D9-E$4)*(1+NORMINV(RAND(),INPUTS!$B$28,INPUTS!$B$29)))) -> 1384799.8 | F9: =IF(F$5=0,E9,MAX(0,(E9-F$4)*(1+NORMINV(RAND(),INPUTS!$B$28,INPUTS!$B$29)))) -> 1343223.3 | G9: =IF(G$5=0,F9,MAX(0,(F9-G$4)*(1+NORMINV(RAND(),INPUTS!$B$28,INPUTS!$B$29)))) -> 1526574.9 | H9: =IF(H$5=0,G9,MAX(0,(G9-H$4)*(1+NORMINV(RAND(),INPUTS!$B$28,INPUTS!$B$29)))) -> 1512904 | I9: =IF(I$5=0,H9,MAX(0,(H9-I$4)*(1+NORMINV(RAND(),INPUTS!$B$28,INPUTS!$B$29)))) -> 1669044.1 | J9: =IF(J$5=0,I9,MAX(0,(I9-J$4)*(1+NORMINV(RAND(),INPUTS!$B$28,INPUTS!$B$29)))) -> 1510453.9 | K9: =IF(K$5=0,J9,MAX(0,(J9-K$4)*(1+NORMINV(RAND(),INPUTS!$B$28,INPUTS!$B$29)))) -> 2000533.6 | ... BJ9: =IF(BJ$5=0,BI9,MAX(0,(BI9-BJ$4)*(1+NORMINV(RAND(),INPUTS!$B$28,INPUTS!$B$29)))) -> 3205204.5
A10: 3 | B10: =LOOKUP(9.99E+307,C10:BJ10) -> 6980204.2 | C10: =IF(C$5=0,INPUTS!$B$35,MAX(0,(INPUTS!$B$35-C$4)*(1+NORMINV(RAND(),INPUTS!$B$28,INPUTS!$B$29)))) -> 1438089.3 | D10: =IF(D$5=0,C10,MAX(0,(C10-D$4)*(1+NORMINV(RAND(),INPUTS!$B$28,INPUTS!$B$29)))) -> 1440191.9 | E10: =IF(E$5=0,D10,MAX(0,(D10-E$4)*(1+NORMINV(RAND(),INPUTS!$B$28,INPUTS!$B$29)))) -> 1326002.1 | F10: =IF(F$5=0,E10,MAX(0,(E10-F$4)*(1+NORMINV(RAND(),INPUTS!$B$28,INPUTS!$B$29)))) -> 1347622.8 | G10: =IF(G$5=0,F10,MAX(0,(F10-G$4)*(1+NORMINV(RAND(),INPUTS!$B$28,INPUTS!$B$29)))) -> 1419924.4 | H10: =IF(H$5=0,G10,MAX(0,(G10-H$4)*(1+NORMINV(RAND(),INPUTS!$B$28,INPUTS!$B$29)))) -> 1490670.8 | I10: =IF(I$5=0,H10,MAX(0,(H10-I$4)*(1+NORMINV(RAND(),INPUTS!$B$28,INPUTS!$B$29)))) -> 1640567.3 | J10: =IF(J$5=0,I10,MAX(0,(I10-J$4)*(1+NORMINV(RAND(),INPUTS!$B$28,INPUTS!$B$29)))) -> 1868502.9 | K10: =IF(K$5=0,J10,MAX(0,(J10-K$4)*(1+NORMINV(RAND(),INPUTS!$B$28,INPUTS!$B$29)))) -> 2062072.4 | ... BJ10: =IF(BJ$5=0,BI10,MAX(0,(BI10-BJ$4)*(1+NORMINV(RAND(),INPUTS!$B$28,INPUTS!$B$29)))) -> 6980204.2
A11: 4 | B11: =LOOKUP(9.99E+307,C11:BJ11) -> 3001969.6 | C11: =IF(C$5=0,INPUTS!$B$35,MAX(0,(INPUTS!$B$35-C$4)*(1+NORMINV(RAND(),INPUTS!$B$28,INPUTS!$B$29)))) -> 1644365.3 | D11: =IF(D$5=0,C11,MAX(0,(C11-D$4)*(1+NORMINV(RAND(),INPUTS!$B$28,INPUTS!$B$29)))) -> 1746726.1 | E11: =IF(E$5=0,D11,MAX(0,(D11-E$4)*(1+NORMINV(RAND(),INPUTS!$B$28,INPUTS!$B$29)))) -> 1504292.4 | F11: =IF(F$5=0,E11,MAX(0,(E11-F$4)*(1+NORMINV(RAND(),INPUTS!$B$28,INPUTS!$B$29)))) -> 1409698.4 | G11: =IF(G$5=0,F11,MAX(0,(F11-G$4)*(1+NORMINV(RAND(),INPUTS!$B$28,INPUTS!$B$29)))) -> 1607754.4 | H11: =IF(H$5=0,G11,MAX(0,(G11-H$4)*(1+NORMINV(RAND(),INPUTS!$B$28,INPUTS!$B$29)))) -> 1537320.6 | I11: =IF(I$5=0,H11,MAX(0,(H11-I$4)*(1+NORMINV(RAND(),INPUTS!$B$28,INPUTS!$B$29)))) -> 1386971.6 | J11: =IF(J$5=0,I11,MAX(0,(I11-J$4)*(1+NORMINV(RAND(),INPUTS!$B$28,INPUTS!$B$29)))) -> 1438958.7 | K11: =IF(K$5=0,J11,MAX(0,(J11-K$4)*(1+NORMINV(RAND(),INPUTS!$B$28,INPUTS!$B$29)))) -> 1256193.2 | ... BJ11: =IF(BJ$5=0,BI11,MAX(0,(BI11-BJ$4)*(1+NORMINV(RAND(),INPUTS!$B$28,INPUTS!$B$29)))) -> 3001969.6
A12: 5 | B12: =LOOKUP(9.99E+307,C12:BJ12) -> 713100.22 | C12: =IF(C$5=0,INPUTS!$B$35,MAX(0,(INPUTS!$B$35-C$4)*(1+NORMINV(RAND(),INPUTS!$B$28,INPUTS!$B$29)))) -> 1675694.5 | D12: =IF(D$5=0,C12,MAX(0,(C12-D$4)*(1+NORMINV(RAND(),INPUTS!$B$28,INPUTS!$B$29)))) -> 1678916.5 | E12: =IF(E$5=0,D12,MAX(0,(D12-E$4)*(1+NORMINV(RAND(),INPUTS!$B$28,INPUTS!$B$29)))) -> 1803610.2 | F12: =IF(F$5=0,E12,MAX(0,(E12-F$4)*(1+NORMINV(RAND(),INPUTS!$B$28,INPUTS!$B$29)))) -> 1548802.5 | G12: =IF(G$5=0,F12,MAX(0,(F12-G$4)*(1+NORMINV(RAND(),INPUTS!$B$28,INPUTS!$B$29)))) -> 1532006.5 | H12: =IF(H$5=0,G12,MAX(0,(G12-H$4)*(1+NORMINV(RAND(),INPUTS!$B$28,INPUTS!$B$29)))) -> 1633312.6 | I12: =IF(I$5=0,H12,MAX(0,(H12-I$4)*(1+NORMINV(RAND(),INPUTS!$B$28,INPUTS!$B$29)))) -> 1563115.3 | J12: =IF(J$5=0,I12,MAX(0,(I12-J$4)*(1+NORMINV(RAND(),INPUTS!$B$28,INPUTS!$B$29)))) -> 1541510.5 | K12: =IF(K$5=0,J12,MAX(0,(J12-K$4)*(1+NORMINV(RAND(),INPUTS!$B$28,INPUTS!$B$29)))) -> 1948740.5 | ... BJ12: =IF(BJ$5=0,BI12,MAX(0,(BI12-BJ$4)*(1+NORMINV(RAND(),INPUTS!$B$28,INPUTS!$B$29)))) -> 713100.22
A13: 6 | B13: =LOOKUP(9.99E+307,C13:BJ13) -> 768956.76 | C13: =IF(C$5=0,INPUTS!$B$35,MAX(0,(INPUTS!$B$35-C$4)*(1+NORMINV(RAND(),INPUTS!$B$28,INPUTS!$B$29)))) -> 1835299.6 | D13: =IF(D$5=0,C13,MAX(0,(C13-D$4)*(1+NORMINV(RAND(),INPUTS!$B$28,INPUTS!$B$29)))) -> 1699539.9 | E13: =IF(E$5=0,D13,MAX(0,(D13-E$4)*(1+NORMINV(RAND(),INPUTS!$B$28,INPUTS!$B$29)))) -> 1780389.4 | F13: =IF(F$5=0,E13,MAX(0,(E13-F$4)*(1+NORMINV(RAND(),INPUTS!$B$28,INPUTS!$B$29)))) -> 1749627.4 | G13: =IF(G$5=0,F13,MAX(0,(F13-G$4)*(1+NORMINV(RAND(),INPUTS!$B$28,INPUTS!$B$29)))) -> 1662927.6 | H13: =IF(H$5=0,G13,MAX(0,(G13-H$4)*(1+NORMINV(RAND(),INPUTS!$B$28,INPUTS!$B$29)))) -> 1693730.6 | I13: =IF(I$5=0,H13,MAX(0,(H13-I$4)*(1+NORMINV(RAND(),INPUTS!$B$28,INPUTS!$B$29)))) -> 1809834.3 | J13: =IF(J$5=0,I13,MAX(0,(I13-J$4)*(1+NORMINV(RAND(),INPUTS!$B$28,INPUTS!$B$29)))) -> 1535591.6 | K13: =IF(K$5=0,J13,MAX(0,(J13-K$4)*(1+NORMINV(RAND(),INPUTS!$B$28,INPUTS!$B$29)))) -> 1472474.7 | ... BJ13: =IF(BJ$5=0,BI13,MAX(0,(BI13-BJ$4)*(1+NORMINV(RAND(),INPUTS!$B$28,INPUTS!$B$29)))) -> 768956.76
A14: 7 | B14: =LOOKUP(9.99E+307,C14:BJ14) -> 856759.91 | C14: =IF(C$5=0,INPUTS!$B$35,MAX(0,(INPUTS!$B$35-C$4)*(1+NORMINV(RAND(),INPUTS!$B$28,INPUTS!$B$29)))) -> 1589529.9 | D14: =IF(D$5=0,C14,MAX(0,(C14-D$4)*(1+NORMINV(RAND(),INPUTS!$B$28,INPUTS!$B$29)))) -> 1602491.1 | E14: =IF(E$5=0,D14,MAX(0,(D14-E$4)*(1+NORMINV(RAND(),INPUTS!$B$28,INPUTS!$B$29)))) -> 1597603.6 | F14: =IF(F$5=0,E14,MAX(0,(E14-F$4)*(1+NORMINV(RAND(),INPUTS!$B$28,INPUTS!$B$29)))) -> 1548125.4 | G14: =IF(G$5=0,F14,MAX(0,(F14-G$4)*(1+NORMINV(RAND(),INPUTS!$B$28,INPUTS!$B$29)))) -> 1158552.3 | H14: =IF(H$5=0,G14,MAX(0,(G14-H$4)*(1+NORMINV(RAND(),INPUTS!$B$28,INPUTS!$B$29)))) -> 1147777.1 | I14: =IF(I$5=0,H14,MAX(0,(H14-I$4)*(1+NORMINV(RAND(),INPUTS!$B$28,INPUTS!$B$29)))) -> 984824.13 | J14: =IF(J$5=0,I14,MAX(0,(I14-J$4)*(1+NORMINV(RAND(),INPUTS!$B$28,INPUTS!$B$29)))) -> 1042645.6 | K14: =IF(K$5=0,J14,MAX(0,(J14-K$4)*(1+NORMINV(RAND(),INPUTS!$B$28,INPUTS!$B$29)))) -> 913434.55 | ... BJ14: =IF(BJ$5=0,BI14,MAX(0,(BI14-BJ$4)*(1+NORMINV(RAND(),INPUTS!$B$28,INPUTS!$B$29)))) -> 856759.91
A15: 8 | B15: =LOOKUP(9.99E+307,C15:BJ15) -> 0 | C15: =IF(C$5=0,INPUTS!$B$35,MAX(0,(INPUTS!$B$35-C$4)*(1+NORMINV(RAND(),INPUTS!$B$28,INPUTS!$B$29)))) -> 1601938.9 | D15: =IF(D$5=0,C15,MAX(0,(C15-D$4)*(1+NORMINV(RAND(),INPUTS!$B$28,INPUTS!$B$29)))) -> 1340985.7 | E15: =IF(E$5=0,D15,MAX(0,(D15-E$4)*(1+NORMINV(RAND(),INPUTS!$B$28,INPUTS!$B$29)))) -> 1245716.5 | F15: =IF(F$5=0,E15,MAX(0,(E15-F$4)*(1+NORMINV(RAND(),INPUTS!$B$28,INPUTS!$B$29)))) -> 1207354.3 | G15: =IF(G$5=0,F15,MAX(0,(F15-G$4)*(1+NORMINV(RAND(),INPUTS!$B$28,INPUTS!$B$29)))) -> 1089640 | H15: =IF(H$5=0,G15,MAX(0,(G15-H$4)*(1+NORMINV(RAND(),INPUTS!$B$28,INPUTS!$B$29)))) -> 1127110.7 | I15: =IF(I$5=0,H15,MAX(0,(H15-I$4)*(1+NORMINV(RAND(),INPUTS!$B$28,INPUTS!$B$29)))) -> 860150.14 | J15: =IF(J$5=0,I15,MAX(0,(I15-J$4)*(1+NORMINV(RAND(),INPUTS!$B$28,INPUTS!$B$29)))) -> 927940.42 | K15: =IF(K$5=0,J15,MAX(0,(J15-K$4)*(1+NORMINV(RAND(),INPUTS!$B$28,INPUTS!$B$29)))) -> 946825.09 | ... BJ15: =IF(BJ$5=0,BI15,MAX(0,(BI15-BJ$4)*(1+NORMINV(RAND(),INPUTS!$B$28,INPUTS!$B$29)))) -> 0
A16: 9 | B16: =LOOKUP(9.99E+307,C16:BJ16) -> 5993997.4 | C16: =IF(C$5=0,INPUTS!$B$35,MAX(0,(INPUTS!$B$35-C$4)*(1+NORMINV(RAND(),INPUTS!$B$28,INPUTS!$B$29)))) -> 1432141.3 | D16: =IF(D$5=0,C16,MAX(0,(C16-D$4)*(1+NORMINV(RAND(),INPUTS!$B$28,INPUTS!$B$29)))) -> 1558234.3 | E16: =IF(E$5=0,D16,MAX(0,(D16-E$4)*(1+NORMINV(RAND(),INPUTS!$B$28,INPUTS!$B$29)))) -> 1944009.9 | F16: =IF(F$5=0,E16,MAX(0,(E16-F$4)*(1+NORMINV(RAND(),INPUTS!$B$28,INPUTS!$B$29)))) -> 1771447 | G16: =IF(G$5=0,F16,MAX(0,(F16-G$4)*(1+NORMINV(RAND(),INPUTS!$B$28,INPUTS!$B$29)))) -> 2011783.4 | H16: =IF(H$5=0,G16,MAX(0,(G16-H$4)*(1+NORMINV(RAND(),INPUTS!$B$28,INPUTS!$B$29)))) -> 1691021.6 | I16: =IF(I$5=0,H16,MAX(0,(H16-I$4)*(1+NORMINV(RAND(),INPUTS!$B$28,INPUTS!$B$29)))) -> 1851846.9 | J16: =IF(J$5=0,I16,MAX(0,(I16-J$4)*(1+NORMINV(RAND(),INPUTS!$B$28,INPUTS!$B$29)))) -> 1628544.3 | K16: =IF(K$5=0,J16,MAX(0,(J16-K$4)*(1+NORMINV(RAND(),INPUTS!$B$28,INPUTS!$B$29)))) -> 1544650.5 | ... BJ16: =IF(BJ$5=0,BI16,MAX(0,(BI16-BJ$4)*(1+NORMINV(RAND(),INPUTS!$B$28,INPUTS!$B$29)))) -> 5993997.4
A17: 10 | B17: =LOOKUP(9.99E+307,C17:BJ17) -> 7277754.9 | C17: =IF(C$5=0,INPUTS!$B$35,MAX(0,(INPUTS!$B$35-C$4)*(1+NORMINV(RAND(),INPUTS!$B$28,INPUTS!$B$29)))) -> 1759255.9 | D17: =IF(D$5=0,C17,MAX(0,(C17-D$4)*(1+NORMINV(RAND(),INPUTS!$B$28,INPUTS!$B$29)))) -> 1835833.1 | E17: =IF(E$5=0,D17,MAX(0,(D17-E$4)*(1+NORMINV(RAND(),INPUTS!$B$28,INPUTS!$B$29)))) -> 1479060.7 | F17: =IF(F$5=0,E17,MAX(0,(E17-F$4)*(1+NORMINV(RAND(),INPUTS!$B$28,INPUTS!$B$29)))) -> 1499633 | G17: =IF(G$5=0,F17,MAX(0,(F17-G$4)*(1+NORMINV(RAND(),INPUTS!$B$28,INPUTS!$B$29)))) -> 1917459.9 | H17: =IF(H$5=0,G17,MAX(0,(G17-H$4)*(1+NORMINV(RAND(),INPUTS!$B$28,INPUTS!$B$29)))) -> 2045807.8 | I17: =IF(I$5=0,H17,MAX(0,(H17-I$4)*(1+NORMINV(RAND(),INPUTS!$B$28,INPUTS!$B$29)))) -> 2660087.3 | J17: =IF(J$5=0,I17,MAX(0,(I17-J$4)*(1+NORMINV(RAND(),INPUTS!$B$28,INPUTS!$B$29)))) -> 2747001.8 | K17: =IF(K$5=0,J17,MAX(0,(J17-K$4)*(1+NORMINV(RAND(),INPUTS!$B$28,INPUTS!$B$29)))) -> 3428800.3 | ... BJ17: =IF(BJ$5=0,BI17,MAX(0,(BI17-BJ$4)*(1+NORMINV(RAND(),INPUTS!$B$28,INPUTS!$B$29)))) -> 7277754.9
A18: 11 | B18: =LOOKUP(9.99E+307,C18:BJ18) -> 8732287.4 | C18: =IF(C$5=0,INPUTS!$B$35,MAX(0,(INPUTS!$B$35-C$4)*(1+NORMINV(RAND(),INPUTS!$B$28,INPUTS!$B$29)))) -> 1507598.9 | D18: =IF(D$5=0,C18,MAX(0,(C18-D$4)*(1+NORMINV(RAND(),INPUTS!$B$28,INPUTS!$B$29)))) -> 1346994.7 | E18: =IF(E$5=0,D18,MAX(0,(D18-E$4)*(1+NORMINV(RAND(),INPUTS!$B$28,INPUTS!$B$29)))) -> 1417036.7 | F18: =IF(F$5=0,E18,MAX(0,(E18-F$4)*(1+NORMINV(RAND(),INPUTS!$B$28,INPUTS!$B$29)))) -> 1376024.3 | G18: =IF(G$5=0,F18,MAX(0,(F18-G$4)*(1+NORMINV(RAND(),INPUTS!$B$28,INPUTS!$B$29)))) -> 1426449 | H18: =IF(H$5=0,G18,MAX(0,(G18-H$4)*(1+NORMINV(RAND(),INPUTS!$B$28,INPUTS!$B$29)))) -> 1403724.3 | I18: =IF(I$5=0,H18,MAX(0,(H18-I$4)*(1+NORMINV(RAND(),INPUTS!$B$28,INPUTS!$B$29)))) -> 1427059.3 | J18: =IF(J$5=0,I18,MAX(0,(I18-J$4)*(1+NORMINV(RAND(),INPUTS!$B$28,INPUTS!$B$29)))) -> 1666656.7 | K18: =IF(K$5=0,J18,MAX(0,(J18-K$4)*(1+NORMINV(RAND(),INPUTS!$B$28,INPUTS!$B$29)))) -> 1369966.3 | ... BJ18: =IF(BJ$5=0,BI18,MAX(0,(BI18-BJ$4)*(1+NORMINV(RAND(),INPUTS!$B$28,INPUTS!$B$29)))) -> 8732287.4
A19: 12 | B19: =LOOKUP(9.99E+307,C19:BJ19) -> 6001955.2 | C19: =IF(C$5=0,INPUTS!$B$35,MAX(0,(INPUTS!$B$35-C$4)*(1+NORMINV(RAND(),INPUTS!$B$28,INPUTS!$B$29)))) -> 1640322 | D19: =IF(D$5=0,C19,MAX(0,(C19-D$4)*(1+NORMINV(RAND(),INPUTS!$B$28,INPUTS!$B$29)))) -> 1822953 | E19: =IF(E$5=0,D19,MAX(0,(D19-E$4)*(1+NORMINV(RAND(),INPUTS!$B$28,INPUTS!$B$29)))) -> 2017185 | F19: =IF(F$5=0,E19,MAX(0,(E19-F$4)*(1+NORMINV(RAND(),INPUTS!$B$28,INPUTS!$B$29)))) -> 1810870.6 | G19: =IF(G$5=0,F19,MAX(0,(F19-G$4)*(1+NORMINV(RAND(),INPUTS!$B$28,INPUTS!$B$29)))) -> 1224060.6 | H19: =IF(H$5=0,G19,MAX(0,(G19-H$4)*(1+NORMINV(RAND(),INPUTS!$B$28,INPUTS!$B$29)))) -> 1425653 | I19: =IF(I$5=0,H19,MAX(0,(H19-I$4)*(1+NORMINV(RAND(),INPUTS!$B$28,INPUTS!$B$29)))) -> 1451316.4 | J19: =IF(J$5=0,I19,MAX(0,(I19-J$4)*(1+NORMINV(RAND(),INPUTS!$B$28,INPUTS!$B$29)))) -> 1638622.1 | K19: =IF(K$5=0,J19,MAX(0,(J19-K$4)*(1+NORMINV(RAND(),INPUTS!$B$28,INPUTS!$B$29)))) -> 1864151.9 | ... BJ19: =IF(BJ$5=0,BI19,MAX(0,(BI19-BJ$4)*(1+NORMINV(RAND(),INPUTS!$B$28,INPUTS!$B$29)))) -> 6001955.2
... A207: 200 | B207: =LOOKUP(9.99E+307,C207:BJ207) -> 3208716.2 | C207: =IF(C$5=0,INPUTS!$B$35,MAX(0,(INPUTS!$B$35-C$4)*(1+NORMINV(RAND(),INPUTS!$B$28,INPUTS!$B$29)))) -> 1795991.1 | D207: =IF(D$5=0,C207,MAX(0,(C207-D$4)*(1+NORMINV(RAND(),INPUTS!$B$28,INPUTS!$B$29)))) -> 1691821.6 | E207: =IF(E$5=0,D207,MAX(0,(D207-E$4)*(1+NORMINV(RAND(),INPUTS!$B$28,INPUTS!$B$29)))) -> 2112079.3 | F207: =IF(F$5=0,E207,MAX(0,(E207-F$4)*(1+NORMINV(RAND(),INPUTS!$B$28,INPUTS!$B$29)))) -> 1987161.1 | G207: =IF(G$5=0,F207,MAX(0,(F207-G$4)*(1+NORMINV(RAND(),INPUTS!$B$28,INPUTS!$B$29)))) -> 1974897.4 | H207: =IF(H$5=0,G207,MAX(0,(G207-H$4)*(1+NORMINV(RAND(),INPUTS!$B$28,INPUTS!$B$29)))) -> 2078315.4 | I207: =IF(I$5=0,H207,MAX(0,(H207-I$4)*(1+NORMINV(RAND(),INPUTS!$B$28,INPUTS!$B$29)))) -> 2654907.9 | J207: =IF(J$5=0,I207,MAX(0,(I207-J$4)*(1+NORMINV(RAND(),INPUTS!$B$28,INPUTS!$B$29)))) -> 3286604.2 | K207: =IF(K$5=0,J207,MAX(0,(J207-K$4)*(1+NORMINV(RAND(),INPUTS!$B$28,INPUTS!$B$29)))) -> 3741859.5 | ... BJ207: =IF(BJ$5=0,BI207,MAX(0,(BI207-BJ$4)*(1+NORMINV(RAND(),INPUTS!$B$28,INPUTS!$B$29)))) -> 3208716.2
A210: RESULTS
A211: Success Rate (money lasts to life expectancy) | B211: =COUNTIF(B8:B207,">0")/200 -> 0.94
A212: Median Final Balance | B212: =MEDIAN(B8:B207) -> 3623977.6
A213: 10th Percentile (bad luck scenario) | B213: =PERCENTILE(B8:B207,0.1) -> 307678.86
A214: 90th Percentile (good luck scenario) | B214: =PERCENTILE(B8:B207,0.9) -> 14503054
A216: Guide: 90%+ success = robust. 75–90% = acceptable with flexibility. Below 75% = revisit spending or retirement age.

Sheet RISK FLAGS
A1: AUTOMATED RISK FLAGS
A2: All flags pull live from BRIDGE, POST-59.5, ROTH LADDER and MONTE CARLO.
A4: Risk Check | B4: Status | C4: Detail
A5: Withdrawal rate ≤ 4%? | B5: =IF(INPUTS!B33<=0.04,"✓ OK","⚠ HIGH — "&TEXT(INPUTS!B33,"0.0%")) -> ⚠ HIGH — 4.0% | C5: =IF(INPUTS!B33<=0.04,"Initial rate "&TEXT(INPUTS!B33,"0.0%")&" within guideline.","Exceeds 4% rule. At a 35+ yr horizon target 3.3%. Reduce spending or grow portfolio.") -> Exceeds 4% rule. At a 35+ yr horizon target 3.3%. Reduce spending or grow portfolio.
A6: Taxable funds entire bridge? | B6: =IF(INPUTS!$B$32=0,"✓ FUNDED",IF(SUM(BRIDGE!J4:K28)=0,"✓ FUNDED","⚠ GAP")) -> ✓ FUNDED | C6: =IF(INPUTS!$B$32=0,"No bridge needed — retiring at or after 59½.",IF(SUM(BRIDGE!J4:K28)=0,"Taxable+cash covers every bridge year.","Taxable runs out — "&TEXT(SUM(BRIDGE!J4:K28),"$#,##0")&" must come from Roth/401k before 59½ (penalty + tax risk).")) -> Taxable+cash covers every bridge year.
A7: No 401k draws before 59½? | B7: =IF(INPUTS!$B$32=0,"✓ CLEAN",IF(SUM(BRIDGE!K4:K28)=0,"✓ CLEAN","✗ PENALTY RISK")) -> ✓ CLEAN | C7: =IF(INPUTS!$B$32=0,"No bridge — no early 401k withdrawals needed.",IF(SUM(BRIDGE!K4:K28)=0,"No early 401k withdrawals.","401k tapped for "&TEXT(SUM(BRIDGE!K4:K28),"$#,##0")&" before 59½ — 10% penalty unless Rule of 55 or 72(t) SEPP applies.")) -> No early 401k withdrawals.
A8: Cash buffer ≥ 1 year? | B8: =IF(INPUTS!B18>=INPUTS!B22,"✓ OK","⚠ THIN") -> ✓ OK | C8: ="Cash covers "&TEXT(INPUTS!B18/INPUTS!B22,"0.0")&" years of spending. 1–2 yrs protects against selling in a downturn." -> Cash covers 1.4 years of spending. 1–2 yrs protects against selling in a downturn.
A9: ACA cliff clear in all bridge years? | B9: =IF(COUNTIF('ROTH LADDER'!G6:G30,"⚠*")=0,"✓ OK","⚠ "&COUNTIF('ROTH LADDER'!G6:G30,"⚠*")&" YR(S) OVER") -> ✓ OK | C9: =IF(COUNTIF('ROTH LADDER'!G6:G30,"⚠*")=0,"MAGI under est. 400% FPL cliff every bridge year.","Conversions push MAGI over the cliff in "&COUNTIF('ROTH LADDER'!G6:G30,"⚠*")&" year(s) — reduce conversion or lose the ACA subsidy.") -> MAGI under est. 400% FPL cliff every bridge year.
A10: SS delay opportunity | B10: =IF(INPUTS!B7<70,"💡 CONSIDER 70","✓ MAXED") -> 💡 CONSIDER 70 | C10: =IF(INPUTS!B7<70,"Delaying from "&INPUTS!B7&" to 70 adds ~"&TEXT(INPUTS!B25*0.08*(70-INPUTS!B7),"$#,##0")&"/yr permanently (8%/yr).","Claiming at 70 = maximum benefit.") -> Delaying from 67 to 70 adds ~$5,760/yr permanently (8%/yr).
A11: IRMAA Medicare trigger? | B11: =IF(INPUTS!B22+INPUTS!B24<IF(INPUTS!B9="MFJ",218000,109000),"✓ OK","⚠ REVIEW") -> ✓ OK | C11: ="2026 IRMAA starts at "&IF(INPUTS!B9="MFJ","$218,000 (MFJ)","$109,000 (Single)")&" MAGI (2-yr lookback). Large Roth conversions near Medicare age can trigger surcharges." -> 2026 IRMAA starts at $218,000 (MFJ) MAGI (2-yr lookback). Large Roth conversions near Medicare age can trigger surcharges.
A12: Portfolio survives to life expectancy? | B12: =IF(IFERROR('POST-59.5'!F51,0)>0,"✓ FUNDED","✗ DEPLETED") -> ✓ FUNDED | C12: =IF(IFERROR('POST-59.5'!F51,0)>0,"Projected "&TEXT('POST-59.5'!F51,"$#,##0")&" at age "&INPUTS!B8&".","Deterministic projection depletes before age "&INPUTS!B8&" — cut spending, delay retirement, or add income.") -> Projected $5,339,452 at age 90.
A13: Monte Carlo success ≥ 80%? | B13: =IF('MONTE CARLO'!B211>=0.8,"✓ "&TEXT('MONTE CARLO'!B211,"0%"),"⚠ "&TEXT('MONTE CARLO'!B211,"0%")) -> ✓ 94% | C13: =IF('MONTE CARLO'!B211>=0.9,"Robust across randomized sequences.",IF('MONTE CARLO'!B211>=0.75,"Acceptable — needs spending flexibility in bad markets.","Fragile — plan fails too often under sequence risk.")) -> Robust across randomized sequences.

Sheet REBALANCE
A1: ANNUAL REBALANCE TRACKER
A2: Current Value column links to INPUTS balances — update the split below to match your actual holdings.
A4: Asset Class | B4: Target % | C4: Current Value | D4: Current % | E4: Drift | F4: Action
A5: US Total Market | B5: 0.4 | C5: =INPUTS!B15*0.6+INPUTS!B16*0.55+INPUTS!B17*0.7 -> 672500 | D5: =C5/$C$11 -> 0.54897959 | E5: =D5-B5 -> 0.14897959 | F5: =IF(E5<-0.05,"ADD — underweight",IF(E5>0.05,"TRIM — overweight","Hold")) -> TRIM — overweight
A6: International | B6: 0.15 | C6: =INPUTS!B15*0.25+INPUTS!B16*0.15 -> 185000 | D6: =C6/$C$11 -> 0.15102041 | E6: =D6-B6 -> 0.0010204082 | F6: =IF(E6<-0.05,"ADD — underweight",IF(E6>0.05,"TRIM — overweight","Hold")) -> Hold
A7: Small Cap Value | B7: 0.05 | C7: =INPUTS!B17*0.3 -> 45000 | D7: =C7/$C$11 -> 0.036734694 | E7: =D7-B7 -> -0.013265306 | F7: =IF(E7<-0.05,"ADD — underweight",IF(E7>0.05,"TRIM — overweight","Hold")) -> Hold
A8: Bonds (Total) | B8: 0.25 | C8: =INPUTS!B16*0.3 -> 195000 | D8: =C8/$C$11 -> 0.15918367 | E8: =D8-B8 -> -0.090816327 | F8: =IF(E8<-0.05,"ADD — underweight",IF(E8>0.05,"TRIM — overweight","Hold")) -> ADD — underweight
A9: Cash / MM | B9: 0.1 | C9: =INPUTS!B18 -> 75000 | D9: =C9/$C$11 -> 0.06122449 | E9: =D9-B9 -> -0.03877551 | F9: =IF(E9<-0.05,"ADD — underweight",IF(E9>0.05,"TRIM — overweight","Hold")) -> Hold
A10: Real Estate (REIT) | B10: 0.05 | C10: =INPUTS!B15*0.15 -> 52500 | D10: =C10/$C$11 -> 0.042857143 | E10: =D10-B10 -> -0.0071428571 | F10: =IF(E10<-0.05,"ADD — underweight",IF(E10>0.05,"TRIM — overweight","Hold")) -> Hold
A11: TOTAL | B11: =SUM(B5:B10) -> 1 | C11: =SUM(C5:C10) -> 1225000
A13: The default split is an estimate — overwrite Current Value cells with your real holdings for accurate drift.
