Workbook

Sheet COVER
B3: BridgeToRetired
B4: PRO RETIREMENT BRIDGE PLANNER
B5: Version 3.0 · 2026 Tax Year · bridgetoretired.com
B10: WHAT'S INSIDE
B11: INPUTS | C11: Ages, balances, spending, state, filing status — single entry point for all sheets
B12: BRIDGE | C12: Year-by-year funding plan retirement → 59½ with Taxable → Roth → 401k cascade
B13: TAX ESTIMATE | C13: Federal tax per bridge year — MFJ or Single brackets switchable in INPUTS
B14: ROTH LADDER | C14: Optimal Roth conversions with 12% bracket space and ACA cliff cross-check per year
B15: POST-59.5 | C15: Portfolio projection 59½ → life expectancy with Social Security income modeled
B16: MONTE CARLO | C16: 200-scenario simulator — plan success rate across randomized return sequences
B17: RISK FLAGS | C17: 9 automated checks: withdrawal rate, ACA cliff, IRMAA, SS delay, Monte Carlo
B18: REBALANCE | C18: Annual target vs actual allocation by asset class with drift alerts and signals
B20: COLOR CODING GUIDE
B22: Blue text = Input cells — change these to your numbers
B23: Green text = Linked from another sheet
B24: Black text = Formula / calculated — do not edit
B25: Gold highlight = Key result or flag
B27: ⚠ Not financial advice. For modeling purposes only. Consult a qualified fee-only advisor.

Sheet INPUTS
A1: RETIREMENT INPUTS
A2: Blue cells are inputs. Change any value — every sheet updates automatically.
A3: PERSONAL
A4: PERSONAL
A5: Current Age | B5: 52
A6: Planned Retirement Age | B6: 55
A7: Social Security Claiming Age | B7: 67 | D7: 62 / 67 / 70
A8: Life Expectancy (planning age) | B8: 90 | D8: Conservative = 90–95
A9: Filing Status | B9: MFJ | D9: MFJ or Single — drives TAX ESTIMATE brackets
A10: State of Residence | B10: TX | D10: No-tax states: AK FL NV NH SD TN TX WA WY
A11: State Tax Rate (if any) | B11: 0 | D11: 0% for the 9 no-tax states; else your flat est.
A12: First Projection Year | B12: 2026
A13: PORTFOLIO BALANCES
A14: PORTFOLIO BALANCES (TODAY)
A15: Taxable Brokerage | B15: 350000
A16: Traditional 401k / IRA | B16: 650000
A17: Roth IRA / Roth 401k | B17: 150000
A18: Cash / Money Market | B18: 75000 | D18: Bridge buffer — counted in taxable cascade
A19: SPENDING & INCOME | B19: =B15+B16+B17+B18 -> 1225000
A21: SPENDING & INCOME
A22: Annual Spending (today $) | B22: 55000
A23: Inflation Rate | B23: 0.025
A24: RETURN ASSUMPTIONS | B24: 0 | D24: Pension, rental, part-time during bridge
A25: Estimated Social Security ($/yr today $) | B25: 24000 | D25: At claiming age
A27: RETURN ASSUMPTIONS
A28: AUTO-CALCULATED | B28: 0.065
A29: Portfolio Volatility (std dev) | B29: 0.12 | D29: Used by MONTE CARLO. 60/40 ≈ 10–12%
A31: AUTO-CALCULATED
A32: Bridge Length (years) | B32: =MAX(0, 59.5 - B6) -> 4.5
A33: Withdrawal Rate | B33: =B22/B19 -> 0.044897959
A34: Std Deduction (2026) | B34: =IF(B9="MFJ",30000,15000) -> 30000

Sheet BRIDGE
A1: BRIDGE FUNDING PLAN · Retirement to Age 59½
A2: Withdrawal cascade: Taxable+Cash first → Roth → 401k. Rows auto-blank past 59½.
A3: Year | B3: Age | C3: Spending (Inflated) | D3: Other Income | E3: Net Needed | F3: Taxable+Cash Start | G3: Roth Start | H3: 401k Start | I3: From Taxable | J3: From Roth | K3: From 401k | L3: Taxable End | M3: Roth End | N3: 401k End | O3: Total End
A4: =IF(INPUTS!$B$32=0,"No bridge needed — retiring at or after age 59½. See POST-59.5 for your projection.",IF(0>=INPUTS!$B$32,"",INPUTS!$B$12+(INPUTS!$B$6-INPUTS!$B$5)+0)) -> 2029 | B4: =IF(INPUTS!$B$32=0,"",IF(0>=INPUTS!$B$32,"",INPUTS!$B$6+0)) -> 55 | C4: =IF(INPUTS!$B$32=0,"",IF(0>=INPUTS!$B$32,"",INPUTS!$B$22*(1+INPUTS!$B$23)^(INPUTS!$B$6-INPUTS!$B$5+0))) -> 59228.984 | D4: =IF(INPUTS!$B$32=0,"",IF(0>=INPUTS!$B$32,"",INPUTS!$B$24)) -> 0 | E4: =IF(INPUTS!$B$32=0,"",IF(0>=INPUTS!$B$32,"",MAX(0,C4-D4))) -> 59228.984 | F4: =IF(INPUTS!$B$32=0,"",IF(0>=INPUTS!$B$32,"",INPUTS!$B$15+INPUTS!$B$18)) -> 425000 | G4: =IF(INPUTS!$B$32=0,"",IF(0>=INPUTS!$B$32,"",INPUTS!$B$17)) -> 150000 | H4: =IF(INPUTS!$B$32=0,"",IF(0>=INPUTS!$B$32,"",INPUTS!$B$16)) -> 650000 | I4: =IF(INPUTS!$B$32=0,"",IF(0>=INPUTS!$B$32,"",MIN(E4,F4))) -> 59228.984 | J4: =IF(INPUTS!$B$32=0,"",IF(0>=INPUTS!$B$32,"",MIN(E4-I4,G4))) -> 0 | K4: =IF(INPUTS!$B$32=0,"",IF(0>=INPUTS!$B$32,"",MIN(E4-I4-J4,H4))) -> 0 | L4: =IF(INPUTS!$B$32=0,"",IF(0>=INPUTS!$B$32,"",(F4-I4)*(1+INPUTS!$B$28))) -> 389546.13 | M4: =IF(INPUTS!$B$32=0,"",IF(0>=INPUTS!$B$32,"",(G4-J4)*(1+INPUTS!$B$28))) -> 159750 | N4: =IF(INPUTS!$B$32=0,"",IF(0>=INPUTS!$B$32,"",(H4-K4)*(1+INPUTS!$B$28))) -> 692250 | O4: =IF(INPUTS!$B$32=0,"",IF(0>=INPUTS!$B$32,"",L4+M4+N4)) -> 1241546.1
A5: =IF(INPUTS!$B$32=0,"",IF(1>=INPUTS!$B$32,"",INPUTS!$B$12+(INPUTS!$B$6-INPUTS!$B$5)+1)) -> 2030 | B5: =IF(INPUTS!$B$32=0,"",IF(1>=INPUTS!$B$32,"",INPUTS!$B$6+1)) -> 56 | C5: =IF(INPUTS!$B$32=0,"",IF(1>=INPUTS!$B$32,"",INPUTS!$B$22*(1+INPUTS!$B$23)^(INPUTS!$B$6-INPUTS!$B$5+1))) -> 60709.709 | D5: =IF(INPUTS!$B$32=0,"",IF(1>=INPUTS!$B$32,"",INPUTS!$B$24)) -> 0 | E5: =IF(INPUTS!$B$32=0,"",IF(1>=INPUTS!$B$32,"",MAX(0,C5-D5))) -> 60709.709 | F5: =IF(INPUTS!$B$32=0,"",IF(1>=INPUTS!$B$32,"",L4)) -> 389546.13 | G5: =IF(INPUTS!$B$32=0,"",IF(1>=INPUTS!$B$32,"",M4)) -> 159750 | H5: =IF(INPUTS!$B$32=0,"",IF(1>=INPUTS!$B$32,"",N4)) -> 692250 | I5: =IF(INPUTS!$B$32=0,"",IF(1>=INPUTS!$B$32,"",MIN(E5,F5))) -> 60709.709 | J5: =IF(INPUTS!$B$32=0,"",IF(1>=INPUTS!$B$32,"",MIN(E5-I5,G5))) -> 0 | K5: =IF(INPUTS!$B$32=0,"",IF(1>=INPUTS!$B$32,"",MIN(E5-I5-J5,H5))) -> 0 | L5: =IF(INPUTS!$B$32=0,"",IF(1>=INPUTS!$B$32,"",(F5-I5)*(1+INPUTS!$B$28))) -> 350210.79 | M5: =IF(INPUTS!$B$32=0,"",IF(1>=INPUTS!$B$32,"",(G5-J5)*(1+INPUTS!$B$28))) -> 170133.75 | N5: =IF(INPUTS!$B$32=0,"",IF(1>=INPUTS!$B$32,"",(H5-K5)*(1+INPUTS!$B$28))) -> 737246.25 | O5: =IF(INPUTS!$B$32=0,"",IF(1>=INPUTS!$B$32,"",L5+M5+N5)) -> 1257590.8
A6: =IF(INPUTS!$B$32=0,"",IF(2>=INPUTS!$B$32,"",INPUTS!$B$12+(INPUTS!$B$6-INPUTS!$B$5)+2)) -> 2031 | B6: =IF(INPUTS!$B$32=0,"",IF(2>=INPUTS!$B$32,"",INPUTS!$B$6+2)) -> 57 | C6: =IF(INPUTS!$B$32=0,"",IF(2>=INPUTS!$B$32,"",INPUTS!$B$22*(1+INPUTS!$B$23)^(INPUTS!$B$6-INPUTS!$B$5+2))) -> 62227.452 | D6: =IF(INPUTS!$B$32=0,"",IF(2>=INPUTS!$B$32,"",INPUTS!$B$24)) -> 0 | E6: =IF(INPUTS!$B$32=0,"",IF(2>=INPUTS!$B$32,"",MAX(0,C6-D6))) -> 62227.452 | F6: =IF(INPUTS!$B$32=0,"",IF(2>=INPUTS!$B$32,"",L5)) -> 350210.79 | G6: =IF(INPUTS!$B$32=0,"",IF(2>=INPUTS!$B$32,"",M5)) -> 170133.75 | H6: =IF(INPUTS!$B$32=0,"",IF(2>=INPUTS!$B$32,"",N5)) -> 737246.25 | I6: =IF(INPUTS!$B$32=0,"",IF(2>=INPUTS!$B$32,"",MIN(E6,F6))) -> 62227.452 | J6: =IF(INPUTS!$B$32=0,"",IF(2>=INPUTS!$B$32,"",MIN(E6-I6,G6))) -> 0 | K6: =IF(INPUTS!$B$32=0,"",IF(2>=INPUTS!$B$32,"",MIN(E6-I6-J6,H6))) -> 0 | L6: =IF(INPUTS!$B$32=0,"",IF(2>=INPUTS!$B$32,"",(F6-I6)*(1+INPUTS!$B$28))) -> 306702.26 | M6: =IF(INPUTS!$B$32=0,"",IF(2>=INPUTS!$B$32,"",(G6-J6)*(1+INPUTS!$B$28))) -> 181192.44 | N6: =IF(INPUTS!$B$32=0,"",IF(2>=INPUTS!$B$32,"",(H6-K6)*(1+INPUTS!$B$28))) -> 785167.26 | O6: =IF(INPUTS!$B$32=0,"",IF(2>=INPUTS!$B$32,"",L6+M6+N6)) -> 1273062
A7: =IF(INPUTS!$B$32=0,"",IF(3>=INPUTS!$B$32,"",INPUTS!$B$12+(INPUTS!$B$6-INPUTS!$B$5)+3)) -> 2032 | B7: =IF(INPUTS!$B$32=0,"",IF(3>=INPUTS!$B$32,"",INPUTS!$B$6+3)) -> 58 | C7: =IF(INPUTS!$B$32=0,"",IF(3>=INPUTS!$B$32,"",INPUTS!$B$22*(1+INPUTS!$B$23)^(INPUTS!$B$6-INPUTS!$B$5+3))) -> 63783.138 | D7: =IF(INPUTS!$B$32=0,"",IF(3>=INPUTS!$B$32,"",INPUTS!$B$24)) -> 0 | E7: =IF(INPUTS!$B$32=0,"",IF(3>=INPUTS!$B$32,"",MAX(0,C7-D7))) -> 63783.138 | F7: =IF(INPUTS!$B$32=0,"",IF(3>=INPUTS!$B$32,"",L6)) -> 306702.26 | G7: =IF(INPUTS!$B$32=0,"",IF(3>=INPUTS!$B$32,"",M6)) -> 181192.44 | H7: =IF(INPUTS!$B$32=0,"",IF(3>=INPUTS!$B$32,"",N6)) -> 785167.26 | I7: =IF(INPUTS!$B$32=0,"",IF(3>=INPUTS!$B$32,"",MIN(E7,F7))) -> 63783.138 | J7: =IF(INPUTS!$B$32=0,"",IF(3>=INPUTS!$B$32,"",MIN(E7-I7,G7))) -> 0 | K7: =IF(INPUTS!$B$32=0,"",IF(3>=INPUTS!$B$32,"",MIN(E7-I7-J7,H7))) -> 0 | L7: =IF(INPUTS!$B$32=0,"",IF(3>=INPUTS!$B$32,"",(F7-I7)*(1+INPUTS!$B$28))) -> 258708.86 | M7: =IF(INPUTS!$B$32=0,"",IF(3>=INPUTS!$B$32,"",(G7-J7)*(1+INPUTS!$B$28))) -> 192969.95 | N7: =IF(INPUTS!$B$32=0,"",IF(3>=INPUTS!$B$32,"",(H7-K7)*(1+INPUTS!$B$28))) -> 836203.13 | O7: =IF(INPUTS!$B$32=0,"",IF(3>=INPUTS!$B$32,"",L7+M7+N7)) -> 1287881.9
A8: =IF(INPUTS!$B$32=0,"",IF(4>=INPUTS!$B$32,"",INPUTS!$B$12+(INPUTS!$B$6-INPUTS!$B$5)+4)) -> 2033 | B8: =IF(INPUTS!$B$32=0,"",IF(4>=INPUTS!$B$32,"",INPUTS!$B$6+4)) -> 59 | C8: =IF(INPUTS!$B$32=0,"",IF(4>=INPUTS!$B$32,"",INPUTS!$B$22*(1+INPUTS!$B$23)^(INPUTS!$B$6-INPUTS!$B$5+4))) -> 65377.716 | D8: =IF(INPUTS!$B$32=0,"",IF(4>=INPUTS!$B$32,"",INPUTS!$B$24)) -> 0 | E8: =IF(INPUTS!$B$32=0,"",IF(4>=INPUTS!$B$32,"",MAX(0,C8-D8))) -> 65377.716 | F8: =IF(INPUTS!$B$32=0,"",IF(4>=INPUTS!$B$32,"",L7)) -> 258708.86 | G8: =IF(INPUTS!$B$32=0,"",IF(4>=INPUTS!$B$32,"",M7)) -> 192969.95 | H8: =IF(INPUTS!$B$32=0,"",IF(4>=INPUTS!$B$32,"",N7)) -> 836203.13 | I8: =IF(INPUTS!$B$32=0,"",IF(4>=INPUTS!$B$32,"",MIN(E8,F8))) -> 65377.716 | J8: =IF(INPUTS!$B$32=0,"",IF(4>=INPUTS!$B$32,"",MIN(E8-I8,G8))) -> 0 | K8: =IF(INPUTS!$B$32=0,"",IF(4>=INPUTS!$B$32,"",MIN(E8-I8-J8,H8))) -> 0 | L8: =IF(INPUTS!$B$32=0,"",IF(4>=INPUTS!$B$32,"",(F8-I8)*(1+INPUTS!$B$28))) -> 205897.67 | M8: =IF(INPUTS!$B$32=0,"",IF(4>=INPUTS!$B$32,"",(G8-J8)*(1+INPUTS!$B$28))) -> 205513 | N8: =IF(INPUTS!$B$32=0,"",IF(4>=INPUTS!$B$32,"",(H8-K8)*(1+INPUTS!$B$28))) -> 890556.33 | O8: =IF(INPUTS!$B$32=0,"",IF(4>=INPUTS!$B$32,"",L8+M8+N8)) -> 1301967
A9: =IF(INPUTS!$B$32=0,"",IF(5>=INPUTS!$B$32,"",INPUTS!$B$12+(INPUTS!$B$6-INPUTS!$B$5)+5)) | B9: =IF(INPUTS!$B$32=0,"",IF(5>=INPUTS!$B$32,"",INPUTS!$B$6+5)) | C9: =IF(INPUTS!$B$32=0,"",IF(5>=INPUTS!$B$32,"",INPUTS!$B$22*(1+INPUTS!$B$23)^(INPUTS!$B$6-INPUTS!$B$5+5))) | D9: =IF(INPUTS!$B$32=0,"",IF(5>=INPUTS!$B$32,"",INPUTS!$B$24)) | E9: =IF(INPUTS!$B$32=0,"",IF(5>=INPUTS!$B$32,"",MAX(0,C9-D9))) | F9: =IF(INPUTS!$B$32=0,"",IF(5>=INPUTS!$B$32,"",L8)) | G9: =IF(INPUTS!$B$32=0,"",IF(5>=INPUTS!$B$32,"",M8)) | H9: =IF(INPUTS!$B$32=0,"",IF(5>=INPUTS!$B$32,"",N8)) | I9: =IF(INPUTS!$B$32=0,"",IF(5>=INPUTS!$B$32,"",MIN(E9,F9))) | J9: =IF(INPUTS!$B$32=0,"",IF(5>=INPUTS!$B$32,"",MIN(E9-I9,G9))) | K9: =IF(INPUTS!$B$32=0,"",IF(5>=INPUTS!$B$32,"",MIN(E9-I9-J9,H9))) | L9: =IF(INPUTS!$B$32=0,"",IF(5>=INPUTS!$B$32,"",(F9-I9)*(1+INPUTS!$B$28))) | M9: =IF(INPUTS!$B$32=0,"",IF(5>=INPUTS!$B$32,"",(G9-J9)*(1+INPUTS!$B$28))) | N9: =IF(INPUTS!$B$32=0,"",IF(5>=INPUTS!$B$32,"",(H9-K9)*(1+INPUTS!$B$28))) | O9: =IF(INPUTS!$B$32=0,"",IF(5>=INPUTS!$B$32,"",L9+M9+N9))
A10: =IF(INPUTS!$B$32=0,"",IF(6>=INPUTS!$B$32,"",INPUTS!$B$12+(INPUTS!$B$6-INPUTS!$B$5)+6)) | B10: =IF(INPUTS!$B$32=0,"",IF(6>=INPUTS!$B$32,"",INPUTS!$B$6+6)) | C10: =IF(INPUTS!$B$32=0,"",IF(6>=INPUTS!$B$32,"",INPUTS!$B$22*(1+INPUTS!$B$23)^(INPUTS!$B$6-INPUTS!$B$5+6))) | D10: =IF(INPUTS!$B$32=0,"",IF(6>=INPUTS!$B$32,"",INPUTS!$B$24)) | E10: =IF(INPUTS!$B$32=0,"",IF(6>=INPUTS!$B$32,"",MAX(0,C10-D10))) | F10: =IF(INPUTS!$B$32=0,"",IF(6>=INPUTS!$B$32,"",L9)) | G10: =IF(INPUTS!$B$32=0,"",IF(6>=INPUTS!$B$32,"",M9)) | H10: =IF(INPUTS!$B$32=0,"",IF(6>=INPUTS!$B$32,"",N9)) | I10: =IF(INPUTS!$B$32=0,"",IF(6>=INPUTS!$B$32,"",MIN(E10,F10))) | J10: =IF(INPUTS!$B$32=0,"",IF(6>=INPUTS!$B$32,"",MIN(E10-I10,G10))) | K10: =IF(INPUTS!$B$32=0,"",IF(6>=INPUTS!$B$32,"",MIN(E10-I10-J10,H10))) | L10: =IF(INPUTS!$B$32=0,"",IF(6>=INPUTS!$B$32,"",(F10-I10)*(1+INPUTS!$B$28))) | M10: =IF(INPUTS!$B$32=0,"",IF(6>=INPUTS!$B$32,"",(G10-J10)*(1+INPUTS!$B$28))) | N10: =IF(INPUTS!$B$32=0,"",IF(6>=INPUTS!$B$32,"",(H10-K10)*(1+INPUTS!$B$28))) | O10: =IF(INPUTS!$B$32=0,"",IF(6>=INPUTS!$B$32,"",L10+M10+N10))
A11: =IF(INPUTS!$B$32=0,"",IF(7>=INPUTS!$B$32,"",INPUTS!$B$12+(INPUTS!$B$6-INPUTS!$B$5)+7)) | B11: =IF(INPUTS!$B$32=0,"",IF(7>=INPUTS!$B$32,"",INPUTS!$B$6+7)) | C11: =IF(INPUTS!$B$32=0,"",IF(7>=INPUTS!$B$32,"",INPUTS!$B$22*(1+INPUTS!$B$23)^(INPUTS!$B$6-INPUTS!$B$5+7))) | D11: =IF(INPUTS!$B$32=0,"",IF(7>=INPUTS!$B$32,"",INPUTS!$B$24)) | E11: =IF(INPUTS!$B$32=0,"",IF(7>=INPUTS!$B$32,"",MAX(0,C11-D11))) | F11: =IF(INPUTS!$B$32=0,"",IF(7>=INPUTS!$B$32,"",L10)) | G11: =IF(INPUTS!$B$32=0,"",IF(7>=INPUTS!$B$32,"",M10)) | H11: =IF(INPUTS!$B$32=0,"",IF(7>=INPUTS!$B$32,"",N10)) | I11: =IF(INPUTS!$B$32=0,"",IF(7>=INPUTS!$B$32,"",MIN(E11,F11))) | J11: =IF(INPUTS!$B$32=0,"",IF(7>=INPUTS!$B$32,"",MIN(E11-I11,G11))) | K11: =IF(INPUTS!$B$32=0,"",IF(7>=INPUTS!$B$32,"",MIN(E11-I11-J11,H11))) | L11: =IF(INPUTS!$B$32=0,"",IF(7>=INPUTS!$B$32,"",(F11-I11)*(1+INPUTS!$B$28))) | M11: =IF(INPUTS!$B$32=0,"",IF(7>=INPUTS!$B$32,"",(G11-J11)*(1+INPUTS!$B$28))) | N11: =IF(INPUTS!$B$32=0,"",IF(7>=INPUTS!$B$32,"",(H11-K11)*(1+INPUTS!$B$28))) | O11: =IF(INPUTS!$B$32=0,"",IF(7>=INPUTS!$B$32,"",L11+M11+N11))
A12: =IF(INPUTS!$B$32=0,"",IF(8>=INPUTS!$B$32,"",INPUTS!$B$12+(INPUTS!$B$6-INPUTS!$B$5)+8)) | B12: =IF(INPUTS!$B$32=0,"",IF(8>=INPUTS!$B$32,"",INPUTS!$B$6+8)) | C12: =IF(INPUTS!$B$32=0,"",IF(8>=INPUTS!$B$32,"",INPUTS!$B$22*(1+INPUTS!$B$23)^(INPUTS!$B$6-INPUTS!$B$5+8))) | D12: =IF(INPUTS!$B$32=0,"",IF(8>=INPUTS!$B$32,"",INPUTS!$B$24)) | E12: =IF(INPUTS!$B$32=0,"",IF(8>=INPUTS!$B$32,"",MAX(0,C12-D12))) | F12: =IF(INPUTS!$B$32=0,"",IF(8>=INPUTS!$B$32,"",L11)) | G12: =IF(INPUTS!$B$32=0,"",IF(8>=INPUTS!$B$32,"",M11)) | H12: =IF(INPUTS!$B$32=0,"",IF(8>=INPUTS!$B$32,"",N11)) | I12: =IF(INPUTS!$B$32=0,"",IF(8>=INPUTS!$B$32,"",MIN(E12,F12))) | J12: =IF(INPUTS!$B$32=0,"",IF(8>=INPUTS!$B$32,"",MIN(E12-I12,G12))) | K12: =IF(INPUTS!$B$32=0,"",IF(8>=INPUTS!$B$32,"",MIN(E12-I12-J12,H12))) | L12: =IF(INPUTS!$B$32=0,"",IF(8>=INPUTS!$B$32,"",(F12-I12)*(1+INPUTS!$B$28))) | M12: =IF(INPUTS!$B$32=0,"",IF(8>=INPUTS!$B$32,"",(G12-J12)*(1+INPUTS!$B$28))) | N12: =IF(INPUTS!$B$32=0,"",IF(8>=INPUTS!$B$32,"",(H12-K12)*(1+INPUTS!$B$28))) | O12: =IF(INPUTS!$B$32=0,"",IF(8>=INPUTS!$B$32,"",L12+M12+N12))
A13: =IF(INPUTS!$B$32=0,"",IF(9>=INPUTS!$B$32,"",INPUTS!$B$12+(INPUTS!$B$6-INPUTS!$B$5)+9)) | B13: =IF(INPUTS!$B$32=0,"",IF(9>=INPUTS!$B$32,"",INPUTS!$B$6+9)) | C13: =IF(INPUTS!$B$32=0,"",IF(9>=INPUTS!$B$32,"",INPUTS!$B$22*(1+INPUTS!$B$23)^(INPUTS!$B$6-INPUTS!$B$5+9))) | D13: =IF(INPUTS!$B$32=0,"",IF(9>=INPUTS!$B$32,"",INPUTS!$B$24)) | E13: =IF(INPUTS!$B$32=0,"",IF(9>=INPUTS!$B$32,"",MAX(0,C13-D13))) | F13: =IF(INPUTS!$B$32=0,"",IF(9>=INPUTS!$B$32,"",L12)) | G13: =IF(INPUTS!$B$32=0,"",IF(9>=INPUTS!$B$32,"",M12)) | H13: =IF(INPUTS!$B$32=0,"",IF(9>=INPUTS!$B$32,"",N12)) | I13: =IF(INPUTS!$B$32=0,"",IF(9>=INPUTS!$B$32,"",MIN(E13,F13))) | J13: =IF(INPUTS!$B$32=0,"",IF(9>=INPUTS!$B$32,"",MIN(E13-I13,G13))) | K13: =IF(INPUTS!$B$32=0,"",IF(9>=INPUTS!$B$32,"",MIN(E13-I13-J13,H13))) | L13: =IF(INPUTS!$B$32=0,"",IF(9>=INPUTS!$B$32,"",(F13-I13)*(1+INPUTS!$B$28))) | M13: =IF(INPUTS!$B$32=0,"",IF(9>=INPUTS!$B$32,"",(G13-J13)*(1+INPUTS!$B$28))) | N13: =IF(INPUTS!$B$32=0,"",IF(9>=INPUTS!$B$32,"",(H13-K13)*(1+INPUTS!$B$28))) | O13: =IF(INPUTS!$B$32=0,"",IF(9>=INPUTS!$B$32,"",L13+M13+N13))
A14: =IF(INPUTS!$B$32=0,"",IF(10>=INPUTS!$B$32,"",INPUTS!$B$12+(INPUTS!$B$6-INPUTS!$B$5)+10)) | B14: =IF(INPUTS!$B$32=0,"",IF(10>=INPUTS!$B$32,"",INPUTS!$B$6+10)) | C14: =IF(INPUTS!$B$32=0,"",IF(10>=INPUTS!$B$32,"",INPUTS!$B$22*(1+INPUTS!$B$23)^(INPUTS!$B$6-INPUTS!$B$5+10))) | D14: =IF(INPUTS!$B$32=0,"",IF(10>=INPUTS!$B$32,"",INPUTS!$B$24)) | E14: =IF(INPUTS!$B$32=0,"",IF(10>=INPUTS!$B$32,"",MAX(0,C14-D14))) | F14: =IF(INPUTS!$B$32=0,"",IF(10>=INPUTS!$B$32,"",L13)) | G14: =IF(INPUTS!$B$32=0,"",IF(10>=INPUTS!$B$32,"",M13)) | H14: =IF(INPUTS!$B$32=0,"",IF(10>=INPUTS!$B$32,"",N13)) | I14: =IF(INPUTS!$B$32=0,"",IF(10>=INPUTS!$B$32,"",MIN(E14,F14))) | J14: =IF(INPUTS!$B$32=0,"",IF(10>=INPUTS!$B$32,"",MIN(E14-I14,G14))) | K14: =IF(INPUTS!$B$32=0,"",IF(10>=INPUTS!$B$32,"",MIN(E14-I14-J14,H14))) | L14: =IF(INPUTS!$B$32=0,"",IF(10>=INPUTS!$B$32,"",(F14-I14)*(1+INPUTS!$B$28))) | M14: =IF(INPUTS!$B$32=0,"",IF(10>=INPUTS!$B$32,"",(G14-J14)*(1+INPUTS!$B$28))) | N14: =IF(INPUTS!$B$32=0,"",IF(10>=INPUTS!$B$32,"",(H14-K14)*(1+INPUTS!$B$28))) | O14: =IF(INPUTS!$B$32=0,"",IF(10>=INPUTS!$B$32,"",L14+M14+N14))
A15: =IF(INPUTS!$B$32=0,"",IF(11>=INPUTS!$B$32,"",INPUTS!$B$12+(INPUTS!$B$6-INPUTS!$B$5)+11)) | B15: =IF(INPUTS!$B$32=0,"",IF(11>=INPUTS!$B$32,"",INPUTS!$B$6+11)) | C15: =IF(INPUTS!$B$32=0,"",IF(11>=INPUTS!$B$32,"",INPUTS!$B$22*(1+INPUTS!$B$23)^(INPUTS!$B$6-INPUTS!$B$5+11))) | D15: =IF(INPUTS!$B$32=0,"",IF(11>=INPUTS!$B$32,"",INPUTS!$B$24)) | E15: =IF(INPUTS!$B$32=0,"",IF(11>=INPUTS!$B$32,"",MAX(0,C15-D15))) | F15: =IF(INPUTS!$B$32=0,"",IF(11>=INPUTS!$B$32,"",L14)) | G15: =IF(INPUTS!$B$32=0,"",IF(11>=INPUTS!$B$32,"",M14)) | H15: =IF(INPUTS!$B$32=0,"",IF(11>=INPUTS!$B$32,"",N14)) | I15: =IF(INPUTS!$B$32=0,"",IF(11>=INPUTS!$B$32,"",MIN(E15,F15))) | J15: =IF(INPUTS!$B$32=0,"",IF(11>=INPUTS!$B$32,"",MIN(E15-I15,G15))) | K15: =IF(INPUTS!$B$32=0,"",IF(11>=INPUTS!$B$32,"",MIN(E15-I15-J15,H15))) | L15: =IF(INPUTS!$B$32=0,"",IF(11>=INPUTS!$B$32,"",(F15-I15)*(1+INPUTS!$B$28))) | M15: =IF(INPUTS!$B$32=0,"",IF(11>=INPUTS!$B$32,"",(G15-J15)*(1+INPUTS!$B$28))) | N15: =IF(INPUTS!$B$32=0,"",IF(11>=INPUTS!$B$32,"",(H15-K15)*(1+INPUTS!$B$28))) | O15: =IF(INPUTS!$B$32=0,"",IF(11>=INPUTS!$B$32,"",L15+M15+N15))
A16: =IF(INPUTS!$B$32=0,"",IF(12>=INPUTS!$B$32,"",INPUTS!$B$12+(INPUTS!$B$6-INPUTS!$B$5)+12)) | B16: =IF(INPUTS!$B$32=0,"",IF(12>=INPUTS!$B$32,"",INPUTS!$B$6+12)) | C16: =IF(INPUTS!$B$32=0,"",IF(12>=INPUTS!$B$32,"",INPUTS!$B$22*(1+INPUTS!$B$23)^(INPUTS!$B$6-INPUTS!$B$5+12))) | D16: =IF(INPUTS!$B$32=0,"",IF(12>=INPUTS!$B$32,"",INPUTS!$B$24)) | E16: =IF(INPUTS!$B$32=0,"",IF(12>=INPUTS!$B$32,"",MAX(0,C16-D16))) | F16: =IF(INPUTS!$B$32=0,"",IF(12>=INPUTS!$B$32,"",L15)) | G16: =IF(INPUTS!$B$32=0,"",IF(12>=INPUTS!$B$32,"",M15)) | H16: =IF(INPUTS!$B$32=0,"",IF(12>=INPUTS!$B$32,"",N15)) | I16: =IF(INPUTS!$B$32=0,"",IF(12>=INPUTS!$B$32,"",MIN(E16,F16))) | J16: =IF(INPUTS!$B$32=0,"",IF(12>=INPUTS!$B$32,"",MIN(E16-I16,G16))) | K16: =IF(INPUTS!$B$32=0,"",IF(12>=INPUTS!$B$32,"",MIN(E16-I16-J16,H16))) | L16: =IF(INPUTS!$B$32=0,"",IF(12>=INPUTS!$B$32,"",(F16-I16)*(1+INPUTS!$B$28))) | M16: =IF(INPUTS!$B$32=0,"",IF(12>=INPUTS!$B$32,"",(G16-J16)*(1+INPUTS!$B$28))) | N16: =IF(INPUTS!$B$32=0,"",IF(12>=INPUTS!$B$32,"",(H16-K16)*(1+INPUTS!$B$28))) | O16: =IF(INPUTS!$B$32=0,"",IF(12>=INPUTS!$B$32,"",L16+M16+N16))
A17: =IF(INPUTS!$B$32=0,"",IF(13>=INPUTS!$B$32,"",INPUTS!$B$12+(INPUTS!$B$6-INPUTS!$B$5)+13)) | B17: =IF(INPUTS!$B$32=0,"",IF(13>=INPUTS!$B$32,"",INPUTS!$B$6+13)) | C17: =IF(INPUTS!$B$32=0,"",IF(13>=INPUTS!$B$32,"",INPUTS!$B$22*(1+INPUTS!$B$23)^(INPUTS!$B$6-INPUTS!$B$5+13))) | D17: =IF(INPUTS!$B$32=0,"",IF(13>=INPUTS!$B$32,"",INPUTS!$B$24)) | E17: =IF(INPUTS!$B$32=0,"",IF(13>=INPUTS!$B$32,"",MAX(0,C17-D17))) | F17: =IF(INPUTS!$B$32=0,"",IF(13>=INPUTS!$B$32,"",L16)) | G17: =IF(INPUTS!$B$32=0,"",IF(13>=INPUTS!$B$32,"",M16)) | H17: =IF(INPUTS!$B$32=0,"",IF(13>=INPUTS!$B$32,"",N16)) | I17: =IF(INPUTS!$B$32=0,"",IF(13>=INPUTS!$B$32,"",MIN(E17,F17))) | J17: =IF(INPUTS!$B$32=0,"",IF(13>=INPUTS!$B$32,"",MIN(E17-I17,G17))) | K17: =IF(INPUTS!$B$32=0,"",IF(13>=INPUTS!$B$32,"",MIN(E17-I17-J17,H17))) | L17: =IF(INPUTS!$B$32=0,"",IF(13>=INPUTS!$B$32,"",(F17-I17)*(1+INPUTS!$B$28))) | M17: =IF(INPUTS!$B$32=0,"",IF(13>=INPUTS!$B$32,"",(G17-J17)*(1+INPUTS!$B$28))) | N17: =IF(INPUTS!$B$32=0,"",IF(13>=INPUTS!$B$32,"",(H17-K17)*(1+INPUTS!$B$28))) | O17: =IF(INPUTS!$B$32=0,"",IF(13>=INPUTS!$B$32,"",L17+M17+N17))
A18: =IF(INPUTS!$B$32=0,"",IF(14>=INPUTS!$B$32,"",INPUTS!$B$12+(INPUTS!$B$6-INPUTS!$B$5)+14)) | B18: =IF(INPUTS!$B$32=0,"",IF(14>=INPUTS!$B$32,"",INPUTS!$B$6+14)) | C18: =IF(INPUTS!$B$32=0,"",IF(14>=INPUTS!$B$32,"",INPUTS!$B$22*(1+INPUTS!$B$23)^(INPUTS!$B$6-INPUTS!$B$5+14))) | D18: =IF(INPUTS!$B$32=0,"",IF(14>=INPUTS!$B$32,"",INPUTS!$B$24)) | E18: =IF(INPUTS!$B$32=0,"",IF(14>=INPUTS!$B$32,"",MAX(0,C18-D18))) | F18: =IF(INPUTS!$B$32=0,"",IF(14>=INPUTS!$B$32,"",L17)) | G18: =IF(INPUTS!$B$32=0,"",IF(14>=INPUTS!$B$32,"",M17)) | H18: =IF(INPUTS!$B$32=0,"",IF(14>=INPUTS!$B$32,"",N17)) | I18: =IF(INPUTS!$B$32=0,"",IF(14>=INPUTS!$B$32,"",MIN(E18,F18))) | J18: =IF(INPUTS!$B$32=0,"",IF(14>=INPUTS!$B$32,"",MIN(E18-I18,G18))) | K18: =IF(INPUTS!$B$32=0,"",IF(14>=INPUTS!$B$32,"",MIN(E18-I18-J18,H18))) | L18: =IF(INPUTS!$B$32=0,"",IF(14>=INPUTS!$B$32,"",(F18-I18)*(1+INPUTS!$B$28))) | M18: =IF(INPUTS!$B$32=0,"",IF(14>=INPUTS!$B$32,"",(G18-J18)*(1+INPUTS!$B$28))) | N18: =IF(INPUTS!$B$32=0,"",IF(14>=INPUTS!$B$32,"",(H18-K18)*(1+INPUTS!$B$28))) | O18: =IF(INPUTS!$B$32=0,"",IF(14>=INPUTS!$B$32,"",L18+M18+N18))
A20: END OF BRIDGE → | C20: =IF(INPUTS!$B$32=0,INPUTS!$B$22,IFERROR(LOOKUP(9.99E+307,C4:C18),INPUTS!$B$22)) -> 65377.716 | L20: =IF(INPUTS!$B$32=0,INPUTS!$B$15+INPUTS!$B$18,IFERROR(LOOKUP(9.99E+307,L4:L18),INPUTS!$B$15+INPUTS!$B$18)) -> 205897.67 | M20: =IF(INPUTS!$B$32=0,INPUTS!$B$17,IFERROR(LOOKUP(9.99E+307,M4:M18),INPUTS!$B$17)) -> 205513 | N20: =IF(INPUTS!$B$32=0,INPUTS!$B$16,IFERROR(LOOKUP(9.99E+307,N4:N18),INPUTS!$B$16)) -> 890556.33

Sheet TAX ESTIMATE
A1: FEDERAL TAX ESTIMATE · Bridge Years
A2: =IF(INPUTS!B9="MFJ","Using 2026 MFJ brackets + $30,000 standard deduction.","Using 2026 Single brackets + $15,000 standard deduction.") -> Using 2026 MFJ brackets + $30,000 standard deduction.
A4: 2026 BRACKETS (auto-switch via INPUTS Filing Status)
A5: Rate | B5: From | C5: To | D5: RateΔ
A6: 0.1 | B6: =IF(INPUTS!$B$9="MFJ",0,0) -> 0 | C6: =IF(INPUTS!$B$9="MFJ",23850,11925) -> 23850 | D6: 0.1
A7: 0.12 | B7: =IF(INPUTS!$B$9="MFJ",23850,11925) -> 23850 | C7: =IF(INPUTS!$B$9="MFJ",96950,48475) -> 96950 | D7: 0.02
A8: 0.22 | B8: =IF(INPUTS!$B$9="MFJ",96950,48475) -> 96950 | C8: =IF(INPUTS!$B$9="MFJ",206700,103350) -> 206700 | D8: 0.1
A9: 0.24 | B9: =IF(INPUTS!$B$9="MFJ",206700,103350) -> 206700 | C9: =IF(INPUTS!$B$9="MFJ",394600,197300) -> 394600 | D9: 0.02
A10: 0.32 | B10: =IF(INPUTS!$B$9="MFJ",394600,197300) -> 394600 | C10: =IF(INPUTS!$B$9="MFJ",501050,250525) -> 501050 | D10: 0.08
A11: 0.35 | B11: =IF(INPUTS!$B$9="MFJ",501050,250525) -> 501050 | C11: =IF(INPUTS!$B$9="MFJ",751600,375800) -> 751600 | D11: 0.03
A12: 0.37 | B12: =IF(INPUTS!$B$9="MFJ",751600,375800) -> 751600 | C12: =IF(INPUTS!$B$9="MFJ",99999999,99999999) -> 99999999 | D12: 0.02
A14: ESTIMATED TAX BY BRIDGE YEAR
A16: Year | B16: Income (401k+Roth conv.) | C16: Std Deduction | D16: Taxable Income | E16: Fed Tax | F16: State Tax | G16: Note
A17: =BRIDGE!A4 -> 2029 | B17: =IF(BRIDGE!A4="","",BRIDGE!K4+'ROTH LADDER'!D6) -> 81760 | C17: =IF(A17="","",INPUTS!$B$34) -> 30000 | D17: =IF(A17="","",MAX(0,B17-C17)) -> 51760 | E17: =IF(A17="","",SUMPRODUCT(((D17-$B$6:$B$12)>0)*(D17-$B$6:$B$12)*$D$6:$D$12)) -> 5734.2 | F17: =IF(A17="","",D17*INPUTS!$B$11) -> 0
A18: =BRIDGE!A5 -> 2030 | B18: =IF(BRIDGE!A5="","",BRIDGE!K5+'ROTH LADDER'!D7) -> 81760 | C18: =IF(A18="","",INPUTS!$B$34) -> 30000 | D18: =IF(A18="","",MAX(0,B18-C18)) -> 51760 | E18: =IF(A18="","",SUMPRODUCT(((D18-$B$6:$B$12)>0)*(D18-$B$6:$B$12)*$D$6:$D$12)) -> 5734.2 | F18: =IF(A18="","",D18*INPUTS!$B$11) -> 0
A19: =BRIDGE!A6 -> 2031 | B19: =IF(BRIDGE!A6="","",BRIDGE!K6+'ROTH LADDER'!D8) -> 81760 | C19: =IF(A19="","",INPUTS!$B$34) -> 30000 | D19: =IF(A19="","",MAX(0,B19-C19)) -> 51760 | E19: =IF(A19="","",SUMPRODUCT(((D19-$B$6:$B$12)>0)*(D19-$B$6:$B$12)*$D$6:$D$12)) -> 5734.2 | F19: =IF(A19="","",D19*INPUTS!$B$11) -> 0
A20: =BRIDGE!A7 -> 2032 | B20: =IF(BRIDGE!A7="","",BRIDGE!K7+'ROTH LADDER'!D9) -> 81760 | C20: =IF(A20="","",INPUTS!$B$34) -> 30000 | D20: =IF(A20="","",MAX(0,B20-C20)) -> 51760 | E20: =IF(A20="","",SUMPRODUCT(((D20-$B$6:$B$12)>0)*(D20-$B$6:$B$12)*$D$6:$D$12)) -> 5734.2 | F20: =IF(A20="","",D20*INPUTS!$B$11) -> 0
A21: =BRIDGE!A8 -> 2033 | B21: =IF(BRIDGE!A8="","",BRIDGE!K8+'ROTH LADDER'!D10) -> 81760 | C21: =IF(A21="","",INPUTS!$B$34) -> 30000 | D21: =IF(A21="","",MAX(0,B21-C21)) -> 51760 | E21: =IF(A21="","",SUMPRODUCT(((D21-$B$6:$B$12)>0)*(D21-$B$6:$B$12)*$D$6:$D$12)) -> 5734.2 | F21: =IF(A21="","",D21*INPUTS!$B$11) -> 0
A22: =BRIDGE!A9 | B22: =IF(BRIDGE!A9="","",BRIDGE!K9+'ROTH LADDER'!D11) | C22: =IF(A22="","",INPUTS!$B$34) | D22: =IF(A22="","",MAX(0,B22-C22)) | E22: =IF(A22="","",SUMPRODUCT(((D22-$B$6:$B$12)>0)*(D22-$B$6:$B$12)*$D$6:$D$12)) | F22: =IF(A22="","",D22*INPUTS!$B$11)
A23: =BRIDGE!A10 | B23: =IF(BRIDGE!A10="","",BRIDGE!K10+'ROTH LADDER'!D12) | C23: =IF(A23="","",INPUTS!$B$34) | D23: =IF(A23="","",MAX(0,B23-C23)) | E23: =IF(A23="","",SUMPRODUCT(((D23-$B$6:$B$12)>0)*(D23-$B$6:$B$12)*$D$6:$D$12)) | F23: =IF(A23="","",D23*INPUTS!$B$11)
A24: =BRIDGE!A11 | B24: =IF(BRIDGE!A11="","",BRIDGE!K11+'ROTH LADDER'!D13) | C24: =IF(A24="","",INPUTS!$B$34) | D24: =IF(A24="","",MAX(0,B24-C24)) | E24: =IF(A24="","",SUMPRODUCT(((D24-$B$6:$B$12)>0)*(D24-$B$6:$B$12)*$D$6:$D$12)) | F24: =IF(A24="","",D24*INPUTS!$B$11)
A25: =BRIDGE!A12 | B25: =IF(BRIDGE!A12="","",BRIDGE!K12+'ROTH LADDER'!D14) | C25: =IF(A25="","",INPUTS!$B$34) | D25: =IF(A25="","",MAX(0,B25-C25)) | E25: =IF(A25="","",SUMPRODUCT(((D25-$B$6:$B$12)>0)*(D25-$B$6:$B$12)*$D$6:$D$12)) | F25: =IF(A25="","",D25*INPUTS!$B$11)
A26: =BRIDGE!A13 | B26: =IF(BRIDGE!A13="","",BRIDGE!K13+'ROTH LADDER'!D15) | C26: =IF(A26="","",INPUTS!$B$34) | D26: =IF(A26="","",MAX(0,B26-C26)) | E26: =IF(A26="","",SUMPRODUCT(((D26-$B$6:$B$12)>0)*(D26-$B$6:$B$12)*$D$6:$D$12)) | F26: =IF(A26="","",D26*INPUTS!$B$11)
A27: =BRIDGE!A14 | B27: =IF(BRIDGE!A14="","",BRIDGE!K14+'ROTH LADDER'!D16) | C27: =IF(A27="","",INPUTS!$B$34) | D27: =IF(A27="","",MAX(0,B27-C27)) | E27: =IF(A27="","",SUMPRODUCT(((D27-$B$6:$B$12)>0)*(D27-$B$6:$B$12)*$D$6:$D$12)) | F27: =IF(A27="","",D27*INPUTS!$B$11)
A28: =BRIDGE!A15 | B28: =IF(BRIDGE!A15="","",BRIDGE!K15+'ROTH LADDER'!D17) | C28: =IF(A28="","",INPUTS!$B$34) | D28: =IF(A28="","",MAX(0,B28-C28)) | E28: =IF(A28="","",SUMPRODUCT(((D28-$B$6:$B$12)>0)*(D28-$B$6:$B$12)*$D$6:$D$12)) | F28: =IF(A28="","",D28*INPUTS!$B$11)
... A31: =BRIDGE!A18 | B31: =IF(BRIDGE!A18="","",BRIDGE!K18+'ROTH LADDER'!D20) | C31: =IF(A31="","",INPUTS!$B$34) | D31: =IF(A31="","",MAX(0,B31-C31)) | E31: =IF(A31="","",SUMPRODUCT(((D31-$B$6:$B$12)>0)*(D31-$B$6:$B$12)*$D$6:$D$12)) | F31: =IF(A31="","",D31*INPUTS!$B$11)

Sheet ROTH LADDER
A1: ROTH CONVERSION LADDER · 5-Year Pipeline
A2: Suggested conversion = remaining 12% bracket space after bridge income. Each rung unlocks penalty-free after 5 years.
A3: ACA WARNING: conversions count toward MAGI. The cross-check below flags any year total MAGI exceeds the est. 400% FPL cliff (~$81,760 for 2-person household, 2026).
A5: Year | B5: Age | C5: 12% Bracket Space Left | D5: Suggested Conversion | E5: Tax on Conv. (12%) | F5: MAGI (income+conv.) | G5: ACA Cliff Check | H5: Unlocks Penalty-Free
A6: =BRIDGE!A4 -> 2029 | B6: =BRIDGE!B4 -> 55 | C6: =IF(A6="","",MAX(0,'TAX ESTIMATE'!$C$7-MAX(0,BRIDGE!K4-INPUTS!$B$34))) -> 96950 | D6: =IF(A6="","",MAX(0,MIN(C6,81760-BRIDGE!K4))) -> 81760 | E6: =IF(A6="","",D6*0.12) -> 9811.2 | F6: =IF(A6="","",BRIDGE!K4+D6) -> 81760 | G6: =IF(A6="","",IF(F6>81760,"⚠ OVER CLIFF — trims subsidy to $0","✓ Under cliff")) -> ✓ Under cliff | H6: =IF(A6="","",A6+5&" (5-yr rule)") -> 2034 (5-yr rule)
A7: =BRIDGE!A5 -> 2030 | B7: =BRIDGE!B5 -> 56 | C7: =IF(A7="","",MAX(0,'TAX ESTIMATE'!$C$7-MAX(0,BRIDGE!K5-INPUTS!$B$34))) -> 96950 | D7: =IF(A7="","",MAX(0,MIN(C7,81760-BRIDGE!K5))) -> 81760 | E7: =IF(A7="","",D7*0.12) -> 9811.2 | F7: =IF(A7="","",BRIDGE!K5+D7) -> 81760 | G7: =IF(A7="","",IF(F7>81760,"⚠ OVER CLIFF — trims subsidy to $0","✓ Under cliff")) -> ✓ Under cliff | H7: =IF(A7="","",A7+5&" (5-yr rule)") -> 2035 (5-yr rule)
A8: =BRIDGE!A6 -> 2031 | B8: =BRIDGE!B6 -> 57 | C8: =IF(A8="","",MAX(0,'TAX ESTIMATE'!$C$7-MAX(0,BRIDGE!K6-INPUTS!$B$34))) -> 96950 | D8: =IF(A8="","",MAX(0,MIN(C8,81760-BRIDGE!K6))) -> 81760 | E8: =IF(A8="","",D8*0.12) -> 9811.2 | F8: =IF(A8="","",BRIDGE!K6+D8) -> 81760 | G8: =IF(A8="","",IF(F8>81760,"⚠ OVER CLIFF — trims subsidy to $0","✓ Under cliff")) -> ✓ Under cliff | H8: =IF(A8="","",A8+5&" (5-yr rule)") -> 2036 (5-yr rule)
A9: =BRIDGE!A7 -> 2032 | B9: =BRIDGE!B7 -> 58 | C9: =IF(A9="","",MAX(0,'TAX ESTIMATE'!$C$7-MAX(0,BRIDGE!K7-INPUTS!$B$34))) -> 96950 | D9: =IF(A9="","",MAX(0,MIN(C9,81760-BRIDGE!K7))) -> 81760 | E9: =IF(A9="","",D9*0.12) -> 9811.2 | F9: =IF(A9="","",BRIDGE!K7+D9) -> 81760 | G9: =IF(A9="","",IF(F9>81760,"⚠ OVER CLIFF — trims subsidy to $0","✓ Under cliff")) -> ✓ Under cliff | H9: =IF(A9="","",A9+5&" (5-yr rule)") -> 2037 (5-yr rule)
A10: =BRIDGE!A8 -> 2033 | B10: =BRIDGE!B8 -> 59 | C10: =IF(A10="","",MAX(0,'TAX ESTIMATE'!$C$7-MAX(0,BRIDGE!K8-INPUTS!$B$34))) -> 96950 | D10: =IF(A10="","",MAX(0,MIN(C10,81760-BRIDGE!K8))) -> 81760 | E10: =IF(A10="","",D10*0.12) -> 9811.2 | F10: =IF(A10="","",BRIDGE!K8+D10) -> 81760 | G10: =IF(A10="","",IF(F10>81760,"⚠ OVER CLIFF — trims subsidy to $0","✓ Under cliff")) -> ✓ Under cliff | H10: =IF(A10="","",A10+5&" (5-yr rule)") -> 2038 (5-yr rule)
A11: =BRIDGE!A9 | B11: =BRIDGE!B9 | C11: =IF(A11="","",MAX(0,'TAX ESTIMATE'!$C$7-MAX(0,BRIDGE!K9-INPUTS!$B$34))) | D11: =IF(A11="","",MAX(0,MIN(C11,81760-BRIDGE!K9))) | E11: =IF(A11="","",D11*0.12) | F11: =IF(A11="","",BRIDGE!K9+D11) | G11: =IF(A11="","",IF(F11>81760,"⚠ OVER CLIFF — trims subsidy to $0","✓ Under cliff")) | H11: =IF(A11="","",A11+5&" (5-yr rule)")
A12: =BRIDGE!A10 | B12: =BRIDGE!B10 | C12: =IF(A12="","",MAX(0,'TAX ESTIMATE'!$C$7-MAX(0,BRIDGE!K10-INPUTS!$B$34))) | D12: =IF(A12="","",MAX(0,MIN(C12,81760-BRIDGE!K10))) | E12: =IF(A12="","",D12*0.12) | F12: =IF(A12="","",BRIDGE!K10+D12) | G12: =IF(A12="","",IF(F12>81760,"⚠ OVER CLIFF — trims subsidy to $0","✓ Under cliff")) | H12: =IF(A12="","",A12+5&" (5-yr rule)")
A13: =BRIDGE!A11 | B13: =BRIDGE!B11 | C13: =IF(A13="","",MAX(0,'TAX ESTIMATE'!$C$7-MAX(0,BRIDGE!K11-INPUTS!$B$34))) | D13: =IF(A13="","",MAX(0,MIN(C13,81760-BRIDGE!K11))) | E13: =IF(A13="","",D13*0.12) | F13: =IF(A13="","",BRIDGE!K11+D13) | G13: =IF(A13="","",IF(F13>81760,"⚠ OVER CLIFF — trims subsidy to $0","✓ Under cliff")) | H13: =IF(A13="","",A13+5&" (5-yr rule)")
A14: =BRIDGE!A12 | B14: =BRIDGE!B12 | C14: =IF(A14="","",MAX(0,'TAX ESTIMATE'!$C$7-MAX(0,BRIDGE!K12-INPUTS!$B$34))) | D14: =IF(A14="","",MAX(0,MIN(C14,81760-BRIDGE!K12))) | E14: =IF(A14="","",D14*0.12) | F14: =IF(A14="","",BRIDGE!K12+D14) | G14: =IF(A14="","",IF(F14>81760,"⚠ OVER CLIFF — trims subsidy to $0","✓ Under cliff")) | H14: =IF(A14="","",A14+5&" (5-yr rule)")
A15: =BRIDGE!A13 | B15: =BRIDGE!B13 | C15: =IF(A15="","",MAX(0,'TAX ESTIMATE'!$C$7-MAX(0,BRIDGE!K13-INPUTS!$B$34))) | D15: =IF(A15="","",MAX(0,MIN(C15,81760-BRIDGE!K13))) | E15: =IF(A15="","",D15*0.12) | F15: =IF(A15="","",BRIDGE!K13+D15) | G15: =IF(A15="","",IF(F15>81760,"⚠ OVER CLIFF — trims subsidy to $0","✓ Under cliff")) | H15: =IF(A15="","",A15+5&" (5-yr rule)")
A16: =BRIDGE!A14 | B16: =BRIDGE!B14 | C16: =IF(A16="","",MAX(0,'TAX ESTIMATE'!$C$7-MAX(0,BRIDGE!K14-INPUTS!$B$34))) | D16: =IF(A16="","",MAX(0,MIN(C16,81760-BRIDGE!K14))) | E16: =IF(A16="","",D16*0.12) | F16: =IF(A16="","",BRIDGE!K14+D16) | G16: =IF(A16="","",IF(F16>81760,"⚠ OVER CLIFF — trims subsidy to $0","✓ Under cliff")) | H16: =IF(A16="","",A16+5&" (5-yr rule)")
A17: =BRIDGE!A15 | B17: =BRIDGE!B15 | C17: =IF(A17="","",MAX(0,'TAX ESTIMATE'!$C$7-MAX(0,BRIDGE!K15-INPUTS!$B$34))) | D17: =IF(A17="","",MAX(0,MIN(C17,81760-BRIDGE!K15))) | E17: =IF(A17="","",D17*0.12) | F17: =IF(A17="","",BRIDGE!K15+D17) | G17: =IF(A17="","",IF(F17>81760,"⚠ OVER CLIFF — trims subsidy to $0","✓ Under cliff")) | H17: =IF(A17="","",A17+5&" (5-yr rule)")
... A20: =BRIDGE!A18 | B20: =BRIDGE!B18 | C20: =IF(A20="","",MAX(0,'TAX ESTIMATE'!$C$7-MAX(0,BRIDGE!K18-INPUTS!$B$34))) | D20: =IF(A20="","",MAX(0,MIN(C20,81760-BRIDGE!K18))) | E20: =IF(A20="","",D20*0.12) | F20: =IF(A20="","",BRIDGE!K18+D20) | G20: =IF(A20="","",IF(F20>81760,"⚠ OVER CLIFF — trims subsidy to $0","✓ Under cliff")) | H20: =IF(A20="","",A20+5&" (5-yr rule)")
A22: Suggested Conversion = smaller of 12% bracket space and ACA cliff headroom ($81,760 MAGI). Overwrite any year to convert more — the cliff check (col G) will warn you of the subsidy cost.

Sheet POST-59.5
A1: POST-59½ PROJECTION · To Life Expectancy
A2: 401k draws first, Roth preserved. Social Security (inflated) reduces withdrawals from claiming age.
A4: Year | B4: Age | C4: Spending (Infl.) | D4: SS Income | E4: Other Income | F4: Net Withdrawal | G4: 401k+Taxable Bal. | H4: Roth Bal.
A5: =IF(INPUTS!$B$32+0>INPUTS!$B$8-INPUTS!$B$6,"",INPUTS!$B$12+(INPUTS!$B$6-INPUTS!$B$5)+INPUTS!$B$32+0) -> 2033.5 | B5: =IF(INPUTS!$B$32+0>INPUTS!$B$8-INPUTS!$B$6,"",59.5+0) -> 59.5 | C5: =IF(INPUTS!$B$32+0>INPUTS!$B$8-INPUTS!$B$6,"",INPUTS!$B$22*(1+INPUTS!$B$23)^(A5-INPUTS!$B$12)) -> 66189.893 | D5: =IF(INPUTS!$B$32+0>INPUTS!$B$8-INPUTS!$B$6,"",IF(B5>=INPUTS!$B$7,INPUTS!$B$25*(1+INPUTS!$B$23)^(A5-INPUTS!$B$12),0)) -> 0 | E5: =IF(INPUTS!$B$32+0>INPUTS!$B$8-INPUTS!$B$6,"",INPUTS!$B$24) -> 0 | F5: =IF(INPUTS!$B$32+0>INPUTS!$B$8-INPUTS!$B$6,"",MAX(0,C5-D5-E5)) -> 66189.893 | G5: =MAX(0,(BRIDGE!L20+BRIDGE!N20-F5))*(1+INPUTS!$B$28) -> 1097231.3 | H5: =MAX(0,BRIDGE!M20*(1+INPUTS!$B$28)) -> 218871.34
A6: =IF(INPUTS!$B$32+1>INPUTS!$B$8-INPUTS!$B$6,"",INPUTS!$B$12+(INPUTS!$B$6-INPUTS!$B$5)+INPUTS!$B$32+1) -> 2034.5 | B6: =IF(INPUTS!$B$32+1>INPUTS!$B$8-INPUTS!$B$6,"",59.5+1) -> 60.5 | C6: =IF(INPUTS!$B$32+1>INPUTS!$B$8-INPUTS!$B$6,"",INPUTS!$B$22*(1+INPUTS!$B$23)^(A6-INPUTS!$B$12)) -> 67844.64 | D6: =IF(INPUTS!$B$32+1>INPUTS!$B$8-INPUTS!$B$6,"",IF(B6>=INPUTS!$B$7,INPUTS!$B$25*(1+INPUTS!$B$23)^(A6-INPUTS!$B$12),0)) -> 0 | E6: =IF(INPUTS!$B$32+1>INPUTS!$B$8-INPUTS!$B$6,"",INPUTS!$B$24) -> 0 | F6: =IF(A6="","",IF(G5+H5=0,0,MAX(0,C6-D6-E6))) -> 67844.64 | G6: =IF(A6="","",MAX(0,G5-F6)*(1+INPUTS!$B$28)) -> 1096296.8 | H6: =IF(A6="","",MAX(0,H5-MAX(0,F6-G5))*(1+INPUTS!$B$28)) -> 233097.98
A7: =IF(INPUTS!$B$32+2>INPUTS!$B$8-INPUTS!$B$6,"",INPUTS!$B$12+(INPUTS!$B$6-INPUTS!$B$5)+INPUTS!$B$32+2) -> 2035.5 | B7: =IF(INPUTS!$B$32+2>INPUTS!$B$8-INPUTS!$B$6,"",59.5+2) -> 61.5 | C7: =IF(INPUTS!$B$32+2>INPUTS!$B$8-INPUTS!$B$6,"",INPUTS!$B$22*(1+INPUTS!$B$23)^(A7-INPUTS!$B$12)) -> 69540.756 | D7: =IF(INPUTS!$B$32+2>INPUTS!$B$8-INPUTS!$B$6,"",IF(B7>=INPUTS!$B$7,INPUTS!$B$25*(1+INPUTS!$B$23)^(A7-INPUTS!$B$12),0)) -> 0 | E7: =IF(INPUTS!$B$32+2>INPUTS!$B$8-INPUTS!$B$6,"",INPUTS!$B$24) -> 0 | F7: =IF(A7="","",IF(G6+H6=0,0,MAX(0,C7-D7-E7))) -> 69540.756 | G7: =IF(A7="","",MAX(0,G6-F7)*(1+INPUTS!$B$28)) -> 1093495.1 | H7: =IF(A7="","",MAX(0,H6-MAX(0,F7-G6))*(1+INPUTS!$B$28)) -> 248249.35
A8: =IF(INPUTS!$B$32+3>INPUTS!$B$8-INPUTS!$B$6,"",INPUTS!$B$12+(INPUTS!$B$6-INPUTS!$B$5)+INPUTS!$B$32+3) -> 2036.5 | B8: =IF(INPUTS!$B$32+3>INPUTS!$B$8-INPUTS!$B$6,"",59.5+3) -> 62.5 | C8: =IF(INPUTS!$B$32+3>INPUTS!$B$8-INPUTS!$B$6,"",INPUTS!$B$22*(1+INPUTS!$B$23)^(A8-INPUTS!$B$12)) -> 71279.275 | D8: =IF(INPUTS!$B$32+3>INPUTS!$B$8-INPUTS!$B$6,"",IF(B8>=INPUTS!$B$7,INPUTS!$B$25*(1+INPUTS!$B$23)^(A8-INPUTS!$B$12),0)) -> 0 | E8: =IF(INPUTS!$B$32+3>INPUTS!$B$8-INPUTS!$B$6,"",INPUTS!$B$24) -> 0 | F8: =IF(A8="","",IF(G7+H7=0,0,MAX(0,C8-D8-E8))) -> 71279.275 | G8: =IF(A8="","",MAX(0,G7-F8)*(1+INPUTS!$B$28)) -> 1088659.9 | H8: =IF(A8="","",MAX(0,H7-MAX(0,F8-G7))*(1+INPUTS!$B$28)) -> 264385.56
A9: =IF(INPUTS!$B$32+4>INPUTS!$B$8-INPUTS!$B$6,"",INPUTS!$B$12+(INPUTS!$B$6-INPUTS!$B$5)+INPUTS!$B$32+4) -> 2037.5 | B9: =IF(INPUTS!$B$32+4>INPUTS!$B$8-INPUTS!$B$6,"",59.5+4) -> 63.5 | C9: =IF(INPUTS!$B$32+4>INPUTS!$B$8-INPUTS!$B$6,"",INPUTS!$B$22*(1+INPUTS!$B$23)^(A9-INPUTS!$B$12)) -> 73061.257 | D9: =IF(INPUTS!$B$32+4>INPUTS!$B$8-INPUTS!$B$6,"",IF(B9>=INPUTS!$B$7,INPUTS!$B$25*(1+INPUTS!$B$23)^(A9-INPUTS!$B$12),0)) -> 0 | E9: =IF(INPUTS!$B$32+4>INPUTS!$B$8-INPUTS!$B$6,"",INPUTS!$B$24) -> 0 | F9: =IF(A9="","",IF(G8+H8=0,0,MAX(0,C9-D9-E9))) -> 73061.257 | G9: =IF(A9="","",MAX(0,G8-F9)*(1+INPUTS!$B$28)) -> 1081612.6 | H9: =IF(A9="","",MAX(0,H8-MAX(0,F9-G8))*(1+INPUTS!$B$28)) -> 281570.62
A10: =IF(INPUTS!$B$32+5>INPUTS!$B$8-INPUTS!$B$6,"",INPUTS!$B$12+(INPUTS!$B$6-INPUTS!$B$5)+INPUTS!$B$32+5) -> 2038.5 | B10: =IF(INPUTS!$B$32+5>INPUTS!$B$8-INPUTS!$B$6,"",59.5+5) -> 64.5 | C10: =IF(INPUTS!$B$32+5>INPUTS!$B$8-INPUTS!$B$6,"",INPUTS!$B$22*(1+INPUTS!$B$23)^(A10-INPUTS!$B$12)) -> 74887.789 | D10: =IF(INPUTS!$B$32+5>INPUTS!$B$8-INPUTS!$B$6,"",IF(B10>=INPUTS!$B$7,INPUTS!$B$25*(1+INPUTS!$B$23)^(A10-INPUTS!$B$12),0)) -> 0 | E10: =IF(INPUTS!$B$32+5>INPUTS!$B$8-INPUTS!$B$6,"",INPUTS!$B$24) -> 0 | F10: =IF(A10="","",IF(G9+H9=0,0,MAX(0,C10-D10-E10))) -> 74887.789 | G10: =IF(A10="","",MAX(0,G9-F10)*(1+INPUTS!$B$28)) -> 1072161.9 | H10: =IF(A10="","",MAX(0,H9-MAX(0,F10-G9))*(1+INPUTS!$B$28)) -> 299872.71
A11: =IF(INPUTS!$B$32+6>INPUTS!$B$8-INPUTS!$B$6,"",INPUTS!$B$12+(INPUTS!$B$6-INPUTS!$B$5)+INPUTS!$B$32+6) -> 2039.5 | B11: =IF(INPUTS!$B$32+6>INPUTS!$B$8-INPUTS!$B$6,"",59.5+6) -> 65.5 | C11: =IF(INPUTS!$B$32+6>INPUTS!$B$8-INPUTS!$B$6,"",INPUTS!$B$22*(1+INPUTS!$B$23)^(A11-INPUTS!$B$12)) -> 76759.983 | D11: =IF(INPUTS!$B$32+6>INPUTS!$B$8-INPUTS!$B$6,"",IF(B11>=INPUTS!$B$7,INPUTS!$B$25*(1+INPUTS!$B$23)^(A11-INPUTS!$B$12),0)) -> 0 | E11: =IF(INPUTS!$B$32+6>INPUTS!$B$8-INPUTS!$B$6,"",INPUTS!$B$24) -> 0 | F11: =IF(A11="","",IF(G10+H10=0,0,MAX(0,C11-D11-E11))) -> 76759.983 | G11: =IF(A11="","",MAX(0,G10-F11)*(1+INPUTS!$B$28)) -> 1060103 | H11: =IF(A11="","",MAX(0,H10-MAX(0,F11-G10))*(1+INPUTS!$B$28)) -> 319364.44
A12: =IF(INPUTS!$B$32+7>INPUTS!$B$8-INPUTS!$B$6,"",INPUTS!$B$12+(INPUTS!$B$6-INPUTS!$B$5)+INPUTS!$B$32+7) -> 2040.5 | B12: =IF(INPUTS!$B$32+7>INPUTS!$B$8-INPUTS!$B$6,"",59.5+7) -> 66.5 | C12: =IF(INPUTS!$B$32+7>INPUTS!$B$8-INPUTS!$B$6,"",INPUTS!$B$22*(1+INPUTS!$B$23)^(A12-INPUTS!$B$12)) -> 78678.983 | D12: =IF(INPUTS!$B$32+7>INPUTS!$B$8-INPUTS!$B$6,"",IF(B12>=INPUTS!$B$7,INPUTS!$B$25*(1+INPUTS!$B$23)^(A12-INPUTS!$B$12),0)) -> 0 | E12: =IF(INPUTS!$B$32+7>INPUTS!$B$8-INPUTS!$B$6,"",INPUTS!$B$24) -> 0 | F12: =IF(A12="","",IF(G11+H11=0,0,MAX(0,C12-D12-E12))) -> 78678.983 | G12: =IF(A12="","",MAX(0,G11-F12)*(1+INPUTS!$B$28)) -> 1045216.6 | H12: =IF(A12="","",MAX(0,H11-MAX(0,F12-G11))*(1+INPUTS!$B$28)) -> 340123.12
A13: =IF(INPUTS!$B$32+8>INPUTS!$B$8-INPUTS!$B$6,"",INPUTS!$B$12+(INPUTS!$B$6-INPUTS!$B$5)+INPUTS!$B$32+8) -> 2041.5 | B13: =IF(INPUTS!$B$32+8>INPUTS!$B$8-INPUTS!$B$6,"",59.5+8) -> 67.5 | C13: =IF(INPUTS!$B$32+8>INPUTS!$B$8-INPUTS!$B$6,"",INPUTS!$B$22*(1+INPUTS!$B$23)^(A13-INPUTS!$B$12)) -> 80645.958 | D13: =IF(INPUTS!$B$32+8>INPUTS!$B$8-INPUTS!$B$6,"",IF(B13>=INPUTS!$B$7,INPUTS!$B$25*(1+INPUTS!$B$23)^(A13-INPUTS!$B$12),0)) -> 35190.963 | E13: =IF(INPUTS!$B$32+8>INPUTS!$B$8-INPUTS!$B$6,"",INPUTS!$B$24) -> 0 | F13: =IF(A13="","",IF(G12+H12=0,0,MAX(0,C13-D13-E13))) -> 45454.994 | G13: =IF(A13="","",MAX(0,G12-F13)*(1+INPUTS!$B$28)) -> 1064746.1 | H13: =IF(A13="","",MAX(0,H12-MAX(0,F13-G12))*(1+INPUTS!$B$28)) -> 362231.13
A14: =IF(INPUTS!$B$32+9>INPUTS!$B$8-INPUTS!$B$6,"",INPUTS!$B$12+(INPUTS!$B$6-INPUTS!$B$5)+INPUTS!$B$32+9) -> 2042.5 | B14: =IF(INPUTS!$B$32+9>INPUTS!$B$8-INPUTS!$B$6,"",59.5+9) -> 68.5 | C14: =IF(INPUTS!$B$32+9>INPUTS!$B$8-INPUTS!$B$6,"",INPUTS!$B$22*(1+INPUTS!$B$23)^(A14-INPUTS!$B$12)) -> 82662.107 | D14: =IF(INPUTS!$B$32+9>INPUTS!$B$8-INPUTS!$B$6,"",IF(B14>=INPUTS!$B$7,INPUTS!$B$25*(1+INPUTS!$B$23)^(A14-INPUTS!$B$12),0)) -> 36070.737 | E14: =IF(INPUTS!$B$32+9>INPUTS!$B$8-INPUTS!$B$6,"",INPUTS!$B$24) -> 0 | F14: =IF(A14="","",IF(G13+H13=0,0,MAX(0,C14-D14-E14))) -> 46591.369 | G14: =IF(A14="","",MAX(0,G13-F14)*(1+INPUTS!$B$28)) -> 1084334.8 | H14: =IF(A14="","",MAX(0,H13-MAX(0,F14-G13))*(1+INPUTS!$B$28)) -> 385776.15
A15: =IF(INPUTS!$B$32+10>INPUTS!$B$8-INPUTS!$B$6,"",INPUTS!$B$12+(INPUTS!$B$6-INPUTS!$B$5)+INPUTS!$B$32+10) -> 2043.5 | B15: =IF(INPUTS!$B$32+10>INPUTS!$B$8-INPUTS!$B$6,"",59.5+10) -> 69.5 | C15: =IF(INPUTS!$B$32+10>INPUTS!$B$8-INPUTS!$B$6,"",INPUTS!$B$22*(1+INPUTS!$B$23)^(A15-INPUTS!$B$12)) -> 84728.659 | D15: =IF(INPUTS!$B$32+10>INPUTS!$B$8-INPUTS!$B$6,"",IF(B15>=INPUTS!$B$7,INPUTS!$B$25*(1+INPUTS!$B$23)^(A15-INPUTS!$B$12),0)) -> 36972.506 | E15: =IF(INPUTS!$B$32+10>INPUTS!$B$8-INPUTS!$B$6,"",INPUTS!$B$24) -> 0 | F15: =IF(A15="","",IF(G14+H14=0,0,MAX(0,C15-D15-E15))) -> 47756.153 | G15: =IF(A15="","",MAX(0,G14-F15)*(1+INPUTS!$B$28)) -> 1103956.3 | H15: =IF(A15="","",MAX(0,H14-MAX(0,F15-G14))*(1+INPUTS!$B$28)) -> 410851.6
A16: =IF(INPUTS!$B$32+11>INPUTS!$B$8-INPUTS!$B$6,"",INPUTS!$B$12+(INPUTS!$B$6-INPUTS!$B$5)+INPUTS!$B$32+11) -> 2044.5 | B16: =IF(INPUTS!$B$32+11>INPUTS!$B$8-INPUTS!$B$6,"",59.5+11) -> 70.5 | C16: =IF(INPUTS!$B$32+11>INPUTS!$B$8-INPUTS!$B$6,"",INPUTS!$B$22*(1+INPUTS!$B$23)^(A16-INPUTS!$B$12)) -> 86846.876 | D16: =IF(INPUTS!$B$32+11>INPUTS!$B$8-INPUTS!$B$6,"",IF(B16>=INPUTS!$B$7,INPUTS!$B$25*(1+INPUTS!$B$23)^(A16-INPUTS!$B$12),0)) -> 37896.818 | E16: =IF(INPUTS!$B$32+11>INPUTS!$B$8-INPUTS!$B$6,"",INPUTS!$B$24) -> 0 | F16: =IF(A16="","",IF(G15+H15=0,0,MAX(0,C16-D16-E16))) -> 48950.057 | G16: =IF(A16="","",MAX(0,G15-F16)*(1+INPUTS!$B$28)) -> 1123581.6 | H16: =IF(A16="","",MAX(0,H15-MAX(0,F16-G15))*(1+INPUTS!$B$28)) -> 437556.95
A17: =IF(INPUTS!$B$32+12>INPUTS!$B$8-INPUTS!$B$6,"",INPUTS!$B$12+(INPUTS!$B$6-INPUTS!$B$5)+INPUTS!$B$32+12) -> 2045.5 | B17: =IF(INPUTS!$B$32+12>INPUTS!$B$8-INPUTS!$B$6,"",59.5+12) -> 71.5 | C17: =IF(INPUTS!$B$32+12>INPUTS!$B$8-INPUTS!$B$6,"",INPUTS!$B$22*(1+INPUTS!$B$23)^(A17-INPUTS!$B$12)) -> 89018.048 | D17: =IF(INPUTS!$B$32+12>INPUTS!$B$8-INPUTS!$B$6,"",IF(B17>=INPUTS!$B$7,INPUTS!$B$25*(1+INPUTS!$B$23)^(A17-INPUTS!$B$12),0)) -> 38844.239 | E17: =IF(INPUTS!$B$32+12>INPUTS!$B$8-INPUTS!$B$6,"",INPUTS!$B$24) -> 0 | F17: =IF(A17="","",IF(G16+H16=0,0,MAX(0,C17-D17-E17))) -> 50173.809 | G17: =IF(A17="","",MAX(0,G16-F17)*(1+INPUTS!$B$28)) -> 1143179.3 | H17: =IF(A17="","",MAX(0,H16-MAX(0,F17-G16))*(1+INPUTS!$B$28)) -> 465998.16
A18: =IF(INPUTS!$B$32+13>INPUTS!$B$8-INPUTS!$B$6,"",INPUTS!$B$12+(INPUTS!$B$6-INPUTS!$B$5)+INPUTS!$B$32+13) -> 2046.5 | B18: =IF(INPUTS!$B$32+13>INPUTS!$B$8-INPUTS!$B$6,"",59.5+13) -> 72.5 | C18: =IF(INPUTS!$B$32+13>INPUTS!$B$8-INPUTS!$B$6,"",INPUTS!$B$22*(1+INPUTS!$B$23)^(A18-INPUTS!$B$12)) -> 91243.499 | D18: =IF(INPUTS!$B$32+13>INPUTS!$B$8-INPUTS!$B$6,"",IF(B18>=INPUTS!$B$7,INPUTS!$B$25*(1+INPUTS!$B$23)^(A18-INPUTS!$B$12),0)) -> 39815.345 | E18: =IF(INPUTS!$B$32+13>INPUTS!$B$8-INPUTS!$B$6,"",INPUTS!$B$24) -> 0 | F18: =IF(A18="","",IF(G17+H17=0,0,MAX(0,C18-D18-E18))) -> 51428.154 | G18: =IF(A18="","",MAX(0,G17-F18)*(1+INPUTS!$B$28)) -> 1162715 | H18: =IF(A18="","",MAX(0,H17-MAX(0,F18-G17))*(1+INPUTS!$B$28)) -> 496288.04
A19: =IF(INPUTS!$B$32+14>INPUTS!$B$8-INPUTS!$B$6,"",INPUTS!$B$12+(INPUTS!$B$6-INPUTS!$B$5)+INPUTS!$B$32+14) -> 2047.5 | B19: =IF(INPUTS!$B$32+14>INPUTS!$B$8-INPUTS!$B$6,"",59.5+14) -> 73.5 | C19: =IF(INPUTS!$B$32+14>INPUTS!$B$8-INPUTS!$B$6,"",INPUTS!$B$22*(1+INPUTS!$B$23)^(A19-INPUTS!$B$12)) -> 93524.586 | D19: =IF(INPUTS!$B$32+14>INPUTS!$B$8-INPUTS!$B$6,"",IF(B19>=INPUTS!$B$7,INPUTS!$B$25*(1+INPUTS!$B$23)^(A19-INPUTS!$B$12),0)) -> 40810.729 | E19: =IF(INPUTS!$B$32+14>INPUTS!$B$8-INPUTS!$B$6,"",INPUTS!$B$24) -> 0 | F19: =IF(A19="","",IF(G18+H18=0,0,MAX(0,C19-D19-E19))) -> 52713.858 | G19: =IF(A19="","",MAX(0,G18-F19)*(1+INPUTS!$B$28)) -> 1182151.2 | H19: =IF(A19="","",MAX(0,H18-MAX(0,F19-G18))*(1+INPUTS!$B$28)) -> 528546.76
A20: =IF(INPUTS!$B$32+15>INPUTS!$B$8-INPUTS!$B$6,"",INPUTS!$B$12+(INPUTS!$B$6-INPUTS!$B$5)+INPUTS!$B$32+15) -> 2048.5 | B20: =IF(INPUTS!$B$32+15>INPUTS!$B$8-INPUTS!$B$6,"",59.5+15) -> 74.5 | C20: =IF(INPUTS!$B$32+15>INPUTS!$B$8-INPUTS!$B$6,"",INPUTS!$B$22*(1+INPUTS!$B$23)^(A20-INPUTS!$B$12)) -> 95862.701 | D20: =IF(INPUTS!$B$32+15>INPUTS!$B$8-INPUTS!$B$6,"",IF(B20>=INPUTS!$B$7,INPUTS!$B$25*(1+INPUTS!$B$23)^(A20-INPUTS!$B$12),0)) -> 41830.997 | E20: =IF(INPUTS!$B$32+15>INPUTS!$B$8-INPUTS!$B$6,"",INPUTS!$B$24) -> 0 | F20: =IF(A20="","",IF(G19+H19=0,0,MAX(0,C20-D20-E20))) -> 54031.704 | G20: =IF(A20="","",MAX(0,G19-F20)*(1+INPUTS!$B$28)) -> 1201447.2 | H20: =IF(A20="","",MAX(0,H19-MAX(0,F20-G19))*(1+INPUTS!$B$28)) -> 562902.3
A21: =IF(INPUTS!$B$32+16>INPUTS!$B$8-INPUTS!$B$6,"",INPUTS!$B$12+(INPUTS!$B$6-INPUTS!$B$5)+INPUTS!$B$32+16) -> 2049.5 | B21: =IF(INPUTS!$B$32+16>INPUTS!$B$8-INPUTS!$B$6,"",59.5+16) -> 75.5 | C21: =IF(INPUTS!$B$32+16>INPUTS!$B$8-INPUTS!$B$6,"",INPUTS!$B$22*(1+INPUTS!$B$23)^(A21-INPUTS!$B$12)) -> 98259.268 | D21: =IF(INPUTS!$B$32+16>INPUTS!$B$8-INPUTS!$B$6,"",IF(B21>=INPUTS!$B$7,INPUTS!$B$25*(1+INPUTS!$B$23)^(A21-INPUTS!$B$12),0)) -> 42876.772 | E21: =IF(INPUTS!$B$32+16>INPUTS!$B$8-INPUTS!$B$6,"",INPUTS!$B$24) -> 0 | F21: =IF(A21="","",IF(G20+H20=0,0,MAX(0,C21-D21-E21))) -> 55382.497 | G21: =IF(A21="","",MAX(0,G20-F21)*(1+INPUTS!$B$28)) -> 1220559 | H21: =IF(A21="","",MAX(0,H20-MAX(0,F21-G20))*(1+INPUTS!$B$28)) -> 599490.95
A22: =IF(INPUTS!$B$32+17>INPUTS!$B$8-INPUTS!$B$6,"",INPUTS!$B$12+(INPUTS!$B$6-INPUTS!$B$5)+INPUTS!$B$32+17) -> 2050.5 | B22: =IF(INPUTS!$B$32+17>INPUTS!$B$8-INPUTS!$B$6,"",59.5+17) -> 76.5 | C22: =IF(INPUTS!$B$32+17>INPUTS!$B$8-INPUTS!$B$6,"",INPUTS!$B$22*(1+INPUTS!$B$23)^(A22-INPUTS!$B$12)) -> 100715.75 | D22: =IF(INPUTS!$B$32+17>INPUTS!$B$8-INPUTS!$B$6,"",IF(B22>=INPUTS!$B$7,INPUTS!$B$25*(1+INPUTS!$B$23)^(A22-INPUTS!$B$12),0)) -> 43948.691 | E22: =IF(INPUTS!$B$32+17>INPUTS!$B$8-INPUTS!$B$6,"",INPUTS!$B$24) -> 0 | F22: =IF(A22="","",IF(G21+H21=0,0,MAX(0,C22-D22-E22))) -> 56767.059 | G22: =IF(A22="","",MAX(0,G21-F22)*(1+INPUTS!$B$28)) -> 1239438.4 | H22: =IF(A22="","",MAX(0,H21-MAX(0,F22-G21))*(1+INPUTS!$B$28)) -> 638457.86
A23: =IF(INPUTS!$B$32+18>INPUTS!$B$8-INPUTS!$B$6,"",INPUTS!$B$12+(INPUTS!$B$6-INPUTS!$B$5)+INPUTS!$B$32+18) -> 2051.5 | B23: =IF(INPUTS!$B$32+18>INPUTS!$B$8-INPUTS!$B$6,"",59.5+18) -> 77.5 | C23: =IF(INPUTS!$B$32+18>INPUTS!$B$8-INPUTS!$B$6,"",INPUTS!$B$22*(1+INPUTS!$B$23)^(A23-INPUTS!$B$12)) -> 103233.64 | D23: =IF(INPUTS!$B$32+18>INPUTS!$B$8-INPUTS!$B$6,"",IF(B23>=INPUTS!$B$7,INPUTS!$B$25*(1+INPUTS!$B$23)^(A23-INPUTS!$B$12),0)) -> 45047.408 | E23: =IF(INPUTS!$B$32+18>INPUTS!$B$8-INPUTS!$B$6,"",INPUTS!$B$24) -> 0 | F23: =IF(A23="","",IF(G22+H22=0,0,MAX(0,C23-D23-E23))) -> 58186.236 | G23: =IF(A23="","",MAX(0,G22-F23)*(1+INPUTS!$B$28)) -> 1258033.5 | H23: =IF(A23="","",MAX(0,H22-MAX(0,F23-G22))*(1+INPUTS!$B$28)) -> 679957.62
A24: =IF(INPUTS!$B$32+19>INPUTS!$B$8-INPUTS!$B$6,"",INPUTS!$B$12+(INPUTS!$B$6-INPUTS!$B$5)+INPUTS!$B$32+19) -> 2052.5 | B24: =IF(INPUTS!$B$32+19>INPUTS!$B$8-INPUTS!$B$6,"",59.5+19) -> 78.5 | C24: =IF(INPUTS!$B$32+19>INPUTS!$B$8-INPUTS!$B$6,"",INPUTS!$B$22*(1+INPUTS!$B$23)^(A24-INPUTS!$B$12)) -> 105814.48 | D24: =IF(INPUTS!$B$32+19>INPUTS!$B$8-INPUTS!$B$6,"",IF(B24>=INPUTS!$B$7,INPUTS!$B$25*(1+INPUTS!$B$23)^(A24-INPUTS!$B$12),0)) -> 46173.593 | E24: =IF(INPUTS!$B$32+19>INPUTS!$B$8-INPUTS!$B$6,"",INPUTS!$B$24) -> 0 | F24: =IF(A24="","",IF(G23+H23=0,0,MAX(0,C24-D24-E24))) -> 59640.892 | G24: =IF(A24="","",MAX(0,G23-F24)*(1+INPUTS!$B$28)) -> 1276288.2 | H24: =IF(A24="","",MAX(0,H23-MAX(0,F24-G23))*(1+INPUTS!$B$28)) -> 724154.87
A25: =IF(INPUTS!$B$32+20>INPUTS!$B$8-INPUTS!$B$6,"",INPUTS!$B$12+(INPUTS!$B$6-INPUTS!$B$5)+INPUTS!$B$32+20) -> 2053.5 | B25: =IF(INPUTS!$B$32+20>INPUTS!$B$8-INPUTS!$B$6,"",59.5+20) -> 79.5 | C25: =IF(INPUTS!$B$32+20>INPUTS!$B$8-INPUTS!$B$6,"",INPUTS!$B$22*(1+INPUTS!$B$23)^(A25-INPUTS!$B$12)) -> 108459.85 | D25: =IF(INPUTS!$B$32+20>INPUTS!$B$8-INPUTS!$B$6,"",IF(B25>=INPUTS!$B$7,INPUTS!$B$25*(1+INPUTS!$B$23)^(A25-INPUTS!$B$12),0)) -> 47327.933 | E25: =IF(INPUTS!$B$32+20>INPUTS!$B$8-INPUTS!$B$6,"",INPUTS!$B$24) -> 0 | F25: =IF(A25="","",IF(G24+H24=0,0,MAX(0,C25-D25-E25))) -> 61131.914 | G25: =IF(A25="","",MAX(0,G24-F25)*(1+INPUTS!$B$28)) -> 1294141.4 | H25: =IF(A25="","",MAX(0,H24-MAX(0,F25-G24))*(1+INPUTS!$B$28)) -> 771224.93
A26: =IF(INPUTS!$B$32+21>INPUTS!$B$8-INPUTS!$B$6,"",INPUTS!$B$12+(INPUTS!$B$6-INPUTS!$B$5)+INPUTS!$B$32+21) -> 2054.5 | B26: =IF(INPUTS!$B$32+21>INPUTS!$B$8-INPUTS!$B$6,"",59.5+21) -> 80.5 | C26: =IF(INPUTS!$B$32+21>INPUTS!$B$8-INPUTS!$B$6,"",INPUTS!$B$22*(1+INPUTS!$B$23)^(A26-INPUTS!$B$12)) -> 111171.34 | D26: =IF(INPUTS!$B$32+21>INPUTS!$B$8-INPUTS!$B$6,"",IF(B26>=INPUTS!$B$7,INPUTS!$B$25*(1+INPUTS!$B$23)^(A26-INPUTS!$B$12),0)) -> 48511.132 | E26: =IF(INPUTS!$B$32+21>INPUTS!$B$8-INPUTS!$B$6,"",INPUTS!$B$24) -> 0 | F26: =IF(A26="","",IF(G25+H25=0,0,MAX(0,C26-D26-E26))) -> 62660.212 | G26: =IF(A26="","",MAX(0,G25-F26)*(1+INPUTS!$B$28)) -> 1311527.5 | H26: =IF(A26="","",MAX(0,H25-MAX(0,F26-G25))*(1+INPUTS!$B$28)) -> 821354.55
A27: =IF(INPUTS!$B$32+22>INPUTS!$B$8-INPUTS!$B$6,"",INPUTS!$B$12+(INPUTS!$B$6-INPUTS!$B$5)+INPUTS!$B$32+22) -> 2055.5 | B27: =IF(INPUTS!$B$32+22>INPUTS!$B$8-INPUTS!$B$6,"",59.5+22) -> 81.5 | C27: =IF(INPUTS!$B$32+22>INPUTS!$B$8-INPUTS!$B$6,"",INPUTS!$B$22*(1+INPUTS!$B$23)^(A27-INPUTS!$B$12)) -> 113950.63 | D27: =IF(INPUTS!$B$32+22>INPUTS!$B$8-INPUTS!$B$6,"",IF(B27>=INPUTS!$B$7,INPUTS!$B$25*(1+INPUTS!$B$23)^(A27-INPUTS!$B$12),0)) -> 49723.91 | E27: =IF(INPUTS!$B$32+22>INPUTS!$B$8-INPUTS!$B$6,"",INPUTS!$B$24) -> 0 | F27: =IF(A27="","",IF(G26+H26=0,0,MAX(0,C27-D27-E27))) -> 64226.717 | G27: =IF(A27="","",MAX(0,G26-F27)*(1+INPUTS!$B$28)) -> 1328375.3 | H27: =IF(A27="","",MAX(0,H26-MAX(0,F27-G26))*(1+INPUTS!$B$28)) -> 874742.6
A28: =IF(INPUTS!$B$32+23>INPUTS!$B$8-INPUTS!$B$6,"",INPUTS!$B$12+(INPUTS!$B$6-INPUTS!$B$5)+INPUTS!$B$32+23) -> 2056.5 | B28: =IF(INPUTS!$B$32+23>INPUTS!$B$8-INPUTS!$B$6,"",59.5+23) -> 82.5 | C28: =IF(INPUTS!$B$32+23>INPUTS!$B$8-INPUTS!$B$6,"",INPUTS!$B$22*(1+INPUTS!$B$23)^(A28-INPUTS!$B$12)) -> 116799.39 | D28: =IF(INPUTS!$B$32+23>INPUTS!$B$8-INPUTS!$B$6,"",IF(B28>=INPUTS!$B$7,INPUTS!$B$25*(1+INPUTS!$B$23)^(A28-INPUTS!$B$12),0)) -> 50967.008 | E28: =IF(INPUTS!$B$32+23>INPUTS!$B$8-INPUTS!$B$6,"",INPUTS!$B$24) -> 0 | F28: =IF(A28="","",IF(G27+H27=0,0,MAX(0,C28-D28-E28))) -> 65832.385 | G28: =IF(A28="","",MAX(0,G27-F28)*(1+INPUTS!$B$28)) -> 1344608.2 | H28: =IF(A28="","",MAX(0,H27-MAX(0,F28-G27))*(1+INPUTS!$B$28)) -> 931600.87
A29: =IF(INPUTS!$B$32+24>INPUTS!$B$8-INPUTS!$B$6,"",INPUTS!$B$12+(INPUTS!$B$6-INPUTS!$B$5)+INPUTS!$B$32+24) -> 2057.5 | B29: =IF(INPUTS!$B$32+24>INPUTS!$B$8-INPUTS!$B$6,"",59.5+24) -> 83.5 | C29: =IF(INPUTS!$B$32+24>INPUTS!$B$8-INPUTS!$B$6,"",INPUTS!$B$22*(1+INPUTS!$B$23)^(A29-INPUTS!$B$12)) -> 119719.38 | D29: =IF(INPUTS!$B$32+24>INPUTS!$B$8-INPUTS!$B$6,"",IF(B29>=INPUTS!$B$7,INPUTS!$B$25*(1+INPUTS!$B$23)^(A29-INPUTS!$B$12),0)) -> 52241.183 | E29: =IF(INPUTS!$B$32+24>INPUTS!$B$8-INPUTS!$B$6,"",INPUTS!$B$24) -> 0 | F29: =IF(A29="","",IF(G28+H28=0,0,MAX(0,C29-D29-E29))) -> 67478.194 | G29: =IF(A29="","",MAX(0,G28-F29)*(1+INPUTS!$B$28)) -> 1360143.5 | H29: =IF(A29="","",MAX(0,H28-MAX(0,F29-G28))*(1+INPUTS!$B$28)) -> 992154.92
A30: =IF(INPUTS!$B$32+25>INPUTS!$B$8-INPUTS!$B$6,"",INPUTS!$B$12+(INPUTS!$B$6-INPUTS!$B$5)+INPUTS!$B$32+25) -> 2058.5 | B30: =IF(INPUTS!$B$32+25>INPUTS!$B$8-INPUTS!$B$6,"",59.5+25) -> 84.5 | C30: =IF(INPUTS!$B$32+25>INPUTS!$B$8-INPUTS!$B$6,"",INPUTS!$B$22*(1+INPUTS!$B$23)^(A30-INPUTS!$B$12)) -> 122712.36 | D30: =IF(INPUTS!$B$32+25>INPUTS!$B$8-INPUTS!$B$6,"",IF(B30>=INPUTS!$B$7,INPUTS!$B$25*(1+INPUTS!$B$23)^(A30-INPUTS!$B$12),0)) -> 53547.212 | E30: =IF(INPUTS!$B$32+25>INPUTS!$B$8-INPUTS!$B$6,"",INPUTS!$B$24) -> 0 | F30: =IF(A30="","",IF(G29+H29=0,0,MAX(0,C30-D30-E30))) -> 69165.149 | G30: =IF(A30="","",MAX(0,G29-F30)*(1+INPUTS!$B$28)) -> 1374891.9 | H30: =IF(A30="","",MAX(0,H29-MAX(0,F30-G29))*(1+INPUTS!$B$28)) -> 1056645
A31: =IF(INPUTS!$B$32+26>INPUTS!$B$8-INPUTS!$B$6,"",INPUTS!$B$12+(INPUTS!$B$6-INPUTS!$B$5)+INPUTS!$B$32+26) -> 2059.5 | B31: =IF(INPUTS!$B$32+26>INPUTS!$B$8-INPUTS!$B$6,"",59.5+26) -> 85.5 | C31: =IF(INPUTS!$B$32+26>INPUTS!$B$8-INPUTS!$B$6,"",INPUTS!$B$22*(1+INPUTS!$B$23)^(A31-INPUTS!$B$12)) -> 125780.17 | D31: =IF(INPUTS!$B$32+26>INPUTS!$B$8-INPUTS!$B$6,"",IF(B31>=INPUTS!$B$7,INPUTS!$B$25*(1+INPUTS!$B$23)^(A31-INPUTS!$B$12),0)) -> 54885.893 | E31: =IF(INPUTS!$B$32+26>INPUTS!$B$8-INPUTS!$B$6,"",INPUTS!$B$24) -> 0 | F31: =IF(A31="","",IF(G30+H30=0,0,MAX(0,C31-D31-E31))) -> 70894.278 | G31: =IF(A31="","",MAX(0,G30-F31)*(1+INPUTS!$B$28)) -> 1388757.5 | H31: =IF(A31="","",MAX(0,H30-MAX(0,F31-G30))*(1+INPUTS!$B$28)) -> 1125326.9
A32: =IF(INPUTS!$B$32+27>INPUTS!$B$8-INPUTS!$B$6,"",INPUTS!$B$12+(INPUTS!$B$6-INPUTS!$B$5)+INPUTS!$B$32+27) -> 2060.5 | B32: =IF(INPUTS!$B$32+27>INPUTS!$B$8-INPUTS!$B$6,"",59.5+27) -> 86.5 | C32: =IF(INPUTS!$B$32+27>INPUTS!$B$8-INPUTS!$B$6,"",INPUTS!$B$22*(1+INPUTS!$B$23)^(A32-INPUTS!$B$12)) -> 128924.68 | D32: =IF(INPUTS!$B$32+27>INPUTS!$B$8-INPUTS!$B$6,"",IF(B32>=INPUTS!$B$7,INPUTS!$B$25*(1+INPUTS!$B$23)^(A32-INPUTS!$B$12),0)) -> 56258.04 | E32: =IF(INPUTS!$B$32+27>INPUTS!$B$8-INPUTS!$B$6,"",INPUTS!$B$24) -> 0 | F32: =IF(A32="","",IF(G31+H31=0,0,MAX(0,C32-D32-E32))) -> 72666.635 | G32: =IF(A32="","",MAX(0,G31-F32)*(1+INPUTS!$B$28)) -> 1401636.7 | H32: =IF(A32="","",MAX(0,H31-MAX(0,F32-G31))*(1+INPUTS!$B$28)) -> 1198473.2
A33: =IF(INPUTS!$B$32+28>INPUTS!$B$8-INPUTS!$B$6,"",INPUTS!$B$12+(INPUTS!$B$6-INPUTS!$B$5)+INPUTS!$B$32+28) -> 2061.5 | B33: =IF(INPUTS!$B$32+28>INPUTS!$B$8-INPUTS!$B$6,"",59.5+28) -> 87.5 | C33: =IF(INPUTS!$B$32+28>INPUTS!$B$8-INPUTS!$B$6,"",INPUTS!$B$22*(1+INPUTS!$B$23)^(A33-INPUTS!$B$12)) -> 132147.79 | D33: =IF(INPUTS!$B$32+28>INPUTS!$B$8-INPUTS!$B$6,"",IF(B33>=INPUTS!$B$7,INPUTS!$B$25*(1+INPUTS!$B$23)^(A33-INPUTS!$B$12),0)) -> 57664.491 | E33: =IF(INPUTS!$B$32+28>INPUTS!$B$8-INPUTS!$B$6,"",INPUTS!$B$24) -> 0 | F33: =IF(A33="","",IF(G32+H32=0,0,MAX(0,C33-D33-E33))) -> 74483.301 | G33: =IF(A33="","",MAX(0,G32-F33)*(1+INPUTS!$B$28)) -> 1413418.4 | H33: =IF(A33="","",MAX(0,H32-MAX(0,F33-G32))*(1+INPUTS!$B$28)) -> 1276373.9
A34: =IF(INPUTS!$B$32+29>INPUTS!$B$8-INPUTS!$B$6,"",INPUTS!$B$12+(INPUTS!$B$6-INPUTS!$B$5)+INPUTS!$B$32+29) -> 2062.5 | B34: =IF(INPUTS!$B$32+29>INPUTS!$B$8-INPUTS!$B$6,"",59.5+29) -> 88.5 | C34: =IF(INPUTS!$B$32+29>INPUTS!$B$8-INPUTS!$B$6,"",INPUTS!$B$22*(1+INPUTS!$B$23)^(A34-INPUTS!$B$12)) -> 135451.49 | D34: =IF(INPUTS!$B$32+29>INPUTS!$B$8-INPUTS!$B$6,"",IF(B34>=INPUTS!$B$7,INPUTS!$B$25*(1+INPUTS!$B$23)^(A34-INPUTS!$B$12),0)) -> 59106.103 | E34: =IF(INPUTS!$B$32+29>INPUTS!$B$8-INPUTS!$B$6,"",INPUTS!$B$24) -> 0 | F34: =IF(A34="","",IF(G33+H33=0,0,MAX(0,C34-D34-E34))) -> 76345.383 | G34: =IF(A34="","",MAX(0,G33-F34)*(1+INPUTS!$B$28)) -> 1423982.8 | H34: =IF(A34="","",MAX(0,H33-MAX(0,F34-G33))*(1+INPUTS!$B$28)) -> 1359338.2
A35: =IF(INPUTS!$B$32+30>INPUTS!$B$8-INPUTS!$B$6,"",INPUTS!$B$12+(INPUTS!$B$6-INPUTS!$B$5)+INPUTS!$B$32+30) -> 2063.5 | B35: =IF(INPUTS!$B$32+30>INPUTS!$B$8-INPUTS!$B$6,"",59.5+30) -> 89.5 | C35: =IF(INPUTS!$B$32+30>INPUTS!$B$8-INPUTS!$B$6,"",INPUTS!$B$22*(1+INPUTS!$B$23)^(A35-INPUTS!$B$12)) -> 138837.77 | D35: =IF(INPUTS!$B$32+30>INPUTS!$B$8-INPUTS!$B$6,"",IF(B35>=INPUTS!$B$7,INPUTS!$B$25*(1+INPUTS!$B$23)^(A35-INPUTS!$B$12),0)) -> 60583.756 | E35: =IF(INPUTS!$B$32+30>INPUTS!$B$8-INPUTS!$B$6,"",INPUTS!$B$24) -> 0 | F35: =IF(A35="","",IF(G34+H34=0,0,MAX(0,C35-D35-E35))) -> 78254.018 | G35: =IF(A35="","",MAX(0,G34-F35)*(1+INPUTS!$B$28)) -> 1433201.1 | H35: =IF(A35="","",MAX(0,H34-MAX(0,F35-G34))*(1+INPUTS!$B$28)) -> 1447695.2
A36: =IF(INPUTS!$B$32+31>INPUTS!$B$8-INPUTS!$B$6,"",INPUTS!$B$12+(INPUTS!$B$6-INPUTS!$B$5)+INPUTS!$B$32+31) | B36: =IF(INPUTS!$B$32+31>INPUTS!$B$8-INPUTS!$B$6,"",59.5+31) | C36: =IF(INPUTS!$B$32+31>INPUTS!$B$8-INPUTS!$B$6,"",INPUTS!$B$22*(1+INPUTS!$B$23)^(A36-INPUTS!$B$12)) | D36: =IF(INPUTS!$B$32+31>INPUTS!$B$8-INPUTS!$B$6,"",IF(B36>=INPUTS!$B$7,INPUTS!$B$25*(1+INPUTS!$B$23)^(A36-INPUTS!$B$12),0)) | E36: =IF(INPUTS!$B$32+31>INPUTS!$B$8-INPUTS!$B$6,"",INPUTS!$B$24) | F36: =IF(A36="","",IF(G35+H35=0,0,MAX(0,C36-D36-E36))) | G36: =IF(A36="","",MAX(0,G35-F36)*(1+INPUTS!$B$28)) | H36: =IF(A36="","",MAX(0,H35-MAX(0,F36-G35))*(1+INPUTS!$B$28))
A37: =IF(INPUTS!$B$32+32>INPUTS!$B$8-INPUTS!$B$6,"",INPUTS!$B$12+(INPUTS!$B$6-INPUTS!$B$5)+INPUTS!$B$32+32) | B37: =IF(INPUTS!$B$32+32>INPUTS!$B$8-INPUTS!$B$6,"",59.5+32) | C37: =IF(INPUTS!$B$32+32>INPUTS!$B$8-INPUTS!$B$6,"",INPUTS!$B$22*(1+INPUTS!$B$23)^(A37-INPUTS!$B$12)) | D37: =IF(INPUTS!$B$32+32>INPUTS!$B$8-INPUTS!$B$6,"",IF(B37>=INPUTS!$B$7,INPUTS!$B$25*(1+INPUTS!$B$23)^(A37-INPUTS!$B$12),0)) | E37: =IF(INPUTS!$B$32+32>INPUTS!$B$8-INPUTS!$B$6,"",INPUTS!$B$24) | F37: =IF(A37="","",IF(G36+H36=0,0,MAX(0,C37-D37-E37))) | G37: =IF(A37="","",MAX(0,G36-F37)*(1+INPUTS!$B$28)) | H37: =IF(A37="","",MAX(0,H36-MAX(0,F37-G36))*(1+INPUTS!$B$28))
A38: =IF(INPUTS!$B$32+33>INPUTS!$B$8-INPUTS!$B$6,"",INPUTS!$B$12+(INPUTS!$B$6-INPUTS!$B$5)+INPUTS!$B$32+33) | B38: =IF(INPUTS!$B$32+33>INPUTS!$B$8-INPUTS!$B$6,"",59.5+33) | C38: =IF(INPUTS!$B$32+33>INPUTS!$B$8-INPUTS!$B$6,"",INPUTS!$B$22*(1+INPUTS!$B$23)^(A38-INPUTS!$B$12)) | D38: =IF(INPUTS!$B$32+33>INPUTS!$B$8-INPUTS!$B$6,"",IF(B38>=INPUTS!$B$7,INPUTS!$B$25*(1+INPUTS!$B$23)^(A38-INPUTS!$B$12),0)) | E38: =IF(INPUTS!$B$32+33>INPUTS!$B$8-INPUTS!$B$6,"",INPUTS!$B$24) | F38: =IF(A38="","",IF(G37+H37=0,0,MAX(0,C38-D38-E38))) | G38: =IF(A38="","",MAX(0,G37-F38)*(1+INPUTS!$B$28)) | H38: =IF(A38="","",MAX(0,H37-MAX(0,F38-G37))*(1+INPUTS!$B$28))
A39: =IF(INPUTS!$B$32+34>INPUTS!$B$8-INPUTS!$B$6,"",INPUTS!$B$12+(INPUTS!$B$6-INPUTS!$B$5)+INPUTS!$B$32+34) | B39: =IF(INPUTS!$B$32+34>INPUTS!$B$8-INPUTS!$B$6,"",59.5+34) | C39: =IF(INPUTS!$B$32+34>INPUTS!$B$8-INPUTS!$B$6,"",INPUTS!$B$22*(1+INPUTS!$B$23)^(A39-INPUTS!$B$12)) | D39: =IF(INPUTS!$B$32+34>INPUTS!$B$8-INPUTS!$B$6,"",IF(B39>=INPUTS!$B$7,INPUTS!$B$25*(1+INPUTS!$B$23)^(A39-INPUTS!$B$12),0)) | E39: =IF(INPUTS!$B$32+34>INPUTS!$B$8-INPUTS!$B$6,"",INPUTS!$B$24) | F39: =IF(A39="","",IF(G38+H38=0,0,MAX(0,C39-D39-E39))) | G39: =IF(A39="","",MAX(0,G38-F39)*(1+INPUTS!$B$28)) | H39: =IF(A39="","",MAX(0,H38-MAX(0,F39-G38))*(1+INPUTS!$B$28))
A40: =IF(INPUTS!$B$32+35>INPUTS!$B$8-INPUTS!$B$6,"",INPUTS!$B$12+(INPUTS!$B$6-INPUTS!$B$5)+INPUTS!$B$32+35) | B40: =IF(INPUTS!$B$32+35>INPUTS!$B$8-INPUTS!$B$6,"",59.5+35) | C40: =IF(INPUTS!$B$32+35>INPUTS!$B$8-INPUTS!$B$6,"",INPUTS!$B$22*(1+INPUTS!$B$23)^(A40-INPUTS!$B$12)) | D40: =IF(INPUTS!$B$32+35>INPUTS!$B$8-INPUTS!$B$6,"",IF(B40>=INPUTS!$B$7,INPUTS!$B$25*(1+INPUTS!$B$23)^(A40-INPUTS!$B$12),0)) | E40: =IF(INPUTS!$B$32+35>INPUTS!$B$8-INPUTS!$B$6,"",INPUTS!$B$24) | F40: =IF(A40="","",IF(G39+H39=0,0,MAX(0,C40-D40-E40))) | G40: =IF(A40="","",MAX(0,G39-F40)*(1+INPUTS!$B$28)) | H40: =IF(A40="","",MAX(0,H39-MAX(0,F40-G39))*(1+INPUTS!$B$28))
A42: BALANCE AT LIFE EXPECTANCY → | F42: =IFERROR(G42+H42,0) -> 2880896.3 | G42: =IFERROR(LOOKUP(9.99E+307,G5:G40),0) -> 1433201.1 | H42: =IFERROR(LOOKUP(9.99E+307,H5:H40),0) -> 1447695.2

Sheet MONTE CARLO
A1: MONTE CARLO SIMULATOR · 200 Randomized Return Sequences
A2: Each row = one possible retirement. Returns drawn from Normal(mean=INPUTS return, sd=INPUTS volatility). Press F9 / Ctrl+Shift+F9 to re-run.
A4: Net Withdrawal → | C4: =IFERROR(MAX(0,INPUTS!$B$22*(1+INPUTS!$B$23)^(INPUTS!$B$6-INPUTS!$B$5+0)-IF(INPUTS!$B$6+0>=INPUTS!$B$7,INPUTS!$B$25*(1+INPUTS!$B$23)^(INPUTS!$B$6-INPUTS!$B$5+0),0)-INPUTS!$B$24),0) -> 59228.984 | D4: =IFERROR(MAX(0,INPUTS!$B$22*(1+INPUTS!$B$23)^(INPUTS!$B$6-INPUTS!$B$5+1)-IF(INPUTS!$B$6+1>=INPUTS!$B$7,INPUTS!$B$25*(1+INPUTS!$B$23)^(INPUTS!$B$6-INPUTS!$B$5+1),0)-INPUTS!$B$24),0) -> 60709.709 | E4: =IFERROR(MAX(0,INPUTS!$B$22*(1+INPUTS!$B$23)^(INPUTS!$B$6-INPUTS!$B$5+2)-IF(INPUTS!$B$6+2>=INPUTS!$B$7,INPUTS!$B$25*(1+INPUTS!$B$23)^(INPUTS!$B$6-INPUTS!$B$5+2),0)-INPUTS!$B$24),0) -> 62227.452 | F4: =IFERROR(MAX(0,INPUTS!$B$22*(1+INPUTS!$B$23)^(INPUTS!$B$6-INPUTS!$B$5+3)-IF(INPUTS!$B$6+3>=INPUTS!$B$7,INPUTS!$B$25*(1+INPUTS!$B$23)^(INPUTS!$B$6-INPUTS!$B$5+3),0)-INPUTS!$B$24),0) -> 63783.138 | G4: =IFERROR(MAX(0,INPUTS!$B$22*(1+INPUTS!$B$23)^(INPUTS!$B$6-INPUTS!$B$5+4)-IF(INPUTS!$B$6+4>=INPUTS!$B$7,INPUTS!$B$25*(1+INPUTS!$B$23)^(INPUTS!$B$6-INPUTS!$B$5+4),0)-INPUTS!$B$24),0) -> 65377.716 | H4: =IFERROR(MAX(0,INPUTS!$B$22*(1+INPUTS!$B$23)^(INPUTS!$B$6-INPUTS!$B$5+5)-IF(INPUTS!$B$6+5>=INPUTS!$B$7,INPUTS!$B$25*(1+INPUTS!$B$23)^(INPUTS!$B$6-INPUTS!$B$5+5),0)-INPUTS!$B$24),0) -> 67012.159 | I4: =IFERROR(MAX(0,INPUTS!$B$22*(1+INPUTS!$B$23)^(INPUTS!$B$6-INPUTS!$B$5+6)-IF(INPUTS!$B$6+6>=INPUTS!$B$7,INPUTS!$B$25*(1+INPUTS!$B$23)^(INPUTS!$B$6-INPUTS!$B$5+6),0)-INPUTS!$B$24),0) -> 68687.463 | J4: =IFERROR(MAX(0,INPUTS!$B$22*(1+INPUTS!$B$23)^(INPUTS!$B$6-INPUTS!$B$5+7)-IF(INPUTS!$B$6+7>=INPUTS!$B$7,INPUTS!$B$25*(1+INPUTS!$B$23)^(INPUTS!$B$6-INPUTS!$B$5+7),0)-INPUTS!$B$24),0) -> 70404.65 | K4: =IFERROR(MAX(0,INPUTS!$B$22*(1+INPUTS!$B$23)^(INPUTS!$B$6-INPUTS!$B$5+8)-IF(INPUTS!$B$6+8>=INPUTS!$B$7,INPUTS!$B$25*(1+INPUTS!$B$23)^(INPUTS!$B$6-INPUTS!$B$5+8),0)-INPUTS!$B$24),0) -> 72164.766 | L4: =IFERROR(MAX(0,INPUTS!$B$22*(1+INPUTS!$B$23)^(INPUTS!$B$6-INPUTS!$B$5+9)-IF(INPUTS!$B$6+9>=INPUTS!$B$7,INPUTS!$B$25*(1+INPUTS!$B$23)^(INPUTS!$B$6-INPUTS!$B$5+9),0)-INPUTS!$B$24),0) -> 73968.885 | M4: =IFERROR(MAX(0,INPUTS!$B$22*(1+INPUTS!$B$23)^(INPUTS!$B$6-INPUTS!$B$5+10)-IF(INPUTS!$B$6+10>=INPUTS!$B$7,INPUTS!$B$25*(1+INPUTS!$B$23)^(INPUTS!$B$6-INPUTS!$B$5+10),0)-INPUTS!$B$24),0) -> 75818.107 | N4: =IFERROR(MAX(0,INPUTS!$B$22*(1+INPUTS!$B$23)^(INPUTS!$B$6-INPUTS!$B$5+11)-IF(INPUTS!$B$6+11>=INPUTS!$B$7,INPUTS!$B$25*(1+INPUTS!$B$23)^(INPUTS!$B$6-INPUTS!$B$5+11),0)-INPUTS!$B$24),0) -> 77713.56 | O4: =IFERROR(MAX(0,INPUTS!$B$22*(1+INPUTS!$B$23)^(INPUTS!$B$6-INPUTS!$B$5+12)-IF(INPUTS!$B$6+12>=INPUTS!$B$7,INPUTS!$B$25*(1+INPUTS!$B$23)^(INPUTS!$B$6-INPUTS!$B$5+12),0)-INPUTS!$B$24),0) -> 44897.243 | P4: =IFERROR(MAX(0,INPUTS!$B$22*(1+INPUTS!$B$23)^(INPUTS!$B$6-INPUTS!$B$5+13)-IF(INPUTS!$B$6+13>=INPUTS!$B$7,INPUTS!$B$25*(1+INPUTS!$B$23)^(INPUTS!$B$6-INPUTS!$B$5+13),0)-INPUTS!$B$24),0) -> 46019.674 | Q4: =IFERROR(MAX(0,INPUTS!$B$22*(1+INPUTS!$B$23)^(INPUTS!$B$6-INPUTS!$B$5+14)-IF(INPUTS!$B$6+14>=INPUTS!$B$7,INPUTS!$B$25*(1+INPUTS!$B$23)^(INPUTS!$B$6-INPUTS!$B$5+14),0)-INPUTS!$B$24),0) -> 47170.166 | R4: =IFERROR(MAX(0,INPUTS!$B$22*(1+INPUTS!$B$23)^(INPUTS!$B$6-INPUTS!$B$5+15)-IF(INPUTS!$B$6+15>=INPUTS!$B$7,INPUTS!$B$25*(1+INPUTS!$B$23)^(INPUTS!$B$6-INPUTS!$B$5+15),0)-INPUTS!$B$24),0) -> 48349.42 | S4: =IFERROR(MAX(0,INPUTS!$B$22*(1+INPUTS!$B$23)^(INPUTS!$B$6-INPUTS!$B$5+16)-IF(INPUTS!$B$6+16>=INPUTS!$B$7,INPUTS!$B$25*(1+INPUTS!$B$23)^(INPUTS!$B$6-INPUTS!$B$5+16),0)-INPUTS!$B$24),0) -> 49558.156 | T4: =IFERROR(MAX(0,INPUTS!$B$22*(1+INPUTS!$B$23)^(INPUTS!$B$6-INPUTS!$B$5+17)-IF(INPUTS!$B$6+17>=INPUTS!$B$7,INPUTS!$B$25*(1+INPUTS!$B$23)^(INPUTS!$B$6-INPUTS!$B$5+17),0)-INPUTS!$B$24),0) -> 50797.11 | U4: =IFERROR(MAX(0,INPUTS!$B$22*(1+INPUTS!$B$23)^(INPUTS!$B$6-INPUTS!$B$5+18)-IF(INPUTS!$B$6+18>=INPUTS!$B$7,INPUTS!$B$25*(1+INPUTS!$B$23)^(INPUTS!$B$6-INPUTS!$B$5+18),0)-INPUTS!$B$24),0) -> 52067.037 | V4: =IFERROR(MAX(0,INPUTS!$B$22*(1+INPUTS!$B$23)^(INPUTS!$B$6-INPUTS!$B$5+19)-IF(INPUTS!$B$6+19>=INPUTS!$B$7,INPUTS!$B$25*(1+INPUTS!$B$23)^(INPUTS!$B$6-INPUTS!$B$5+19),0)-INPUTS!$B$24),0) -> 53368.713 | W4: =IFERROR(MAX(0,INPUTS!$B$22*(1+INPUTS!$B$23)^(INPUTS!$B$6-INPUTS!$B$5+20)-IF(INPUTS!$B$6+20>=INPUTS!$B$7,INPUTS!$B$25*(1+INPUTS!$B$23)^(INPUTS!$B$6-INPUTS!$B$5+20),0)-INPUTS!$B$24),0) -> 54702.931 | X4: =IFERROR(MAX(0,INPUTS!$B$22*(1+INPUTS!$B$23)^(INPUTS!$B$6-INPUTS!$B$5+21)-IF(INPUTS!$B$6+21>=INPUTS!$B$7,INPUTS!$B$25*(1+INPUTS!$B$23)^(INPUTS!$B$6-INPUTS!$B$5+21),0)-INPUTS!$B$24),0) -> 56070.504 | Y4: =IFERROR(MAX(0,INPUTS!$B$22*(1+INPUTS!$B$23)^(INPUTS!$B$6-INPUTS!$B$5+22)-IF(INPUTS!$B$6+22>=INPUTS!$B$7,INPUTS!$B$25*(1+INPUTS!$B$23)^(INPUTS!$B$6-INPUTS!$B$5+22),0)-INPUTS!$B$24),0) -> 57472.267 | Z4: =IFERROR(MAX(0,INPUTS!$B$22*(1+INPUTS!$B$23)^(INPUTS!$B$6-INPUTS!$B$5+23)-IF(INPUTS!$B$6+23>=INPUTS!$B$7,INPUTS!$B$25*(1+INPUTS!$B$23)^(INPUTS!$B$6-INPUTS!$B$5+23),0)-INPUTS!$B$24),0) -> 58909.074 | AA4: =IFERROR(MAX(0,INPUTS!$B$22*(1+INPUTS!$B$23)^(INPUTS!$B$6-INPUTS!$B$5+24)-IF(INPUTS!$B$6+24>=INPUTS!$B$7,INPUTS!$B$25*(1+INPUTS!$B$23)^(INPUTS!$B$6-INPUTS!$B$5+24),0)-INPUTS!$B$24),0) -> 60381.801 | AB4: =IFERROR(MAX(0,INPUTS!$B$22*(1+INPUTS!$B$23)^(INPUTS!$B$6-INPUTS!$B$5+25)-IF(INPUTS!$B$6+25>=INPUTS!$B$7,INPUTS!$B$25*(1+INPUTS!$B$23)^(INPUTS!$B$6-INPUTS!$B$5+25),0)-INPUTS!$B$24),0) -> 61891.346 | AC4: =IFERROR(MAX(0,INPUTS!$B$22*(1+INPUTS!$B$23)^(INPUTS!$B$6-INPUTS!$B$5+26)-IF(INPUTS!$B$6+26>=INPUTS!$B$7,INPUTS!$B$25*(1+INPUTS!$B$23)^(INPUTS!$B$6-INPUTS!$B$5+26),0)-INPUTS!$B$24),0) -> 63438.629 | AD4: =IFERROR(MAX(0,INPUTS!$B$22*(1+INPUTS!$B$23)^(INPUTS!$B$6-INPUTS!$B$5+27)-IF(INPUTS!$B$6+27>=INPUTS!$B$7,INPUTS!$B$25*(1+INPUTS!$B$23)^(INPUTS!$B$6-INPUTS!$B$5+27),0)-INPUTS!$B$24),0) -> 65024.595 | AE4: =IFERROR(MAX(0,INPUTS!$B$22*(1+INPUTS!$B$23)^(INPUTS!$B$6-INPUTS!$B$5+28)-IF(INPUTS!$B$6+28>=INPUTS!$B$7,INPUTS!$B$25*(1+INPUTS!$B$23)^(INPUTS!$B$6-INPUTS!$B$5+28),0)-INPUTS!$B$24),0) -> 66650.21 | AF4: =IFERROR(MAX(0,INPUTS!$B$22*(1+INPUTS!$B$23)^(INPUTS!$B$6-INPUTS!$B$5+29)-IF(INPUTS!$B$6+29>=INPUTS!$B$7,INPUTS!$B$25*(1+INPUTS!$B$23)^(INPUTS!$B$6-INPUTS!$B$5+29),0)-INPUTS!$B$24),0) -> 68316.465 | AG4: =IFERROR(MAX(0,INPUTS!$B$22*(1+INPUTS!$B$23)^(INPUTS!$B$6-INPUTS!$B$5+30)-IF(INPUTS!$B$6+30>=INPUTS!$B$7,INPUTS!$B$25*(1+INPUTS!$B$23)^(INPUTS!$B$6-INPUTS!$B$5+30),0)-INPUTS!$B$24),0) -> 70024.377 | AH4: =IFERROR(MAX(0,INPUTS!$B$22*(1+INPUTS!$B$23)^(INPUTS!$B$6-INPUTS!$B$5+31)-IF(INPUTS!$B$6+31>=INPUTS!$B$7,INPUTS!$B$25*(1+INPUTS!$B$23)^(INPUTS!$B$6-INPUTS!$B$5+31),0)-INPUTS!$B$24),0) -> 71774.986 | AI4: =IFERROR(MAX(0,INPUTS!$B$22*(1+INPUTS!$B$23)^(INPUTS!$B$6-INPUTS!$B$5+32)-IF(INPUTS!$B$6+32>=INPUTS!$B$7,INPUTS!$B$25*(1+INPUTS!$B$23)^(INPUTS!$B$6-INPUTS!$B$5+32),0)-INPUTS!$B$24),0) -> 73569.361 | AJ4: =IFERROR(MAX(0,INPUTS!$B$22*(1+INPUTS!$B$23)^(INPUTS!$B$6-INPUTS!$B$5+33)-IF(INPUTS!$B$6+33>=INPUTS!$B$7,INPUTS!$B$25*(1+INPUTS!$B$23)^(INPUTS!$B$6-INPUTS!$B$5+33),0)-INPUTS!$B$24),0) -> 75408.595 | AK4: =IFERROR(MAX(0,INPUTS!$B$22*(1+INPUTS!$B$23)^(INPUTS!$B$6-INPUTS!$B$5+34)-IF(INPUTS!$B$6+34>=INPUTS!$B$7,INPUTS!$B$25*(1+INPUTS!$B$23)^(INPUTS!$B$6-INPUTS!$B$5+34),0)-INPUTS!$B$24),0) -> 77293.81 | AL4: =IFERROR(MAX(0,INPUTS!$B$22*(1+INPUTS!$B$23)^(INPUTS!$B$6-INPUTS!$B$5+35)-IF(INPUTS!$B$6+35>=INPUTS!$B$7,INPUTS!$B$25*(1+INPUTS!$B$23)^(INPUTS!$B$6-INPUTS!$B$5+35),0)-INPUTS!$B$24),0) -> 79226.155 | AM4: =IFERROR(MAX(0,INPUTS!$B$22*(1+INPUTS!$B$23)^(INPUTS!$B$6-INPUTS!$B$5+36)-IF(INPUTS!$B$6+36>=INPUTS!$B$7,INPUTS!$B$25*(1+INPUTS!$B$23)^(INPUTS!$B$6-INPUTS!$B$5+36),0)-INPUTS!$B$24),0) -> 81206.809 | AN4: =IFERROR(MAX(0,INPUTS!$B$22*(1+INPUTS!$B$23)^(INPUTS!$B$6-INPUTS!$B$5+37)-IF(INPUTS!$B$6+37>=INPUTS!$B$7,INPUTS!$B$25*(1+INPUTS!$B$23)^(INPUTS!$B$6-INPUTS!$B$5+37),0)-INPUTS!$B$24),0) -> 83236.979 | AO4: =IFERROR(MAX(0,INPUTS!$B$22*(1+INPUTS!$B$23)^(INPUTS!$B$6-INPUTS!$B$5+38)-IF(INPUTS!$B$6+38>=INPUTS!$B$7,INPUTS!$B$25*(1+INPUTS!$B$23)^(INPUTS!$B$6-INPUTS!$B$5+38),0)-INPUTS!$B$24),0) -> 85317.903 | AP4: =IFERROR(MAX(0,INPUTS!$B$22*(1+INPUTS!$B$23)^(INPUTS!$B$6-INPUTS!$B$5+39)-IF(INPUTS!$B$6+39>=INPUTS!$B$7,INPUTS!$B$25*(1+INPUTS!$B$23)^(INPUTS!$B$6-INPUTS!$B$5+39),0)-INPUTS!$B$24),0) -> 87450.851
A5: Years active → | C5: =IF(INPUTS!$B$6+0>INPUTS!$B$8,0,1) -> 1 | D5: =IF(INPUTS!$B$6+1>INPUTS!$B$8,0,1) -> 1 | E5: =IF(INPUTS!$B$6+2>INPUTS!$B$8,0,1) -> 1 | F5: =IF(INPUTS!$B$6+3>INPUTS!$B$8,0,1) -> 1 | G5: =IF(INPUTS!$B$6+4>INPUTS!$B$8,0,1) -> 1 | H5: =IF(INPUTS!$B$6+5>INPUTS!$B$8,0,1) -> 1 | I5: =IF(INPUTS!$B$6+6>INPUTS!$B$8,0,1) -> 1 | J5: =IF(INPUTS!$B$6+7>INPUTS!$B$8,0,1) -> 1 | K5: =IF(INPUTS!$B$6+8>INPUTS!$B$8,0,1) -> 1 | L5: =IF(INPUTS!$B$6+9>INPUTS!$B$8,0,1) -> 1 | M5: =IF(INPUTS!$B$6+10>INPUTS!$B$8,0,1) -> 1 | N5: =IF(INPUTS!$B$6+11>INPUTS!$B$8,0,1) -> 1 | O5: =IF(INPUTS!$B$6+12>INPUTS!$B$8,0,1) -> 1 | P5: =IF(INPUTS!$B$6+13>INPUTS!$B$8,0,1) -> 1 | Q5: =IF(INPUTS!$B$6+14>INPUTS!$B$8,0,1) -> 1 | R5: =IF(INPUTS!$B$6+15>INPUTS!$B$8,0,1) -> 1 | S5: =IF(INPUTS!$B$6+16>INPUTS!$B$8,0,1) -> 1 | T5: =IF(INPUTS!$B$6+17>INPUTS!$B$8,0,1) -> 1 | U5: =IF(INPUTS!$B$6+18>INPUTS!$B$8,0,1) -> 1 | V5: =IF(INPUTS!$B$6+19>INPUTS!$B$8,0,1) -> 1 | W5: =IF(INPUTS!$B$6+20>INPUTS!$B$8,0,1) -> 1 | X5: =IF(INPUTS!$B$6+21>INPUTS!$B$8,0,1) -> 1 | Y5: =IF(INPUTS!$B$6+22>INPUTS!$B$8,0,1) -> 1 | Z5: =IF(INPUTS!$B$6+23>INPUTS!$B$8,0,1) -> 1 | AA5: =IF(INPUTS!$B$6+24>INPUTS!$B$8,0,1) -> 1 | AB5: =IF(INPUTS!$B$6+25>INPUTS!$B$8,0,1) -> 1 | AC5: =IF(INPUTS!$B$6+26>INPUTS!$B$8,0,1) -> 1 | AD5: =IF(INPUTS!$B$6+27>INPUTS!$B$8,0,1) -> 1 | AE5: =IF(INPUTS!$B$6+28>INPUTS!$B$8,0,1) -> 1 | AF5: =IF(INPUTS!$B$6+29>INPUTS!$B$8,0,1) -> 1 | AG5: =IF(INPUTS!$B$6+30>INPUTS!$B$8,0,1) -> 1 | AH5: =IF(INPUTS!$B$6+31>INPUTS!$B$8,0,1) -> 1 | AI5: =IF(INPUTS!$B$6+32>INPUTS!$B$8,0,1) -> 1 | AJ5: =IF(INPUTS!$B$6+33>INPUTS!$B$8,0,1) -> 1 | AK5: =IF(INPUTS!$B$6+34>INPUTS!$B$8,0,1) -> 1 | AL5: =IF(INPUTS!$B$6+35>INPUTS!$B$8,0,1) -> 1 | AM5: =IF(INPUTS!$B$6+36>INPUTS!$B$8,0,1) -> 0 | AN5: =IF(INPUTS!$B$6+37>INPUTS!$B$8,0,1) -> 0 | AO5: =IF(INPUTS!$B$6+38>INPUTS!$B$8,0,1) -> 0 | AP5: =IF(INPUTS!$B$6+39>INPUTS!$B$8,0,1) -> 0
A7: Sim # | B7: Final Balance | C7: Y1 | D7: Y2 | E7: Y3 | F7: Y4 | G7: Y5 | H7: Y6 | I7: Y7 | J7: Y8 | K7: Y9 | L7: Y10 | M7: Y11 | N7: Y12 | O7: Y13 | P7: Y14 | Q7: Y15 | R7: Y16 | S7: Y17 | T7: Y18 | U7: Y19 | V7: Y20 | W7: Y21 | X7: Y22 | Y7: Y23 | Z7: Y24 | AA7: Y25 | AB7: Y26 | AC7: Y27 | AD7: Y28 | AE7: Y29 | AF7: Y30 | AG7: Y31 | AH7: Y32 | AI7: Y33 | AJ7: Y34 | AK7: Y35 | AL7: Y36 | AM7: Y37 | AN7: Y38 | AO7: Y39 | AP7: Y40
A8: 1 | B8: =LOOKUP(9.99E+307,C8:AP8) -> 1945893.4 | C8: =IF(C$5=0,INPUTS!$B$19,MAX(0,(INPUTS!$B$19-C$4)*(1+NORMINV(RAND(),INPUTS!$B$28,INPUTS!$B$29)))) -> 1376485.7 | D8: =IF(D$5=0,C8,MAX(0,(C8-D$4)*(1+NORMINV(RAND(),INPUTS!$B$28,INPUTS!$B$29)))) -> 1616177.8 | E8: =IF(E$5=0,D8,MAX(0,(D8-E$4)*(1+NORMINV(RAND(),INPUTS!$B$28,INPUTS!$B$29)))) -> 1393980.7 | F8: =IF(F$5=0,E8,MAX(0,(E8-F$4)*(1+NORMINV(RAND(),INPUTS!$B$28,INPUTS!$B$29)))) -> 1248142.8 | G8: =IF(G$5=0,F8,MAX(0,(F8-G$4)*(1+NORMINV(RAND(),INPUTS!$B$28,INPUTS!$B$29)))) -> 1336960.4 | H8: =IF(H$5=0,G8,MAX(0,(G8-H$4)*(1+NORMINV(RAND(),INPUTS!$B$28,INPUTS!$B$29)))) -> 1297461.3 | I8: =IF(I$5=0,H8,MAX(0,(H8-I$4)*(1+NORMINV(RAND(),INPUTS!$B$28,INPUTS!$B$29)))) -> 1257828.2 | J8: =IF(J$5=0,I8,MAX(0,(I8-J$4)*(1+NORMINV(RAND(),INPUTS!$B$28,INPUTS!$B$29)))) -> 1324696.1 | K8: =IF(K$5=0,J8,MAX(0,(J8-K$4)*(1+NORMINV(RAND(),INPUTS!$B$28,INPUTS!$B$29)))) -> 1331353.4 | ... AP8: =IF(AP$5=0,AO8,MAX(0,(AO8-AP$4)*(1+NORMINV(RAND(),INPUTS!$B$28,INPUTS!$B$29)))) -> 1945893.4
A9: 2 | B9: =LOOKUP(9.99E+307,C9:AP9) -> 494377.2 | C9: =IF(C$5=0,INPUTS!$B$19,MAX(0,(INPUTS!$B$19-C$4)*(1+NORMINV(RAND(),INPUTS!$B$28,INPUTS!$B$29)))) -> 1138214.3 | D9: =IF(D$5=0,C9,MAX(0,(C9-D$4)*(1+NORMINV(RAND(),INPUTS!$B$28,INPUTS!$B$29)))) -> 1152968.4 | E9: =IF(E$5=0,D9,MAX(0,(D9-E$4)*(1+NORMINV(RAND(),INPUTS!$B$28,INPUTS!$B$29)))) -> 1138781.9 | F9: =IF(F$5=0,E9,MAX(0,(E9-F$4)*(1+NORMINV(RAND(),INPUTS!$B$28,INPUTS!$B$29)))) -> 1227514.2 | G9: =IF(G$5=0,F9,MAX(0,(F9-G$4)*(1+NORMINV(RAND(),INPUTS!$B$28,INPUTS!$B$29)))) -> 1369658.6 | H9: =IF(H$5=0,G9,MAX(0,(G9-H$4)*(1+NORMINV(RAND(),INPUTS!$B$28,INPUTS!$B$29)))) -> 1369078.5 | I9: =IF(I$5=0,H9,MAX(0,(H9-I$4)*(1+NORMINV(RAND(),INPUTS!$B$28,INPUTS!$B$29)))) -> 1362142.1 | J9: =IF(J$5=0,I9,MAX(0,(I9-J$4)*(1+NORMINV(RAND(),INPUTS!$B$28,INPUTS!$B$29)))) -> 1317667.6 | K9: =IF(K$5=0,J9,MAX(0,(J9-K$4)*(1+NORMINV(RAND(),INPUTS!$B$28,INPUTS!$B$29)))) -> 1191236.4 | ... AP9: =IF(AP$5=0,AO9,MAX(0,(AO9-AP$4)*(1+NORMINV(RAND(),INPUTS!$B$28,INPUTS!$B$29)))) -> 494377.2
A10: 3 | B10: =LOOKUP(9.99E+307,C10:AP10) -> 9555977.6 | C10: =IF(C$5=0,INPUTS!$B$19,MAX(0,(INPUTS!$B$19-C$4)*(1+NORMINV(RAND(),INPUTS!$B$28,INPUTS!$B$29)))) -> 1251648.5 | D10: =IF(D$5=0,C10,MAX(0,(C10-D$4)*(1+NORMINV(RAND(),INPUTS!$B$28,INPUTS!$B$29)))) -> 1411218.4 | E10: =IF(E$5=0,D10,MAX(0,(D10-E$4)*(1+NORMINV(RAND(),INPUTS!$B$28,INPUTS!$B$29)))) -> 1600442.9 | F10: =IF(F$5=0,E10,MAX(0,(E10-F$4)*(1+NORMINV(RAND(),INPUTS!$B$28,INPUTS!$B$29)))) -> 1625795.3 | G10: =IF(G$5=0,F10,MAX(0,(F10-G$4)*(1+NORMINV(RAND(),INPUTS!$B$28,INPUTS!$B$29)))) -> 1674557 | H10: =IF(H$5=0,G10,MAX(0,(G10-H$4)*(1+NORMINV(RAND(),INPUTS!$B$28,INPUTS!$B$29)))) -> 1527006.6 | I10: =IF(I$5=0,H10,MAX(0,(H10-I$4)*(1+NORMINV(RAND(),INPUTS!$B$28,INPUTS!$B$29)))) -> 1666863.9 | J10: =IF(J$5=0,I10,MAX(0,(I10-J$4)*(1+NORMINV(RAND(),INPUTS!$B$28,INPUTS!$B$29)))) -> 1700401.6 | K10: =IF(K$5=0,J10,MAX(0,(J10-K$4)*(1+NORMINV(RAND(),INPUTS!$B$28,INPUTS!$B$29)))) -> 1771466.4 | ... AP10: =IF(AP$5=0,AO10,MAX(0,(AO10-AP$4)*(1+NORMINV(RAND(),INPUTS!$B$28,INPUTS!$B$29)))) -> 9555977.6
A11: 4 | B11: =LOOKUP(9.99E+307,C11:AP11) -> 0 | C11: =IF(C$5=0,INPUTS!$B$19,MAX(0,(INPUTS!$B$19-C$4)*(1+NORMINV(RAND(),INPUTS!$B$28,INPUTS!$B$29)))) -> 1256713.9 | D11: =IF(D$5=0,C11,MAX(0,(C11-D$4)*(1+NORMINV(RAND(),INPUTS!$B$28,INPUTS!$B$29)))) -> 1216597.9 | E11: =IF(E$5=0,D11,MAX(0,(D11-E$4)*(1+NORMINV(RAND(),INPUTS!$B$28,INPUTS!$B$29)))) -> 1234988.4 | F11: =IF(F$5=0,E11,MAX(0,(E11-F$4)*(1+NORMINV(RAND(),INPUTS!$B$28,INPUTS!$B$29)))) -> 1224407.3 | G11: =IF(G$5=0,F11,MAX(0,(F11-G$4)*(1+NORMINV(RAND(),INPUTS!$B$28,INPUTS!$B$29)))) -> 1275668.1 | H11: =IF(H$5=0,G11,MAX(0,(G11-H$4)*(1+NORMINV(RAND(),INPUTS!$B$28,INPUTS!$B$29)))) -> 1024383.4 | I11: =IF(I$5=0,H11,MAX(0,(H11-I$4)*(1+NORMINV(RAND(),INPUTS!$B$28,INPUTS!$B$29)))) -> 921743.47 | J11: =IF(J$5=0,I11,MAX(0,(I11-J$4)*(1+NORMINV(RAND(),INPUTS!$B$28,INPUTS!$B$29)))) -> 876426.34 | K11: =IF(K$5=0,J11,MAX(0,(J11-K$4)*(1+NORMINV(RAND(),INPUTS!$B$28,INPUTS!$B$29)))) -> 822115.1 | ... AP11: =IF(AP$5=0,AO11,MAX(0,(AO11-AP$4)*(1+NORMINV(RAND(),INPUTS!$B$28,INPUTS!$B$29)))) -> 0
A12: 5 | B12: =LOOKUP(9.99E+307,C12:AP12) -> 0 | C12: =IF(C$5=0,INPUTS!$B$19,MAX(0,(INPUTS!$B$19-C$4)*(1+NORMINV(RAND(),INPUTS!$B$28,INPUTS!$B$29)))) -> 1307219.8 | D12: =IF(D$5=0,C12,MAX(0,(C12-D$4)*(1+NORMINV(RAND(),INPUTS!$B$28,INPUTS!$B$29)))) -> 1127931.4 | E12: =IF(E$5=0,D12,MAX(0,(D12-E$4)*(1+NORMINV(RAND(),INPUTS!$B$28,INPUTS!$B$29)))) -> 1170391.4 | F12: =IF(F$5=0,E12,MAX(0,(E12-F$4)*(1+NORMINV(RAND(),INPUTS!$B$28,INPUTS!$B$29)))) -> 1223757.2 | G12: =IF(G$5=0,F12,MAX(0,(F12-G$4)*(1+NORMINV(RAND(),INPUTS!$B$28,INPUTS!$B$29)))) -> 1279371.6 | H12: =IF(H$5=0,G12,MAX(0,(G12-H$4)*(1+NORMINV(RAND(),INPUTS!$B$28,INPUTS!$B$29)))) -> 1229774.5 | I12: =IF(I$5=0,H12,MAX(0,(H12-I$4)*(1+NORMINV(RAND(),INPUTS!$B$28,INPUTS!$B$29)))) -> 1105662 | J12: =IF(J$5=0,I12,MAX(0,(I12-J$4)*(1+NORMINV(RAND(),INPUTS!$B$28,INPUTS!$B$29)))) -> 1016072.9 | K12: =IF(K$5=0,J12,MAX(0,(J12-K$4)*(1+NORMINV(RAND(),INPUTS!$B$28,INPUTS!$B$29)))) -> 845041.9 | ... AP12: =IF(AP$5=0,AO12,MAX(0,(AO12-AP$4)*(1+NORMINV(RAND(),INPUTS!$B$28,INPUTS!$B$29)))) -> 0
A13: 6 | B13: =LOOKUP(9.99E+307,C13:AP13) -> 2746070.6 | C13: =IF(C$5=0,INPUTS!$B$19,MAX(0,(INPUTS!$B$19-C$4)*(1+NORMINV(RAND(),INPUTS!$B$28,INPUTS!$B$29)))) -> 1219359.6 | D13: =IF(D$5=0,C13,MAX(0,(C13-D$4)*(1+NORMINV(RAND(),INPUTS!$B$28,INPUTS!$B$29)))) -> 1272427.3 | E13: =IF(E$5=0,D13,MAX(0,(D13-E$4)*(1+NORMINV(RAND(),INPUTS!$B$28,INPUTS!$B$29)))) -> 1392645.6 | F13: =IF(F$5=0,E13,MAX(0,(E13-F$4)*(1+NORMINV(RAND(),INPUTS!$B$28,INPUTS!$B$29)))) -> 1534872.7 | G13: =IF(G$5=0,F13,MAX(0,(F13-G$4)*(1+NORMINV(RAND(),INPUTS!$B$28,INPUTS!$B$29)))) -> 1659650.6 | H13: =IF(H$5=0,G13,MAX(0,(G13-H$4)*(1+NORMINV(RAND(),INPUTS!$B$28,INPUTS!$B$29)))) -> 1616076.5 | I13: =IF(I$5=0,H13,MAX(0,(H13-I$4)*(1+NORMINV(RAND(),INPUTS!$B$28,INPUTS!$B$29)))) -> 1701726.3 | J13: =IF(J$5=0,I13,MAX(0,(I13-J$4)*(1+NORMINV(RAND(),INPUTS!$B$28,INPUTS!$B$29)))) -> 1484428.6 | K13: =IF(K$5=0,J13,MAX(0,(J13-K$4)*(1+NORMINV(RAND(),INPUTS!$B$28,INPUTS!$B$29)))) -> 1341116.1 | ... AP13: =IF(AP$5=0,AO13,MAX(0,(AO13-AP$4)*(1+NORMINV(RAND(),INPUTS!$B$28,INPUTS!$B$29)))) -> 2746070.6
A14: 7 | B14: =LOOKUP(9.99E+307,C14:AP14) -> 2397750 | C14: =IF(C$5=0,INPUTS!$B$19,MAX(0,(INPUTS!$B$19-C$4)*(1+NORMINV(RAND(),INPUTS!$B$28,INPUTS!$B$29)))) -> 1109358.1 | D14: =IF(D$5=0,C14,MAX(0,(C14-D$4)*(1+NORMINV(RAND(),INPUTS!$B$28,INPUTS!$B$29)))) -> 1078113.9 | E14: =IF(E$5=0,D14,MAX(0,(D14-E$4)*(1+NORMINV(RAND(),INPUTS!$B$28,INPUTS!$B$29)))) -> 1139323.7 | F14: =IF(F$5=0,E14,MAX(0,(E14-F$4)*(1+NORMINV(RAND(),INPUTS!$B$28,INPUTS!$B$29)))) -> 1249492.2 | G14: =IF(G$5=0,F14,MAX(0,(F14-G$4)*(1+NORMINV(RAND(),INPUTS!$B$28,INPUTS!$B$29)))) -> 1401032.9 | H14: =IF(H$5=0,G14,MAX(0,(G14-H$4)*(1+NORMINV(RAND(),INPUTS!$B$28,INPUTS!$B$29)))) -> 1359440.3 | I14: =IF(I$5=0,H14,MAX(0,(H14-I$4)*(1+NORMINV(RAND(),INPUTS!$B$28,INPUTS!$B$29)))) -> 1496211.1 | J14: =IF(J$5=0,I14,MAX(0,(I14-J$4)*(1+NORMINV(RAND(),INPUTS!$B$28,INPUTS!$B$29)))) -> 1562569.2 | K14: =IF(K$5=0,J14,MAX(0,(J14-K$4)*(1+NORMINV(RAND(),INPUTS!$B$28,INPUTS!$B$29)))) -> 1909037.8 | ... AP14: =IF(AP$5=0,AO14,MAX(0,(AO14-AP$4)*(1+NORMINV(RAND(),INPUTS!$B$28,INPUTS!$B$29)))) -> 2397750
A15: 8 | B15: =LOOKUP(9.99E+307,C15:AP15) -> 1867150.5 | C15: =IF(C$5=0,INPUTS!$B$19,MAX(0,(INPUTS!$B$19-C$4)*(1+NORMINV(RAND(),INPUTS!$B$28,INPUTS!$B$29)))) -> 1269223.4 | D15: =IF(D$5=0,C15,MAX(0,(C15-D$4)*(1+NORMINV(RAND(),INPUTS!$B$28,INPUTS!$B$29)))) -> 1002330.2 | E15: =IF(E$5=0,D15,MAX(0,(D15-E$4)*(1+NORMINV(RAND(),INPUTS!$B$28,INPUTS!$B$29)))) -> 943456.38 | F15: =IF(F$5=0,E15,MAX(0,(E15-F$4)*(1+NORMINV(RAND(),INPUTS!$B$28,INPUTS!$B$29)))) -> 934946.98 | G15: =IF(G$5=0,F15,MAX(0,(F15-G$4)*(1+NORMINV(RAND(),INPUTS!$B$28,INPUTS!$B$29)))) -> 991187.83 | H15: =IF(H$5=0,G15,MAX(0,(G15-H$4)*(1+NORMINV(RAND(),INPUTS!$B$28,INPUTS!$B$29)))) -> 817806.23 | I15: =IF(I$5=0,H15,MAX(0,(H15-I$4)*(1+NORMINV(RAND(),INPUTS!$B$28,INPUTS!$B$29)))) -> 746102.8 | J15: =IF(J$5=0,I15,MAX(0,(I15-J$4)*(1+NORMINV(RAND(),INPUTS!$B$28,INPUTS!$B$29)))) -> 778727.51 | K15: =IF(K$5=0,J15,MAX(0,(J15-K$4)*(1+NORMINV(RAND(),INPUTS!$B$28,INPUTS!$B$29)))) -> 960991.12 | ... AP15: =IF(AP$5=0,AO15,MAX(0,(AO15-AP$4)*(1+NORMINV(RAND(),INPUTS!$B$28,INPUTS!$B$29)))) -> 1867150.5
A16: 9 | B16: =LOOKUP(9.99E+307,C16:AP16) -> 0 | C16: =IF(C$5=0,INPUTS!$B$19,MAX(0,(INPUTS!$B$19-C$4)*(1+NORMINV(RAND(),INPUTS!$B$28,INPUTS!$B$29)))) -> 1124373.2 | D16: =IF(D$5=0,C16,MAX(0,(C16-D$4)*(1+NORMINV(RAND(),INPUTS!$B$28,INPUTS!$B$29)))) -> 844995.32 | E16: =IF(E$5=0,D16,MAX(0,(D16-E$4)*(1+NORMINV(RAND(),INPUTS!$B$28,INPUTS!$B$29)))) -> 808966.37 | F16: =IF(F$5=0,E16,MAX(0,(E16-F$4)*(1+NORMINV(RAND(),INPUTS!$B$28,INPUTS!$B$29)))) -> 816344.69 | G16: =IF(G$5=0,F16,MAX(0,(F16-G$4)*(1+NORMINV(RAND(),INPUTS!$B$28,INPUTS!$B$29)))) -> 850530.13 | H16: =IF(H$5=0,G16,MAX(0,(G16-H$4)*(1+NORMINV(RAND(),INPUTS!$B$28,INPUTS!$B$29)))) -> 895574.06 | I16: =IF(I$5=0,H16,MAX(0,(H16-I$4)*(1+NORMINV(RAND(),INPUTS!$B$28,INPUTS!$B$29)))) -> 875092.66 | J16: =IF(J$5=0,I16,MAX(0,(I16-J$4)*(1+NORMINV(RAND(),INPUTS!$B$28,INPUTS!$B$29)))) -> 814081.13 | K16: =IF(K$5=0,J16,MAX(0,(J16-K$4)*(1+NORMINV(RAND(),INPUTS!$B$28,INPUTS!$B$29)))) -> 894436.75 | ... AP16: =IF(AP$5=0,AO16,MAX(0,(AO16-AP$4)*(1+NORMINV(RAND(),INPUTS!$B$28,INPUTS!$B$29)))) -> 0
A17: 10 | B17: =LOOKUP(9.99E+307,C17:AP17) -> 0 | C17: =IF(C$5=0,INPUTS!$B$19,MAX(0,(INPUTS!$B$19-C$4)*(1+NORMINV(RAND(),INPUTS!$B$28,INPUTS!$B$29)))) -> 1198774.1 | D17: =IF(D$5=0,C17,MAX(0,(C17-D$4)*(1+NORMINV(RAND(),INPUTS!$B$28,INPUTS!$B$29)))) -> 1238412.9 | E17: =IF(E$5=0,D17,MAX(0,(D17-E$4)*(1+NORMINV(RAND(),INPUTS!$B$28,INPUTS!$B$29)))) -> 969736.9 | F17: =IF(F$5=0,E17,MAX(0,(E17-F$4)*(1+NORMINV(RAND(),INPUTS!$B$28,INPUTS!$B$29)))) -> 1142500.4 | G17: =IF(G$5=0,F17,MAX(0,(F17-G$4)*(1+NORMINV(RAND(),INPUTS!$B$28,INPUTS!$B$29)))) -> 1149668.9 | H17: =IF(H$5=0,G17,MAX(0,(G17-H$4)*(1+NORMINV(RAND(),INPUTS!$B$28,INPUTS!$B$29)))) -> 924246.15 | I17: =IF(I$5=0,H17,MAX(0,(H17-I$4)*(1+NORMINV(RAND(),INPUTS!$B$28,INPUTS!$B$29)))) -> 796325.12 | J17: =IF(J$5=0,I17,MAX(0,(I17-J$4)*(1+NORMINV(RAND(),INPUTS!$B$28,INPUTS!$B$29)))) -> 795881.82 | K17: =IF(K$5=0,J17,MAX(0,(J17-K$4)*(1+NORMINV(RAND(),INPUTS!$B$28,INPUTS!$B$29)))) -> 757586.98 | ... AP17: =IF(AP$5=0,AO17,MAX(0,(AO17-AP$4)*(1+NORMINV(RAND(),INPUTS!$B$28,INPUTS!$B$29)))) -> 0
A18: 11 | B18: =LOOKUP(9.99E+307,C18:AP18) -> 25286.573 | C18: =IF(C$5=0,INPUTS!$B$19,MAX(0,(INPUTS!$B$19-C$4)*(1+NORMINV(RAND(),INPUTS!$B$28,INPUTS!$B$29)))) -> 916833.32 | D18: =IF(D$5=0,C18,MAX(0,(C18-D$4)*(1+NORMINV(RAND(),INPUTS!$B$28,INPUTS!$B$29)))) -> 1021549.1 | E18: =IF(E$5=0,D18,MAX(0,(D18-E$4)*(1+NORMINV(RAND(),INPUTS!$B$28,INPUTS!$B$29)))) -> 1001100.9 | F18: =IF(F$5=0,E18,MAX(0,(E18-F$4)*(1+NORMINV(RAND(),INPUTS!$B$28,INPUTS!$B$29)))) -> 1003270.4 | G18: =IF(G$5=0,F18,MAX(0,(F18-G$4)*(1+NORMINV(RAND(),INPUTS!$B$28,INPUTS!$B$29)))) -> 1130245.9 | H18: =IF(H$5=0,G18,MAX(0,(G18-H$4)*(1+NORMINV(RAND(),INPUTS!$B$28,INPUTS!$B$29)))) -> 1053383.8 | I18: =IF(I$5=0,H18,MAX(0,(H18-I$4)*(1+NORMINV(RAND(),INPUTS!$B$28,INPUTS!$B$29)))) -> 864496.97 | J18: =IF(J$5=0,I18,MAX(0,(I18-J$4)*(1+NORMINV(RAND(),INPUTS!$B$28,INPUTS!$B$29)))) -> 809343.77 | K18: =IF(K$5=0,J18,MAX(0,(J18-K$4)*(1+NORMINV(RAND(),INPUTS!$B$28,INPUTS!$B$29)))) -> 771405.84 | ... AP18: =IF(AP$5=0,AO18,MAX(0,(AO18-AP$4)*(1+NORMINV(RAND(),INPUTS!$B$28,INPUTS!$B$29)))) -> 25286.573
A19: 12 | B19: =LOOKUP(9.99E+307,C19:AP19) -> 4161216.5 | C19: =IF(C$5=0,INPUTS!$B$19,MAX(0,(INPUTS!$B$19-C$4)*(1+NORMINV(RAND(),INPUTS!$B$28,INPUTS!$B$29)))) -> 1359033.9 | D19: =IF(D$5=0,C19,MAX(0,(C19-D$4)*(1+NORMINV(RAND(),INPUTS!$B$28,INPUTS!$B$29)))) -> 1466997 | E19: =IF(E$5=0,D19,MAX(0,(D19-E$4)*(1+NORMINV(RAND(),INPUTS!$B$28,INPUTS!$B$29)))) -> 1623226.4 | F19: =IF(F$5=0,E19,MAX(0,(E19-F$4)*(1+NORMINV(RAND(),INPUTS!$B$28,INPUTS!$B$29)))) -> 1698586.3 | G19: =IF(G$5=0,F19,MAX(0,(F19-G$4)*(1+NORMINV(RAND(),INPUTS!$B$28,INPUTS!$B$29)))) -> 1637081.4 | H19: =IF(H$5=0,G19,MAX(0,(G19-H$4)*(1+NORMINV(RAND(),INPUTS!$B$28,INPUTS!$B$29)))) -> 1680534.8 | I19: =IF(I$5=0,H19,MAX(0,(H19-I$4)*(1+NORMINV(RAND(),INPUTS!$B$28,INPUTS!$B$29)))) -> 1595968.9 | J19: =IF(J$5=0,I19,MAX(0,(I19-J$4)*(1+NORMINV(RAND(),INPUTS!$B$28,INPUTS!$B$29)))) -> 1578888.5 | K19: =IF(K$5=0,J19,MAX(0,(J19-K$4)*(1+NORMINV(RAND(),INPUTS!$B$28,INPUTS!$B$29)))) -> 1482066.9 | ... AP19: =IF(AP$5=0,AO19,MAX(0,(AO19-AP$4)*(1+NORMINV(RAND(),INPUTS!$B$28,INPUTS!$B$29)))) -> 4161216.5
... A207: 200 | B207: =LOOKUP(9.99E+307,C207:AP207) -> 4581154.8 | C207: =IF(C$5=0,INPUTS!$B$19,MAX(0,(INPUTS!$B$19-C$4)*(1+NORMINV(RAND(),INPUTS!$B$28,INPUTS!$B$29)))) -> 1261109.9 | D207: =IF(D$5=0,C207,MAX(0,(C207-D$4)*(1+NORMINV(RAND(),INPUTS!$B$28,INPUTS!$B$29)))) -> 1350301 | E207: =IF(E$5=0,D207,MAX(0,(D207-E$4)*(1+NORMINV(RAND(),INPUTS!$B$28,INPUTS!$B$29)))) -> 1336748.4 | F207: =IF(F$5=0,E207,MAX(0,(E207-F$4)*(1+NORMINV(RAND(),INPUTS!$B$28,INPUTS!$B$29)))) -> 1463606.4 | G207: =IF(G$5=0,F207,MAX(0,(F207-G$4)*(1+NORMINV(RAND(),INPUTS!$B$28,INPUTS!$B$29)))) -> 1066903.3 | H207: =IF(H$5=0,G207,MAX(0,(G207-H$4)*(1+NORMINV(RAND(),INPUTS!$B$28,INPUTS!$B$29)))) -> 1077534.5 | I207: =IF(I$5=0,H207,MAX(0,(H207-I$4)*(1+NORMINV(RAND(),INPUTS!$B$28,INPUTS!$B$29)))) -> 1086134.4 | J207: =IF(J$5=0,I207,MAX(0,(I207-J$4)*(1+NORMINV(RAND(),INPUTS!$B$28,INPUTS!$B$29)))) -> 1346695.6 | K207: =IF(K$5=0,J207,MAX(0,(J207-K$4)*(1+NORMINV(RAND(),INPUTS!$B$28,INPUTS!$B$29)))) -> 1432877.1 | ... AP207: =IF(AP$5=0,AO207,MAX(0,(AO207-AP$4)*(1+NORMINV(RAND(),INPUTS!$B$28,INPUTS!$B$29)))) -> 4581154.8
A210: RESULTS
A211: Success Rate (money lasts to life expectancy) | B211: =COUNTIF(B8:B207,">0")/200 -> 0.705
A212: Median Final Balance | B212: =MEDIAN(B8:B207) -> 1158486.4
A213: 10th Percentile (bad luck scenario) | B213: =PERCENTILE(B8:B207,0.1) -> 0
A214: 90th Percentile (good luck scenario) | B214: =PERCENTILE(B8:B207,0.9) -> 6838828.9
A216: Guide: 90%+ success = robust. 75–90% = acceptable with flexibility. Below 75% = revisit spending or retirement age.

Sheet RISK FLAGS
A1: AUTOMATED RISK FLAGS
A2: All flags pull live from BRIDGE, POST-59.5, ROTH LADDER and MONTE CARLO.
A4: Risk Check | B4: Status | C4: Detail
A5: Withdrawal rate ≤ 4%? | B5: =IF(INPUTS!B33<=0.04,"✓ OK","⚠ HIGH — "&TEXT(INPUTS!B33,"0.0%")) -> ⚠ HIGH — 4.5% | C5: =IF(INPUTS!B33<=0.04,"Initial rate "&TEXT(INPUTS!B33,"0.0%")&" within guideline.","Exceeds 4% rule. At a 35+ yr horizon target 3.3%. Reduce spending or grow portfolio.") -> Exceeds 4% rule. At a 35+ yr horizon target 3.3%. Reduce spending or grow portfolio.
A6: Taxable funds entire bridge? | B6: =IF(INPUTS!$B$32=0,"✓ FUNDED",IF(SUM(BRIDGE!J4:K18)=0,"✓ FUNDED","⚠ GAP")) -> ✓ FUNDED | C6: =IF(INPUTS!$B$32=0,"No bridge needed — retiring at or after 59½.",IF(SUM(BRIDGE!J4:K18)=0,"Taxable+cash covers every bridge year.","Bridge dips into Roth/401k — see BRIDGE cols J–K for which years.")) -> Taxable+cash covers every bridge year.
A7: No 401k draws before 59½? | B7: =IF(INPUTS!$B$32=0,"✓ CLEAN",IF(SUM(BRIDGE!K4:K18)=0,"✓ CLEAN","✗ PENALTY RISK")) -> ✓ CLEAN | C7: =IF(INPUTS!$B$32=0,"No bridge — no early 401k withdrawals needed.",IF(SUM(BRIDGE!K4:K18)=0,"No early 401k withdrawals.","401k tapped during bridge = 10% penalty unless using 72(t). Total: "&TEXT(SUM(BRIDGE!K4:K18),"$#,##0"))) -> No early 401k withdrawals.
A8: Cash buffer ≥ 1 year? | B8: =IF(INPUTS!B18>=INPUTS!B22,"✓ OK","⚠ THIN") -> ✓ OK | C8: ="Cash covers "&TEXT(INPUTS!B18/INPUTS!B22,"0.0")&" years of spending. 1–2 yrs protects against selling in a downturn." -> Cash covers 1.4 years of spending. 1–2 yrs protects against selling in a downturn.
A9: ACA cliff clear in all bridge years? | B9: =IF(COUNTIF('ROTH LADDER'!G6:G20,"⚠*")=0,"✓ OK","⚠ "&COUNTIF('ROTH LADDER'!G6:G20,"⚠*")&" YR(S) OVER") -> ✓ OK | C9: =IF(COUNTIF('ROTH LADDER'!G6:G20,"⚠*")=0,"MAGI under est. 400% FPL cliff every bridge year.","Conversions push MAGI over the cliff in flagged years — trim those conversions. See ROTH LADDER col G.") -> MAGI under est. 400% FPL cliff every bridge year.
A10: SS delay opportunity | B10: =IF(INPUTS!B7<70,"💡 CONSIDER 70","✓ MAXED") -> 💡 CONSIDER 70 | C10: =IF(INPUTS!B7<70,"Delaying from "&INPUTS!B7&" to 70 adds ~"&TEXT(INPUTS!B25*0.08*(70-INPUTS!B7),"$#,##0")&"/yr permanently (8%/yr).","Claiming at 70 = maximum benefit.") -> Delaying from 67 to 70 adds ~$5,760/yr permanently (8%/yr).
A11: IRMAA Medicare trigger? | B11: =IF(INPUTS!B22+INPUTS!B24<IF(INPUTS!B9="MFJ",212000,106000),"✓ OK","⚠ REVIEW") -> ✓ OK | C11: ="2026 IRMAA starts at "&IF(INPUTS!B9="MFJ","$212,000 (MFJ)","$106,000 (Single)")&" MAGI. Large Roth conversions near Medicare age can trigger surcharges." -> 2026 IRMAA starts at $212,000 (MFJ) MAGI. Large Roth conversions near Medicare age can trigger surcharges.
A12: Portfolio survives to life expectancy? | B12: =IF(IFERROR('POST-59.5'!F42,0)>0,"✓ FUNDED","✗ DEPLETED") -> ✓ FUNDED | C12: =IF(IFERROR('POST-59.5'!F42,0)>0,"Projected "&TEXT('POST-59.5'!F42,"$#,##0")&" at age "&INPUTS!B8&".","Deterministic projection depletes — reduce spending or delay retirement.") -> Projected $2,880,896 at age 90.
A13: Monte Carlo success ≥ 80%? | B13: =IF('MONTE CARLO'!B211>=0.8,"✓ "&TEXT('MONTE CARLO'!B211,"0%"),"⚠ "&TEXT('MONTE CARLO'!B211,"0%")) -> ⚠ 71% | C13: =IF('MONTE CARLO'!B211>=0.9,"Robust across randomized sequences.",IF('MONTE CARLO'!B211>=0.75,"Acceptable — needs spending flexibility in bad markets.","Fragile — plan fails too often under sequence risk.")) -> Fragile — plan fails too often under sequence risk.

Sheet REBALANCE
A1: ANNUAL REBALANCE TRACKER
A2: Current Value column links to INPUTS balances — update the split below to match your actual holdings.
A4: Asset Class | B4: Target % | C4: Current Value | D4: Current % | E4: Drift | F4: Action
A5: US Total Market | B5: 0.4 | C5: =INPUTS!B15*0.6+INPUTS!B16*0.55+INPUTS!B17*0.7 -> 672500 | D5: =C5/$C$11 -> 0.54897959 | E5: =D5-B5 -> 0.14897959 | F5: =IF(E5<-0.05,"ADD — underweight",IF(E5>0.05,"TRIM — overweight","Hold")) -> TRIM — overweight
A6: International | B6: 0.15 | C6: =INPUTS!B15*0.25+INPUTS!B16*0.15 -> 185000 | D6: =C6/$C$11 -> 0.15102041 | E6: =D6-B6 -> 0.0010204082 | F6: =IF(E6<-0.05,"ADD — underweight",IF(E6>0.05,"TRIM — overweight","Hold")) -> Hold
A7: Small Cap Value | B7: 0.05 | C7: =INPUTS!B17*0.3 -> 45000 | D7: =C7/$C$11 -> 0.036734694 | E7: =D7-B7 -> -0.013265306 | F7: =IF(E7<-0.05,"ADD — underweight",IF(E7>0.05,"TRIM — overweight","Hold")) -> Hold
A8: Bonds (Total) | B8: 0.25 | C8: =INPUTS!B16*0.3 -> 195000 | D8: =C8/$C$11 -> 0.15918367 | E8: =D8-B8 -> -0.090816327 | F8: =IF(E8<-0.05,"ADD — underweight",IF(E8>0.05,"TRIM — overweight","Hold")) -> ADD — underweight
A9: Cash / MM | B9: 0.1 | C9: =INPUTS!B18 -> 75000 | D9: =C9/$C$11 -> 0.06122449 | E9: =D9-B9 -> -0.03877551 | F9: =IF(E9<-0.05,"ADD — underweight",IF(E9>0.05,"TRIM — overweight","Hold")) -> Hold
A10: Real Estate (REIT) | B10: 0.05 | C10: =INPUTS!B15*0.15 -> 52500 | D10: =C10/$C$11 -> 0.042857143 | E10: =D10-B10 -> -0.0071428571 | F10: =IF(E10<-0.05,"ADD — underweight",IF(E10>0.05,"TRIM — overweight","Hold")) -> Hold
A11: TOTAL | B11: =SUM(B5:B10) -> 1 | C11: =SUM(C5:C10) -> 1225000
A13: The default split is an estimate — overwrite Current Value cells with your real holdings for accurate drift.
