Workbook

Sheet COVER
B3: BridgeToRetired
B4: PRO RETIREMENT BRIDGE PLANNER
B5: Version 1.0 · 2026 Tax Year · bridgetoretired.com
B9: WHAT'S INSIDE
B11: INPUTS | C11: Enter your retirement assumptions — age, balances, spending, inflation
B12: BRIDGE | C12: Year-by-year bridge funding plan from retirement to age 59½
B13: ROTH LADDER | C13: Roth conversion schedule to minimize taxes across bridge years
B14: TAX ESTIMATE | C14: Federal tax estimate for each bridge year — bracket management
B15: POST-59½ | C15: Portfolio projection from 59½ through age 90
B16: RISK FLAGS | C16: Automated risk detection — sequence risk, ACA cliffs, IRMAA triggers
B17: REBALANCE | C17: Annual rebalance tracker — target vs actual allocation
B20: COLOR CODING GUIDE
B22: Blue text = Input cells — change these to your numbers
B23: Green text = Linked from another sheet
B24: Black text = Formula / calculated — do not edit
B25: Gold highlight = Key result or flag
B28: ⚠ Not financial advice. For modeling purposes only. Consult a fee-only advisor.

Sheet INPUTS
B2: RETIREMENT INPUTS
B3: Blue cells are inputs. Change any value and all sheets update automatically.
B5: PERSONAL DETAILS
B6: Current Age | C6: 52 | D6: Your age today
B7: Planned Retirement Age | C7: 55 | D7: Age you stop working
B8: Social Security Claiming Age | C8: 67 | D8: 62 / 67 / 70 recommended
B9: Life Expectancy (planning age) | C9: 90 | D9: Conservative = 90–95
B10: State of Residence | C10: TX | D10: Affects tax estimates
B12: PORTFOLIO BALANCES (TODAY)
B13: Taxable Brokerage Account | C13: 350000 | D13: Stocks, ETFs, index funds
B14: Traditional 401k / IRA | C14: 650000 | D14: Pre-tax retirement accounts
B15: Roth IRA / Roth 401k | C15: 150000 | D15: After-tax retirement accounts
B16: Cash / Money Market | C16: 75000 | D16: Emergency + bridge buffer
B17: Other Assets | C17: 0 | D17: Real estate equity, etc.
B19: TOTAL PORTFOLIO | C19: =SUM(C13:C17) -> 1225000
B21: SPENDING & INCOME
B22: Annual Spending (today's $) | C22: 55000 | D22: All living expenses
B23: Inflation Rate | C23: 0.025 | D23: 2.5% default
B24: Other Retirement Income | C24: 0 | D24: Pension, rental, part-time
B25: Estimated Social Security | C25: 24000 | D25: Annual SS at claiming age
B27: RETURN ASSUMPTIONS
B28: Portfolio Return (nominal) | C28: 0.065 | D28: 6.5% default
B29: Equity Allocation | C29: 0.65 | D29: 65% stocks default
B30: Bond / Cash Allocation | C30: =1-C29 -> 0.35 | D30: Auto-calculated
B32: BRIDGE METRICS (AUTO-CALCULATED)
B33: Bridge Length (years) | C33: =MAX(0,59.5-C7) -> 4.5
B34: Withdrawal Rate | C34: =C22/C19 -> 0.044897959
B35: Taxable Bridge Coverage | C35: =IFERROR(C13/(C22*C33),0) -> 1.4141414

Sheet BRIDGE
B2: BRIDGE FUNDING PLAN · Retirement to Age 59½
B3: Year | C3: Age | D3: Spending (Inflated) | E3: Taxable Withdrawal | F3: Roth Withdrawal | G3: Other Income | H3: Net Needed | I3: Taxable Balance | J3: Roth Balance | K3: 401k Balance | L3: Total Portfolio
B4: 1 | C4: =INPUTS!$C$7+0 -> 55 | D4: =INPUTS!$C$22*(1+INPUTS!$C$23)^0 -> 55000 | E4: =MIN(D4-INPUTS!$C$24,INPUTS!$C$13) -> 55000 | F4: 0 | G4: =INPUTS!$C$24 -> 0 | H4: =MAX(0,D4-E4-F4-G4) -> 0 | I4: =INPUTS!$C$13*(1+INPUTS!$C$28)-E4 -> 317750 | J4: =INPUTS!$C$15*(1+INPUTS!$C$28)-F4 -> 159750 | K4: =INPUTS!$C$14*(1+INPUTS!$C$28) -> 692250 | L4: =I4+J4+K4 -> 1169750
B5: 2 | C5: =INPUTS!$C$7+1 -> 56 | D5: =D4*(1+INPUTS!$C$23) -> 56375 | E5: =MIN(D5-INPUTS!$C$24,H4) -> 0 | F5: 0 | G5: =INPUTS!$C$24 -> 0 | H5: =MAX(0,D5-E5-F5-G5) -> 56375 | I5: =MAX(0,I4*(1+INPUTS!$C$28)-E5) -> 338403.75 | J5: =J4*(1+INPUTS!$C$28)-F5 -> 170133.75 | K5: =K4*(1+INPUTS!$C$28) -> 737246.25 | L5: =I5+J5+K5 -> 1245783.8
B6: 3 | C6: =INPUTS!$C$7+2 -> 57 | D6: =D5*(1+INPUTS!$C$23) -> 57784.375 | E6: =MIN(D6-INPUTS!$C$24,H5) -> 56375 | F6: 0 | G6: =INPUTS!$C$24 -> 0 | H6: =MAX(0,D6-E6-F6-G6) -> 1409.375 | I6: =MAX(0,I5*(1+INPUTS!$C$28)-E6) -> 304024.99 | J6: =J5*(1+INPUTS!$C$28)-F6 -> 181192.44 | K6: =K5*(1+INPUTS!$C$28) -> 785167.26 | L6: =I6+J6+K6 -> 1270384.7
B7: 4 | C7: =INPUTS!$C$7+3 -> 58 | D7: =D6*(1+INPUTS!$C$23) -> 59228.984 | E7: =MIN(D7-INPUTS!$C$24,H6) -> 1409.375 | F7: 0 | G7: =INPUTS!$C$24 -> 0 | H7: =MAX(0,D7-E7-F7-G7) -> 57819.609 | I7: =MAX(0,I6*(1+INPUTS!$C$28)-E7) -> 322377.24 | J7: =J6*(1+INPUTS!$C$28)-F7 -> 192969.95 | K7: =K6*(1+INPUTS!$C$28) -> 836203.13 | L7: =I7+J7+K7 -> 1351550.3
B8: 5 | C8: =INPUTS!$C$7+4 -> 59 | D8: =D7*(1+INPUTS!$C$23) -> 60709.709 | E8: =MIN(D8-INPUTS!$C$24,H7) -> 57819.609 | F8: 0 | G8: =INPUTS!$C$24 -> 0 | H8: =MAX(0,D8-E8-F8-G8) -> 2890.0996 | I8: =MAX(0,I7*(1+INPUTS!$C$28)-E8) -> 285512.15 | J8: =J7*(1+INPUTS!$C$28)-F8 -> 205513 | K8: =K7*(1+INPUTS!$C$28) -> 890556.33 | L8: =I8+J8+K8 -> 1381581.5
B9: 6 | C9: =INPUTS!$C$7+5 -> 60 | D9: =D8*(1+INPUTS!$C$23) -> 62227.452 | E9: =MIN(D9-INPUTS!$C$24,H8) -> 2890.0996 | F9: 0 | G9: =INPUTS!$C$24 -> 0 | H9: =MAX(0,D9-E9-F9-G9) -> 59337.352 | I9: =MAX(0,I8*(1+INPUTS!$C$28)-E9) -> 301180.35 | J9: =J8*(1+INPUTS!$C$28)-F9 -> 218871.34 | K9: =K8*(1+INPUTS!$C$28) -> 948442.49 | L9: =I9+J9+K9 -> 1468494.2
B10: 7 | C10: =INPUTS!$C$7+6 -> 61 | D10: =D9*(1+INPUTS!$C$23) -> 63783.138 | E10: =MIN(D10-INPUTS!$C$24,H9) -> 59337.352 | F10: 0 | G10: =INPUTS!$C$24 -> 0 | H10: =MAX(0,D10-E10-F10-G10) -> 4445.7859 | I10: =MAX(0,I9*(1+INPUTS!$C$28)-E10) -> 261419.72 | J10: =J9*(1+INPUTS!$C$28)-F10 -> 233097.98 | K10: =K9*(1+INPUTS!$C$28) -> 1010091.3 | L10: =I10+J10+K10 -> 1504609
B11: 8 | C11: =INPUTS!$C$7+7 -> 62 | D11: =D10*(1+INPUTS!$C$23) -> 65377.716 | E11: =MIN(D11-INPUTS!$C$24,H10) -> 4445.7859 | F11: 0 | G11: =INPUTS!$C$24 -> 0 | H11: =MAX(0,D11-E11-F11-G11) -> 60931.931 | I11: =MAX(0,I10*(1+INPUTS!$C$28)-E11) -> 273966.21 | J11: =J10*(1+INPUTS!$C$28)-F11 -> 248249.35 | K11: =K10*(1+INPUTS!$C$28) -> 1075747.2 | L11: =I11+J11+K11 -> 1597962.7
B12: 9 | C12: =INPUTS!$C$7+8 -> 63 | D12: =D11*(1+INPUTS!$C$23) -> 67012.159 | E12: =MIN(D12-INPUTS!$C$24,H11) -> 60931.931 | F12: 0 | G12: =INPUTS!$C$24 -> 0 | H12: =MAX(0,D12-E12-F12-G12) -> 6080.2288 | I12: =MAX(0,I11*(1+INPUTS!$C$28)-E12) -> 230842.08 | J12: =J11*(1+INPUTS!$C$28)-F12 -> 264385.56 | K12: =K11*(1+INPUTS!$C$28) -> 1145670.8 | L12: =I12+J12+K12 -> 1640898.4
B13: 10 | C13: =INPUTS!$C$7+9 -> 64 | D13: =D12*(1+INPUTS!$C$23) -> 68687.463 | E13: =MIN(D13-INPUTS!$C$24,H12) -> 6080.2288 | F13: 0 | G13: =INPUTS!$C$24 -> 0 | H13: =MAX(0,D13-E13-F13-G13) -> 62607.235 | I13: =MAX(0,I12*(1+INPUTS!$C$28)-E13) -> 239766.59 | J13: =J12*(1+INPUTS!$C$28)-F13 -> 281570.62 | K13: =K12*(1+INPUTS!$C$28) -> 1220139.4 | L13: =I13+J13+K13 -> 1741476.6
B14: 11 | C14: =INPUTS!$C$7+10 -> 65 | D14: =D13*(1+INPUTS!$C$23) -> 70404.65 | E14: =MIN(D14-INPUTS!$C$24,H13) -> 62607.235 | F14: 0 | G14: =INPUTS!$C$24 -> 0 | H14: =MAX(0,D14-E14-F14-G14) -> 7797.4154 | I14: =MAX(0,I13*(1+INPUTS!$C$28)-E14) -> 192744.18 | J14: =J13*(1+INPUTS!$C$28)-F14 -> 299872.71 | K14: =K13*(1+INPUTS!$C$28) -> 1299448.4 | L14: =I14+J14+K14 -> 1792065.3
B15: 12 | C15: =INPUTS!$C$7+11 -> 66 | D15: =D14*(1+INPUTS!$C$23) -> 72164.766 | E15: =MIN(D15-INPUTS!$C$24,H14) -> 7797.4154 | F15: 0 | G15: =INPUTS!$C$24 -> 0 | H15: =MAX(0,D15-E15-F15-G15) -> 64367.351 | I15: =MAX(0,I14*(1+INPUTS!$C$28)-E15) -> 197475.14 | J15: =J14*(1+INPUTS!$C$28)-F15 -> 319364.44 | K15: =K14*(1+INPUTS!$C$28) -> 1383912.6 | L15: =I15+J15+K15 -> 1900752.1
B16: 13 | C16: =INPUTS!$C$7+12 -> 67 | D16: =D15*(1+INPUTS!$C$23) -> 73968.885 | E16: =MIN(D16-INPUTS!$C$24,H15) -> 64367.351 | F16: 0 | G16: =INPUTS!$C$24 -> 0 | H16: =MAX(0,D16-E16-F16-G16) -> 9601.5346 | I16: =MAX(0,I15*(1+INPUTS!$C$28)-E16) -> 145943.67 | J16: =J15*(1+INPUTS!$C$28)-F16 -> 340123.12 | K16: =K15*(1+INPUTS!$C$28) -> 1473866.9 | L16: =I16+J16+K16 -> 1959933.7
B17: 14 | C17: =INPUTS!$C$7+13 -> 68 | D17: =D16*(1+INPUTS!$C$23) -> 75818.107 | E17: =MIN(D17-INPUTS!$C$24,H16) -> 9601.5346 | F17: 0 | G17: =INPUTS!$C$24 -> 0 | H17: =MAX(0,D17-E17-F17-G17) -> 66216.573 | I17: =MAX(0,I16*(1+INPUTS!$C$28)-E17) -> 145828.48 | J17: =J16*(1+INPUTS!$C$28)-F17 -> 362231.13 | K17: =K16*(1+INPUTS!$C$28) -> 1569668.2 | L17: =I17+J17+K17 -> 2077727.8
B18: 15 | C18: =INPUTS!$C$7+14 -> 69 | D18: =D17*(1+INPUTS!$C$23) -> 77713.56 | E18: =MIN(D18-INPUTS!$C$24,H17) -> 66216.573 | F18: 0 | G18: =INPUTS!$C$24 -> 0 | H18: =MAX(0,D18-E18-F18-G18) -> 11496.987 | I18: =MAX(0,I17*(1+INPUTS!$C$28)-E18) -> 89090.758 | J18: =J17*(1+INPUTS!$C$28)-F18 -> 385776.15 | K18: =K17*(1+INPUTS!$C$28) -> 1671696.7 | L18: =I18+J18+K18 -> 2146563.6
B19: 16 | C19: =INPUTS!$C$7+15 -> 70 | D19: =D18*(1+INPUTS!$C$23) -> 79656.399 | E19: =MIN(D19-INPUTS!$C$24,H18) -> 11496.987 | F19: 0 | G19: =INPUTS!$C$24 -> 0 | H19: =MAX(0,D19-E19-F19-G19) -> 68159.412 | I19: =MAX(0,I18*(1+INPUTS!$C$28)-E19) -> 83384.67 | J19: =J18*(1+INPUTS!$C$28)-F19 -> 410851.6 | K19: =K18*(1+INPUTS!$C$28) -> 1780356.9 | L19: =I19+J19+K19 -> 2274593.2
B20: 17 | C20: =INPUTS!$C$7+16 -> 71 | D20: =D19*(1+INPUTS!$C$23) -> 81647.809 | E20: =MIN(D20-INPUTS!$C$24,H19) -> 68159.412 | F20: 0 | G20: =INPUTS!$C$24 -> 0 | H20: =MAX(0,D20-E20-F20-G20) -> 13488.397 | I20: =MAX(0,I19*(1+INPUTS!$C$28)-E20) -> 20645.261 | J20: =J19*(1+INPUTS!$C$28)-F20 -> 437556.95 | K20: =K19*(1+INPUTS!$C$28) -> 1896080.1 | L20: =I20+J20+K20 -> 2354282.4
B21: 18 | C21: =INPUTS!$C$7+17 -> 72 | D21: =D20*(1+INPUTS!$C$23) -> 83689.004 | E21: =MIN(D21-INPUTS!$C$24,H20) -> 13488.397 | F21: 0 | G21: =INPUTS!$C$24 -> 0 | H21: =MAX(0,D21-E21-F21-G21) -> 70200.607 | I21: =MAX(0,I20*(1+INPUTS!$C$28)-E21) -> 8498.8059 | J21: =J20*(1+INPUTS!$C$28)-F21 -> 465998.16 | K21: =K20*(1+INPUTS!$C$28) -> 2019325.3 | L21: =I21+J21+K21 -> 2493822.3
B22: 19 | C22: =INPUTS!$C$7+18 -> 73 | D22: =D21*(1+INPUTS!$C$23) -> 85781.229 | E22: =MIN(D22-INPUTS!$C$24,H21) -> 70200.607 | F22: 0 | G22: =INPUTS!$C$24 -> 0 | H22: =MAX(0,D22-E22-F22-G22) -> 15580.622 | I22: =MAX(0,I21*(1+INPUTS!$C$28)-E22) -> 0 | J22: =J21*(1+INPUTS!$C$28)-F22 -> 496288.04 | K22: =K21*(1+INPUTS!$C$28) -> 2150581.5 | L22: =I22+J22+K22 -> 2646869.5
B23: 20 | C23: =INPUTS!$C$7+19 -> 74 | D23: =D22*(1+INPUTS!$C$23) -> 87925.76 | E23: =MIN(D23-INPUTS!$C$24,H22) -> 15580.622 | F23: 0 | G23: =INPUTS!$C$24 -> 0 | H23: =MAX(0,D23-E23-F23-G23) -> 72345.138 | I23: =MAX(0,I22*(1+INPUTS!$C$28)-E23) -> 0 | J23: =J22*(1+INPUTS!$C$28)-F23 -> 528546.76 | K23: =K22*(1+INPUTS!$C$28) -> 2290369.3 | L23: =I23+J23+K23 -> 2818916.1

Sheet TAX ESTIMATE
B2: FEDERAL TAX ESTIMATE · Bridge Years
B3: Simplified estimate — single filer. Consult CPA for full tax planning.
B5: 2026 FEDERAL TAX BRACKETS (Married Filing Jointly)
B6: Rate | C6: From | D6: To
B7: 10% | C7: 0 | D7: 23850
B8: 12% | C8: 23850 | D8: 96950
B9: 22% | C9: 96950 | D9: 206700
B10: 24% | C10: 206700 | D10: 394600
B11: 32% | C11: 394600 | D11: 501050
B12: 35% | C12: 501050 | D12: 751600
B13: 37% | C13: 751600 | D13: No limit
B17: ESTIMATED TAX BY YEAR
B18: Year | C18: Gross Income | D18: Std Deduction | E18: Taxable Income | F18: Est. Tax
B19: 1 | C19: =BRIDGE!E4+BRIDGE!F4+INPUTS!$C$24 -> 55000 | D19: 29200 | E19: =MAX(0,C19-D19) -> 25800 | F19: =IF(E19<=23850,E19*0.1,IF(E19<=96950,2385+(E19-23850)*0.12,IF(E19<=206700,11142+(E19-96950)*0.22,2385+(E19-23850)*0.12))) -> 2619
B20: 2 | C20: =BRIDGE!E5+BRIDGE!F5+INPUTS!$C$24 -> 0 | D20: 29200 | E20: =MAX(0,C20-D20) -> 0 | F20: =IF(E20<=23850,E20*0.1,IF(E20<=96950,2385+(E20-23850)*0.12,IF(E20<=206700,11142+(E20-96950)*0.22,2385+(E20-23850)*0.12))) -> 0
B21: 3 | C21: =BRIDGE!E6+BRIDGE!F6+INPUTS!$C$24 -> 56375 | D21: 29200 | E21: =MAX(0,C21-D21) -> 27175 | F21: =IF(E21<=23850,E21*0.1,IF(E21<=96950,2385+(E21-23850)*0.12,IF(E21<=206700,11142+(E21-96950)*0.22,2385+(E21-23850)*0.12))) -> 2784
B22: 4 | C22: =BRIDGE!E7+BRIDGE!F7+INPUTS!$C$24 -> 1409.375 | D22: 29200 | E22: =MAX(0,C22-D22) -> 0 | F22: =IF(E22<=23850,E22*0.1,IF(E22<=96950,2385+(E22-23850)*0.12,IF(E22<=206700,11142+(E22-96950)*0.22,2385+(E22-23850)*0.12))) -> 0
B23: 5 | C23: =BRIDGE!E8+BRIDGE!F8+INPUTS!$C$24 -> 57819.609 | D23: 29200 | E23: =MAX(0,C23-D23) -> 28619.609 | F23: =IF(E23<=23850,E23*0.1,IF(E23<=96950,2385+(E23-23850)*0.12,IF(E23<=206700,11142+(E23-96950)*0.22,2385+(E23-23850)*0.12))) -> 2957.3531
B24: 6 | C24: =BRIDGE!E9+BRIDGE!F9+INPUTS!$C$24 -> 2890.0996 | D24: 29200 | E24: =MAX(0,C24-D24) -> 0 | F24: =IF(E24<=23850,E24*0.1,IF(E24<=96950,2385+(E24-23850)*0.12,IF(E24<=206700,11142+(E24-96950)*0.22,2385+(E24-23850)*0.12))) -> 0
B25: 7 | C25: =BRIDGE!E10+BRIDGE!F10+INPUTS!$C$24 -> 59337.352 | D25: 29200 | E25: =MAX(0,C25-D25) -> 30137.352 | F25: =IF(E25<=23850,E25*0.1,IF(E25<=96950,2385+(E25-23850)*0.12,IF(E25<=206700,11142+(E25-96950)*0.22,2385+(E25-23850)*0.12))) -> 3139.4823
B26: 8 | C26: =BRIDGE!E11+BRIDGE!F11+INPUTS!$C$24 -> 4445.7859 | D26: 29200 | E26: =MAX(0,C26-D26) -> 0 | F26: =IF(E26<=23850,E26*0.1,IF(E26<=96950,2385+(E26-23850)*0.12,IF(E26<=206700,11142+(E26-96950)*0.22,2385+(E26-23850)*0.12))) -> 0
B27: 9 | C27: =BRIDGE!E12+BRIDGE!F12+INPUTS!$C$24 -> 60931.931 | D27: 29200 | E27: =MAX(0,C27-D27) -> 31731.931 | F27: =IF(E27<=23850,E27*0.1,IF(E27<=96950,2385+(E27-23850)*0.12,IF(E27<=206700,11142+(E27-96950)*0.22,2385+(E27-23850)*0.12))) -> 3330.8317
B28: 10 | C28: =BRIDGE!E13+BRIDGE!F13+INPUTS!$C$24 -> 6080.2288 | D28: 29200 | E28: =MAX(0,C28-D28) -> 0 | F28: =IF(E28<=23850,E28*0.1,IF(E28<=96950,2385+(E28-23850)*0.12,IF(E28<=206700,11142+(E28-96950)*0.22,2385+(E28-23850)*0.12))) -> 0

Sheet ROTH LADDER
B2: ROTH CONVERSION LADDER · 5-Year Pipeline
B3: Convert Traditional 401k/IRA to Roth each year. Conversions are accessible penalty-free after 5 years.
B5: Year | C5: Age | D5: 12% Bracket Remaining | E5: Conversion Amount | F5: Tax on Conversion | G5: Net Roth Added | H5: Roth Balance | I5: Available (5yr later)
B6: 1 | C6: =INPUTS!$C$7+0 -> 55 | D6: =MAX(0,96950-'TAX ESTIMATE'!C19) -> 41950 | E6: 0 | F6: =E6*0.12 -> 0 | G6: =E6-F6 -> 0 | H6: =INPUTS!$C$15+G6 -> 150000 | I6: Not yet available
B7: 2 | C7: =INPUTS!$C$7+1 -> 56 | D7: =MAX(0,96950-'TAX ESTIMATE'!C20) -> 96950 | E7: 0 | F7: =E7*0.12 -> 0 | G7: =E7-F7 -> 0 | H7: =H6*(1+INPUTS!$C$28)+G7 -> 159750 | I7: Not yet available
B8: 3 | C8: =INPUTS!$C$7+2 -> 57 | D8: =MAX(0,96950-'TAX ESTIMATE'!C21) -> 40575 | E8: 0 | F8: =E8*0.12 -> 0 | G8: =E8-F8 -> 0 | H8: =H7*(1+INPUTS!$C$28)+G8 -> 170133.75 | I8: Not yet available
B9: 4 | C9: =INPUTS!$C$7+3 -> 58 | D9: =MAX(0,96950-'TAX ESTIMATE'!C22) -> 95540.625 | E9: 0 | F9: =E9*0.12 -> 0 | G9: =E9-F9 -> 0 | H9: =H8*(1+INPUTS!$C$28)+G9 -> 181192.44 | I9: Not yet available
B10: 5 | C10: =INPUTS!$C$7+4 -> 59 | D10: =MAX(0,96950-'TAX ESTIMATE'!C23) -> 39130.391 | E10: 0 | F10: =E10*0.12 -> 0 | G10: =E10-F10 -> 0 | H10: =H9*(1+INPUTS!$C$28)+G10 -> 192969.95 | I10: Not yet available
B11: 6 | C11: =INPUTS!$C$7+5 -> 60 | D11: =MAX(0,96950-'TAX ESTIMATE'!C24) -> 94059.9 | E11: 0 | F11: =E11*0.12 -> 0 | G11: =E11-F11 -> 0 | H11: =H10*(1+INPUTS!$C$28)+G11 -> 205513 | I11: =G6 -> 0
B12: 7 | C12: =INPUTS!$C$7+6 -> 61 | D12: =MAX(0,96950-'TAX ESTIMATE'!C25) -> 37612.648 | E12: 0 | F12: =E12*0.12 -> 0 | G12: =E12-F12 -> 0 | H12: =H11*(1+INPUTS!$C$28)+G12 -> 218871.34 | I12: =G7 -> 0
B13: 8 | C13: =INPUTS!$C$7+7 -> 62 | D13: =MAX(0,96950-'TAX ESTIMATE'!C26) -> 92504.214 | E13: 0 | F13: =E13*0.12 -> 0 | G13: =E13-F13 -> 0 | H13: =H12*(1+INPUTS!$C$28)+G13 -> 233097.98 | I13: =G8 -> 0
B14: 9 | C14: =INPUTS!$C$7+8 -> 63 | D14: =MAX(0,96950-'TAX ESTIMATE'!C27) -> 36018.069 | E14: 0 | F14: =E14*0.12 -> 0 | G14: =E14-F14 -> 0 | H14: =H13*(1+INPUTS!$C$28)+G14 -> 248249.35 | I14: =G9 -> 0
B15: 10 | C15: =INPUTS!$C$7+9 -> 64 | D15: =MAX(0,96950-'TAX ESTIMATE'!C28) -> 90869.771 | E15: 0 | F15: =E15*0.12 -> 0 | G15: =E15-F15 -> 0 | H15: =H14*(1+INPUTS!$C$28)+G15 -> 264385.56 | I15: =G10 -> 0
B16: 11 | C16: =INPUTS!$C$7+10 -> 65 | D16: =MAX(0,96950-'TAX ESTIMATE'!C29) -> 96950 | E16: 0 | F16: =E16*0.12 -> 0 | G16: =E16-F16 -> 0 | H16: =H15*(1+INPUTS!$C$28)+G16 -> 281570.62 | I16: =G11 -> 0
B17: 12 | C17: =INPUTS!$C$7+11 -> 66 | D17: =MAX(0,96950-'TAX ESTIMATE'!C30) -> 96950 | E17: 0 | F17: =E17*0.12 -> 0 | G17: =E17-F17 -> 0 | H17: =H16*(1+INPUTS!$C$28)+G17 -> 299872.71 | I17: =G12 -> 0
B18: 13 | C18: =INPUTS!$C$7+12 -> 67 | D18: =MAX(0,96950-'TAX ESTIMATE'!C31) -> 96950 | E18: 0 | F18: =E18*0.12 -> 0 | G18: =E18-F18 -> 0 | H18: =H17*(1+INPUTS!$C$28)+G18 -> 319364.44 | I18: =G13 -> 0
B19: 14 | C19: =INPUTS!$C$7+13 -> 68 | D19: =MAX(0,96950-'TAX ESTIMATE'!C32) -> 96950 | E19: 0 | F19: =E19*0.12 -> 0 | G19: =E19-F19 -> 0 | H19: =H18*(1+INPUTS!$C$28)+G19 -> 340123.12 | I19: =G14 -> 0
B20: 15 | C20: =INPUTS!$C$7+14 -> 69 | D20: =MAX(0,96950-'TAX ESTIMATE'!C33) -> 96950 | E20: 0 | F20: =E20*0.12 -> 0 | G20: =E20-F20 -> 0 | H20: =H19*(1+INPUTS!$C$28)+G20 -> 362231.13 | I20: =G15 -> 0

Sheet POST-59½
B2: POST-59½ PROJECTION · Full Portfolio Access Phase
B4: Year | C4: Age | D4: Spending | E4: SS Income | F4: Portfolio Withdrawal | G4: Taxable Balance | H4: 401k Balance | I4: Total Portfolio
B5: 1 | C5: 60 | D5: =INPUTS!$C$22*(1+INPUTS!$C$23)^(MAX(0,59.5-INPUTS!$C$7)+0) -> 61463.896 | E5: =IF(60>=INPUTS!$C$8,INPUTS!$C$25*(1+INPUTS!$C$23)^(60-INPUTS!$C$8),0) -> 0 | F5: =MAX(0,D5-E5-INPUTS!$C$24) -> 61463.896 | G5: =MAX(0,BRIDGE!I23*(1+INPUTS!$C$28)-F5) -> 0 | H5: =BRIDGE!K23*(1+INPUTS!$C$28) -> 2439243.3 | I5: =G5+H5 -> 2439243.3
B6: 2 | C6: 61 | D6: =INPUTS!$C$22*(1+INPUTS!$C$23)^(MAX(0,59.5-INPUTS!$C$7)+1) -> 63000.493 | E6: =IF(61>=INPUTS!$C$8,INPUTS!$C$25*(1+INPUTS!$C$23)^(61-INPUTS!$C$8),0) -> 0 | F6: =MAX(0,D6-E6-INPUTS!$C$24) -> 63000.493 | G6: =MAX(0,G5*(1+INPUTS!$C$28)-F6) -> 0 | H6: =MAX(0,H5*(1+INPUTS!$C$28)-MAX(0,F6-G5)) -> 2534793.6 | I6: =G6+H6 -> 2534793.6
B7: 3 | C7: 62 | D7: =INPUTS!$C$22*(1+INPUTS!$C$23)^(MAX(0,59.5-INPUTS!$C$7)+2) -> 64575.506 | E7: =IF(62>=INPUTS!$C$8,INPUTS!$C$25*(1+INPUTS!$C$23)^(62-INPUTS!$C$8),0) -> 0 | F7: =MAX(0,D7-E7-INPUTS!$C$24) -> 64575.506 | G7: =MAX(0,G6*(1+INPUTS!$C$28)-F7) -> 0 | H7: =MAX(0,H6*(1+INPUTS!$C$28)-MAX(0,F7-G6)) -> 2634979.7 | I7: =G7+H7 -> 2634979.7
B8: 4 | C8: 63 | D8: =INPUTS!$C$22*(1+INPUTS!$C$23)^(MAX(0,59.5-INPUTS!$C$7)+3) -> 66189.893 | E8: =IF(63>=INPUTS!$C$8,INPUTS!$C$25*(1+INPUTS!$C$23)^(63-INPUTS!$C$8),0) -> 0 | F8: =MAX(0,D8-E8-INPUTS!$C$24) -> 66189.893 | G8: =MAX(0,G7*(1+INPUTS!$C$28)-F8) -> 0 | H8: =MAX(0,H7*(1+INPUTS!$C$28)-MAX(0,F8-G7)) -> 2740063.5 | I8: =G8+H8 -> 2740063.5
B9: 5 | C9: 64 | D9: =INPUTS!$C$22*(1+INPUTS!$C$23)^(MAX(0,59.5-INPUTS!$C$7)+4) -> 67844.64 | E9: =IF(64>=INPUTS!$C$8,INPUTS!$C$25*(1+INPUTS!$C$23)^(64-INPUTS!$C$8),0) -> 0 | F9: =MAX(0,D9-E9-INPUTS!$C$24) -> 67844.64 | G9: =MAX(0,G8*(1+INPUTS!$C$28)-F9) -> 0 | H9: =MAX(0,H8*(1+INPUTS!$C$28)-MAX(0,F9-G8)) -> 2850323 | I9: =G9+H9 -> 2850323
B10: 6 | C10: 65 | D10: =INPUTS!$C$22*(1+INPUTS!$C$23)^(MAX(0,59.5-INPUTS!$C$7)+5) -> 69540.756 | E10: =IF(65>=INPUTS!$C$8,INPUTS!$C$25*(1+INPUTS!$C$23)^(65-INPUTS!$C$8),0) -> 0 | F10: =MAX(0,D10-E10-INPUTS!$C$24) -> 69540.756 | G10: =MAX(0,G9*(1+INPUTS!$C$28)-F10) -> 0 | H10: =MAX(0,H9*(1+INPUTS!$C$28)-MAX(0,F10-G9)) -> 2966053.2 | I10: =G10+H10 -> 2966053.2
B11: 7 | C11: 66 | D11: =INPUTS!$C$22*(1+INPUTS!$C$23)^(MAX(0,59.5-INPUTS!$C$7)+6) -> 71279.275 | E11: =IF(66>=INPUTS!$C$8,INPUTS!$C$25*(1+INPUTS!$C$23)^(66-INPUTS!$C$8),0) -> 0 | F11: =MAX(0,D11-E11-INPUTS!$C$24) -> 71279.275 | G11: =MAX(0,G10*(1+INPUTS!$C$28)-F11) -> 0 | H11: =MAX(0,H10*(1+INPUTS!$C$28)-MAX(0,F11-G10)) -> 3087567.4 | I11: =G11+H11 -> 3087567.4
B12: 8 | C12: 67 | D12: =INPUTS!$C$22*(1+INPUTS!$C$23)^(MAX(0,59.5-INPUTS!$C$7)+7) -> 73061.257 | E12: =IF(67>=INPUTS!$C$8,INPUTS!$C$25*(1+INPUTS!$C$23)^(67-INPUTS!$C$8),0) -> 24000 | F12: =MAX(0,D12-E12-INPUTS!$C$24) -> 49061.257 | G12: =MAX(0,G11*(1+INPUTS!$C$28)-F12) -> 0 | H12: =MAX(0,H11*(1+INPUTS!$C$28)-MAX(0,F12-G11)) -> 3239198 | I12: =G12+H12 -> 3239198
B13: 9 | C13: 68 | D13: =INPUTS!$C$22*(1+INPUTS!$C$23)^(MAX(0,59.5-INPUTS!$C$7)+8) -> 74887.789 | E13: =IF(68>=INPUTS!$C$8,INPUTS!$C$25*(1+INPUTS!$C$23)^(68-INPUTS!$C$8),0) -> 24600 | F13: =MAX(0,D13-E13-INPUTS!$C$24) -> 50287.789 | G13: =MAX(0,G12*(1+INPUTS!$C$28)-F13) -> 0 | H13: =MAX(0,H12*(1+INPUTS!$C$28)-MAX(0,F13-G12)) -> 3399458.1 | I13: =G13+H13 -> 3399458.1
B14: 10 | C14: 69 | D14: =INPUTS!$C$22*(1+INPUTS!$C$23)^(MAX(0,59.5-INPUTS!$C$7)+9) -> 76759.983 | E14: =IF(69>=INPUTS!$C$8,INPUTS!$C$25*(1+INPUTS!$C$23)^(69-INPUTS!$C$8),0) -> 25215 | F14: =MAX(0,D14-E14-INPUTS!$C$24) -> 51544.983 | G14: =MAX(0,G13*(1+INPUTS!$C$28)-F14) -> 0 | H14: =MAX(0,H13*(1+INPUTS!$C$28)-MAX(0,F14-G13)) -> 3568877.9 | I14: =G14+H14 -> 3568877.9
B15: 11 | C15: 70 | D15: =INPUTS!$C$22*(1+INPUTS!$C$23)^(MAX(0,59.5-INPUTS!$C$7)+10) -> 78678.983 | E15: =IF(70>=INPUTS!$C$8,INPUTS!$C$25*(1+INPUTS!$C$23)^(70-INPUTS!$C$8),0) -> 25845.375 | F15: =MAX(0,D15-E15-INPUTS!$C$24) -> 52833.608 | G15: =MAX(0,G14*(1+INPUTS!$C$28)-F15) -> 0 | H15: =MAX(0,H14*(1+INPUTS!$C$28)-MAX(0,F15-G14)) -> 3748021.3 | I15: =G15+H15 -> 3748021.3
B16: 12 | C16: 71 | D16: =INPUTS!$C$22*(1+INPUTS!$C$23)^(MAX(0,59.5-INPUTS!$C$7)+11) -> 80645.958 | E16: =IF(71>=INPUTS!$C$8,INPUTS!$C$25*(1+INPUTS!$C$23)^(71-INPUTS!$C$8),0) -> 26491.509 | F16: =MAX(0,D16-E16-INPUTS!$C$24) -> 54154.448 | G16: =MAX(0,G15*(1+INPUTS!$C$28)-F16) -> 0 | H16: =MAX(0,H15*(1+INPUTS!$C$28)-MAX(0,F16-G15)) -> 3937488.3 | I16: =G16+H16 -> 3937488.3
B17: 13 | C17: 72 | D17: =INPUTS!$C$22*(1+INPUTS!$C$23)^(MAX(0,59.5-INPUTS!$C$7)+12) -> 82662.107 | E17: =IF(72>=INPUTS!$C$8,INPUTS!$C$25*(1+INPUTS!$C$23)^(72-INPUTS!$C$8),0) -> 27153.797 | F17: =MAX(0,D17-E17-INPUTS!$C$24) -> 55508.309 | G17: =MAX(0,G16*(1+INPUTS!$C$28)-F17) -> 0 | H17: =MAX(0,H16*(1+INPUTS!$C$28)-MAX(0,F17-G16)) -> 4137916.7 | I17: =G17+H17 -> 4137916.7
B18: 14 | C18: 73 | D18: =INPUTS!$C$22*(1+INPUTS!$C$23)^(MAX(0,59.5-INPUTS!$C$7)+13) -> 84728.659 | E18: =IF(73>=INPUTS!$C$8,INPUTS!$C$25*(1+INPUTS!$C$23)^(73-INPUTS!$C$8),0) -> 27832.642 | F18: =MAX(0,D18-E18-INPUTS!$C$24) -> 56896.017 | G18: =MAX(0,G17*(1+INPUTS!$C$28)-F18) -> 0 | H18: =MAX(0,H17*(1+INPUTS!$C$28)-MAX(0,F18-G17)) -> 4349985.3 | I18: =G18+H18 -> 4349985.3
B19: 15 | C19: 74 | D19: =INPUTS!$C$22*(1+INPUTS!$C$23)^(MAX(0,59.5-INPUTS!$C$7)+14) -> 86846.876 | E19: =IF(74>=INPUTS!$C$8,INPUTS!$C$25*(1+INPUTS!$C$23)^(74-INPUTS!$C$8),0) -> 28528.458 | F19: =MAX(0,D19-E19-INPUTS!$C$24) -> 58318.418 | G19: =MAX(0,G18*(1+INPUTS!$C$28)-F19) -> 0 | H19: =MAX(0,H18*(1+INPUTS!$C$28)-MAX(0,F19-G18)) -> 4574415.9 | I19: =G19+H19 -> 4574415.9
B20: 16 | C20: 75 | D20: =INPUTS!$C$22*(1+INPUTS!$C$23)^(MAX(0,59.5-INPUTS!$C$7)+15) -> 89018.048 | E20: =IF(75>=INPUTS!$C$8,INPUTS!$C$25*(1+INPUTS!$C$23)^(75-INPUTS!$C$8),0) -> 29241.67 | F20: =MAX(0,D20-E20-INPUTS!$C$24) -> 59776.378 | G20: =MAX(0,G19*(1+INPUTS!$C$28)-F20) -> 0 | H20: =MAX(0,H19*(1+INPUTS!$C$28)-MAX(0,F20-G19)) -> 4811976.6 | I20: =G20+H20 -> 4811976.6
B21: 17 | C21: 76 | D21: =INPUTS!$C$22*(1+INPUTS!$C$23)^(MAX(0,59.5-INPUTS!$C$7)+16) -> 91243.499 | E21: =IF(76>=INPUTS!$C$8,INPUTS!$C$25*(1+INPUTS!$C$23)^(76-INPUTS!$C$8),0) -> 29972.711 | F21: =MAX(0,D21-E21-INPUTS!$C$24) -> 61270.787 | G21: =MAX(0,G20*(1+INPUTS!$C$28)-F21) -> 0 | H21: =MAX(0,H20*(1+INPUTS!$C$28)-MAX(0,F21-G20)) -> 5063484.2 | I21: =G21+H21 -> 5063484.2
B22: 18 | C22: 77 | D22: =INPUTS!$C$22*(1+INPUTS!$C$23)^(MAX(0,59.5-INPUTS!$C$7)+17) -> 93524.586 | E22: =IF(77>=INPUTS!$C$8,INPUTS!$C$25*(1+INPUTS!$C$23)^(77-INPUTS!$C$8),0) -> 30722.029 | F22: =MAX(0,D22-E22-INPUTS!$C$24) -> 62802.557 | G22: =MAX(0,G21*(1+INPUTS!$C$28)-F22) -> 0 | H22: =MAX(0,H21*(1+INPUTS!$C$28)-MAX(0,F22-G21)) -> 5329808.2 | I22: =G22+H22 -> 5329808.2
B23: 19 | C23: 78 | D23: =INPUTS!$C$22*(1+INPUTS!$C$23)^(MAX(0,59.5-INPUTS!$C$7)+18) -> 95862.701 | E23: =IF(78>=INPUTS!$C$8,INPUTS!$C$25*(1+INPUTS!$C$23)^(78-INPUTS!$C$8),0) -> 31490.08 | F23: =MAX(0,D23-E23-INPUTS!$C$24) -> 64372.621 | G23: =MAX(0,G22*(1+INPUTS!$C$28)-F23) -> 0 | H23: =MAX(0,H22*(1+INPUTS!$C$28)-MAX(0,F23-G22)) -> 5611873.1 | I23: =G23+H23 -> 5611873.1
B24: 20 | C24: 79 | D24: =INPUTS!$C$22*(1+INPUTS!$C$23)^(MAX(0,59.5-INPUTS!$C$7)+19) -> 98259.268 | E24: =IF(79>=INPUTS!$C$8,INPUTS!$C$25*(1+INPUTS!$C$23)^(79-INPUTS!$C$8),0) -> 32277.332 | F24: =MAX(0,D24-E24-INPUTS!$C$24) -> 65981.937 | G24: =MAX(0,G23*(1+INPUTS!$C$28)-F24) -> 0 | H24: =MAX(0,H23*(1+INPUTS!$C$28)-MAX(0,F24-G23)) -> 5910662.9 | I24: =G24+H24 -> 5910662.9
B25: 21 | C25: 80 | D25: =INPUTS!$C$22*(1+INPUTS!$C$23)^(MAX(0,59.5-INPUTS!$C$7)+20) -> 100715.75 | E25: =IF(80>=INPUTS!$C$8,INPUTS!$C$25*(1+INPUTS!$C$23)^(80-INPUTS!$C$8),0) -> 33084.265 | F25: =MAX(0,D25-E25-INPUTS!$C$24) -> 67631.485 | G25: =MAX(0,G24*(1+INPUTS!$C$28)-F25) -> 0 | H25: =MAX(0,H24*(1+INPUTS!$C$28)-MAX(0,F25-G24)) -> 6227224.5 | I25: =G25+H25 -> 6227224.5
B26: 22 | C26: 81 | D26: =INPUTS!$C$22*(1+INPUTS!$C$23)^(MAX(0,59.5-INPUTS!$C$7)+21) -> 103233.64 | E26: =IF(81>=INPUTS!$C$8,INPUTS!$C$25*(1+INPUTS!$C$23)^(81-INPUTS!$C$8),0) -> 33911.372 | F26: =MAX(0,D26-E26-INPUTS!$C$24) -> 69322.272 | G26: =MAX(0,G25*(1+INPUTS!$C$28)-F26) -> 0 | H26: =MAX(0,H25*(1+INPUTS!$C$28)-MAX(0,F26-G25)) -> 6562671.8 | I26: =G26+H26 -> 6562671.8
B27: 23 | C27: 82 | D27: =INPUTS!$C$22*(1+INPUTS!$C$23)^(MAX(0,59.5-INPUTS!$C$7)+22) -> 105814.48 | E27: =IF(82>=INPUTS!$C$8,INPUTS!$C$25*(1+INPUTS!$C$23)^(82-INPUTS!$C$8),0) -> 34759.156 | F27: =MAX(0,D27-E27-INPUTS!$C$24) -> 71055.329 | G27: =MAX(0,G26*(1+INPUTS!$C$28)-F27) -> 0 | H27: =MAX(0,H26*(1+INPUTS!$C$28)-MAX(0,F27-G26)) -> 6918190.1 | I27: =G27+H27 -> 6918190.1
B28: 24 | C28: 83 | D28: =INPUTS!$C$22*(1+INPUTS!$C$23)^(MAX(0,59.5-INPUTS!$C$7)+23) -> 108459.85 | E28: =IF(83>=INPUTS!$C$8,INPUTS!$C$25*(1+INPUTS!$C$23)^(83-INPUTS!$C$8),0) -> 35628.135 | F28: =MAX(0,D28-E28-INPUTS!$C$24) -> 72831.712 | G28: =MAX(0,G27*(1+INPUTS!$C$28)-F28) -> 0 | H28: =MAX(0,H27*(1+INPUTS!$C$28)-MAX(0,F28-G27)) -> 7295040.8 | I28: =G28+H28 -> 7295040.8
B29: 25 | C29: 84 | D29: =INPUTS!$C$22*(1+INPUTS!$C$23)^(MAX(0,59.5-INPUTS!$C$7)+24) -> 111171.34 | E29: =IF(84>=INPUTS!$C$8,INPUTS!$C$25*(1+INPUTS!$C$23)^(84-INPUTS!$C$8),0) -> 36518.838 | F29: =MAX(0,D29-E29-INPUTS!$C$24) -> 74652.505 | G29: =MAX(0,G28*(1+INPUTS!$C$28)-F29) -> 0 | H29: =MAX(0,H28*(1+INPUTS!$C$28)-MAX(0,F29-G28)) -> 7694565.9 | I29: =G29+H29 -> 7694565.9
B30: 26 | C30: 85 | D30: =INPUTS!$C$22*(1+INPUTS!$C$23)^(MAX(0,59.5-INPUTS!$C$7)+25) -> 113950.63 | E30: =IF(85>=INPUTS!$C$8,INPUTS!$C$25*(1+INPUTS!$C$23)^(85-INPUTS!$C$8),0) -> 37431.809 | F30: =MAX(0,D30-E30-INPUTS!$C$24) -> 76518.818 | G30: =MAX(0,G29*(1+INPUTS!$C$28)-F30) -> 0 | H30: =MAX(0,H29*(1+INPUTS!$C$28)-MAX(0,F30-G29)) -> 8118193.9 | I30: =G30+H30 -> 8118193.9
B31: 27 | C31: 86 | D31: =INPUTS!$C$22*(1+INPUTS!$C$23)^(MAX(0,59.5-INPUTS!$C$7)+26) -> 116799.39 | E31: =IF(86>=INPUTS!$C$8,INPUTS!$C$25*(1+INPUTS!$C$23)^(86-INPUTS!$C$8),0) -> 38367.604 | F31: =MAX(0,D31-E31-INPUTS!$C$24) -> 78431.788 | G31: =MAX(0,G30*(1+INPUTS!$C$28)-F31) -> 0 | H31: =MAX(0,H30*(1+INPUTS!$C$28)-MAX(0,F31-G30)) -> 8567444.7 | I31: =G31+H31 -> 8567444.7
B32: 28 | C32: 87 | D32: =INPUTS!$C$22*(1+INPUTS!$C$23)^(MAX(0,59.5-INPUTS!$C$7)+27) -> 119719.38 | E32: =IF(87>=INPUTS!$C$8,INPUTS!$C$25*(1+INPUTS!$C$23)^(87-INPUTS!$C$8),0) -> 39326.795 | F32: =MAX(0,D32-E32-INPUTS!$C$24) -> 80392.583 | G32: =MAX(0,G31*(1+INPUTS!$C$28)-F32) -> 0 | H32: =MAX(0,H31*(1+INPUTS!$C$28)-MAX(0,F32-G31)) -> 9043936.1 | I32: =G32+H32 -> 9043936.1
B33: 29 | C33: 88 | D33: =INPUTS!$C$22*(1+INPUTS!$C$23)^(MAX(0,59.5-INPUTS!$C$7)+28) -> 122712.36 | E33: =IF(88>=INPUTS!$C$8,INPUTS!$C$25*(1+INPUTS!$C$23)^(88-INPUTS!$C$8),0) -> 40309.964 | F33: =MAX(0,D33-E33-INPUTS!$C$24) -> 82402.397 | G33: =MAX(0,G32*(1+INPUTS!$C$28)-F33) -> 0 | H33: =MAX(0,H32*(1+INPUTS!$C$28)-MAX(0,F33-G32)) -> 9549389.5 | I33: =G33+H33 -> 9549389.5
B34: 30 | C34: 89 | D34: =INPUTS!$C$22*(1+INPUTS!$C$23)^(MAX(0,59.5-INPUTS!$C$7)+29) -> 125780.17 | E34: =IF(89>=INPUTS!$C$8,INPUTS!$C$25*(1+INPUTS!$C$23)^(89-INPUTS!$C$8),0) -> 41317.714 | F34: =MAX(0,D34-E34-INPUTS!$C$24) -> 84462.457 | G34: =MAX(0,G33*(1+INPUTS!$C$28)-F34) -> 0 | H34: =MAX(0,H33*(1+INPUTS!$C$28)-MAX(0,F34-G33)) -> 10085637 | I34: =G34+H34 -> 10085637
B35: 31 | C35: 90 | D35: =INPUTS!$C$22*(1+INPUTS!$C$23)^(MAX(0,59.5-INPUTS!$C$7)+30) -> 128924.68 | E35: =IF(90>=INPUTS!$C$8,INPUTS!$C$25*(1+INPUTS!$C$23)^(90-INPUTS!$C$8),0) -> 42350.656 | F35: =MAX(0,D35-E35-INPUTS!$C$24) -> 86574.019 | G35: =MAX(0,G34*(1+INPUTS!$C$28)-F35) -> 0 | H35: =MAX(0,H34*(1+INPUTS!$C$28)-MAX(0,F35-G34)) -> 10654630 | I35: =G35+H35 -> 10654630

Sheet RISK FLAGS
B2: AUTOMATED RISK FLAGS
B3: Flags update automatically as you change INPUTS. Green = OK · Red = Review needed.
B5: Risk Check | C5: Status | D5: Notes
B6: Withdrawal Rate > 4% | C6: =IF(INPUTS!C34>0.04,"⚠ HIGH RISK","✓ OK") -> ⚠ HIGH RISK | D6: =IF(INPUTS!C34>0.04,"Withdrawal rate "&TEXT(INPUTS!C34,"0.0%")&" exceeds 4% rule. Consider reducing spending or delaying retirement.","Withdrawal rate "&TEXT(INPUTS!C34,"0.0%")&" is within safe range.") -> Withdrawal rate 4.5% exceeds 4% rule. Consider reducing spending or delaying retirement.
B7: Taxable Bridge Gap | C7: =IF(INPUTS!C35<1,"⚠ UNDERFUNDED","✓ FUNDED") -> ✓ FUNDED | D7: =IF(INPUTS!C35<1,"Taxable account covers "&TEXT(INPUTS!C35,"0%")&" of bridge. Gap of $"&TEXT(INPUTS!C22*INPUTS!C33-INPUTS!C13,"#,##0")&". Consider 72(t) SEPP.","Taxable fully funds bridge years.") -> Taxable fully funds bridge years.
B8: Cash Buffer < 1 Year | C8: =IF(INPUTS!C16<INPUTS!C22,"⚠ LOW BUFFER","✓ OK") -> ✓ OK | D8: =IF(INPUTS!C16<INPUTS!C22,"Cash buffer of $"&TEXT(INPUTS!C16,"#,##0")&" is less than 1 year of spending. Sequence-of-returns risk.","Cash buffer covers "&TEXT(INPUTS!C16/INPUTS!C22,"0.0")&" years of spending.") -> Cash buffer covers 1.4 years of spending.
B9: ACA Subsidy Cliff Risk | C9: =IF(INPUTS!C22>58000,"⚠ REVIEW ACA","✓ OK") -> ✓ OK | D9: =IF(INPUTS!C22>58000,"Income may push past ACA cliff. Model MAGI carefully with Roth conversions.","Spending level suggests ACA subsidies likely available.") -> Spending level suggests ACA subsidies likely available.
B10: SS Delay Opportunity | C10: =IF(INPUTS!C8<70,"💡 CONSIDER DELAY","✓ CLAIMING 70") -> 💡 CONSIDER DELAY | D10: =IF(INPUTS!C8<70,"Delaying SS from "&INPUTS!C8&" to 70 adds "&TEXT((70-INPUTS!C8)*0.08*INPUTS!C25,"$#,##0")&"/yr. Model the breakeven.","Claiming at 70 maximizes lifetime SS benefit.") -> Delaying SS from 67 to 70 adds $5,760/yr. Model the breakeven.
B11: IRMAA Medicare Trigger | C11: =IF(INPUTS!C22>103000,"⚠ IRMAA RISK","✓ OK") -> ✓ OK | D11: =IF(INPUTS!C22>103000,"Income above $103k triggers Medicare IRMAA surcharges at age 65+. Plan Roth conversions carefully.","Income below IRMAA threshold. Safe for Medicare planning.") -> Income below IRMAA threshold. Safe for Medicare planning.
B12: Portfolio Survives to 90 | C12: =IF('POST-59½'!I35>0,"✓ FUNDED TO 90","⚠ SHORTFALL") -> ✓ FUNDED TO 90 | D12: =IF('POST-59½'!I35>0,"Portfolio projects to $"&TEXT('POST-59½'!I35,"#,##0")&" at age 90.","Portfolio depleted before age 90. Increase savings or reduce spending.") -> Portfolio projects to $10,654,630 at age 90.

Sheet REBALANCE
B2: ANNUAL REBALANCE TRACKER
B4: Asset Class | C4: Target % | D4: Current Value | E4: Current % | F4: Drift | G4: Action | H4: Notes
B5: US Total Market | C5: 0.4 | D5: 0 | E5: =IFERROR(D5/SUM(D5:D10),0) -> 0 | F5: =E5-C5 -> -0.4 | G5: =IF(ABS(F5)>0.05,IF(F5>0,"TRIM — overweight","ADD — underweight"),"Hold") -> ADD — underweight
B6: International | C6: 0.15 | D6: 0 | E6: =IFERROR(D6/SUM(D5:D10),0) -> 0 | F6: =E6-C6 -> -0.15 | G6: =IF(ABS(F6)>0.05,IF(F6>0,"TRIM — overweight","ADD — underweight"),"Hold") -> ADD — underweight
B7: Small Cap Value | C7: 0.1 | D7: 0 | E7: =IFERROR(D7/SUM(D5:D10),0) -> 0 | F7: =E7-C7 -> -0.1 | G7: =IF(ABS(F7)>0.05,IF(F7>0,"TRIM — overweight","ADD — underweight"),"Hold") -> ADD — underweight
B8: Bonds (Total) | C8: 0.25 | D8: 0 | E8: =IFERROR(D8/SUM(D5:D10),0) -> 0 | F8: =E8-C8 -> -0.25 | G8: =IF(ABS(F8)>0.05,IF(F8>0,"TRIM — overweight","ADD — underweight"),"Hold") -> ADD — underweight
B9: Cash / MM | C9: 0.05 | D9: 0 | E9: =IFERROR(D9/SUM(D5:D10),0) -> 0 | F9: =E9-C9 -> -0.05 | G9: =IF(ABS(F9)>0.05,IF(F9>0,"TRIM — overweight","ADD — underweight"),"Hold") -> Hold
B10: Real Estate (REIT) | C10: 0.05 | D10: 0 | E10: =IFERROR(D10/SUM(D5:D10),0) -> 0 | F10: =E10-C10 -> -0.05 | G10: =IF(ABS(F10)>0.05,IF(F10>0,"TRIM — overweight","ADD — underweight"),"Hold") -> Hold
B11: TOTAL | C11: =SUM(C5:C10) -> 1 | D11: =SUM(D5:D10) -> 0
